Workbook
Name Active_Client: Control_Panel!$C$11
Name Active_Year: Control_Panel!$C$8
Name Activity_Type: Dropdown_Lists!$G$4:$G$5
Name AdjToIncome: INDIRECT("Y"&Active_Year&"!$N$14")
Name Adjustment_Docs: Dropdown_Lists!$E$35:$E$39
Name Adjustment_Profiles: Dropdown_Lists!$E$19:$E$23
Name AGI: INDIRECT("Y"&Active_Year&"!$N$15")
Name BI_ACTIVE_NONSE: INDIRECT("Y"&Active_Year&"!$J$27")
Name BI_PASSIVE: INDIRECT("Y"&Active_Year&"!$J$28")
Name BI_SE_SUBJECT: INDIRECT("Y"&Active_Year&"!$J$26")
Name Bucket: Dropdown_Lists!$A$4:$A$11
Name BusinessIncome_Docs: Dropdown_Lists!$A$35:$A$41
Name BusinessIncome_Profiles: Dropdown_Lists!$A$19:$A$27
Name BusinessLoss: INDIRECT("Y"&Active_Year&"!$J$42")
Name CapitalGains_Docs: Dropdown_Lists!$D$35:$D$38
Name CapitalGains_Profiles: Dropdown_Lists!$D$19:$D$23
Name CG_LT: INDIRECT("Y"&Active_Year&"!$J$31")
Name CG_ST: INDIRECT("Y"&Active_Year&"!$J$32")
Name Credit_Docs: Dropdown_Lists!$G$35:$G$37
Name Credit_Profiles: Dropdown_Lists!$G$19:$G$21
Name Drill_Line: INDIRECT("Y"&Active_Year&"!$I$49")
Name Filing_Status: Control_Panel!$C$15
Name InvestmentIncome_Docs: Dropdown_Lists!$C$35:$C$37
Name InvestmentIncome_Profiles: Dropdown_Lists!$C$19:$C$22
Name IsSSTB: INDIRECT("Y"&Active_Year&"!$J$45")
Name Itemized_Docs: Dropdown_Lists!$F$35:$F$38
Name Itemized_Profiles: Dropdown_Lists!$F$19:$F$22
Name Line_1z_Wages: INDIRECT("Y"&Active_Year&"!$N$6")
Name Line_2a_TaxExempt: INDIRECT("Y"&Active_Year&"!$N$7")
Name Line_2b_TaxInt: INDIRECT("Y"&Active_Year&"!$N$8")
Name Line_3a_QualDiv: INDIRECT("Y"&Active_Year&"!$N$9")
Name Line_3b_OrdDiv: INDIRECT("Y"&Active_Year&"!$N$10")
Name Line_7_CapGain: INDIRECT("Y"&Active_Year&"!$N$11")
Name Line_8_OtherInc: INDIRECT("Y"&Active_Year&"!$N$12")
Name MAGI: INDIRECT("Y"&Active_Year&"!$J$38")
Name NetSEIncome: INDIRECT("Y"&Active_Year&"!$J$43")
Name NII: INDIRECT("Y"&Active_Year&"!$J$39")
Name NIIT_Class: Dropdown_Lists!$C$4:$C$7
Name NOL_Carryforward: INDIRECT("Y"&Active_Year&"!$J$46")
Name OrdIncome: INDIRECT("Y"&Active_Year&"!$J$37")
Name Payment_Docs: Dropdown_Lists!$H$35:$H$36
Name Payment_Profiles: Dropdown_Lists!$H$19:$H$20
Name Provenance: Dropdown_Lists!$D$4:$D$13
Name QBI_Deduction: INDIRECT("Y"&Active_Year&"!$N$17")
Name QBI_Income: INDIRECT("Y"&Active_Year&"!$J$40")
Name QUAL_DIV: INDIRECT("Y"&Active_Year&"!$J$30")
Name SEC1250: INDIRECT("Y"&Active_Year&"!$J$33")
Name Slicer_Activity_Type: #N/A
Name Slicer_Activity_Type1: #N/A
Name Slicer_Activity_Type2: #N/A
Name Slicer_Activity_Type3: #N/A
Name Slicer_Bucket: #N/A
Name Slicer_Bucket1: #N/A
Name Slicer_ClientID: #N/A
Name Slicer_ClientID1: #N/A
Name Slicer_NIIT_Class: #N/A
Name Slicer_QBI_Eligible: #N/A
Name Slicer_SE_Subject: #N/A
Name Slicer_Year: #N/A
Name Slicer_Year1: #N/A

Sheet Control_Panel
B2: TAX WORKBOOK — CONTROL PANEL
B3: Settings, navigation, and input reference — start here.
B5: ▸ SETTINGS
B7: PLAN STATUS
B8: Plan Year | C8: 2025
B9: Plan Maturity | C9: Standard Assumptions
B10: Engagement Leader | C10: TBD
B11: Active Client | C11: SAMPLE
B12: Last Refresh | C12: 46161
B14: TAX PROFILE
B15: Filing Status | C15: MFJ
B16: State of Residence | C16: UT
B17: Taxpayer Age | C17: 42
B18: Spouse Age | C18: 40
B19: Dependent Children | C19: 2
B20: REPS Qualified | C20: No
B21: Business is SSTB? | C21: No
B23: ▸ ACTIVE YEAR SNAPSHOT
B24: AGI | C24: {=TEXT(AGI,"$#,##0")}
B25: Taxable Income | C25: {=TEXT(TaxableIncome,"$#,##0")}
B26: Effective Rate | C26: {=TEXT(IFERROR(INDIRECT("Y"&Active_Year&"!I130"),0),"0.0%")}
B27: Total Tax | C27: {=TEXT(IFERROR(INDIRECT("Y"&Active_Year&"!I129"),0),"$#,##0")}
B28: QBI Deduction | C28: {=TEXT(QBI_Deduction,"($#,##0)")}
B30: ▸ NAVIGATION
B32: INPUT / CONFIG
B33: =HYPERLINK("#Master_Inputs!A1", "Master_Inputs") | C33: Baseline income/deductions + committed strategies
B34: =HYPERLINK("#AsFiled!A1", "AsFiled") | C34: Filed return data by year for PY reconciliation
B35: =HYPERLINK("#Carryovers!A1", "Carryovers") | C35: PAL, CL, NOL manual inputs + calculator
B37: YEAR SANDBOXES
B38: =HYPERLINK("#Y2023!A1", "Y2023") | C38: Strategies (A5:F10), rollup, 7-calculator
B39: =HYPERLINK("#Y2024!A1", "Y2024") | C39: Strategies (A5:F10), rollup, 7-calculator
B40: =HYPERLINK("#Y2025!A1", "Y2025") | C40: Strategies (A5:F10), rollup, 7-calculator
B41: =HYPERLINK("#Y2026!A1", "Y2026") | C41: Strategies (A5:F10), rollup, 7-calculator
B42: =HYPERLINK("#Y2027!A1", "Y2027") | C42: Strategies (A5:F10), rollup, 7-calculator
B43: =HYPERLINK("#Y2028!A1", "Y2028") | C43: Strategies (A5:F10), rollup, 7-calculator
B45: DASHBOARDS / RECON
B46: =HYPERLINK("#Tax_Plan_Dashboard!A1", "Tax_Plan_Dashboard") | C46: KPIs + charts with year dropdown
B47: =HYPERLINK("#PY_Recon!A1", "PY_Recon") | C47: Prior year baseline vs AsFiled reconciliation
B48: =HYPERLINK("#Pivot_GPD!A1", "Pivot_GPD") | C48: Multi-year GETPIVOTDATA bridge + VP_ named ranges
B50: PIVOT ENGINE (do not modify)
B51: =HYPERLINK("#Pivot_Summary!A1", "Pivot_Summary") | C51: SUMIFS grid: 1040 lines × years
B52: =HYPERLINK("#Pivot_Medium!A1", "Pivot_Medium") | C52: SUMIFS grid: Line 8 breakout by treatment
B53: =HYPERLINK("#Pivot_Detailed!A1", "Pivot_Detailed") | C53: SUMIFS grid: informational lines (2a, 3a)
B54: =HYPERLINK("#Pivot_Helpers!A1", "Pivot_Helpers") | C54: SUMIFS grid: helper amounts × years
B56: VISUAL PIVOTS
B57: =HYPERLINK("#Visual_Pivot_Income!A1", "Visual_Pivot_Income") | C57: PivotTable: income by 1040 line
B58: =HYPERLINK("#Visual_Pivot_BusinessIncome!A1", "Visual_Pivot_BusinessIncome") | C58: PivotTable: business by treatment
B59: =HYPERLINK("#Visual_Pivot_ByPayor!A1", "Visual_Pivot_ByPayor") | C59: PivotTable: income by payor
B60: =HYPERLINK("#Visual_Pivot_HelperCarveOuts!A1", "Visual_Pivot_HelperCarveOuts") | C60: PivotTable: helper carve-outs
B62: REFERENCE
B63: =HYPERLINK("#Tax_Ref!A1", "Tax_Ref") | C63: Rate tables + Treatment_Profile_Map (5 tables)
B64: =HYPERLINK("#Dropdown_Lists!A1", "Dropdown_Lists") | C64: Validation source lists
B65: =HYPERLINK("#Framework_Ref!A1", "Framework_Ref") | C65: Canon v1.4 + Pecking Order + Strategies catalog
B66: =HYPERLINK("#Glossary!A1", "Glossary") | C66: 100+ terms, PTET table + Tax Limitations
B67: =HYPERLINK("#Questionnaire!A1", "Questionnaire") | C67: 26-question strategy intake (auto-detects from data)
B68: =HYPERLINK("#Connections!A1", "Connections") | C68: External file paths + extraction mapping
B69: =HYPERLINK("#Projection_History!A1", "Projection_History") | C69: Projected vs filed accuracy tracking
B70: =HYPERLINK("#Change_Log!A1", "Change_Log") | C70: Audit trail
B71: =HYPERLINK("#Setup_Guide!A1", "Setup_Guide") | C71: Onboarding + LAMBDA/VBA/Schema docs

Sheet Master_Inputs
A1: MASTER INPUTS — committed baseline source-input items (one row per source document per year)
A2: Adjustments and strategies live on the year sheet. Master is just where baseline data lives.
A4: InputID | B4: Year | C4: ClientID | D4: ClientName | E4: Bucket | F4: Treatment_Profile | G4: Source_Document | H4: Activity_Type | I4: Provenance | J4: Payor | K4: Baseline_Amount | L4: Helper_Amount | M4: Helper_Treatment | N4: SE_Subject | O4: NIIT_Class | P4: QBI_Eligible | Q4: Primary_Line | R4: Consider | S4: Notes
A5: CED|2024|Wages|01 | B5: 2024 | C5: CEDILLO | D5: Ron Cedillo | E5: Wages | F5: W2_SCorpOwner | G5: W-2 | H5: Baseline | I5: PBC - Reviewed | J5: Acme S-Corp | K5: 153648 | L5: 0 | M5: OWNER_PAY | N5: No | O5: Active | P5: No | Q5: 1z | R5: Owner reasonable comp
A6: CED|2024|BI|01 | B6: 2024 | C6: CEDILLO | D6: Ron Cedillo | E6: Business Income | F6: K1_PTP_Passive | G6: K-1 | H6: Baseline | I6: PBC - Reviewed | J6: Cedillo Partnership | K6: -100766 | L6: 0 | M6: K1_SPLIT | N6: No | O6: Passive | P6: Yes | Q6: 8 | R6: Passive loss
A7: CED|2024|II|01 | B7: 2024 | C7: CEDILLO | D7: Ron Cedillo | E7: Investment Income | F7: Div_Ordinary | G7: 1099-DIV | H7: Baseline | I7: PBC - Reviewed | J7: Brokerage | K7: 25922 | L7: 0 | M7: QUAL_DIV | N7: No | O7: Portfolio | P7: No | Q7: 3b | R7: All non-qualified
A8: CED|2024|CG|01 | B8: 2024 | C8: CEDILLO | D8: Ron Cedillo | E8: Capital Gains | F8: LTCG_Stock | G8: 1099-B | H8: Baseline | I8: PBC - Reviewed | J8: Brokerage | K8: 14487 | L8: 0 | M8: LTCG_SPLIT | N8: No | O8: Portfolio | P8: No | Q8: 7 | R8: All long-term
A9: SAM|2025|Wages|01 | B9: 2025 | C9: SAMPLE | D9: Sample Client | E9: Wages | F9: W2_SCorpOwner | G9: W-2 | H9: Baseline | I9: Estimate - Preparer | J9: SampleCo S-Corp | K9: 100000 | L9: 100000 | M9: OWNER_PAY | N9: No | O9: Active | P9: No | Q9: 1z | R9: Owner reasonable comp
A10: SAM|2025|BI|01 | B10: 2025 | C10: SAMPLE | D10: Sample Client | E10: Business Income | F10: K1_SCorp_Active | G10: K-1 | H10: Baseline | I10: PY Rolled Forward | J10: SampleCo S-Corp K-1 | K10: 200000 | L10: 0 | M10: K1_SPLIT | N10: No | O10: Active | P10: Yes | Q10: 8 | R10: Active S-corp K-1
A11: SAM|2025|II_Div|01 | B11: 2025 | C11: SAMPLE | D11: Sample Client | E11: Investment Income | F11: Div_Qualified | G11: 1099-DIV | H11: Baseline | I11: PBC - Received | J11: Brokerage | K11: 10000 | L11: 7000 | M11: QUAL_DIV | N11: No | O11: Portfolio | P11: No | Q11: 3b | R11: $7K qualified
A12: SAM|2025|II_Int|01 | B12: 2025 | C12: SAMPLE | D12: Sample Client | E12: Investment Income | F12: Int_Taxable | G12: 1099-INT | H12: Baseline | I12: PBC - Received | J12: Brokerage | K12: 500 | L12: 0 | M12: NONE | N12: No | O12: Portfolio | P12: No | Q12: 2b | R12: All taxable
A13: SAM|2025|CG|01 | B13: 2025 | C13: SAMPLE | D13: Sample Client | E13: Capital Gains | F13: LTCG_Stock | G13: 1099-B | H13: Baseline | I13: PBC - Requested | J13: Brokerage | K13: 25000 | L13: 0 | M13: LTCG_SPLIT | N13: No | O13: Portfolio | P13: No | Q13: 7 | R13: All long-term
A14: SAM|2025|Itm|01 | B14: 2025 | C14: SAMPLE | D14: Sample Client | E14: Itemized | F14: Itm_SALT | G14: Property Tax Receipt | H14: Baseline | I14: PBC - Received | K14: -10000 | L14: 0 | M14: SALT | N14: No | O14: N/A | P14: No | Q14: 12 | R14: SALT cap
A15: SAM|2025|Strategy|WageOpt|01 | B15: 2025 | C15: SAMPLE | D15: Sample Client | E15: Wages | F15: W2_SCorpOwner | H15: Strategy | I15: Planning | J15: SampleCo S-Corp | K15: -25000 | L15: 0 | M15: OWNER_PAY | N15: No | O15: Active | P15: No | Q15: 1z | R15: Reduce owner W-2 by $25K | S15: STR-001 Committed
A16: SAM|2025|Strategy|WageOpt|02 | B16: 2025 | C16: SAMPLE | D16: Sample Client | E16: Business Income | F16: K1_SCorp_Active | H16: Strategy | I16: Planning | J16: SampleCo S-Corp K-1 | K16: 25000 | L16: 0 | M16: K1_SPLIT | N16: No | O16: Active | P16: Yes | Q16: 8 | R16: Corresponding K-1 increase from wage reduction | S16: STR-001 Committed
A17: SAM|2025|Strategy|HSA|01 | B17: 2025 | C17: SAMPLE | D17: Sample Client | E17: Adjustment | F17: Adj_HSA | H17: Strategy | I17: Planning | K17: -8550 | L17: 0 | M17: NONE | N17: No | O17: N/A | P17: No | Q17: 10 | R17: Family HSA max contribution | S17: STR-002 Committed
A18: SAM|2025|Strategy|CostSeg|01 | B18: 2025 | C18: SAMPLE | D18: Sample Client | E18: Business Income | F18: SchE_Rental | H18: Strategy | I18: Planning | J18: 123 Main St, Salt Lake City | K18: -80000 | L18: 0 | M18: PASSIVE | N18: No | O18: Passive | P18: No | Q18: 8 | R18: Cost seg accelerated depreciation | S18: STR-005 Committed

Sheet AsFiled
B2: ASFILED — Filed Tax Return Data
B3: Filed return amounts by 1040 line. Use Year column filter to view one year at a time. Add rows per year as needed. PY_Recon uses SUMIFS against this table.
B5: InputID | C5: Year | D5: ClientID | E5: ClientName | F5: Bucket | G5: Treatment_Profile | H5: Source_Document | I5: Provenance | J5: Payor | K5: Filed_Amount | L5: Helper_Amount | M5: Helper_Treatment | N5: Primary_Line | O5: Notes
B6: CED|2024|AF|Wages|01 | C6: 2024 | D6: CEDILLO | E6: Ron Cedillo | F6: Wages | G6: W2_SCorpOwner | H6: Filed 1040 | I6: Filed Return | J6: Acme S-Corp | K6: 153648 | L6: 0 | M6: OWNER_PAY | N6: 1z | O6: Per filed Form 1040 Line 1z
B7: CED|2024|AF|BI|01 | C7: 2024 | D7: CEDILLO | E7: Ron Cedillo | F7: Business Income | G7: K1_PTP_Passive | H7: Filed 1040 | I7: Filed Return | J7: Cedillo Partnership | K7: -100766 | L7: 0 | M7: K1_SPLIT | N7: 8 | O7: Per filed Sch 1 / K-1
B8: CED|2024|AF|II|01 | C8: 2024 | D8: CEDILLO | E8: Ron Cedillo | F8: Investment Income | G8: Div_Ordinary | H8: Filed 1040 | I8: Filed Return | J8: Brokerage | K8: 25922 | L8: 0 | M8: QUAL_DIV | N8: 3b | O8: Per filed 1040 Line 3b
B9: CED|2024|AF|CG|01 | C9: 2024 | D9: CEDILLO | E9: Ron Cedillo | F9: Capital Gains | G9: LTCG_Stock | H9: Filed 1040 | I9: Filed Return | J9: Brokerage | K9: 14487 | L9: 0 | M9: LTCG_SPLIT | N9: 7 | O9: Per filed 1040 Line 7
B10: PLACEHOLDER|2023 | C10: 2023 | I10: Estimate | K10: 0 | L10: 0 | O10: Enter 2023 filed data here — add rows as needed
B11: PLACEHOLDER|2025 | C11: 2025 | I11: Estimate | K11: 0 | L11: 0 | O11: Enter 2025 filed data here — add rows as needed
B12: PLACEHOLDER|2026 | C12: 2026 | I12: Estimate | K12: 0 | L12: 0 | O12: Enter 2026 filed data here — add rows as needed
B13: PLACEHOLDER|2027 | C13: 2027 | I13: Estimate | K13: 0 | L13: 0 | O13: Enter 2027 filed data here — add rows as needed
B14: PLACEHOLDER|2028 | C14: 2028 | I14: Estimate | K14: 0 | L14: 0 | O14: Enter 2028 filed data here — add rows as needed

Sheet Tax_Plan_Dashboard
B2: TAX PLAN DASHBOARD
B3: Select year below. KPIs pull baseline from visual pivots via GETPIVOTDATA.
B4: Dashboard Year: | C4: 2025
B5: HEADLINE METRICS | C5: Baseline | D5: Eff w/ Strat | E5: Δ Savings | H5: CHART DATA — Income by 1040 Line
B6: Total Income | C6: {=IFERROR(INDIRECT("Y"&$C$4&"!J13"),0)} | D6: {=IFERROR(INDIRECT("Y"&$C$4&"!O13"),0)} | E6: =C6-D6 | H6: 1040 Line | I6: Amount
B7: Wages (Line 1z) | C7: {=IFERROR(INDIRECT("Y"&$C$4&"!J6"),0)} | D7: {=IFERROR(INDIRECT("Y"&$C$4&"!O6"),0)} | E7: =C7-D7 | H7: 1040 Line | I7: Amount
B8: Business Income (Line 8) | C8: {=IFERROR(INDIRECT("Y"&$C$4&"!J12"),0)} | D8: {=IFERROR(INDIRECT("Y"&$C$4&"!O12"),0)} | E8: =C8-D8 | H8: 1z Wages | I8: =IFERROR(GETPIVOTDATA("Baseline_Amount",Visual_Pivot_Income!$B$5,"Primary_Line","1z","Year",$C$4),0)
B9: Capital Gains (Line 7) | C9: {=IFERROR(INDIRECT("Y"&$C$4&"!J11"),0)} | D9: {=IFERROR(INDIRECT("Y"&$C$4&"!O11"),0)} | E9: =C9-D9 | H9: 2b Tax Interest | I9: =IFERROR(GETPIVOTDATA("Baseline_Amount",Visual_Pivot_Income!$B$5,"Primary_Line","2b","Year",$C$4),0)
B10: Investment Income (3b) | C10: {=IFERROR(INDIRECT("Y"&$C$4&"!J10"),0)} | D10: {=IFERROR(INDIRECT("Y"&$C$4&"!O10"),0)} | E10: =C10-D10 | H10: 3b Dividends | I10: =IFERROR(GETPIVOTDATA("Baseline_Amount",Visual_Pivot_Income!$B$5,"Primary_Line","3b","Year",$C$4),0)
B11: Std/Itemized Ded (Line 12) | C11: {=IFERROR(INDIRECT("Y"&$C$4&"!J16"),0)} | D11: {=IFERROR(INDIRECT("Y"&$C$4&"!O16"),0)} | E11: =C11-D11 | H11: 7 Cap Gains | I11: =IFERROR(GETPIVOTDATA("Baseline_Amount",Visual_Pivot_Income!$B$5,"Primary_Line","7","Year",$C$4),0)
B12: Qualified Dividends | C12: {=IFERROR(INDIRECT("Y"&$C$4&"!I30"),0)} | D12: {=IFERROR(INDIRECT("Y"&$C$4&"!J30"),0)} | E12: =C12-D12 | H12: 8 Business | I12: =IFERROR(GETPIVOTDATA("Baseline_Amount",Visual_Pivot_Income!$B$5,"Primary_Line","8","Year",$C$4),0)
B13: Owner W-2 Wages | C13: {=IFERROR(INDIRECT("Y"&$C$4&"!I23"),0)} | D13: {=IFERROR(INDIRECT("Y"&$C$4&"!J23"),0)} | E13: =C13-D13
H14: CHART DATA — Business by Treatment
B15: BUSINESS INCOME BREAKDOWN | H15: Treatment | I15: Amount
B16: S-Corp K-1 Active | C16: =IFERROR(GETPIVOTDATA("Baseline_Amount",Visual_Pivot_BusinessIncome!$B$5,"Treatment_Profile","K1_SCorp_Active","Year",$C$4),0) | H16: Treatment | I16: Amount
B17: PTP K-1 Passive | C17: =IFERROR(GETPIVOTDATA("Baseline_Amount",Visual_Pivot_BusinessIncome!$B$5,"Treatment_Profile","K1_PTP_Passive","Year",$C$4),0) | H17: K1_SCorp_Active | I17: =IFERROR(GETPIVOTDATA("Baseline_Amount",Visual_Pivot_BusinessIncome!$B$5,"Treatment_Profile","K1_SCorp_Active","Year",$C$4),0)
B18: Schedule E Rental | C18: =IFERROR(GETPIVOTDATA("Baseline_Amount",Visual_Pivot_BusinessIncome!$B$5,"Treatment_Profile","SchE_Rental","Year",$C$4),0) | H18: K1_PTP_Passive | I18: =IFERROR(GETPIVOTDATA("Baseline_Amount",Visual_Pivot_BusinessIncome!$B$5,"Treatment_Profile","K1_PTP_Passive","Year",$C$4),0)
B19: Total Business Income | C19: =IFERROR(GETPIVOTDATA("Baseline_Amount",Visual_Pivot_BusinessIncome!$B$5,"Year",$C$4),0)

Sheet PY_Recon
B2: PY RECON — Baseline vs Filed Return
B3: Compares computed Baseline (tblMaster_Inputs) vs AsFiled (tblAsFiled) for Active_Year + Active_Client. Verify the engine before trusting roll-forward.
B5: Recon Year: | C5: 2025 | D5: Client: | E5: SAMPLE
B7: 1040 Line | C7: Description | D7: Computed (Baseline) | E7: Filed (AsFiled) | F7: Variance | G7: Status
B8: 1z | C8: Wages, salaries, tips | D8: =SUMIFS(tblMaster_Inputs[Baseline_Amount],tblMaster_Inputs[Year],$C$5,tblMaster_Inputs[ClientID],$E$5,tblMaster_Inputs[Primary_Line],"1z") | E8: =SUMIFS(tblAsFiled[Filed_Amount],tblAsFiled[Year],$C$5,tblAsFiled[ClientID],$E$5,tblAsFiled[Primary_Line],"1z") | F8: =D8-E8 | G8: =IF(ABS(F8)<1,"✓ OK","⚠ CHECK")
B9: 2b | C9: Taxable interest | D9: =SUMIFS(tblMaster_Inputs[Baseline_Amount],tblMaster_Inputs[Year],$C$5,tblMaster_Inputs[ClientID],$E$5,tblMaster_Inputs[Primary_Line],"2b") | E9: =SUMIFS(tblAsFiled[Filed_Amount],tblAsFiled[Year],$C$5,tblAsFiled[ClientID],$E$5,tblAsFiled[Primary_Line],"2b") | F9: =D9-E9 | G9: =IF(ABS(F9)<1,"✓ OK","⚠ CHECK")
B10: 3b | C10: Ordinary dividends | D10: =SUMIFS(tblMaster_Inputs[Baseline_Amount],tblMaster_Inputs[Year],$C$5,tblMaster_Inputs[ClientID],$E$5,tblMaster_Inputs[Primary_Line],"3b") | E10: =SUMIFS(tblAsFiled[Filed_Amount],tblAsFiled[Year],$C$5,tblAsFiled[ClientID],$E$5,tblAsFiled[Primary_Line],"3b") | F10: =D10-E10 | G10: =IF(ABS(F10)<1,"✓ OK","⚠ CHECK")
B11: 7 | C11: Capital gain or (loss) | D11: =SUMIFS(tblMaster_Inputs[Baseline_Amount],tblMaster_Inputs[Year],$C$5,tblMaster_Inputs[ClientID],$E$5,tblMaster_Inputs[Primary_Line],"7") | E11: =SUMIFS(tblAsFiled[Filed_Amount],tblAsFiled[Year],$C$5,tblAsFiled[ClientID],$E$5,tblAsFiled[Primary_Line],"7") | F11: =D11-E11 | G11: =IF(ABS(F11)<1,"✓ OK","⚠ CHECK")
B12: 8 | C12: Other income (Sch 1 — business) | D12: =SUMIFS(tblMaster_Inputs[Baseline_Amount],tblMaster_Inputs[Year],$C$5,tblMaster_Inputs[ClientID],$E$5,tblMaster_Inputs[Primary_Line],"8") | E12: =SUMIFS(tblAsFiled[Filed_Amount],tblAsFiled[Year],$C$5,tblAsFiled[ClientID],$E$5,tblAsFiled[Primary_Line],"8") | F12: =D12-E12 | G12: =IF(ABS(F12)<1,"✓ OK","⚠ CHECK")
B13: 9 | C13: TOTAL INCOME | D13: =SUM(D8:D12) | E13: =SUM(E8:E12) | F13: =D13-E13 | G13: =IF(ABS(F13)<1,"✓ OK","⚠ CHECK")
B14: 10 | C14: Adjustments to income | D14: =SUMIFS(tblMaster_Inputs[Baseline_Amount],tblMaster_Inputs[Year],$C$5,tblMaster_Inputs[ClientID],$E$5,tblMaster_Inputs[Primary_Line],"10") | E14: =SUMIFS(tblAsFiled[Filed_Amount],tblAsFiled[Year],$C$5,tblAsFiled[ClientID],$E$5,tblAsFiled[Primary_Line],"10") | F14: =D14-E14 | G14: =IF(ABS(F14)<1,"✓ OK","⚠ CHECK")
B15: 11 | C15: AGI | D15: =D13+D14 | E15: =E13+E14 | F15: =D15-E15 | G15: =IF(ABS(F15)<1,"✓ OK","⚠ CHECK")
B16: 12 | C16: Standard / Itemized deduction | D16: =SUMIFS(tblMaster_Inputs[Baseline_Amount],tblMaster_Inputs[Year],$C$5,tblMaster_Inputs[ClientID],$E$5,tblMaster_Inputs[Primary_Line],"12") | E16: =SUMIFS(tblAsFiled[Filed_Amount],tblAsFiled[Year],$C$5,tblAsFiled[ClientID],$E$5,tblAsFiled[Primary_Line],"12") | F16: =D16-E16 | G16: =IF(ABS(F16)<1,"✓ OK","⚠ CHECK")
B17: 13 | C17: QBI deduction | D17: =SUMIFS(tblMaster_Inputs[Baseline_Amount],tblMaster_Inputs[Year],$C$5,tblMaster_Inputs[ClientID],$E$5,tblMaster_Inputs[Primary_Line],"13") | E17: =SUMIFS(tblAsFiled[Filed_Amount],tblAsFiled[Year],$C$5,tblAsFiled[ClientID],$E$5,tblAsFiled[Primary_Line],"13") | F17: =D17-E17 | G17: =IF(ABS(F17)<1,"✓ OK","⚠ CHECK")
B18: 15 | C18: TAXABLE INCOME | D18: =D15+D16+D17 | E18: =E15+E16+E17 | F18: =D18-E18 | G18: =IF(ABS(F18)<1,"✓ OK","⚠ CHECK")
B20: RECON SUMMARY
B21: Lines matched: | C21: =COUNTIF(G8:G18,"✓ OK") | D21: of | E21: =COUNTA(G8:G18)
B22: Overall status: | C22: =IF(C21=E21,"✓ ALL LINES MATCH","⚠ VARIANCES FOUND — REVIEW BEFORE PLANNING")

Sheet Pivot_GPD
B2: PIVOT GETPIVOTDATA — Multi-Year Named Range Bridge
B3: Full year grid + Active_Year column (→ VP_ named ranges). GETPIVOTDATA pulls directly from visual pivots.
B5: INCOME BY 1040 LINE
B6: Named Range | C6: Description | D6: 2023 | E6: 2024 | F6: 2025 | G6: 2026 | H6: 2027 | I6: 2028 | J6: Active Year
B7: VP_Line_1z_Wages | C7: Wages (1z) | D7: =IFERROR(GETPIVOTDATA("Baseline_Amount",Visual_Pivot_Income!$B$5,"Primary_Line","1z","Year",2023),0) | E7: =IFERROR(GETPIVOTDATA("Baseline_Amount",Visual_Pivot_Income!$B$5,"Primary_Line","1z","Year",2024),0) | F7: =IFERROR(GETPIVOTDATA("Baseline_Amount",Visual_Pivot_Income!$B$5,"Primary_Line","1z","Year",2025),0) | G7: =IFERROR(GETPIVOTDATA("Baseline_Amount",Visual_Pivot_Income!$B$5,"Primary_Line","1z","Year",2026),0) | H7: =IFERROR(GETPIVOTDATA("Baseline_Amount",Visual_Pivot_Income!$B$5,"Primary_Line","1z","Year",2027),0) | I7: =IFERROR(GETPIVOTDATA("Baseline_Amount",Visual_Pivot_Income!$B$5,"Primary_Line","1z","Year",2028),0) | J7: =IFERROR(GETPIVOTDATA("Baseline_Amount",Visual_Pivot_Income!$B$5,"Primary_Line","1z","Year",Active_Year),0)
B8: VP_Line_2b_TaxInt | C8: Tax Interest (2b) | D8: =IFERROR(GETPIVOTDATA("Baseline_Amount",Visual_Pivot_Income!$B$5,"Primary_Line","2b","Year",2023),0) | E8: =IFERROR(GETPIVOTDATA("Baseline_Amount",Visual_Pivot_Income!$B$5,"Primary_Line","2b","Year",2024),0) | F8: =IFERROR(GETPIVOTDATA("Baseline_Amount",Visual_Pivot_Income!$B$5,"Primary_Line","2b","Year",2025),0) | G8: =IFERROR(GETPIVOTDATA("Baseline_Amount",Visual_Pivot_Income!$B$5,"Primary_Line","2b","Year",2026),0) | H8: =IFERROR(GETPIVOTDATA("Baseline_Amount",Visual_Pivot_Income!$B$5,"Primary_Line","2b","Year",2027),0) | I8: =IFERROR(GETPIVOTDATA("Baseline_Amount",Visual_Pivot_Income!$B$5,"Primary_Line","2b","Year",2028),0) | J8: =IFERROR(GETPIVOTDATA("Baseline_Amount",Visual_Pivot_Income!$B$5,"Primary_Line","2b","Year",Active_Year),0)
B9: VP_Line_3b_OrdDiv | C9: Ord Dividends (3b) | D9: =IFERROR(GETPIVOTDATA("Baseline_Amount",Visual_Pivot_Income!$B$5,"Primary_Line","3b","Year",2023),0) | E9: =IFERROR(GETPIVOTDATA("Baseline_Amount",Visual_Pivot_Income!$B$5,"Primary_Line","3b","Year",2024),0) | F9: =IFERROR(GETPIVOTDATA("Baseline_Amount",Visual_Pivot_Income!$B$5,"Primary_Line","3b","Year",2025),0) | G9: =IFERROR(GETPIVOTDATA("Baseline_Amount",Visual_Pivot_Income!$B$5,"Primary_Line","3b","Year",2026),0) | H9: =IFERROR(GETPIVOTDATA("Baseline_Amount",Visual_Pivot_Income!$B$5,"Primary_Line","3b","Year",2027),0) | I9: =IFERROR(GETPIVOTDATA("Baseline_Amount",Visual_Pivot_Income!$B$5,"Primary_Line","3b","Year",2028),0) | J9: =IFERROR(GETPIVOTDATA("Baseline_Amount",Visual_Pivot_Income!$B$5,"Primary_Line","3b","Year",Active_Year),0)
B10: VP_Line_7_CapGain | C10: Cap Gains (7) | D10: =IFERROR(GETPIVOTDATA("Baseline_Amount",Visual_Pivot_Income!$B$5,"Primary_Line","7","Year",2023),0) | E10: =IFERROR(GETPIVOTDATA("Baseline_Amount",Visual_Pivot_Income!$B$5,"Primary_Line","7","Year",2024),0) | F10: =IFERROR(GETPIVOTDATA("Baseline_Amount",Visual_Pivot_Income!$B$5,"Primary_Line","7","Year",2025),0) | G10: =IFERROR(GETPIVOTDATA("Baseline_Amount",Visual_Pivot_Income!$B$5,"Primary_Line","7","Year",2026),0) | H10: =IFERROR(GETPIVOTDATA("Baseline_Amount",Visual_Pivot_Income!$B$5,"Primary_Line","7","Year",2027),0) | I10: =IFERROR(GETPIVOTDATA("Baseline_Amount",Visual_Pivot_Income!$B$5,"Primary_Line","7","Year",2028),0) | J10: =IFERROR(GETPIVOTDATA("Baseline_Amount",Visual_Pivot_Income!$B$5,"Primary_Line","7","Year",Active_Year),0)
B11: VP_Line_8_OtherInc | C11: Business/Other (8) | D11: =IFERROR(GETPIVOTDATA("Baseline_Amount",Visual_Pivot_Income!$B$5,"Primary_Line","8","Year",2023),0) | E11: =IFERROR(GETPIVOTDATA("Baseline_Amount",Visual_Pivot_Income!$B$5,"Primary_Line","8","Year",2024),0) | F11: =IFERROR(GETPIVOTDATA("Baseline_Amount",Visual_Pivot_Income!$B$5,"Primary_Line","8","Year",2025),0) | G11: =IFERROR(GETPIVOTDATA("Baseline_Amount",Visual_Pivot_Income!$B$5,"Primary_Line","8","Year",2026),0) | H11: =IFERROR(GETPIVOTDATA("Baseline_Amount",Visual_Pivot_Income!$B$5,"Primary_Line","8","Year",2027),0) | I11: =IFERROR(GETPIVOTDATA("Baseline_Amount",Visual_Pivot_Income!$B$5,"Primary_Line","8","Year",2028),0) | J11: =IFERROR(GETPIVOTDATA("Baseline_Amount",Visual_Pivot_Income!$B$5,"Primary_Line","8","Year",Active_Year),0)
B12: VP_Line_12_Deduction | C12: Std/Item Ded (12) | D12: =IFERROR(GETPIVOTDATA("Baseline_Amount",Visual_Pivot_Income!$B$5,"Primary_Line","12","Year",2023),0) | E12: =IFERROR(GETPIVOTDATA("Baseline_Amount",Visual_Pivot_Income!$B$5,"Primary_Line","12","Year",2024),0) | F12: =IFERROR(GETPIVOTDATA("Baseline_Amount",Visual_Pivot_Income!$B$5,"Primary_Line","12","Year",2025),0) | G12: =IFERROR(GETPIVOTDATA("Baseline_Amount",Visual_Pivot_Income!$B$5,"Primary_Line","12","Year",2026),0) | H12: =IFERROR(GETPIVOTDATA("Baseline_Amount",Visual_Pivot_Income!$B$5,"Primary_Line","12","Year",2027),0) | I12: =IFERROR(GETPIVOTDATA("Baseline_Amount",Visual_Pivot_Income!$B$5,"Primary_Line","12","Year",2028),0) | J12: =IFERROR(GETPIVOTDATA("Baseline_Amount",Visual_Pivot_Income!$B$5,"Primary_Line","12","Year",Active_Year),0)
B13: VP_TotalIncome | C13: Grand Total | D13: =IFERROR(GETPIVOTDATA("Baseline_Amount",Visual_Pivot_Income!$B$5,"Year",2023),0) | E13: =IFERROR(GETPIVOTDATA("Baseline_Amount",Visual_Pivot_Income!$B$5,"Year",2024),0) | F13: =IFERROR(GETPIVOTDATA("Baseline_Amount",Visual_Pivot_Income!$B$5,"Year",2025),0) | G13: =IFERROR(GETPIVOTDATA("Baseline_Amount",Visual_Pivot_Income!$B$5,"Year",2026),0) | H13: =IFERROR(GETPIVOTDATA("Baseline_Amount",Visual_Pivot_Income!$B$5,"Year",2027),0) | I13: =IFERROR(GETPIVOTDATA("Baseline_Amount",Visual_Pivot_Income!$B$5,"Year",2028),0) | J13: =IFERROR(GETPIVOTDATA("Baseline_Amount",Visual_Pivot_Income!$B$5,"Year",Active_Year),0)
B15: HELPER CARVE-OUTS
B16: Named Range | C16: Description | D16: 2023 | E16: 2024 | F16: 2025 | G16: 2026 | H16: 2027 | I16: 2028 | J16: Active Year
B17: VP_OWNER_PAY | C17: Owner Wages | D17: =IFERROR(GETPIVOTDATA("Helper_Amount",Visual_Pivot_HelperCarveOuts!$B$5,"Helper_Treatment","OWNER_PAY","Year",2023),0) | E17: =IFERROR(GETPIVOTDATA("Helper_Amount",Visual_Pivot_HelperCarveOuts!$B$5,"Helper_Treatment","OWNER_PAY","Year",2024),0) | F17: =IFERROR(GETPIVOTDATA("Helper_Amount",Visual_Pivot_HelperCarveOuts!$B$5,"Helper_Treatment","OWNER_PAY","Year",2025),0) | G17: =IFERROR(GETPIVOTDATA("Helper_Amount",Visual_Pivot_HelperCarveOuts!$B$5,"Helper_Treatment","OWNER_PAY","Year",2026),0) | H17: =IFERROR(GETPIVOTDATA("Helper_Amount",Visual_Pivot_HelperCarveOuts!$B$5,"Helper_Treatment","OWNER_PAY","Year",2027),0) | I17: =IFERROR(GETPIVOTDATA("Helper_Amount",Visual_Pivot_HelperCarveOuts!$B$5,"Helper_Treatment","OWNER_PAY","Year",2028),0) | J17: =IFERROR(GETPIVOTDATA("Helper_Amount",Visual_Pivot_HelperCarveOuts!$B$5,"Helper_Treatment","OWNER_PAY","Year",Active_Year),0)
B18: VP_QUAL_DIV | C18: Qualified Dividends | D18: =IFERROR(GETPIVOTDATA("Helper_Amount",Visual_Pivot_HelperCarveOuts!$B$5,"Helper_Treatment","QUAL_DIV","Year",2023),0) | E18: =IFERROR(GETPIVOTDATA("Helper_Amount",Visual_Pivot_HelperCarveOuts!$B$5,"Helper_Treatment","QUAL_DIV","Year",2024),0) | F18: =IFERROR(GETPIVOTDATA("Helper_Amount",Visual_Pivot_HelperCarveOuts!$B$5,"Helper_Treatment","QUAL_DIV","Year",2025),0) | G18: =IFERROR(GETPIVOTDATA("Helper_Amount",Visual_Pivot_HelperCarveOuts!$B$5,"Helper_Treatment","QUAL_DIV","Year",2026),0) | H18: =IFERROR(GETPIVOTDATA("Helper_Amount",Visual_Pivot_HelperCarveOuts!$B$5,"Helper_Treatment","QUAL_DIV","Year",2027),0) | I18: =IFERROR(GETPIVOTDATA("Helper_Amount",Visual_Pivot_HelperCarveOuts!$B$5,"Helper_Treatment","QUAL_DIV","Year",2028),0) | J18: =IFERROR(GETPIVOTDATA("Helper_Amount",Visual_Pivot_HelperCarveOuts!$B$5,"Helper_Treatment","QUAL_DIV","Year",Active_Year),0)
B20: BUSINESS INCOME BY TREATMENT
B21: Named Range | C21: Description | D21: 2023 | E21: 2024 | F21: 2025 | G21: 2026 | H21: 2027 | I21: 2028 | J21: Active Year
B22: VP_BI_K1_SCorp_Active | C22: S-Corp K-1 Active | D22: =IFERROR(GETPIVOTDATA("Baseline_Amount",Visual_Pivot_BusinessIncome!$B$5,"Treatment_Profile","K1_SCorp_Active","Year",2023),0) | E22: =IFERROR(GETPIVOTDATA("Baseline_Amount",Visual_Pivot_BusinessIncome!$B$5,"Treatment_Profile","K1_SCorp_Active","Year",2024),0) | F22: =IFERROR(GETPIVOTDATA("Baseline_Amount",Visual_Pivot_BusinessIncome!$B$5,"Treatment_Profile","K1_SCorp_Active","Year",2025),0) | G22: =IFERROR(GETPIVOTDATA("Baseline_Amount",Visual_Pivot_BusinessIncome!$B$5,"Treatment_Profile","K1_SCorp_Active","Year",2026),0) | H22: =IFERROR(GETPIVOTDATA("Baseline_Amount",Visual_Pivot_BusinessIncome!$B$5,"Treatment_Profile","K1_SCorp_Active","Year",2027),0) | I22: =IFERROR(GETPIVOTDATA("Baseline_Amount",Visual_Pivot_BusinessIncome!$B$5,"Treatment_Profile","K1_SCorp_Active","Year",2028),0) | J22: =IFERROR(GETPIVOTDATA("Baseline_Amount",Visual_Pivot_BusinessIncome!$B$5,"Treatment_Profile","K1_SCorp_Active","Year",Active_Year),0)
B23: VP_BI_K1_PTP_Passive | C23: PTP K-1 Passive | D23: =IFERROR(GETPIVOTDATA("Baseline_Amount",Visual_Pivot_BusinessIncome!$B$5,"Treatment_Profile","K1_PTP_Passive","Year",2023),0) | E23: =IFERROR(GETPIVOTDATA("Baseline_Amount",Visual_Pivot_BusinessIncome!$B$5,"Treatment_Profile","K1_PTP_Passive","Year",2024),0) | F23: =IFERROR(GETPIVOTDATA("Baseline_Amount",Visual_Pivot_BusinessIncome!$B$5,"Treatment_Profile","K1_PTP_Passive","Year",2025),0) | G23: =IFERROR(GETPIVOTDATA("Baseline_Amount",Visual_Pivot_BusinessIncome!$B$5,"Treatment_Profile","K1_PTP_Passive","Year",2026),0) | H23: =IFERROR(GETPIVOTDATA("Baseline_Amount",Visual_Pivot_BusinessIncome!$B$5,"Treatment_Profile","K1_PTP_Passive","Year",2027),0) | I23: =IFERROR(GETPIVOTDATA("Baseline_Amount",Visual_Pivot_BusinessIncome!$B$5,"Treatment_Profile","K1_PTP_Passive","Year",2028),0) | J23: =IFERROR(GETPIVOTDATA("Baseline_Amount",Visual_Pivot_BusinessIncome!$B$5,"Treatment_Profile","K1_PTP_Passive","Year",Active_Year),0)
B24: VP_BI_SchE_Rental | C24: Sch E Rental | D24: =IFERROR(GETPIVOTDATA("Baseline_Amount",Visual_Pivot_BusinessIncome!$B$5,"Treatment_Profile","SchE_Rental","Year",2023),0) | E24: =IFERROR(GETPIVOTDATA("Baseline_Amount",Visual_Pivot_BusinessIncome!$B$5,"Treatment_Profile","SchE_Rental","Year",2024),0) | F24: =IFERROR(GETPIVOTDATA("Baseline_Amount",Visual_Pivot_BusinessIncome!$B$5,"Treatment_Profile","SchE_Rental","Year",2025),0) | G24: =IFERROR(GETPIVOTDATA("Baseline_Amount",Visual_Pivot_BusinessIncome!$B$5,"Treatment_Profile","SchE_Rental","Year",2026),0) | H24: =IFERROR(GETPIVOTDATA("Baseline_Amount",Visual_Pivot_BusinessIncome!$B$5,"Treatment_Profile","SchE_Rental","Year",2027),0) | I24: =IFERROR(GETPIVOTDATA("Baseline_Amount",Visual_Pivot_BusinessIncome!$B$5,"Treatment_Profile","SchE_Rental","Year",2028),0) | J24: =IFERROR(GETPIVOTDATA("Baseline_Amount",Visual_Pivot_BusinessIncome!$B$5,"Treatment_Profile","SchE_Rental","Year",Active_Year),0)
B25: VP_BI_Total | C25: Business Total | D25: =IFERROR(GETPIVOTDATA("Baseline_Amount",Visual_Pivot_BusinessIncome!$B$5,"Year",2023),0) | E25: =IFERROR(GETPIVOTDATA("Baseline_Amount",Visual_Pivot_BusinessIncome!$B$5,"Year",2024),0) | F25: =IFERROR(GETPIVOTDATA("Baseline_Amount",Visual_Pivot_BusinessIncome!$B$5,"Year",2025),0) | G25: =IFERROR(GETPIVOTDATA("Baseline_Amount",Visual_Pivot_BusinessIncome!$B$5,"Year",2026),0) | H25: =IFERROR(GETPIVOTDATA("Baseline_Amount",Visual_Pivot_BusinessIncome!$B$5,"Year",2027),0) | I25: =IFERROR(GETPIVOTDATA("Baseline_Amount",Visual_Pivot_BusinessIncome!$B$5,"Year",2028),0) | J25: =IFERROR(GETPIVOTDATA("Baseline_Amount",Visual_Pivot_BusinessIncome!$B$5,"Year",Active_Year),0)

Sheet Y2023
A1: Y2023 — standalone tax planning sandbox
A2: Strategies: enter Amount + Status below. Committed strategies flow to rollup M column. Push to Master_Inputs when final.
A4: ▸ STRATEGIES
A5: StrategyID | B5: Strategy Name | C5: TargetLine | D5: Amount | E5: Status | F5: Notes | G5: CounterLine | H5: Line | I5: Description | J5: Baseline (Master) | K5: PY? | L5: S1 Override | M5: Strategies | N5: Effective | O5: Eff w/ Strategies | P5: Drill
A6: STR-001 | B6: S-Corp Wage Optimization | C6: 1z | H6: 1z | I6: Wages | J6: =SUMIFS(tblMaster_Inputs[Baseline_Amount], tblMaster_Inputs[Year], 2023, tblMaster_Inputs[Primary_Line], $H6, tblMaster_Inputs[Activity_Type], "Baseline") | M6: =SUMIFS(tblY2023_Strategies[Amount],tblY2023_Strategies[TargetLine],$H6)-SUMIFS(tblY2023_Strategies[Amount],tblY2023_Strategies[CounterLine],$H6) | N6: =IF(UPPER(K6)="Y",SUMIFS(tblMaster_Inputs[Baseline_Amount],tblMaster_Inputs[Year],2022,tblMaster_Inputs[Primary_Line],"1z"),IF(ISBLANK(L6),J6,L6)) | O6: =N6+M6 | P6: =HYPERLINK("#Y2023!I49", "↗ drill")
A7: STR-002 | B7: HSA Family Max | C7: 10 | H7: 2a | I7: Tax-exempt interest (informational — Helper) | J7: =SUMIFS(tblMaster_Inputs[Helper_Amount], tblMaster_Inputs[Year], 2023, tblMaster_Inputs[Helper_Treatment], "TAX_EXEMPT") | M7: =SUMIFS(tblY2023_Strategies[Amount],tblY2023_Strategies[TargetLine],"2a",tblY2023_Strategies[Status],"Committed") | N7: =IF(UPPER(K7)="Y",SUMIFS(tblMaster_Inputs[Helper_Amount],tblMaster_Inputs[Year],2022,tblMaster_Inputs[Helper_Treatment],"TAX_EXEMPT"),IF(ISBLANK(L7),J7,L7)) | O7: =N7 | P7: =HYPERLINK("#Y2023!I49", "↗ drill")
A8: STR-003 | B8: Charitable Bunching (DAF) | C8: 12 | H8: 2b | I8: Taxable interest | J8: =SUMIFS(tblMaster_Inputs[Baseline_Amount], tblMaster_Inputs[Year], 2023, tblMaster_Inputs[Primary_Line], $H8, tblMaster_Inputs[Activity_Type], "Baseline") | M8: =SUMIFS(tblY2023_Strategies[Amount],tblY2023_Strategies[TargetLine],$H8)-SUMIFS(tblY2023_Strategies[Amount],tblY2023_Strategies[CounterLine],$H8) | N8: =IF(UPPER(K8)="Y",SUMIFS(tblMaster_Inputs[Baseline_Amount],tblMaster_Inputs[Year],2022,tblMaster_Inputs[Primary_Line],"2b"),IF(ISBLANK(L8),J8,L8)) | O8: =N8+M8 | P8: =HYPERLINK("#Y2023!I49", "↗ drill")
A9: STR-004 | B9: SEP-IRA / Solo 401(k) | C9: 10 | H9: 3a | I9: Qualified dividends (informational — Helper) | J9: =SUMIFS(tblMaster_Inputs[Helper_Amount], tblMaster_Inputs[Year], 2023, tblMaster_Inputs[Helper_Treatment], "QUAL_DIV") | M9: =SUMIFS(tblY2023_Strategies[Amount],tblY2023_Strategies[TargetLine],"3a",tblY2023_Strategies[Status],"Committed") | N9: =IF(UPPER(K9)="Y",SUMIFS(tblMaster_Inputs[Helper_Amount],tblMaster_Inputs[Year],2022,tblMaster_Inputs[Helper_Treatment],"QUAL_DIV"),IF(ISBLANK(L9),J9,L9)) | O9: =N9 | P9: =HYPERLINK("#Y2023!I49", "↗ drill")
A10: STR-005 | B10: Cost Seg Study | C10: 8 | H10: 3b | I10: Ordinary dividends (total — incl qualified) | J10: =SUMIFS(tblMaster_Inputs[Baseline_Amount], tblMaster_Inputs[Year], 2023, tblMaster_Inputs[Primary_Line], $H10, tblMaster_Inputs[Activity_Type], "Baseline") | M10: =SUMIFS(tblY2023_Strategies[Amount],tblY2023_Strategies[TargetLine],$H10)-SUMIFS(tblY2023_Strategies[Amount],tblY2023_Strategies[CounterLine],$H10) | N10: =IF(UPPER(K10)="Y",SUMIFS(tblMaster_Inputs[Baseline_Amount],tblMaster_Inputs[Year],2022,tblMaster_Inputs[Primary_Line],"3b"),IF(ISBLANK(L10),J10,L10)) | O10: =N10+M10 | P10: =HYPERLINK("#Y2023!I49", "↗ drill")
A11: STR-006 | B11: Roth Conversion | C11: 1z | H11: 7 | I11: Capital gain or (loss) | J11: =SUMIFS(tblMaster_Inputs[Baseline_Amount], tblMaster_Inputs[Year], 2023, tblMaster_Inputs[Primary_Line], $H11, tblMaster_Inputs[Activity_Type], "Baseline") | M11: =SUMIFS(tblY2023_Strategies[Amount],tblY2023_Strategies[TargetLine],$H11)-SUMIFS(tblY2023_Strategies[Amount],tblY2023_Strategies[CounterLine],$H11) | N11: =IF(UPPER(K11)="Y",SUMIFS(tblMaster_Inputs[Baseline_Amount],tblMaster_Inputs[Year],2022,tblMaster_Inputs[Primary_Line],"7"),IF(ISBLANK(L11),J11,L11)) | O11: =N11+M11 | P11: =HYPERLINK("#Y2023!I49", "↗ drill")
A12: STR-007 | B12: Augusta Rule (§280A) | C12: 8 | H12: 8 | I12: Other income (incl business income via Sch 1) | J12: =SUMIFS(tblMaster_Inputs[Baseline_Amount], tblMaster_Inputs[Year], 2023, tblMaster_Inputs[Primary_Line], $H12, tblMaster_Inputs[Activity_Type], "Baseline") | M12: =SUMIFS(tblY2023_Strategies[Amount],tblY2023_Strategies[TargetLine],$H12)-SUMIFS(tblY2023_Strategies[Amount],tblY2023_Strategies[CounterLine],$H12) | N12: =IF(UPPER(K12)="Y",SUMIFS(tblMaster_Inputs[Baseline_Amount],tblMaster_Inputs[Year],2022,tblMaster_Inputs[Primary_Line],"8"),IF(ISBLANK(L12),J12,L12)) | O12: =N12+M12 | P12: =HYPERLINK("#Y2023!I49", "↗ drill")
A13: STR-008 | B13: Accountable Plan | C13: 8 | H13: 9 | I13: TOTAL INCOME | J13: =J6+J8+J10+J11+J12 | M13: =M6+M8+M10+M11+M12 | N13: =N6+N8+N10+N11+N12 | O13: =O6+O8+O10+O11+O12 | P13: =HYPERLINK("#Y2023!I49", "↗ drill")
A14: STR-009 | B14: Hire Children | C14: 8 | H14: 10 | I14: Adjustments to income | J14: =SUMIFS(tblMaster_Inputs[Baseline_Amount], tblMaster_Inputs[Year], 2023, tblMaster_Inputs[Primary_Line], $H14, tblMaster_Inputs[Activity_Type], "Baseline") | M14: =SUMIFS(tblY2023_Strategies[Amount],tblY2023_Strategies[TargetLine],$H14)-SUMIFS(tblY2023_Strategies[Amount],tblY2023_Strategies[CounterLine],$H14) | N14: =IF(UPPER(K14)="Y",SUMIFS(tblMaster_Inputs[Baseline_Amount],tblMaster_Inputs[Year],2022,tblMaster_Inputs[Primary_Line],"10"),IF(ISBLANK(L14),J14,L14)) | O14: =N14+M14 | P14: =HYPERLINK("#Y2023!I49", "↗ drill")
A15: STR-010 | B15: Entity Restructuring | C15: 8 | H15: 11 | I15: AGI | J15: =J13+J14 | M15: =M13+M14 | N15: =N13+N14 | O15: =O13+O14 | P15: =HYPERLINK("#Y2023!I49", "↗ drill")
A16: STR-011 | B16: Installment Sale / 1031 | C16: 7 | H16: 12 | I16: Std/Itemized deduction | J16: =SUMIFS(tblMaster_Inputs[Baseline_Amount], tblMaster_Inputs[Year], 2023, tblMaster_Inputs[Primary_Line], $H16, tblMaster_Inputs[Activity_Type], "Baseline") | M16: =SUMIFS(tblY2023_Strategies[Amount],tblY2023_Strategies[TargetLine],$H16)-SUMIFS(tblY2023_Strategies[Amount],tblY2023_Strategies[CounterLine],$H16) | N16: =IF(UPPER(K16)="Y",SUMIFS(tblMaster_Inputs[Baseline_Amount],tblMaster_Inputs[Year],2022,tblMaster_Inputs[Primary_Line],"12"),IF(ISBLANK(L16),J16,L16)) | O16: =N16+M16 | P16: =HYPERLINK("#Y2023!I49", "↗ drill")
A17: STR-012 | B17: Bonus Depreciation §168(k) | C17: 8 | H17: 13 | I17: QBI deduction | J17: =SUMIFS(tblMaster_Inputs[Baseline_Amount], tblMaster_Inputs[Year], 2023, tblMaster_Inputs[Primary_Line], $H17, tblMaster_Inputs[Activity_Type], "Baseline") | M17: =SUMIFS(tblY2023_Strategies[Amount],tblY2023_Strategies[TargetLine],$H17)-SUMIFS(tblY2023_Strategies[Amount],tblY2023_Strategies[CounterLine],$H17) | N17: =IF(UPPER(K17)="Y",SUMIFS(tblMaster_Inputs[Baseline_Amount],tblMaster_Inputs[Year],2022,tblMaster_Inputs[Primary_Line],"13"),IF(ISBLANK(L17),J17,L17)) | O17: =N17+M17 | P17: =HYPERLINK("#Y2023!I49", "↗ drill")
A18: STR-013 | B18: R&D Credit §41 | C18: 13 | H18: 15 | I18: TAXABLE INCOME | J18: =J15+J16+J17 | M18: =M15+M16+M17 | N18: =N15+N16+N17 | O18: =O15+O16+O17 | P18: =HYPERLINK("#Y2023!I49", "↗ drill")
A19: STR-014 | B19: SALT PTE Election | C19: 12
A20: STR-015 | B20: Timing / Deferral | C20: 8
A22: ▸ TAX IMPACT SUMMARY | H22: Description | I22: Amount | J22: Effective | K22: Used by
A23: Metric | B23: Baseline | C23: Effective | D23: Eff w/ Strat | E23: Savings | H23: Owner W-2 wages | I23: =SUMIFS(tblMaster_Inputs[Baseline_Amount], tblMaster_Inputs[Year], 2023, tblMaster_Inputs[Treatment_Profile], "W2_SCorpOwner", tblMaster_Inputs[Activity_Type], "Baseline") | J23: =I23+SUMIFS(tblY2023_Strategies[Amount],tblY2023_Strategies[TargetLine],"1z")-SUMIFS(tblY2023_Strategies[Amount],tblY2023_Strategies[CounterLine],"1z") | K23: FICA/Employee
A24: Total Income | B24: =J13 | C24: =N13 | D24: =O13 | E24: =B24-D24 | H24: Third-party W-2 wages | I24: =SUMIFS(tblMaster_Inputs[Baseline_Amount], tblMaster_Inputs[Year], 2023, tblMaster_Inputs[Treatment_Profile], "W2_Employee", tblMaster_Inputs[Activity_Type], "Baseline") | J24: =I24 | K24: SE Tax sharing
A25: Taxable Income | B25: =J18 | C25: =N18 | D25: =O18 | E25: =B25-D25 | H25: Total W-2 wages | I25: =I23+I24 | J25: =J23+J24 | K25: SE Tax sharing
A26: Total Tax | B26: =I133 | C26: =I133 | D26: =J133 | E26: =B26-D26 | H26: Business income subject to SE | I26: =SUMIFS(tblMaster_Inputs[Baseline_Amount], tblMaster_Inputs[Year], 2023, tblMaster_Inputs[Bucket], "Business Income", tblMaster_Inputs[SE_Subject], "Yes", tblMaster_Inputs[Activity_Type], "Baseline") | J26: =I26 | K26: SE Tax base
A27: Effective Rate | B27: =I134 | C27: =I134 | D27: =J134 | E27: =B27-D27 | H27: Active business income NOT SE | I27: =SUMIFS(tblMaster_Inputs[Baseline_Amount], tblMaster_Inputs[Year], 2023, tblMaster_Inputs[Bucket], "Business Income", tblMaster_Inputs[SE_Subject], "No", tblMaster_Inputs[NIIT_Class], "Active", tblMaster_Inputs[Activity_Type], "Baseline") | J27: =I27+SUMIFS(tblY2023_Strategies[Amount],tblY2023_Strategies[TargetLine],"8")-SUMIFS(tblY2023_Strategies[Amount],tblY2023_Strategies[CounterLine],"8") | K27: NIIT/QBI
A28: Committed Strategies | B28: =COUNTIF(tblY2023_Strategies[Status],"Committed") | C28: Net Strategy Impact | D28: =SUMIF(tblY2023_Strategies[Status],"Committed",tblY2023_Strategies[Amount]) | H28: Passive business income/loss | I28: =SUMIFS(tblMaster_Inputs[Baseline_Amount], tblMaster_Inputs[Year], 2023, tblMaster_Inputs[Bucket], "Business Income", tblMaster_Inputs[NIIT_Class], "Passive", tblMaster_Inputs[Activity_Type], "Baseline") | J28: =I28 | K28: Passive Loss/NIIT
H29: Tax-exempt interest | I29: =SUMIFS(tblMaster_Inputs[Helper_Amount], tblMaster_Inputs[Year], 2023, tblMaster_Inputs[Helper_Treatment], "TAX_EXEMPT") | J29: =I29+SUMIFS(tblY2023_Strategies[Amount],tblY2023_Strategies[TargetLine],"2a")-SUMIFS(tblY2023_Strategies[Amount],tblY2023_Strategies[CounterLine],"2a") | K29: MAGI
H30: Qualified dividends carve-out | I30: =SUMIFS(tblMaster_Inputs[Helper_Amount], tblMaster_Inputs[Year], 2023, tblMaster_Inputs[Helper_Treatment], "QUAL_DIV", tblMaster_Inputs[Activity_Type], "Baseline") | J30: =I30 | K30: LTCG stacking
H31: Long-term capital gains | I31: =SUMIFS(tblMaster_Inputs[Baseline_Amount], tblMaster_Inputs[Year], 2023, tblMaster_Inputs[Treatment_Profile], "LTCG_Stock") + SUMIFS(tblMaster_Inputs[Baseline_Amount], tblMaster_Inputs[Year], 2023, tblMaster_Inputs[Treatment_Profile], "LTCG_RE") + SUMIFS(tblMaster_Inputs[Baseline_Amount], tblMaster_Inputs[Year], 2023, tblMaster_Inputs[Treatment_Profile], "LTCG_K1_Passthrough") + SUMIFS(tblMaster_Inputs[Baseline_Amount], tblMaster_Inputs[Year], 2023, tblMaster_Inputs[Treatment_Profile], "Sec1250_Recap", tblMaster_Inputs[Activity_Type], "Baseline") | J31: =I31+SUMIFS(tblY2023_Strategies[Amount],tblY2023_Strategies[TargetLine],"7")-SUMIFS(tblY2023_Strategies[Amount],tblY2023_Strategies[CounterLine],"7") | K31: Cap Gains Tax
H32: Short-term capital gains | I32: =SUMIFS(tblMaster_Inputs[Baseline_Amount], tblMaster_Inputs[Year], 2023, tblMaster_Inputs[Treatment_Profile], "STCG_Stock", tblMaster_Inputs[Activity_Type], "Baseline") | J32: =I32 | K32: Ordinary Tax
H33: §1250 unrecaptured gain | I33: =SUMIFS(tblMaster_Inputs[Helper_Amount], tblMaster_Inputs[Year], 2023, tblMaster_Inputs[Helper_Treatment], "SEC1250", tblMaster_Inputs[Activity_Type], "Baseline") | J33: =I33 | K33: 1250 Tax
H36: Description | I36: Value | J36: Effective | K36: Used by
H37: TI - LTCG - QUAL_DIV - SEC1250 | I37: =J18-I31-I30-I33 | J37: =O18-J31-J30-J33 | K37: Ordinary Tax
H38: AGI + tax-exempt interest | I38: =J15+I29 | J38: =O15+J29 | K38: NIIT
H39: Net investment income | I39: =J8+J10+J11+I28 | J39: =O8+O10+O11+J28 | K39: NIIT
H40: QBI-eligible business income | I40: =I26+I27 | J40: =J26+J27 | K40: QBI
H41: TI before QBI deduction | I41: =J15+J16 | J41: =O15+O16 | K41: QBI cap
H42: Net business loss | I42: =MIN(0,I26+I27+I28) | J42: =MIN(0,J26+J27+J28) | K42: EBL
H43: Net SE income | I43: =I26 | J43: =J26 | K43: SE Tax
J44: =I44
I45: =IF(Control_Panel!C21="Yes",TRUE,FALSE) | J45: =I45
I46: =Carryovers!F52 | J46: =I46
H49: 1z | K49: =HYPERLINK("#Master_Inputs!A1", "✏ open Master_Inputs to edit")
H51: Bucket | I51: Treatment_Profile | K51: Payor | L51: Baseline_Amount | M51: Helper_Amount | N51: Notes
H65: ▸ 7-COMPONENT TAX CALCULATOR | I65: Baseline | J65: Effective | K65: Δ Savings
H66: Dual columns: Baseline (H) vs With Planning (I)
H68: 1. SELF-EMPLOYMENT TAX
H69: SE Tax Label
H70: Net SE Earnings | I70: =I43 | J70: =J43
H71: SE Base (× 0.9235) | I71: =I70*SUMIFS(tblThresholds[Value], tblThresholds[Year], 2023, tblThresholds[FilingStatus], Filing_Status, tblThresholds[Item], "SE_Earnings_Factor") | J71: =J70*SUMIFS(tblThresholds[Value], tblThresholds[Year], 2023, tblThresholds[FilingStatus], Filing_Status, tblThresholds[Item], "SE_Earnings_Factor")
H72: W-2 Wages | I72: =I25 | J72: =J25
H73: Remaining SS Wage Base | I73: =MAX(0,SUMIFS(tblThresholds[Value], tblThresholds[Year], 2023, tblThresholds[FilingStatus], Filing_Status, tblThresholds[Item], "SS_Wage_Base")-I72) | J73: =MAX(0,SUMIFS(tblThresholds[Value], tblThresholds[Year], 2023, tblThresholds[FilingStatus], Filing_Status, tblThresholds[Item], "SS_Wage_Base")-J72)
I74: =MIN(I71,I73) | J74: =MIN(J71,J73)
H75: Social Security Tax (12.4%) | I75: =I74*SUMIFS(tblThresholds[Value], tblThresholds[Year], 2023, tblThresholds[FilingStatus], Filing_Status, tblThresholds[Item], "SS_Rate_Combined") | J75: =J74*SUMIFS(tblThresholds[Value], tblThresholds[Year], 2023, tblThresholds[FilingStatus], Filing_Status, tblThresholds[Item], "SS_Rate_Combined")
H76: Medicare Tax (2.9%) | I76: =I71*SUMIFS(tblThresholds[Value], tblThresholds[Year], 2023, tblThresholds[FilingStatus], Filing_Status, tblThresholds[Item], "Medicare_Rate_Combined") | J76: =J71*SUMIFS(tblThresholds[Value], tblThresholds[Year], 2023, tblThresholds[FilingStatus], Filing_Status, tblThresholds[Item], "Medicare_Rate_Combined")
H77: Addl Medicare (0.9% > threshold) | I77: =MAX(0,(I72+I71-SUMIFS(tblThresholds[Value], tblThresholds[Year], 2023, tblThresholds[FilingStatus], Filing_Status, tblThresholds[Item], "Addl_Medicare_Threshold"))*SUMIFS(tblThresholds[Value], tblThresholds[Year], 2023, tblThresholds[FilingStatus], Filing_Status, tblThresholds[Item], "Addl_Medicare_Rate")) | J77: =MAX(0,(J72+J71-SUMIFS(tblThresholds[Value], tblThresholds[Year], 2023, tblThresholds[FilingStatus], Filing_Status, tblThresholds[Item], "Addl_Medicare_Threshold"))*SUMIFS(tblThresholds[Value], tblThresholds[Year], 2023, tblThresholds[FilingStatus], Filing_Status, tblThresholds[Item], "Addl_Medicare_Rate"))
I78: =-(I75+I76)/2 | J78: =-(J75+J76)/2
H80: TOTAL SE TAX | I80: =I75+I76+I77 | J80: =J75+J76+J77 | K80: =I80-J80
H82: 2. PAYROLL TAX
H83: W-2 Wages | I83: =I25 | J83: =J25
H84: Social Security (6.2%) | I84: =MIN(I83,SUMIFS(tblThresholds[Value], tblThresholds[Year], 2023, tblThresholds[FilingStatus], Filing_Status, tblThresholds[Item], "SS_Wage_Base"))*0.062 | J84: =MIN(J83,SUMIFS(tblThresholds[Value], tblThresholds[Year], 2023, tblThresholds[FilingStatus], Filing_Status, tblThresholds[Item], "SS_Wage_Base"))*0.062
H85: Medicare (1.45%) | I85: =I83*0.0145 | J85: =J83*0.0145
H86: Addl Medicare (0.9% > threshold) | I86: =MAX(0,(I83-SUMIFS(tblThresholds[Value], tblThresholds[Year], 2023, tblThresholds[FilingStatus], Filing_Status, tblThresholds[Item], "Addl_Medicare_Threshold"))*SUMIFS(tblThresholds[Value], tblThresholds[Year], 2023, tblThresholds[FilingStatus], Filing_Status, tblThresholds[Item], "Addl_Medicare_Rate")) | J86: =MAX(0,(J83-SUMIFS(tblThresholds[Value], tblThresholds[Year], 2023, tblThresholds[FilingStatus], Filing_Status, tblThresholds[Item], "Addl_Medicare_Threshold"))*SUMIFS(tblThresholds[Value], tblThresholds[Year], 2023, tblThresholds[FilingStatus], Filing_Status, tblThresholds[Item], "Addl_Medicare_Rate"))
H87: TOTAL PAYROLL TAX | I87: =I84+I85+I86 | J87: =J84+J85+J86 | K87: =I87-J87
H88: Employer Social Security (6.2%) | I88: =I84 | J88: =J84 | K88: =I88-J88
H89: Employer Medicare (1.45%) | I89: =I85 | J89: =J85 | K89: =I89-J89
H91: TOTAL PAYROLL TAX (Employee + Employer) | I91: =I87+I88+I89 | J91: =J87+J88+J89 | K91: =I91-J91
H93: 3. ORDINARY INCOME TAX
H94: Taxable Income | I94: =I37 | J94: =J37
H95: Ordinary Taxable (TI - LTCG - QD) | I95: =MAX(0,I94) | J95: =MAX(0,J94)
H96: Tax (SUMPRODUCT bracket lookup) | I96: {=SUMPRODUCT((tblBrackets_FIT[Year]=2023)*(tblBrackets_FIT[FilingStatus]=Filing_Status)*((I95>tblBrackets_FIT[Upper])*(tblBrackets_FIT[Upper]-tblBrackets_FIT[Lower])+(I95>tblBrackets_FIT[Lower])*(I95<=tblBrackets_FIT[Upper])*(I95-tblBrackets_FIT[Lower]))*tblBrackets_FIT[Rate])} | J96: {=SUMPRODUCT((tblBrackets_FIT[Year]=2023)*(tblBrackets_FIT[FilingStatus]=Filing_Status)*((J95>tblBrackets_FIT[Upper])*(tblBrackets_FIT[Upper]-tblBrackets_FIT[Lower])+(J95>tblBrackets_FIT[Lower])*(J95<=tblBrackets_FIT[Upper])*(J95-tblBrackets_FIT[Lower]))*tblBrackets_FIT[Rate])}
H97: TOTAL ORDINARY TAX | I97: =I96 | J97: =J96 | K97: =I97-J97
H99: 4. CAPITAL GAINS / QUALIFIED DIVIDENDS TAX
H100: LTCG + Qualified Dividends | I100: =I31+I30 | J100: =J31+J30
H101: Sec 1250 Recapture Gain | I101: =I33 | J101: =J33
H102: Stacking Base (Ordinary TI for bracket floor) | I102: =I95 | J102: =J95
H103: Full CG Rate Tax (SUMPRODUCT stack) | I103: {=SUMPRODUCT((Tax_Ref!$B$210:$B$281=2023)*(Tax_Ref!$C$210:$C$281=Filing_Status)*((I102+I100>Tax_Ref!$E$210:$E$281)*(Tax_Ref!$E$210:$E$281-Tax_Ref!$D$210:$D$281)+(I102+I100>Tax_Ref!$D$210:$D$281)*(I102+I100<=Tax_Ref!$E$210:$E$281)*(I102+I100-Tax_Ref!$D$210:$D$281))*Tax_Ref!$F$210:$F$281)} | J103: {=SUMPRODUCT((Tax_Ref!$B$210:$B$281=2023)*(Tax_Ref!$C$210:$C$281=Filing_Status)*((J102+J100>Tax_Ref!$E$210:$E$281)*(Tax_Ref!$E$210:$E$281-Tax_Ref!$D$210:$D$281)+(J102+J100>Tax_Ref!$D$210:$D$281)*(J102+J100<=Tax_Ref!$E$210:$E$281)*(J102+J100-Tax_Ref!$D$210:$D$281))*Tax_Ref!$F$210:$F$281)}
H104: CG Rate Tax on Ordinary only | I104: {=SUMPRODUCT((Tax_Ref!$B$210:$B$281=2023)*(Tax_Ref!$C$210:$C$281=Filing_Status)*((I102>Tax_Ref!$E$210:$E$281)*(Tax_Ref!$E$210:$E$281-Tax_Ref!$D$210:$D$281)+(I102>Tax_Ref!$D$210:$D$281)*(I102<=Tax_Ref!$E$210:$E$281)*(I102-Tax_Ref!$D$210:$D$281))*Tax_Ref!$F$210:$F$281)} | J104: {=SUMPRODUCT((Tax_Ref!$B$210:$B$281=2023)*(Tax_Ref!$C$210:$C$281=Filing_Status)*((J102>Tax_Ref!$E$210:$E$281)*(Tax_Ref!$E$210:$E$281-Tax_Ref!$D$210:$D$281)+(J102>Tax_Ref!$D$210:$D$281)*(J102<=Tax_Ref!$E$210:$E$281)*(J102-Tax_Ref!$D$210:$D$281))*Tax_Ref!$F$210:$F$281)}
H105: Net LTCG/QD Tax | I105: =I103-I104 | J105: =J103-J104
I106: =I33*0.25 | J106: =J33*0.25
H107: TOTAL CAP GAINS TAX | I107: =I105+I106 | J107: =J105+J106 | K107: =I107-J107
H109: 5. NET INVESTMENT INCOME TAX (NIIT)
H110: MAGI | I110: =I38 | J110: =J38
H111: NIIT Threshold | I111: =SUMIFS(tblThresholds[Value], tblThresholds[Year], 2023, tblThresholds[FilingStatus], Filing_Status, tblThresholds[Item], "NIIT_Threshold") | J111: =SUMIFS(tblThresholds[Value], tblThresholds[Year], 2023, tblThresholds[FilingStatus], Filing_Status, tblThresholds[Item], "NIIT_Threshold")
H112: Net Investment Income (NII) | I112: =MAX(0,I39) | J112: =MAX(0,J39)
H113: NIIT Base (lesser of NII or MAGI excess) | I113: =MAX(0,I110-I111) | J113: =MAX(0,J110-J111)
H114: NIIT (3.8%) | I114: =MIN(I112,I113)*SUMIFS(tblThresholds[Value], tblThresholds[Year], 2023, tblThresholds[FilingStatus], Filing_Status, tblThresholds[Item], "NIIT_Rate") | J114: =MIN(J112,J113)*SUMIFS(tblThresholds[Value], tblThresholds[Year], 2023, tblThresholds[FilingStatus], Filing_Status, tblThresholds[Item], "NIIT_Rate") | K114: =I114-J114
H116: 6. QBI DEDUCTION (§199A)
H117: QBI-Eligible Income | I117: =I40 | J117: =J40
H118: 20% of QBI | I118: =MAX(0,I117)*0.2 | J118: =MAX(0,J117)*0.2
H119: 50% of W-2 Wages | I119: =MAX(0,I41)*0.2 | J119: =MAX(0,J41)*0.2
H120: 25% W-2 + 2.5% UBIA | I120: =MAX(I23*0.5, I23*0.25+I44*0.025) | J120: =MAX(J23*0.5, J23*0.25+J44*0.025)
H121: Phase-in applies? | I121: =IF(I41>SUMIFS(tblThresholds[Value], tblThresholds[Year], 2023, tblThresholds[FilingStatus], Filing_Status, tblThresholds[Item], "QBI_Threshold_Start"),"YES","NO") | J121: =IF(J41>SUMIFS(tblThresholds[Value], tblThresholds[Year], 2023, tblThresholds[FilingStatus], Filing_Status, tblThresholds[Item], "QBI_Threshold_Start"),"YES","NO")
H122: QBI DEDUCTION | I122: =IF(AND(I45=TRUE,I41>SUMIFS(tblThresholds[Value], tblThresholds[Year], 2023, tblThresholds[FilingStatus], Filing_Status, tblThresholds[Item], "QBI_Threshold_End")),0,IF(I41<=SUMIFS(tblThresholds[Value], tblThresholds[Year], 2023, tblThresholds[FilingStatus], Filing_Status, tblThresholds[Item], "QBI_Threshold_Start"),MIN(I118,I119),MIN(I118,I119,I120))) | J122: =IF(AND(J45=TRUE,J41>SUMIFS(tblThresholds[Value], tblThresholds[Year], 2023, tblThresholds[FilingStatus], Filing_Status, tblThresholds[Item], "QBI_Threshold_End")),0,IF(J41<=SUMIFS(tblThresholds[Value], tblThresholds[Year], 2023, tblThresholds[FilingStatus], Filing_Status, tblThresholds[Item], "QBI_Threshold_Start"),MIN(J118,J119),MIN(J118,J119,J120))) | K122: =J122-I122
H124: 7. COMBINED TAX SUMMARY
H125: Total Income | I125: =J6+J8+J10+J11+J12 | J125: =O13 | K125: Δ Savings
H126: Ordinary Tax | I126: =I97 | J126: =J97 | K126: =I126-J126
H127: Capital Gains Tax | I127: =I107 | J127: =J107 | K127: =I127-J127
H128: Self-Employment Tax | I128: =I80 | J128: =J80 | K128: =I128-J128
H129: Payroll Tax (Employee + Employer) | I129: =I91 | J129: =J91 | K129: =I129-J129
...

Sheet Y2024
A1: Y2024 — standalone tax planning sandbox
A2: Strategies: enter Amount + Status below. Committed strategies flow to rollup M column. Push to Master_Inputs when final.
A4: ▸ STRATEGIES
A5: StrategyID | B5: Strategy Name | C5: TargetLine | D5: Amount | E5: Status | F5: Notes | G5: CounterLine | H5: Line | I5: Description | J5: Baseline (Master) | K5: PY? | L5: S1 Override | M5: Strategies | N5: Effective | O5: Eff w/ Strategies | P5: Drill
A6: STR-001 | B6: S-Corp Wage Optimization | C6: 1z | H6: 1z | I6: Wages | J6: =SUMIFS(tblMaster_Inputs[Baseline_Amount],tblMaster_Inputs[Year],2024,tblMaster_Inputs[Primary_Line],$H6, tblMaster_Inputs[Activity_Type], "Baseline") | M6: =SUMIFS(tblY2024_Strategies[Amount],tblY2024_Strategies[TargetLine],$H6)-SUMIFS(tblY2024_Strategies[Amount],tblY2024_Strategies[CounterLine],$H6) | N6: =IF(UPPER(K6)="Y",SUMIFS(tblMaster_Inputs[Baseline_Amount],tblMaster_Inputs[Year],2023,tblMaster_Inputs[Primary_Line],"1z"),IF(ISBLANK(L6),J6,L6)) | O6: =N6+M6 | P6: =HYPERLINK("#Y2024!I49", "↗ drill")
A7: STR-002 | B7: HSA Family Max | C7: 10 | H7: 2a | I7: Tax-exempt interest (Helper) | J7: =SUMIFS(tblMaster_Inputs[Helper_Amount],tblMaster_Inputs[Year],2024,tblMaster_Inputs[Helper_Treatment],"TAX_EXEMPT") | M7: =SUMIFS(tblY2024_Strategies[Amount],tblY2024_Strategies[TargetLine],"2a",tblY2024_Strategies[Status],"Committed") | N7: =IF(UPPER(K7)="Y",SUMIFS(tblMaster_Inputs[Helper_Amount],tblMaster_Inputs[Year],2023,tblMaster_Inputs[Helper_Treatment],"TAX_EXEMPT"),IF(ISBLANK(L7),J7,L7)) | O7: =N7 | P7: =HYPERLINK("#Y2024!I49", "↗ drill")
A8: STR-003 | B8: Charitable Bunching (DAF) | C8: 12 | H8: 2b | I8: Taxable interest | J8: =SUMIFS(tblMaster_Inputs[Baseline_Amount],tblMaster_Inputs[Year],2024,tblMaster_Inputs[Primary_Line],$H8, tblMaster_Inputs[Activity_Type], "Baseline") | M8: =SUMIFS(tblY2024_Strategies[Amount],tblY2024_Strategies[TargetLine],$H8)-SUMIFS(tblY2024_Strategies[Amount],tblY2024_Strategies[CounterLine],$H8) | N8: =IF(UPPER(K8)="Y",SUMIFS(tblMaster_Inputs[Baseline_Amount],tblMaster_Inputs[Year],2023,tblMaster_Inputs[Primary_Line],"2b"),IF(ISBLANK(L8),J8,L8)) | O8: =N8+M8 | P8: =HYPERLINK("#Y2024!I49", "↗ drill")
A9: STR-004 | B9: SEP-IRA / Solo 401(k) | C9: 10 | H9: 3a | I9: Qualified dividends (Helper) | J9: =SUMIFS(tblMaster_Inputs[Helper_Amount],tblMaster_Inputs[Year],2024,tblMaster_Inputs[Helper_Treatment],"QUAL_DIV") | M9: =SUMIFS(tblY2024_Strategies[Amount],tblY2024_Strategies[TargetLine],"3a",tblY2024_Strategies[Status],"Committed") | N9: =IF(UPPER(K9)="Y",SUMIFS(tblMaster_Inputs[Helper_Amount],tblMaster_Inputs[Year],2023,tblMaster_Inputs[Helper_Treatment],"QUAL_DIV"),IF(ISBLANK(L9),J9,L9)) | O9: =N9 | P9: =HYPERLINK("#Y2024!I49", "↗ drill")
A10: STR-005 | B10: Cost Seg Study | C10: 8 | H10: 3b | I10: Ordinary dividends | J10: =SUMIFS(tblMaster_Inputs[Baseline_Amount],tblMaster_Inputs[Year],2024,tblMaster_Inputs[Primary_Line],$H10, tblMaster_Inputs[Activity_Type], "Baseline") | M10: =SUMIFS(tblY2024_Strategies[Amount],tblY2024_Strategies[TargetLine],$H10)-SUMIFS(tblY2024_Strategies[Amount],tblY2024_Strategies[CounterLine],$H10) | N10: =IF(UPPER(K10)="Y",SUMIFS(tblMaster_Inputs[Baseline_Amount],tblMaster_Inputs[Year],2023,tblMaster_Inputs[Primary_Line],"3b"),IF(ISBLANK(L10),J10,L10)) | O10: =N10+M10 | P10: =HYPERLINK("#Y2024!I49", "↗ drill")
A11: STR-006 | B11: Roth Conversion | C11: 1z | H11: 7 | I11: Capital gain or (loss) | J11: =SUMIFS(tblMaster_Inputs[Baseline_Amount],tblMaster_Inputs[Year],2024,tblMaster_Inputs[Primary_Line],$H11, tblMaster_Inputs[Activity_Type], "Baseline") | M11: =SUMIFS(tblY2024_Strategies[Amount],tblY2024_Strategies[TargetLine],$H11)-SUMIFS(tblY2024_Strategies[Amount],tblY2024_Strategies[CounterLine],$H11) | N11: =IF(UPPER(K11)="Y",SUMIFS(tblMaster_Inputs[Baseline_Amount],tblMaster_Inputs[Year],2023,tblMaster_Inputs[Primary_Line],"7"),IF(ISBLANK(L11),J11,L11)) | O11: =N11+M11 | P11: =HYPERLINK("#Y2024!I49", "↗ drill")
A12: STR-007 | B12: Augusta Rule (§280A) | C12: 8 | H12: 8 | I12: Other income (business via Sch 1) | J12: =SUMIFS(tblMaster_Inputs[Baseline_Amount],tblMaster_Inputs[Year],2024,tblMaster_Inputs[Primary_Line],$H12, tblMaster_Inputs[Activity_Type], "Baseline") | M12: =SUMIFS(tblY2024_Strategies[Amount],tblY2024_Strategies[TargetLine],$H12)-SUMIFS(tblY2024_Strategies[Amount],tblY2024_Strategies[CounterLine],$H12) | N12: =IF(UPPER(K12)="Y",SUMIFS(tblMaster_Inputs[Baseline_Amount],tblMaster_Inputs[Year],2023,tblMaster_Inputs[Primary_Line],"8"),IF(ISBLANK(L12),J12,L12)) | O12: =N12+M12 | P12: =HYPERLINK("#Y2024!I49", "↗ drill")
A13: STR-008 | B13: Accountable Plan | C13: 8 | H13: 9 | I13: TOTAL INCOME | J13: =J6+J8+J10+J11+J12 | M13: =M6+M8+M10+M11+M12 | N13: =N6+N8+N10+N11+N12 | O13: =O6+O8+O10+O11+O12 | P13: =HYPERLINK("#Y2024!I49", "↗ drill")
A14: STR-009 | B14: Hire Children | C14: 8 | H14: 10 | I14: Adjustments to income | J14: =SUMIFS(tblMaster_Inputs[Baseline_Amount],tblMaster_Inputs[Year],2024,tblMaster_Inputs[Primary_Line],$H14, tblMaster_Inputs[Activity_Type], "Baseline") | M14: =SUMIFS(tblY2024_Strategies[Amount],tblY2024_Strategies[TargetLine],$H14)-SUMIFS(tblY2024_Strategies[Amount],tblY2024_Strategies[CounterLine],$H14) | N14: =IF(UPPER(K14)="Y",SUMIFS(tblMaster_Inputs[Baseline_Amount],tblMaster_Inputs[Year],2023,tblMaster_Inputs[Primary_Line],"10"),IF(ISBLANK(L14),J14,L14)) | O14: =N14+M14 | P14: =HYPERLINK("#Y2024!I49", "↗ drill")
A15: STR-010 | B15: Entity Restructuring | C15: 8 | H15: 11 | I15: AGI | J15: =J13+J14 | M15: =M13+M14 | N15: =N13+N14 | O15: =O13+O14 | P15: =HYPERLINK("#Y2024!I49", "↗ drill")
A16: STR-011 | B16: Installment Sale / 1031 | C16: 7 | H16: 12 | I16: Std/Itemized deduction | J16: =SUMIFS(tblMaster_Inputs[Baseline_Amount],tblMaster_Inputs[Year],2024,tblMaster_Inputs[Primary_Line],$H16, tblMaster_Inputs[Activity_Type], "Baseline") | M16: =SUMIFS(tblY2024_Strategies[Amount],tblY2024_Strategies[TargetLine],$H16)-SUMIFS(tblY2024_Strategies[Amount],tblY2024_Strategies[CounterLine],$H16) | N16: =IF(UPPER(K16)="Y",SUMIFS(tblMaster_Inputs[Baseline_Amount],tblMaster_Inputs[Year],2023,tblMaster_Inputs[Primary_Line],"12"),IF(ISBLANK(L16),J16,L16)) | O16: =N16+M16 | P16: =HYPERLINK("#Y2024!I49", "↗ drill")
A17: STR-012 | B17: Bonus Depreciation §168(k) | C17: 8 | H17: 13 | I17: QBI deduction | J17: =SUMIFS(tblMaster_Inputs[Baseline_Amount],tblMaster_Inputs[Year],2024,tblMaster_Inputs[Primary_Line],$H17, tblMaster_Inputs[Activity_Type], "Baseline") | M17: =SUMIFS(tblY2024_Strategies[Amount],tblY2024_Strategies[TargetLine],$H17)-SUMIFS(tblY2024_Strategies[Amount],tblY2024_Strategies[CounterLine],$H17) | N17: =IF(UPPER(K17)="Y",SUMIFS(tblMaster_Inputs[Baseline_Amount],tblMaster_Inputs[Year],2023,tblMaster_Inputs[Primary_Line],"13"),IF(ISBLANK(L17),J17,L17)) | O17: =N17+M17 | P17: =HYPERLINK("#Y2024!I49", "↗ drill")
A18: STR-013 | B18: R&D Credit §41 | C18: 13 | H18: 15 | I18: TAXABLE INCOME | J18: =J15+J16+J17 | M18: =M15+M16+M17 | N18: =N15+N16+N17 | O18: =O15+O16+O17 | P18: =HYPERLINK("#Y2024!I49", "↗ drill")
A19: STR-014 | B19: SALT PTE Election | C19: 12
A20: STR-015 | B20: Timing / Deferral | C20: 8
A22: ▸ TAX IMPACT SUMMARY | H22: Description | I22: Amount | J22: Effective | K22: Used by
A23: Metric | B23: Baseline | C23: Effective | D23: Eff w/ Strat | E23: Savings | H23: Owner W-2 | I23: =SUMIFS(tblMaster_Inputs[Baseline_Amount],tblMaster_Inputs[Year],2024,tblMaster_Inputs[Treatment_Profile],"W2_SCorpOwner", tblMaster_Inputs[Activity_Type], "Baseline") | J23: =I23+SUMIFS(tblY2024_Strategies[Amount],tblY2024_Strategies[TargetLine],"1z")-SUMIFS(tblY2024_Strategies[Amount],tblY2024_Strategies[CounterLine],"1z")
A24: Total Income | B24: =J13 | C24: =N13 | D24: =O13 | E24: =B24-D24 | H24: Third-party W-2 | I24: =SUMIFS(tblMaster_Inputs[Baseline_Amount],tblMaster_Inputs[Year],2024,tblMaster_Inputs[Treatment_Profile],"W2_Employee", tblMaster_Inputs[Activity_Type], "Baseline") | J24: =I24
A25: Taxable Income | B25: =J18 | C25: =N18 | D25: =O18 | E25: =B25-D25 | H25: Total W-2 | I25: =I23+I24 | J25: =J23+J24
A26: Total Tax | B26: =I133 | C26: =I133 | D26: =J133 | E26: =B26-D26 | H26: SE business income | I26: =SUMIFS(tblMaster_Inputs[Baseline_Amount],tblMaster_Inputs[Year],2024,tblMaster_Inputs[Bucket],"Business Income",tblMaster_Inputs[SE_Subject],"Yes", tblMaster_Inputs[Activity_Type], "Baseline") | J26: =I26
A27: Effective Rate | B27: =I134 | C27: =I134 | D27: =J134 | E27: =B27-D27 | H27: Active non-SE business | I27: =SUMIFS(tblMaster_Inputs[Baseline_Amount],tblMaster_Inputs[Year],2024,tblMaster_Inputs[Bucket],"Business Income",tblMaster_Inputs[SE_Subject],"No",tblMaster_Inputs[NIIT_Class],"Active", tblMaster_Inputs[Activity_Type], "Baseline") | J27: =I27+SUMIFS(tblY2024_Strategies[Amount],tblY2024_Strategies[TargetLine],"8")-SUMIFS(tblY2024_Strategies[Amount],tblY2024_Strategies[CounterLine],"8")
A28: Committed Strategies | B28: =COUNTIF(tblY2024_Strategies[Status],"Committed") | C28: Net Strategy Impact | D28: =SUMIF(tblY2024_Strategies[Status],"Committed",tblY2024_Strategies[Amount]) | H28: Passive business | I28: =SUMIFS(tblMaster_Inputs[Baseline_Amount],tblMaster_Inputs[Year],2024,tblMaster_Inputs[Bucket],"Business Income",tblMaster_Inputs[NIIT_Class],"Passive", tblMaster_Inputs[Activity_Type], "Baseline") | J28: =I28
H29: Tax-exempt interest | I29: =SUMIFS(tblMaster_Inputs[Helper_Amount],tblMaster_Inputs[Year],2024,tblMaster_Inputs[Helper_Treatment],"TAX_EXEMPT") | J29: =I29+SUMIFS(tblY2024_Strategies[Amount],tblY2024_Strategies[TargetLine],"2a")-SUMIFS(tblY2024_Strategies[Amount],tblY2024_Strategies[CounterLine],"2a")
H30: Qualified dividends | I30: =SUMIFS(tblMaster_Inputs[Helper_Amount],tblMaster_Inputs[Year],2024,tblMaster_Inputs[Helper_Treatment],"QUAL_DIV", tblMaster_Inputs[Activity_Type], "Baseline") | J30: =I30
H31: Long-term cap gains | I31: =SUMIFS(tblMaster_Inputs[Baseline_Amount],tblMaster_Inputs[Year],2024,tblMaster_Inputs[Treatment_Profile],"LTCG_Stock")+SUMIFS(tblMaster_Inputs[Baseline_Amount],tblMaster_Inputs[Year],2024,tblMaster_Inputs[Treatment_Profile],"LTCG_RE")+SUMIFS(tblMaster_Inputs[Baseline_Amount],tblMaster_Inputs[Year],2024,tblMaster_Inputs[Treatment_Profile],"LTCG_K1_Passthrough")+SUMIFS(tblMaster_Inputs[Baseline_Amount],tblMaster_Inputs[Year],2024,tblMaster_Inputs[Treatment_Profile],"Sec1250_Recap", tblMaster_Inputs[Activity_Type], "Baseline") | J31: =I31+SUMIFS(tblY2024_Strategies[Amount],tblY2024_Strategies[TargetLine],"7")-SUMIFS(tblY2024_Strategies[Amount],tblY2024_Strategies[CounterLine],"7")
H32: Short-term cap gains | I32: =SUMIFS(tblMaster_Inputs[Baseline_Amount],tblMaster_Inputs[Year],2024,tblMaster_Inputs[Treatment_Profile],"STCG_Stock", tblMaster_Inputs[Activity_Type], "Baseline") | J32: =I32
H33: §1250 gain | I33: =SUMIFS(tblMaster_Inputs[Helper_Amount],tblMaster_Inputs[Year],2024,tblMaster_Inputs[Helper_Treatment],"SEC1250", tblMaster_Inputs[Activity_Type], "Baseline") | J33: =I33
H36: Description | I36: Value | J36: Effective | K36: Used by
H37: TI-LTCG-QUAL_DIV-SEC1250 | I37: =J18-I31-I30-I33 | J37: =O18-J31-J30-J33
H38: AGI+tax-exempt | I38: =J15+I29 | J38: =O15+J29
H39: Net inv income | I39: =J8+J10+J11+I28 | J39: =O8+O10+O11+J28
H40: QBI-eligible | I40: =I26+I27 | J40: =J26+J27
H41: TI before QBI | I41: =J15+J16 | J41: =O15+O16
H42: Net biz loss | I42: =MIN(0,I26+I27+I28) | J42: =MIN(0,J26+J27+J28)
H43: Net SE income | I43: =I26 | J43: =J26
J44: =I44
I45: =IF(Control_Panel!C21="Yes",TRUE,FALSE) | J45: =I45
I46: =Carryovers!F52 | J46: =I46
H49: 1z | K49: =HYPERLINK("#Master_Inputs!A1","✏ open Master_Inputs")
H65: ▸ 7-COMPONENT TAX CALCULATOR | I65: Baseline | J65: Effective | K65: Δ Savings
H66: Dual columns: Baseline (H) vs With Planning (I)
H68: 1. SELF-EMPLOYMENT TAX
H69: SE Tax Label
H70: Net SE Earnings | I70: =I43 | J70: =J43
H71: SE Base (× 0.9235) | I71: =I70*SUMIFS(tblThresholds[Value], tblThresholds[Year], 2024, tblThresholds[FilingStatus], Filing_Status, tblThresholds[Item], "SE_Earnings_Factor") | J71: =J70*SUMIFS(tblThresholds[Value], tblThresholds[Year], 2024, tblThresholds[FilingStatus], Filing_Status, tblThresholds[Item], "SE_Earnings_Factor")
H72: W-2 Wages | I72: =I25 | J72: =J25
H73: Remaining SS Wage Base | I73: =MAX(0,SUMIFS(tblThresholds[Value], tblThresholds[Year], 2024, tblThresholds[FilingStatus], Filing_Status, tblThresholds[Item], "SS_Wage_Base")-I72) | J73: =MAX(0,SUMIFS(tblThresholds[Value], tblThresholds[Year], 2024, tblThresholds[FilingStatus], Filing_Status, tblThresholds[Item], "SS_Wage_Base")-J72)
I74: =MIN(I71,I73) | J74: =MIN(J71,J73)
H75: Social Security Tax (12.4%) | I75: =I74*SUMIFS(tblThresholds[Value], tblThresholds[Year], 2024, tblThresholds[FilingStatus], Filing_Status, tblThresholds[Item], "SS_Rate_Combined") | J75: =J74*SUMIFS(tblThresholds[Value], tblThresholds[Year], 2024, tblThresholds[FilingStatus], Filing_Status, tblThresholds[Item], "SS_Rate_Combined")
H76: Medicare Tax (2.9%) | I76: =I71*SUMIFS(tblThresholds[Value], tblThresholds[Year], 2024, tblThresholds[FilingStatus], Filing_Status, tblThresholds[Item], "Medicare_Rate_Combined") | J76: =J71*SUMIFS(tblThresholds[Value], tblThresholds[Year], 2024, tblThresholds[FilingStatus], Filing_Status, tblThresholds[Item], "Medicare_Rate_Combined")
H77: Addl Medicare (0.9% > threshold) | I77: =MAX(0,(I72+I71-SUMIFS(tblThresholds[Value], tblThresholds[Year], 2024, tblThresholds[FilingStatus], Filing_Status, tblThresholds[Item], "Addl_Medicare_Threshold"))*SUMIFS(tblThresholds[Value], tblThresholds[Year], 2024, tblThresholds[FilingStatus], Filing_Status, tblThresholds[Item], "Addl_Medicare_Rate")) | J77: =MAX(0,(J72+J71-SUMIFS(tblThresholds[Value], tblThresholds[Year], 2024, tblThresholds[FilingStatus], Filing_Status, tblThresholds[Item], "Addl_Medicare_Threshold"))*SUMIFS(tblThresholds[Value], tblThresholds[Year], 2024, tblThresholds[FilingStatus], Filing_Status, tblThresholds[Item], "Addl_Medicare_Rate"))
I78: =-(I75+I76)/2 | J78: =-(J75+J76)/2
H80: TOTAL SE TAX | I80: =I75+I76+I77 | J80: =J75+J76+J77 | K80: =I80-J80
H82: 2. PAYROLL TAX
H83: W-2 Wages | I83: =I25 | J83: =J25
H84: Social Security (6.2%) | I84: =MIN(I83,SUMIFS(tblThresholds[Value], tblThresholds[Year], 2024, tblThresholds[FilingStatus], Filing_Status, tblThresholds[Item], "SS_Wage_Base"))*0.062 | J84: =MIN(J83,SUMIFS(tblThresholds[Value], tblThresholds[Year], 2024, tblThresholds[FilingStatus], Filing_Status, tblThresholds[Item], "SS_Wage_Base"))*0.062
H85: Medicare (1.45%) | I85: =I83*0.0145 | J85: =J83*0.0145
H86: Addl Medicare (0.9% > threshold) | I86: =MAX(0,(I83-SUMIFS(tblThresholds[Value], tblThresholds[Year], 2024, tblThresholds[FilingStatus], Filing_Status, tblThresholds[Item], "Addl_Medicare_Threshold"))*SUMIFS(tblThresholds[Value], tblThresholds[Year], 2024, tblThresholds[FilingStatus], Filing_Status, tblThresholds[Item], "Addl_Medicare_Rate")) | J86: =MAX(0,(J83-SUMIFS(tblThresholds[Value], tblThresholds[Year], 2024, tblThresholds[FilingStatus], Filing_Status, tblThresholds[Item], "Addl_Medicare_Threshold"))*SUMIFS(tblThresholds[Value], tblThresholds[Year], 2024, tblThresholds[FilingStatus], Filing_Status, tblThresholds[Item], "Addl_Medicare_Rate"))
H87: TOTAL PAYROLL TAX | I87: =I84+I85+I86 | J87: =J84+J85+J86 | K87: =I87-J87
H88: Employer Social Security (6.2%) | I88: =I84 | J88: =J84 | K88: =I88-J88
H89: Employer Medicare (1.45%) | I89: =I85 | J89: =J85 | K89: =I89-J89
H91: TOTAL PAYROLL TAX (Employee + Employer) | I91: =I87+I88+I89 | J91: =J87+J88+J89 | K91: =I91-J91
H93: 3. ORDINARY INCOME TAX
H94: Taxable Income | I94: =I37 | J94: =J37
H95: Ordinary Taxable (TI - LTCG - QD) | I95: =MAX(0,I94) | J95: =MAX(0,J94)
H96: Tax (SUMPRODUCT bracket lookup) | I96: {=SUMPRODUCT((tblBrackets_FIT[Year]=2024)*(tblBrackets_FIT[FilingStatus]=Filing_Status)*((I95>tblBrackets_FIT[Upper])*(tblBrackets_FIT[Upper]-tblBrackets_FIT[Lower])+(I95>tblBrackets_FIT[Lower])*(I95<=tblBrackets_FIT[Upper])*(I95-tblBrackets_FIT[Lower]))*tblBrackets_FIT[Rate])} | J96: {=SUMPRODUCT((tblBrackets_FIT[Year]=2024)*(tblBrackets_FIT[FilingStatus]=Filing_Status)*((J95>tblBrackets_FIT[Upper])*(tblBrackets_FIT[Upper]-tblBrackets_FIT[Lower])+(J95>tblBrackets_FIT[Lower])*(J95<=tblBrackets_FIT[Upper])*(J95-tblBrackets_FIT[Lower]))*tblBrackets_FIT[Rate])}
H97: TOTAL ORDINARY TAX | I97: =I96 | J97: =J96 | K97: =I97-J97
H99: 4. CAPITAL GAINS / QUALIFIED DIVIDENDS TAX
H100: LTCG + Qualified Dividends | I100: =I31+I30 | J100: =J31+J30
H101: Sec 1250 Recapture Gain | I101: =I33 | J101: =J33
H102: Stacking Base (Ordinary TI for bracket floor) | I102: =I95 | J102: =J95
H103: Full CG Rate Tax (SUMPRODUCT stack) | I103: {=SUMPRODUCT((Tax_Ref!$B$210:$B$281=2024)*(Tax_Ref!$C$210:$C$281=Filing_Status)*((I102+I100>Tax_Ref!$E$210:$E$281)*(Tax_Ref!$E$210:$E$281-Tax_Ref!$D$210:$D$281)+(I102+I100>Tax_Ref!$D$210:$D$281)*(I102+I100<=Tax_Ref!$E$210:$E$281)*(I102+I100-Tax_Ref!$D$210:$D$281))*Tax_Ref!$F$210:$F$281)} | J103: {=SUMPRODUCT((Tax_Ref!$B$210:$B$281=2024)*(Tax_Ref!$C$210:$C$281=Filing_Status)*((J102+J100>Tax_Ref!$E$210:$E$281)*(Tax_Ref!$E$210:$E$281-Tax_Ref!$D$210:$D$281)+(J102+J100>Tax_Ref!$D$210:$D$281)*(J102+J100<=Tax_Ref!$E$210:$E$281)*(J102+J100-Tax_Ref!$D$210:$D$281))*Tax_Ref!$F$210:$F$281)}
H104: CG Rate Tax on Ordinary only | I104: {=SUMPRODUCT((Tax_Ref!$B$210:$B$281=2024)*(Tax_Ref!$C$210:$C$281=Filing_Status)*((I102>Tax_Ref!$E$210:$E$281)*(Tax_Ref!$E$210:$E$281-Tax_Ref!$D$210:$D$281)+(I102>Tax_Ref!$D$210:$D$281)*(I102<=Tax_Ref!$E$210:$E$281)*(I102-Tax_Ref!$D$210:$D$281))*Tax_Ref!$F$210:$F$281)} | J104: {=SUMPRODUCT((Tax_Ref!$B$210:$B$281=2024)*(Tax_Ref!$C$210:$C$281=Filing_Status)*((J102>Tax_Ref!$E$210:$E$281)*(Tax_Ref!$E$210:$E$281-Tax_Ref!$D$210:$D$281)+(J102>Tax_Ref!$D$210:$D$281)*(J102<=Tax_Ref!$E$210:$E$281)*(J102-Tax_Ref!$D$210:$D$281))*Tax_Ref!$F$210:$F$281)}
H105: Net LTCG/QD Tax | I105: =I103-I104 | J105: =J103-J104
I106: =I33*0.25 | J106: =J33*0.25
H107: TOTAL CAP GAINS TAX | I107: =I105+I106 | J107: =J105+J106 | K107: =I107-J107
H109: 5. NET INVESTMENT INCOME TAX (NIIT)
H110: MAGI | I110: =I38 | J110: =J38
H111: NIIT Threshold | I111: =SUMIFS(tblThresholds[Value], tblThresholds[Year], 2024, tblThresholds[FilingStatus], Filing_Status, tblThresholds[Item], "NIIT_Threshold") | J111: =SUMIFS(tblThresholds[Value], tblThresholds[Year], 2024, tblThresholds[FilingStatus], Filing_Status, tblThresholds[Item], "NIIT_Threshold")
H112: Net Investment Income (NII) | I112: =MAX(0,I39) | J112: =MAX(0,J39)
H113: NIIT Base (lesser of NII or MAGI excess) | I113: =MAX(0,I110-I111) | J113: =MAX(0,J110-J111)
H114: NIIT (3.8%) | I114: =MIN(I112,I113)*SUMIFS(tblThresholds[Value], tblThresholds[Year], 2024, tblThresholds[FilingStatus], Filing_Status, tblThresholds[Item], "NIIT_Rate") | J114: =MIN(J112,J113)*SUMIFS(tblThresholds[Value], tblThresholds[Year], 2024, tblThresholds[FilingStatus], Filing_Status, tblThresholds[Item], "NIIT_Rate") | K114: =I114-J114
H116: 6. QBI DEDUCTION (§199A)
H117: QBI-Eligible Income | I117: =I40 | J117: =J40
H118: 20% of QBI | I118: =MAX(0,I117)*0.2 | J118: =MAX(0,J117)*0.2
H119: 50% of W-2 Wages | I119: =MAX(0,I41)*0.2 | J119: =MAX(0,J41)*0.2
H120: 25% W-2 + 2.5% UBIA | I120: =MAX(I23*0.5, I23*0.25+I44*0.025) | J120: =MAX(J23*0.5, J23*0.25+J44*0.025)
H121: Phase-in applies? | I121: =IF(I41>SUMIFS(tblThresholds[Value], tblThresholds[Year], 2024, tblThresholds[FilingStatus], Filing_Status, tblThresholds[Item], "QBI_Threshold_Start"),"YES","NO") | J121: =IF(J41>SUMIFS(tblThresholds[Value], tblThresholds[Year], 2024, tblThresholds[FilingStatus], Filing_Status, tblThresholds[Item], "QBI_Threshold_Start"),"YES","NO")
H122: QBI DEDUCTION | I122: =IF(AND(I45=TRUE,I41>SUMIFS(tblThresholds[Value], tblThresholds[Year], 2024, tblThresholds[FilingStatus], Filing_Status, tblThresholds[Item], "QBI_Threshold_End")),0,IF(I41<=SUMIFS(tblThresholds[Value], tblThresholds[Year], 2024, tblThresholds[FilingStatus], Filing_Status, tblThresholds[Item], "QBI_Threshold_Start"),MIN(I118,I119),MIN(I118,I119,I120))) | J122: =IF(AND(J45=TRUE,J41>SUMIFS(tblThresholds[Value], tblThresholds[Year], 2024, tblThresholds[FilingStatus], Filing_Status, tblThresholds[Item], "QBI_Threshold_End")),0,IF(J41<=SUMIFS(tblThresholds[Value], tblThresholds[Year], 2024, tblThresholds[FilingStatus], Filing_Status, tblThresholds[Item], "QBI_Threshold_Start"),MIN(J118,J119),MIN(J118,J119,J120))) | K122: =J122-I122
H124: 7. COMBINED TAX SUMMARY
H125: Total Income | I125: =J6+J8+J10+J11+J12 | J125: =O13 | K125: Δ Savings
H126: Ordinary Tax | I126: =I97 | J126: =J97 | K126: =I126-J126
H127: Capital Gains Tax | I127: =I107 | J127: =J107 | K127: =I127-J127
H128: Self-Employment Tax | I128: =I80 | J128: =J80 | K128: =I128-J128
H129: Payroll Tax (Employee + Employer) | I129: =I91 | J129: =J91 | K129: =I129-J129
H130: NIIT | I130: =I114 | J130: =J114 | K130: =I130-J130
...

Sheet Y2025
A1: Y2025 — standalone tax planning sandbox
A2: Strategies: enter Amount + Status below. Committed strategies flow to rollup M column. Push to Master_Inputs when final.
A4: ▸ STRATEGIES
A5: StrategyID | B5: Strategy Name | C5: TargetLine | D5: Amount | E5: Status | F5: Notes | G5: CounterLine | H5: Line | I5: Description | J5: Baseline (Master) | K5: PY? | L5: S1 Override | M5: Strategies | N5: Effective | O5: Eff w/ Strategies | P5: Drill
A6: STR-001 | B6: S-Corp Wage Optimization | C6: 1z | D6: -25000 | E6: Committed | F6: Reduce W-2 $25K, offset by K-1 increase | G6: 8 | H6: 1z | I6: Wages | J6: =SUMIFS(tblMaster_Inputs[Baseline_Amount], tblMaster_Inputs[Year], 2025, tblMaster_Inputs[Primary_Line], $H6, tblMaster_Inputs[Activity_Type], "Baseline") | M6: =SUMIFS(tblY2025_Strategies[Amount],tblY2025_Strategies[TargetLine],$H6)-SUMIFS(tblY2025_Strategies[Amount],tblY2025_Strategies[CounterLine],$H6) | N6: =IF(UPPER(K6)="Y",SUMIFS(tblMaster_Inputs[Baseline_Amount],tblMaster_Inputs[Year],2024,tblMaster_Inputs[Primary_Line],"1z"),IF(ISBLANK(L6),J6,L6)) | O6: =N6+M6 | P6: =HYPERLINK("#Y2025!I49", "↗ drill")
A7: STR-002 | B7: HSA Family Max | C7: 10 | D7: -8550 | E7: Committed | F7: Family HSA contribution | H7: 2a | I7: Tax-exempt interest (informational — Helper) | J7: =TAX_EXEMPT | M7: =SUMIFS(tblY2025_Strategies[Amount],tblY2025_Strategies[TargetLine],"2a",tblY2025_Strategies[Status],"Committed") | N7: =IF(UPPER(K7)="Y",SUMIFS(tblMaster_Inputs[Helper_Amount],tblMaster_Inputs[Year],2024,tblMaster_Inputs[Helper_Treatment],"TAX_EXEMPT"),IF(ISBLANK(L7),J7,L7)) | O7: =N7 | P7: =HYPERLINK("#Y2025!I49", "↗ drill")
A8: STR-003 | B8: Charitable Bunching (DAF) | C8: 12 | D8: 15000 | E8: Proposed | F8: Donor-advised fund stacking | H8: 2b | I8: Taxable interest | J8: =SUMIFS(tblMaster_Inputs[Baseline_Amount], tblMaster_Inputs[Year], 2025, tblMaster_Inputs[Primary_Line], $H8, tblMaster_Inputs[Activity_Type], "Baseline") | M8: =SUMIFS(tblY2025_Strategies[Amount],tblY2025_Strategies[TargetLine],$H8)-SUMIFS(tblY2025_Strategies[Amount],tblY2025_Strategies[CounterLine],$H8) | N8: =IF(UPPER(K8)="Y",SUMIFS(tblMaster_Inputs[Baseline_Amount],tblMaster_Inputs[Year],2024,tblMaster_Inputs[Primary_Line],"2b"),IF(ISBLANK(L8),J8,L8)) | O8: =N8+M8 | P8: =HYPERLINK("#Y2025!I49", "↗ drill")
A9: STR-004 | B9: SEP-IRA / Solo 401(k) | C9: 10 | D9: -7000 | E9: Approved | F9: Retirement contribution | H9: 3a | I9: Qualified dividends (informational — Helper) | J9: =QUAL_DIV | M9: =SUMIFS(tblY2025_Strategies[Amount],tblY2025_Strategies[TargetLine],"3a",tblY2025_Strategies[Status],"Committed") | N9: =IF(UPPER(K9)="Y",SUMIFS(tblMaster_Inputs[Helper_Amount],tblMaster_Inputs[Year],2024,tblMaster_Inputs[Helper_Treatment],"QUAL_DIV"),IF(ISBLANK(L9),J9,L9)) | O9: =N9 | P9: =HYPERLINK("#Y2025!I49", "↗ drill")
A10: STR-005 | B10: Cost Seg Study | C10: 8 | D10: -80000 | E10: Committed | F10: 123 Main St — accelerated depreciation | H10: 3b | I10: Ordinary dividends (total — incl qualified) | J10: =SUMIFS(tblMaster_Inputs[Baseline_Amount], tblMaster_Inputs[Year], 2025, tblMaster_Inputs[Primary_Line], $H10, tblMaster_Inputs[Activity_Type], "Baseline") | M10: =SUMIFS(tblY2025_Strategies[Amount],tblY2025_Strategies[TargetLine],$H10)-SUMIFS(tblY2025_Strategies[Amount],tblY2025_Strategies[CounterLine],$H10) | N10: =IF(UPPER(K10)="Y",SUMIFS(tblMaster_Inputs[Baseline_Amount],tblMaster_Inputs[Year],2024,tblMaster_Inputs[Primary_Line],"3b"),IF(ISBLANK(L10),J10,L10)) | O10: =N10+M10 | P10: =HYPERLINK("#Y2025!I49", "↗ drill")
A11: STR-006 | B11: Roth Conversion | C11: 1z | F11: Conversion amount (increases taxable income) | H11: 7 | I11: Capital gain or (loss) | J11: =SUMIFS(tblMaster_Inputs[Baseline_Amount], tblMaster_Inputs[Year], 2025, tblMaster_Inputs[Primary_Line], $H11, tblMaster_Inputs[Activity_Type], "Baseline") | M11: =SUMIFS(tblY2025_Strategies[Amount],tblY2025_Strategies[TargetLine],$H11)-SUMIFS(tblY2025_Strategies[Amount],tblY2025_Strategies[CounterLine],$H11) | N11: =IF(UPPER(K11)="Y",SUMIFS(tblMaster_Inputs[Baseline_Amount],tblMaster_Inputs[Year],2024,tblMaster_Inputs[Primary_Line],"7"),IF(ISBLANK(L11),J11,L11)) | O11: =N11+M11 | P11: =HYPERLINK("#Y2025!I49", "↗ drill")
A12: STR-007 | B12: Augusta Rule (§280A) | C12: 8 | F12: Home rental to S-Corp (≤14 days, tax-free) | H12: 8 | I12: Other income (incl business income via Sch 1) | J12: =SUMIFS(tblMaster_Inputs[Baseline_Amount], tblMaster_Inputs[Year], 2025, tblMaster_Inputs[Primary_Line], $H12, tblMaster_Inputs[Activity_Type], "Baseline") | M12: =SUMIFS(tblY2025_Strategies[Amount],tblY2025_Strategies[TargetLine],$H12)-SUMIFS(tblY2025_Strategies[Amount],tblY2025_Strategies[CounterLine],$H12) | N12: =IF(UPPER(K12)="Y",SUMIFS(tblMaster_Inputs[Baseline_Amount],tblMaster_Inputs[Year],2024,tblMaster_Inputs[Primary_Line],"8"),IF(ISBLANK(L12),J12,L12)) | O12: =N12+M12 | P12: =HYPERLINK("#Y2025!I49", "↗ drill")
A13: STR-008 | B13: Accountable Plan | C13: 8 | F13: Business expense reimbursement | H13: 9 | I13: TOTAL INCOME | J13: =J6+J8+J10+J11+J12 | M13: =M6+M8+M10+M11+M12 | N13: =N6+N8+N10+N11+N12 | O13: =O6+O8+O10+O11+O12 | P13: =HYPERLINK("#Y2025!I49", "↗ drill")
A14: STR-009 | B14: Hire Children | C14: 8 | F14: Wages to children under §3121(b)(3) | H14: 10 | I14: Adjustments to income | J14: =SUMIFS(tblMaster_Inputs[Baseline_Amount], tblMaster_Inputs[Year], 2025, tblMaster_Inputs[Primary_Line], $H14, tblMaster_Inputs[Activity_Type], "Baseline") | M14: =SUMIFS(tblY2025_Strategies[Amount],tblY2025_Strategies[TargetLine],$H14)-SUMIFS(tblY2025_Strategies[Amount],tblY2025_Strategies[CounterLine],$H14) | N14: =IF(UPPER(K14)="Y",SUMIFS(tblMaster_Inputs[Baseline_Amount],tblMaster_Inputs[Year],2024,tblMaster_Inputs[Primary_Line],"10"),IF(ISBLANK(L14),J14,L14)) | O14: =N14+M14 | P14: =HYPERLINK("#Y2025!I49", "↗ drill")
A15: STR-010 | B15: Entity Restructuring | C15: 8 | F15: Partnership → S-Corp, etc. | H15: 11 | I15: AGI | J15: =J13+J14 | M15: =M13+M14 | N15: =N13+N14 | O15: =O13+O14 | P15: =HYPERLINK("#Y2025!I49", "↗ drill")
A16: STR-011 | B16: Installment Sale / 1031 | C16: 7 | F16: Gain deferral strategies | H16: 12 | I16: Std/Itemized deduction | J16: =SUMIFS(tblMaster_Inputs[Baseline_Amount], tblMaster_Inputs[Year], 2025, tblMaster_Inputs[Primary_Line], $H16, tblMaster_Inputs[Activity_Type], "Baseline") | M16: =SUMIFS(tblY2025_Strategies[Amount],tblY2025_Strategies[TargetLine],$H16)-SUMIFS(tblY2025_Strategies[Amount],tblY2025_Strategies[CounterLine],$H16) | N16: =IF(UPPER(K16)="Y",SUMIFS(tblMaster_Inputs[Baseline_Amount],tblMaster_Inputs[Year],2024,tblMaster_Inputs[Primary_Line],"12"),IF(ISBLANK(L16),J16,L16)) | O16: =N16+M16 | P16: =HYPERLINK("#Y2025!I49", "↗ drill")
A17: STR-012 | B17: Bonus Depreciation §168(k) | C17: 8 | F17: First-year depreciation | H17: 13 | I17: QBI deduction | J17: =SUMIFS(tblMaster_Inputs[Baseline_Amount], tblMaster_Inputs[Year], 2025, tblMaster_Inputs[Primary_Line], $H17, tblMaster_Inputs[Activity_Type], "Baseline") | M17: =SUMIFS(tblY2025_Strategies[Amount],tblY2025_Strategies[TargetLine],$H17)-SUMIFS(tblY2025_Strategies[Amount],tblY2025_Strategies[CounterLine],$H17) | N17: =IF(UPPER(K17)="Y",SUMIFS(tblMaster_Inputs[Baseline_Amount],tblMaster_Inputs[Year],2024,tblMaster_Inputs[Primary_Line],"13"),IF(ISBLANK(L17),J17,L17)) | O17: =N17+M17 | P17: =HYPERLINK("#Y2025!I49", "↗ drill")
A18: STR-013 | B18: R&D Credit §41 | C18: 20 | F18: Research credit | H18: 15 | I18: TAXABLE INCOME | J18: =J15+J16+J17 | M18: =M15+M16+M17 | N18: =N15+N16+N17 | O18: =O15+O16+O17 | P18: =HYPERLINK("#Y2025!I49", "↗ drill")
A19: STR-014 | B19: SALT PTE Election | C19: 12 | F19: State pass-through entity tax
A20: STR-015 | B20: Timing / Deferral | C20: 8 | F20: Income acceleration or deferral
A22: ▸ TAX IMPACT SUMMARY | H22: Description | I22: =N5 | J22: =O5 | K22: Used by
A23: Metric | B23: Baseline | C23: Effective | D23: Eff w/ Strat | E23: Savings | H23: Owner W-2 wages (S-Corp reasonable comp; Treatment_Profile=W2_SCorpOwner) | I23: =SUMIFS(tblMaster_Inputs[Baseline_Amount], tblMaster_Inputs[Year], 2025, tblMaster_Inputs[Treatment_Profile], "W2_SCorpOwner", tblMaster_Inputs[Activity_Type], "Baseline") | J23: =I23+SUMIFS(tblY2025_Strategies[Amount],tblY2025_Strategies[TargetLine],"1z")-SUMIFS(tblY2025_Strategies[Amount],tblY2025_Strategies[CounterLine],"1z") | K23: FICA_Employer/Employee — True Tax Burden box
A24: Total Income | B24: =J13 | C24: =N13 | D24: =O13 | E24: =B24-D24 | H24: Third-party W-2 wages (Treatment_Profile=W2_Employee) | I24: =SUMIFS(tblMaster_Inputs[Baseline_Amount], tblMaster_Inputs[Year], 2025, tblMaster_Inputs[Treatment_Profile], "W2_Employee", tblMaster_Inputs[Activity_Type], "Baseline") | J24: =I24 | K24: Calc_SE_Tax (SS-base sharing) · AddlMedicareTax_FN
A25: Taxable Income | B25: =J18 | C25: =N18 | D25: =O18 | E25: =B25-D25 | H25: Total W-2 wages (owner + third-party) | I25: =I23+I24 | J25: =J23+J24 | K25: Calc_SE_Tax (SS-base sharing) · AddlMedicareTax_FN
A26: Total Tax | B26: =I133 | C26: =I133 | D26: =J133 | E26: =B26-D26 | H26: Business income subject to SE tax (Sch C, Sch F, active K-1 PTP) | I26: =SUMIFS(tblMaster_Inputs[Baseline_Amount], tblMaster_Inputs[Year], 2025, tblMaster_Inputs[Bucket], "Business Income", tblMaster_Inputs[SE_Subject], "Yes", tblMaster_Inputs[Activity_Type], "Baseline") | J26: =I26 | K26: Calc_SE_Tax base · AddlMedicareTax_FN
A27: Effective Rate | B27: =I134 | C27: =I134 | D27: =J134 | E27: =B27-D27 | H27: Active business income NOT subject to SE (active S-Corp K-1, etc.) | I27: =SUMIFS(tblMaster_Inputs[Baseline_Amount], tblMaster_Inputs[Year], 2025, tblMaster_Inputs[Bucket], "Business Income", tblMaster_Inputs[SE_Subject], "No", tblMaster_Inputs[NIIT_Class], "Active", tblMaster_Inputs[Activity_Type], "Baseline") | J27: =I27+SUMIFS(tblY2025_Strategies[Amount],tblY2025_Strategies[TargetLine],"8")-SUMIFS(tblY2025_Strategies[Amount],tblY2025_Strategies[CounterLine],"8") | K27: NIIT exclusion (active) · QBI eligible
A28: Committed Strategies | B28: =COUNTIF(tblY2025_Strategies[Status],"Committed") | C28: Net Strategy Impact | D28: =SUMIF(tblY2025_Strategies[Status],"Committed",tblY2025_Strategies[Amount]) | H28: Passive business income / loss (passive K-1s, Sch E rental) | I28: =SUMIFS(tblMaster_Inputs[Baseline_Amount], tblMaster_Inputs[Year], 2025, tblMaster_Inputs[Bucket], "Business Income", tblMaster_Inputs[NIIT_Class], "Passive", tblMaster_Inputs[Activity_Type], "Baseline") | J28: =I28 | K28: PassiveLossAllowed_FN · NIIT inclusion
H29: Tax-exempt interest (Line 2a; reported but not taxed) | I29: =SUMIFS(tblMaster_Inputs[Helper_Amount], tblMaster_Inputs[Year], 2025, tblMaster_Inputs[Helper_Treatment], "TAX_EXEMPT") | J29: =I29+SUMIFS(tblY2025_Strategies[Amount],tblY2025_Strategies[TargetLine],"2a")-SUMIFS(tblY2025_Strategies[Amount],tblY2025_Strategies[CounterLine],"2a") | K29: NIIT_FN (MAGI base)
H30: Qualified dividends (carve-out of Line 3b; LTCG stack) | I30: =SUMIFS(tblMaster_Inputs[Helper_Amount], tblMaster_Inputs[Year], 2025, tblMaster_Inputs[Helper_Treatment], "QUAL_DIV", tblMaster_Inputs[Activity_Type], "Baseline") | J30: =I30 | K30: Calc_CapGainsTax stacking
H31: Long-term capital gains (LT preferential rate; stacks with qualified div) | I31: =SUMIFS(tblMaster_Inputs[Baseline_Amount], tblMaster_Inputs[Year], 2025, tblMaster_Inputs[Treatment_Profile], "LTCG_Stock") + SUMIFS(tblMaster_Inputs[Baseline_Amount], tblMaster_Inputs[Year], 2025, tblMaster_Inputs[Treatment_Profile], "LTCG_RE") + SUMIFS(tblMaster_Inputs[Baseline_Amount], tblMaster_Inputs[Year], 2025, tblMaster_Inputs[Treatment_Profile], "LTCG_K1_Passthrough") + SUMIFS(tblMaster_Inputs[Baseline_Amount], tblMaster_Inputs[Year], 2025, tblMaster_Inputs[Treatment_Profile], "Sec1250_Recap", tblMaster_Inputs[Activity_Type], "Baseline") | J31: =I31+SUMIFS(tblY2025_Strategies[Amount],tblY2025_Strategies[TargetLine],"7")-SUMIFS(tblY2025_Strategies[Amount],tblY2025_Strategies[CounterLine],"7") | K31: Calc_CapGainsTax
H32: Short-term capital gains (taxed as ordinary income) | I32: =SUMIFS(tblMaster_Inputs[Baseline_Amount], tblMaster_Inputs[Year], 2025, tblMaster_Inputs[Treatment_Profile], "STCG_Stock", tblMaster_Inputs[Activity_Type], "Baseline") | J32: =I32 | K32: Calc_OrdinaryTax (ST folded into ordinary income)
H33: §1250 unrecaptured gain (sub-carve of CG_LT; capped at 25% rate) | I33: =SUMIFS(tblMaster_Inputs[Helper_Amount], tblMaster_Inputs[Year], 2025, tblMaster_Inputs[Helper_Treatment], "SEC1250", tblMaster_Inputs[Activity_Type], "Baseline") | J33: =I33 | K33: Calc_1250Tax
H36: Description | I36: Formula / Value | J36: Effective | K36: Used by LAMBDA
H37: Ordinary income (TaxableIncome - CG_LT - QUAL_DIV - SEC1250) | I37: =J18-I31-I30-I33 | J37: =O18-J31-J30-J33 | K37: Calc_CapGainsTax stacking base · Calc_OrdinaryTax (after carve-outs)
H38: Modified AGI = AGI + tax-exempt interest | I38: =J15+I29 | J38: =O15+J29 | K38: Calc_NIIT · PassiveLossAllowed_FN
H39: Net Investment Income = taxable int + div + cap gain + passive | I39: =J8+J10+J11+I28 | J39: =O8+O10+O11+J28 | K39: Calc_NIIT
H40: QBI-eligible business income (active business) | I40: =I26+I27 | J40: =J26+J27 | K40: Calc_QBI_Simple · QBI_FN
H41: Taxable Income BEFORE QBI deduction (= AGI - StdItemDed) | I41: =J15+J16 | J41: =O15+O16 | K41: Calc_QBI_Simple (cap reference)
H42: Net business loss (only when negative; for EBL limit) | I42: =MIN(0,I26+I27+I28) | J42: =MIN(0,J26+J27+J28) | K42: ExcessBusinessLossLimit_FN
H43: Net SE income (alias of BI_SE_SUBJECT for LAMBDA clarity) | I43: =I26 | J43: =J26 | K43: Calc_SE_Tax · AddlMedicareTax_FN · SETax_FN
H44: Unadjusted Basis Immediately After Acquisition (QBI W-2/UBIA test) | I44: 0 | J44: =I44 | K44: QBI_FN
H45: Is Specified Service Trade or Business? (TRUE/FALSE) | I45: =IF(Control_Panel!C21="Yes",TRUE,FALSE) | J45: =I45 | K45: QBI_FN
H46: NOL carryforward available (from prior-year Carryovers; populate manually for now) | I46: =Carryovers!F52 | J46: =I46 | K46: NOLDeductionAllowed_FN
H49: 1z | K49: =HYPERLINK("#Master_Inputs!A1", "✏ open Master_Inputs to edit")
H51: Bucket | I51: Treatment_Profile | K51: Payor | L51: Baseline_Amount | M51: Helper_Amount | N51: Notes
H65: ▸ 7-COMPONENT TAX CALCULATOR | I65: Baseline | J65: Effective | K65: Δ Savings
H66: Dual columns: Baseline (H) vs With Planning (I)
H68: 1. SELF-EMPLOYMENT TAX
H69: SE Tax Label
H70: Net SE Earnings | I70: =I43 | J70: =J43
H71: SE Base (× 0.9235) | I71: =I70*SUMIFS(tblThresholds[Value], tblThresholds[Year], 2025, tblThresholds[FilingStatus], Filing_Status, tblThresholds[Item], "SE_Earnings_Factor") | J71: =J70*SUMIFS(tblThresholds[Value], tblThresholds[Year], 2025, tblThresholds[FilingStatus], Filing_Status, tblThresholds[Item], "SE_Earnings_Factor")
H72: W-2 Wages | I72: =I25 | J72: =J25
H73: Remaining SS Wage Base | I73: =MAX(0,SUMIFS(tblThresholds[Value], tblThresholds[Year], 2025, tblThresholds[FilingStatus], Filing_Status, tblThresholds[Item], "SS_Wage_Base")-I72) | J73: =MAX(0,SUMIFS(tblThresholds[Value], tblThresholds[Year], 2025, tblThresholds[FilingStatus], Filing_Status, tblThresholds[Item], "SS_Wage_Base")-J72)
I74: =MIN(I71,I73) | J74: =MIN(J71,J73)
H75: Social Security Tax (12.4%) | I75: =I74*SUMIFS(tblThresholds[Value], tblThresholds[Year], 2025, tblThresholds[FilingStatus], Filing_Status, tblThresholds[Item], "SS_Rate_Combined") | J75: =J74*SUMIFS(tblThresholds[Value], tblThresholds[Year], 2025, tblThresholds[FilingStatus], Filing_Status, tblThresholds[Item], "SS_Rate_Combined")
H76: Medicare Tax (2.9%) | I76: =I71*SUMIFS(tblThresholds[Value], tblThresholds[Year], 2025, tblThresholds[FilingStatus], Filing_Status, tblThresholds[Item], "Medicare_Rate_Combined") | J76: =J71*SUMIFS(tblThresholds[Value], tblThresholds[Year], 2025, tblThresholds[FilingStatus], Filing_Status, tblThresholds[Item], "Medicare_Rate_Combined")
H77: Addl Medicare (0.9% > threshold) | I77: =MAX(0,(I72+I71-SUMIFS(tblThresholds[Value], tblThresholds[Year], 2025, tblThresholds[FilingStatus], Filing_Status, tblThresholds[Item], "Addl_Medicare_Threshold"))*SUMIFS(tblThresholds[Value], tblThresholds[Year], 2025, tblThresholds[FilingStatus], Filing_Status, tblThresholds[Item], "Addl_Medicare_Rate")) | J77: =MAX(0,(J72+J71-SUMIFS(tblThresholds[Value], tblThresholds[Year], 2025, tblThresholds[FilingStatus], Filing_Status, tblThresholds[Item], "Addl_Medicare_Threshold"))*SUMIFS(tblThresholds[Value], tblThresholds[Year], 2025, tblThresholds[FilingStatus], Filing_Status, tblThresholds[Item], "Addl_Medicare_Rate"))
I78: =-(I75+I76)/2 | J78: =-(J75+J76)/2
H80: TOTAL SE TAX | I80: =I75+I76+I77 | J80: =J75+J76+J77 | K80: =I80-J80
H82: 2. PAYROLL TAX
H83: W-2 Wages | I83: =I25 | J83: =J25
H84: Social Security (6.2%) | I84: =MIN(I83,SUMIFS(tblThresholds[Value], tblThresholds[Year], 2025, tblThresholds[FilingStatus], Filing_Status, tblThresholds[Item], "SS_Wage_Base"))*0.062 | J84: =MIN(J83,SUMIFS(tblThresholds[Value], tblThresholds[Year], 2025, tblThresholds[FilingStatus], Filing_Status, tblThresholds[Item], "SS_Wage_Base"))*0.062
H85: Medicare (1.45%) | I85: =I83*0.0145 | J85: =J83*0.0145
H86: Addl Medicare (0.9% > threshold) | I86: =MAX(0,(I83-SUMIFS(tblThresholds[Value], tblThresholds[Year], 2025, tblThresholds[FilingStatus], Filing_Status, tblThresholds[Item], "Addl_Medicare_Threshold"))*SUMIFS(tblThresholds[Value], tblThresholds[Year], 2025, tblThresholds[FilingStatus], Filing_Status, tblThresholds[Item], "Addl_Medicare_Rate")) | J86: =MAX(0,(J83-SUMIFS(tblThresholds[Value], tblThresholds[Year], 2025, tblThresholds[FilingStatus], Filing_Status, tblThresholds[Item], "Addl_Medicare_Threshold"))*SUMIFS(tblThresholds[Value], tblThresholds[Year], 2025, tblThresholds[FilingStatus], Filing_Status, tblThresholds[Item], "Addl_Medicare_Rate"))
H87: TOTAL PAYROLL TAX | I87: =I84+I85+I86 | J87: =J84+J85+J86 | K87: =I87-J87
H88: Employer Social Security (6.2%) | I88: =I84 | J88: =J84 | K88: =I88-J88
H89: Employer Medicare (1.45%) | I89: =I85 | J89: =J85 | K89: =I89-J89
H91: TOTAL PAYROLL TAX (Employee + Employer) | I91: =I87+I88+I89 | J91: =J87+J88+J89 | K91: =I91-J91
H93: 3. ORDINARY INCOME TAX
H94: Taxable Income | I94: =I37 | J94: =J37
H95: Ordinary Taxable (TI - LTCG - QD) | I95: =MAX(0,I94) | J95: =MAX(0,J94)
H96: Tax (SUMPRODUCT bracket lookup) | I96: {=SUMPRODUCT((tblBrackets_FIT[Year]=2025)*(tblBrackets_FIT[FilingStatus]=Filing_Status)*((I95>tblBrackets_FIT[Upper])*(tblBrackets_FIT[Upper]-tblBrackets_FIT[Lower])+(I95>tblBrackets_FIT[Lower])*(I95<=tblBrackets_FIT[Upper])*(I95-tblBrackets_FIT[Lower]))*tblBrackets_FIT[Rate])} | J96: {=SUMPRODUCT((tblBrackets_FIT[Year]=2025)*(tblBrackets_FIT[FilingStatus]=Filing_Status)*((J95>tblBrackets_FIT[Upper])*(tblBrackets_FIT[Upper]-tblBrackets_FIT[Lower])+(J95>tblBrackets_FIT[Lower])*(J95<=tblBrackets_FIT[Upper])*(J95-tblBrackets_FIT[Lower]))*tblBrackets_FIT[Rate])}
H97: TOTAL ORDINARY TAX | I97: =I96 | J97: =J96 | K97: =I97-J97
H99: 4. CAPITAL GAINS / QUALIFIED DIVIDENDS TAX
H100: LTCG + Qualified Dividends | I100: =I31+I30 | J100: =J31+J30
H101: Sec 1250 Recapture Gain | I101: =I33 | J101: =J33
H102: Stacking Base (Ordinary TI for bracket floor) | I102: =I95 | J102: =J95
H103: Full CG Rate Tax (SUMPRODUCT stack) | I103: {=SUMPRODUCT((Tax_Ref!$B$210:$B$281=2025)*(Tax_Ref!$C$210:$C$281=Filing_Status)*((I102+I100>Tax_Ref!$E$210:$E$281)*(Tax_Ref!$E$210:$E$281-Tax_Ref!$D$210:$D$281)+(I102+I100>Tax_Ref!$D$210:$D$281)*(I102+I100<=Tax_Ref!$E$210:$E$281)*(I102+I100-Tax_Ref!$D$210:$D$281))*Tax_Ref!$F$210:$F$281)} | J103: {=SUMPRODUCT((Tax_Ref!$B$210:$B$281=2025)*(Tax_Ref!$C$210:$C$281=Filing_Status)*((J102+J100>Tax_Ref!$E$210:$E$281)*(Tax_Ref!$E$210:$E$281-Tax_Ref!$D$210:$D$281)+(J102+J100>Tax_Ref!$D$210:$D$281)*(J102+J100<=Tax_Ref!$E$210:$E$281)*(J102+J100-Tax_Ref!$D$210:$D$281))*Tax_Ref!$F$210:$F$281)}
H104: CG Rate Tax on Ordinary only | I104: {=SUMPRODUCT((Tax_Ref!$B$210:$B$281=2025)*(Tax_Ref!$C$210:$C$281=Filing_Status)*((I102>Tax_Ref!$E$210:$E$281)*(Tax_Ref!$E$210:$E$281-Tax_Ref!$D$210:$D$281)+(I102>Tax_Ref!$D$210:$D$281)*(I102<=Tax_Ref!$E$210:$E$281)*(I102-Tax_Ref!$D$210:$D$281))*Tax_Ref!$F$210:$F$281)} | J104: {=SUMPRODUCT((Tax_Ref!$B$210:$B$281=2025)*(Tax_Ref!$C$210:$C$281=Filing_Status)*((J102>Tax_Ref!$E$210:$E$281)*(Tax_Ref!$E$210:$E$281-Tax_Ref!$D$210:$D$281)+(J102>Tax_Ref!$D$210:$D$281)*(J102<=Tax_Ref!$E$210:$E$281)*(J102-Tax_Ref!$D$210:$D$281))*Tax_Ref!$F$210:$F$281)}
H105: Net LTCG/QD Tax | I105: =I103-I104 | J105: =J103-J104
I106: =I33*0.25 | J106: =J33*0.25
H107: TOTAL CAP GAINS TAX | I107: =I105+I106 | J107: =J105+J106 | K107: =I107-J107
H109: 5. NET INVESTMENT INCOME TAX (NIIT)
H110: MAGI | I110: =I38 | J110: =J38
H111: NIIT Threshold | I111: =SUMIFS(tblThresholds[Value], tblThresholds[Year], 2025, tblThresholds[FilingStatus], Filing_Status, tblThresholds[Item], "NIIT_Threshold") | J111: =SUMIFS(tblThresholds[Value], tblThresholds[Year], 2025, tblThresholds[FilingStatus], Filing_Status, tblThresholds[Item], "NIIT_Threshold")
H112: Net Investment Income (NII) | I112: =MAX(0,I39) | J112: =MAX(0,J39)
H113: NIIT Base (lesser of NII or MAGI excess) | I113: =MAX(0,I110-I111) | J113: =MAX(0,J110-J111)
H114: NIIT (3.8%) | I114: =MIN(I112,I113)*SUMIFS(tblThresholds[Value], tblThresholds[Year], 2025, tblThresholds[FilingStatus], Filing_Status, tblThresholds[Item], "NIIT_Rate") | J114: =MIN(J112,J113)*SUMIFS(tblThresholds[Value], tblThresholds[Year], 2025, tblThresholds[FilingStatus], Filing_Status, tblThresholds[Item], "NIIT_Rate") | K114: =I114-J114
H116: 6. QBI DEDUCTION (§199A)
H117: QBI-Eligible Income | I117: =I40 | J117: =J40
H118: 20% of QBI | I118: =MAX(0,I117)*0.2 | J118: =MAX(0,J117)*0.2
H119: 50% of W-2 Wages | I119: =MAX(0,I41)*0.2 | J119: =MAX(0,J41)*0.2
H120: 25% W-2 + 2.5% UBIA | I120: =MAX(I23*0.5, I23*0.25+I44*0.025) | J120: =MAX(J23*0.5, J23*0.25+J44*0.025)
H121: Phase-in applies? | I121: =IF(I41>SUMIFS(tblThresholds[Value], tblThresholds[Year], 2025, tblThresholds[FilingStatus], Filing_Status, tblThresholds[Item], "QBI_Threshold_Start"),"YES","NO") | J121: =IF(J41>SUMIFS(tblThresholds[Value], tblThresholds[Year], 2025, tblThresholds[FilingStatus], Filing_Status, tblThresholds[Item], "QBI_Threshold_Start"),"YES","NO")
H122: QBI DEDUCTION | I122: =IF(AND(I45=TRUE,I41>SUMIFS(tblThresholds[Value], tblThresholds[Year], 2025, tblThresholds[FilingStatus], Filing_Status, tblThresholds[Item], "QBI_Threshold_End")),0,IF(I41<=SUMIFS(tblThresholds[Value], tblThresholds[Year], 2025, tblThresholds[FilingStatus], Filing_Status, tblThresholds[Item], "QBI_Threshold_Start"),MIN(I118,I119),MIN(I118,I119,I120))) | J122: =IF(AND(J45=TRUE,J41>SUMIFS(tblThresholds[Value], tblThresholds[Year], 2025, tblThresholds[FilingStatus], Filing_Status, tblThresholds[Item], "QBI_Threshold_End")),0,IF(J41<=SUMIFS(tblThresholds[Value], tblThresholds[Year], 2025, tblThresholds[FilingStatus], Filing_Status, tblThresholds[Item], "QBI_Threshold_Start"),MIN(J118,J119),MIN(J118,J119,J120))) | K122: =J122-I122
H124: 7. COMBINED TAX SUMMARY
H125: Total Income | I125: =J6+J8+J10+J11+J12 | J125: =O13 | K125: Δ Savings
H126: Ordinary Tax | I126: =I97 | J126: =J97 | K126: =I126-J126
H127: Capital Gains Tax | I127: =I107 | J127: =J107 | K127: =I127-J127
H128: Self-Employment Tax | I128: =I80 | J128: =J80 | K128: =I128-J128
H129: Payroll Tax (Employee + Employer) | I129: =I91 | J129: =J91 | K129: =I129-J129
...

Sheet Y2026
A1: Y2026 — standalone tax planning sandbox
A2: Strategies: enter Amount + Status below. Committed strategies flow to rollup M column. Push to Master_Inputs when final.
A4: ▸ STRATEGIES
A5: StrategyID | B5: Strategy Name | C5: TargetLine | D5: Amount | E5: Status | F5: Notes | G5: CounterLine | H5: Line | I5: Description | J5: Baseline (Master) | K5: PY? | L5: S1 Override | M5: Strategies | N5: Effective | O5: Eff w/ Strategies | P5: Drill
A6: STR-001 | B6: S-Corp Wage Optimization | C6: 1z | H6: 1z | I6: Wages | J6: =SUMIFS(tblMaster_Inputs[Baseline_Amount],tblMaster_Inputs[Year],2026,tblMaster_Inputs[Primary_Line],$H6, tblMaster_Inputs[Activity_Type], "Baseline") | M6: =SUMIFS(tblY2026_Strategies[Amount],tblY2026_Strategies[TargetLine],$H6)-SUMIFS(tblY2026_Strategies[Amount],tblY2026_Strategies[CounterLine],$H6) | N6: =IF(UPPER(K6)="Y",SUMIFS(tblMaster_Inputs[Baseline_Amount],tblMaster_Inputs[Year],2025,tblMaster_Inputs[Primary_Line],"1z"),IF(ISBLANK(L6),J6,L6)) | O6: =N6+M6 | P6: =HYPERLINK("#Y2026!I49","↗ drill")
A7: STR-002 | B7: HSA Family Max | C7: 10 | H7: 2a | I7: Tax-exempt interest | J7: =SUMIFS(tblMaster_Inputs[Helper_Amount],tblMaster_Inputs[Year],2026,tblMaster_Inputs[Helper_Treatment],"TAX_EXEMPT") | M7: =SUMIFS(tblY2026_Strategies[Amount],tblY2026_Strategies[TargetLine],"2a",tblY2026_Strategies[Status],"Committed") | N7: =IF(UPPER(K7)="Y",SUMIFS(tblMaster_Inputs[Helper_Amount],tblMaster_Inputs[Year],2025,tblMaster_Inputs[Helper_Treatment],"TAX_EXEMPT"),IF(ISBLANK(L7),J7,L7)) | O7: =N7 | P7: =HYPERLINK("#Y2026!I49","↗ drill")
A8: STR-003 | B8: Charitable Bunching (DAF) | C8: 12 | H8: 2b | I8: Taxable interest | J8: =SUMIFS(tblMaster_Inputs[Baseline_Amount],tblMaster_Inputs[Year],2026,tblMaster_Inputs[Primary_Line],$H8, tblMaster_Inputs[Activity_Type], "Baseline") | M8: =SUMIFS(tblY2026_Strategies[Amount],tblY2026_Strategies[TargetLine],$H8)-SUMIFS(tblY2026_Strategies[Amount],tblY2026_Strategies[CounterLine],$H8) | N8: =IF(UPPER(K8)="Y",SUMIFS(tblMaster_Inputs[Baseline_Amount],tblMaster_Inputs[Year],2025,tblMaster_Inputs[Primary_Line],"2b"),IF(ISBLANK(L8),J8,L8)) | O8: =N8+M8 | P8: =HYPERLINK("#Y2026!I49","↗ drill")
A9: STR-004 | B9: SEP-IRA / Solo 401(k) | C9: 10 | H9: 3a | I9: Qualified dividends | J9: =SUMIFS(tblMaster_Inputs[Helper_Amount],tblMaster_Inputs[Year],2026,tblMaster_Inputs[Helper_Treatment],"QUAL_DIV") | M9: =SUMIFS(tblY2026_Strategies[Amount],tblY2026_Strategies[TargetLine],"3a",tblY2026_Strategies[Status],"Committed") | N9: =IF(UPPER(K9)="Y",SUMIFS(tblMaster_Inputs[Helper_Amount],tblMaster_Inputs[Year],2025,tblMaster_Inputs[Helper_Treatment],"QUAL_DIV"),IF(ISBLANK(L9),J9,L9)) | O9: =N9 | P9: =HYPERLINK("#Y2026!I49","↗ drill")
A10: STR-005 | B10: Cost Seg Study | C10: 8 | H10: 3b | I10: Ordinary dividends | J10: =SUMIFS(tblMaster_Inputs[Baseline_Amount],tblMaster_Inputs[Year],2026,tblMaster_Inputs[Primary_Line],$H10, tblMaster_Inputs[Activity_Type], "Baseline") | M10: =SUMIFS(tblY2026_Strategies[Amount],tblY2026_Strategies[TargetLine],$H10)-SUMIFS(tblY2026_Strategies[Amount],tblY2026_Strategies[CounterLine],$H10) | N10: =IF(UPPER(K10)="Y",SUMIFS(tblMaster_Inputs[Baseline_Amount],tblMaster_Inputs[Year],2025,tblMaster_Inputs[Primary_Line],"3b"),IF(ISBLANK(L10),J10,L10)) | O10: =N10+M10 | P10: =HYPERLINK("#Y2026!I49","↗ drill")
A11: STR-006 | B11: Roth Conversion | C11: 1z | H11: 7 | I11: Capital gain/(loss) | J11: =SUMIFS(tblMaster_Inputs[Baseline_Amount],tblMaster_Inputs[Year],2026,tblMaster_Inputs[Primary_Line],$H11, tblMaster_Inputs[Activity_Type], "Baseline") | M11: =SUMIFS(tblY2026_Strategies[Amount],tblY2026_Strategies[TargetLine],$H11)-SUMIFS(tblY2026_Strategies[Amount],tblY2026_Strategies[CounterLine],$H11) | N11: =IF(UPPER(K11)="Y",SUMIFS(tblMaster_Inputs[Baseline_Amount],tblMaster_Inputs[Year],2025,tblMaster_Inputs[Primary_Line],"7"),IF(ISBLANK(L11),J11,L11)) | O11: =N11+M11 | P11: =HYPERLINK("#Y2026!I49","↗ drill")
A12: STR-007 | B12: Augusta Rule (§280A) | C12: 8 | H12: 8 | I12: Other income (business) | J12: =SUMIFS(tblMaster_Inputs[Baseline_Amount],tblMaster_Inputs[Year],2026,tblMaster_Inputs[Primary_Line],$H12, tblMaster_Inputs[Activity_Type], "Baseline") | M12: =SUMIFS(tblY2026_Strategies[Amount],tblY2026_Strategies[TargetLine],$H12)-SUMIFS(tblY2026_Strategies[Amount],tblY2026_Strategies[CounterLine],$H12) | N12: =IF(UPPER(K12)="Y",SUMIFS(tblMaster_Inputs[Baseline_Amount],tblMaster_Inputs[Year],2025,tblMaster_Inputs[Primary_Line],"8"),IF(ISBLANK(L12),J12,L12)) | O12: =N12+M12 | P12: =HYPERLINK("#Y2026!I49","↗ drill")
A13: STR-008 | B13: Accountable Plan | C13: 8 | H13: 9 | I13: TOTAL INCOME | J13: =J6+J8+J10+J11+J12 | M13: =M6+M8+M10+M11+M12 | N13: =N6+N8+N10+N11+N12 | O13: =O6+O8+O10+O11+O12 | P13: =HYPERLINK("#Y2026!I49","↗ drill")
A14: STR-009 | B14: Hire Children | C14: 8 | H14: 10 | I14: Adjustments | J14: =SUMIFS(tblMaster_Inputs[Baseline_Amount],tblMaster_Inputs[Year],2026,tblMaster_Inputs[Primary_Line],$H14, tblMaster_Inputs[Activity_Type], "Baseline") | M14: =SUMIFS(tblY2026_Strategies[Amount],tblY2026_Strategies[TargetLine],$H14)-SUMIFS(tblY2026_Strategies[Amount],tblY2026_Strategies[CounterLine],$H14) | N14: =IF(UPPER(K14)="Y",SUMIFS(tblMaster_Inputs[Baseline_Amount],tblMaster_Inputs[Year],2025,tblMaster_Inputs[Primary_Line],"10"),IF(ISBLANK(L14),J14,L14)) | O14: =N14+M14 | P14: =HYPERLINK("#Y2026!I49","↗ drill")
A15: STR-010 | B15: Entity Restructuring | C15: 8 | H15: 11 | I15: AGI | J15: =J13+J14 | M15: =M13+M14 | N15: =N13+N14 | O15: =O13+O14 | P15: =HYPERLINK("#Y2026!I49","↗ drill")
A16: STR-011 | B16: Installment Sale / 1031 | C16: 7 | H16: 12 | I16: Std/Itemized ded | J16: =SUMIFS(tblMaster_Inputs[Baseline_Amount],tblMaster_Inputs[Year],2026,tblMaster_Inputs[Primary_Line],$H16, tblMaster_Inputs[Activity_Type], "Baseline") | M16: =SUMIFS(tblY2026_Strategies[Amount],tblY2026_Strategies[TargetLine],$H16)-SUMIFS(tblY2026_Strategies[Amount],tblY2026_Strategies[CounterLine],$H16) | N16: =IF(UPPER(K16)="Y",SUMIFS(tblMaster_Inputs[Baseline_Amount],tblMaster_Inputs[Year],2025,tblMaster_Inputs[Primary_Line],"12"),IF(ISBLANK(L16),J16,L16)) | O16: =N16+M16 | P16: =HYPERLINK("#Y2026!I49","↗ drill")
A17: STR-012 | B17: Bonus Depreciation §168(k) | C17: 8 | H17: 13 | I17: QBI deduction | J17: =SUMIFS(tblMaster_Inputs[Baseline_Amount],tblMaster_Inputs[Year],2026,tblMaster_Inputs[Primary_Line],$H17, tblMaster_Inputs[Activity_Type], "Baseline") | M17: =SUMIFS(tblY2026_Strategies[Amount],tblY2026_Strategies[TargetLine],$H17)-SUMIFS(tblY2026_Strategies[Amount],tblY2026_Strategies[CounterLine],$H17) | N17: =IF(UPPER(K17)="Y",SUMIFS(tblMaster_Inputs[Baseline_Amount],tblMaster_Inputs[Year],2025,tblMaster_Inputs[Primary_Line],"13"),IF(ISBLANK(L17),J17,L17)) | O17: =N17+M17 | P17: =HYPERLINK("#Y2026!I49","↗ drill")
A18: STR-013 | B18: R&D Credit §41 | C18: 13 | H18: 15 | I18: TAXABLE INCOME | J18: =J15+J16+J17 | M18: =M15+M16+M17 | N18: =N15+N16+N17 | O18: =O15+O16+O17 | P18: =HYPERLINK("#Y2026!I49","↗ drill")
A19: STR-014 | B19: SALT PTE Election | C19: 12
A20: STR-015 | B20: Timing / Deferral | C20: 8
A22: ▸ TAX IMPACT SUMMARY | H22: Description | I22: Amount | J22: Effective | K22: Used by
A23: Metric | B23: Baseline | C23: Effective | D23: Eff w/ Strat | E23: Savings | H23: Owner W-2 | I23: =SUMIFS(tblMaster_Inputs[Baseline_Amount],tblMaster_Inputs[Year],2026,tblMaster_Inputs[Treatment_Profile],"W2_SCorpOwner", tblMaster_Inputs[Activity_Type], "Baseline") | J23: =I23+SUMIFS(tblY2026_Strategies[Amount],tblY2026_Strategies[TargetLine],"1z")-SUMIFS(tblY2026_Strategies[Amount],tblY2026_Strategies[CounterLine],"1z")
A24: Total Income | B24: =J13 | C24: =N13 | D24: =O13 | E24: =B24-D24 | H24: Third-party W-2 | I24: =SUMIFS(tblMaster_Inputs[Baseline_Amount],tblMaster_Inputs[Year],2026,tblMaster_Inputs[Treatment_Profile],"W2_Employee", tblMaster_Inputs[Activity_Type], "Baseline") | J24: =I24
A25: Taxable Income | B25: =J18 | C25: =N18 | D25: =O18 | E25: =B25-D25 | H25: Total W-2 | I25: =I23+I24 | J25: =J23+J24
A26: Total Tax | B26: =I133 | C26: =I133 | D26: =J133 | E26: =B26-D26 | H26: SE business | I26: =SUMIFS(tblMaster_Inputs[Baseline_Amount],tblMaster_Inputs[Year],2026,tblMaster_Inputs[Bucket],"Business Income",tblMaster_Inputs[SE_Subject],"Yes", tblMaster_Inputs[Activity_Type], "Baseline") | J26: =I26
A27: Effective Rate | B27: =I134 | C27: =I134 | D27: =J134 | E27: =B27-D27 | H27: Active non-SE | I27: =SUMIFS(tblMaster_Inputs[Baseline_Amount],tblMaster_Inputs[Year],2026,tblMaster_Inputs[Bucket],"Business Income",tblMaster_Inputs[SE_Subject],"No",tblMaster_Inputs[NIIT_Class],"Active", tblMaster_Inputs[Activity_Type], "Baseline") | J27: =I27+SUMIFS(tblY2026_Strategies[Amount],tblY2026_Strategies[TargetLine],"8")-SUMIFS(tblY2026_Strategies[Amount],tblY2026_Strategies[CounterLine],"8")
A28: Committed Strategies | B28: =COUNTIF(tblY2026_Strategies[Status],"Committed") | C28: Net Strategy Impact | D28: =SUMIF(tblY2026_Strategies[Status],"Committed",tblY2026_Strategies[Amount]) | H28: Passive business | I28: =SUMIFS(tblMaster_Inputs[Baseline_Amount],tblMaster_Inputs[Year],2026,tblMaster_Inputs[Bucket],"Business Income",tblMaster_Inputs[NIIT_Class],"Passive", tblMaster_Inputs[Activity_Type], "Baseline") | J28: =I28
H29: Tax-exempt int | I29: =SUMIFS(tblMaster_Inputs[Helper_Amount],tblMaster_Inputs[Year],2026,tblMaster_Inputs[Helper_Treatment],"TAX_EXEMPT") | J29: =I29+SUMIFS(tblY2026_Strategies[Amount],tblY2026_Strategies[TargetLine],"2a")-SUMIFS(tblY2026_Strategies[Amount],tblY2026_Strategies[CounterLine],"2a")
H30: Qualified div | I30: =SUMIFS(tblMaster_Inputs[Helper_Amount],tblMaster_Inputs[Year],2026,tblMaster_Inputs[Helper_Treatment],"QUAL_DIV", tblMaster_Inputs[Activity_Type], "Baseline") | J30: =I30
H31: LT cap gains | I31: =SUMIFS(tblMaster_Inputs[Baseline_Amount],tblMaster_Inputs[Year],2026,tblMaster_Inputs[Treatment_Profile],"LTCG_Stock")+SUMIFS(tblMaster_Inputs[Baseline_Amount],tblMaster_Inputs[Year],2026,tblMaster_Inputs[Treatment_Profile],"LTCG_RE")+SUMIFS(tblMaster_Inputs[Baseline_Amount],tblMaster_Inputs[Year],2026,tblMaster_Inputs[Treatment_Profile],"LTCG_K1_Passthrough")+SUMIFS(tblMaster_Inputs[Baseline_Amount],tblMaster_Inputs[Year],2026,tblMaster_Inputs[Treatment_Profile],"Sec1250_Recap", tblMaster_Inputs[Activity_Type], "Baseline") | J31: =I31+SUMIFS(tblY2026_Strategies[Amount],tblY2026_Strategies[TargetLine],"7")-SUMIFS(tblY2026_Strategies[Amount],tblY2026_Strategies[CounterLine],"7")
H32: ST cap gains | I32: =SUMIFS(tblMaster_Inputs[Baseline_Amount],tblMaster_Inputs[Year],2026,tblMaster_Inputs[Treatment_Profile],"STCG_Stock", tblMaster_Inputs[Activity_Type], "Baseline") | J32: =I32
H33: §1250 gain | I33: =SUMIFS(tblMaster_Inputs[Helper_Amount],tblMaster_Inputs[Year],2026,tblMaster_Inputs[Helper_Treatment],"SEC1250", tblMaster_Inputs[Activity_Type], "Baseline") | J33: =I33
H36: Description | I36: Value | J36: Effective | K36: Used by
H37: TI-LTCG-QD-1250 | I37: =J18-I31-I30-I33 | J37: =O18-J31-J30-J33
H38: AGI+tax-exempt | I38: =J15+I29 | J38: =O15+J29
H39: Net inv income | I39: =J8+J10+J11+I28 | J39: =O8+O10+O11+J28
H40: QBI-eligible | I40: =I26+I27 | J40: =J26+J27
H41: TI before QBI | I41: =J15+J16 | J41: =O15+O16
H42: Net biz loss | I42: =MIN(0,I26+I27+I28) | J42: =MIN(0,J26+J27+J28)
H43: Net SE | I43: =I26 | J43: =J26
J44: =I44
I45: =IF(Control_Panel!C21="Yes",TRUE,FALSE) | J45: =I45
I46: =Carryovers!F52 | J46: =I46
H49: 1z | K49: =HYPERLINK("#Master_Inputs!A1","✏ open Master_Inputs")
H65: ▸ 7-COMPONENT TAX CALCULATOR | I65: Baseline | J65: Effective | K65: Δ Savings
H66: Dual columns: Baseline (H) vs With Planning (I)
H68: 1. SELF-EMPLOYMENT TAX
H69: SE Tax Label
H70: Net SE Earnings | I70: =I43 | J70: =J43
H71: SE Base (× 0.9235) | I71: =I70*SUMIFS(tblThresholds[Value], tblThresholds[Year], 2026, tblThresholds[FilingStatus], Filing_Status, tblThresholds[Item], "SE_Earnings_Factor") | J71: =J70*SUMIFS(tblThresholds[Value], tblThresholds[Year], 2026, tblThresholds[FilingStatus], Filing_Status, tblThresholds[Item], "SE_Earnings_Factor")
H72: W-2 Wages | I72: =I25 | J72: =J25
H73: Remaining SS Wage Base | I73: =MAX(0,SUMIFS(tblThresholds[Value], tblThresholds[Year], 2026, tblThresholds[FilingStatus], Filing_Status, tblThresholds[Item], "SS_Wage_Base")-I72) | J73: =MAX(0,SUMIFS(tblThresholds[Value], tblThresholds[Year], 2026, tblThresholds[FilingStatus], Filing_Status, tblThresholds[Item], "SS_Wage_Base")-J72)
I74: =MIN(I71,I73) | J74: =MIN(J71,J73)
H75: Social Security Tax (12.4%) | I75: =I74*SUMIFS(tblThresholds[Value], tblThresholds[Year], 2026, tblThresholds[FilingStatus], Filing_Status, tblThresholds[Item], "SS_Rate_Combined") | J75: =J74*SUMIFS(tblThresholds[Value], tblThresholds[Year], 2026, tblThresholds[FilingStatus], Filing_Status, tblThresholds[Item], "SS_Rate_Combined")
H76: Medicare Tax (2.9%) | I76: =I71*SUMIFS(tblThresholds[Value], tblThresholds[Year], 2026, tblThresholds[FilingStatus], Filing_Status, tblThresholds[Item], "Medicare_Rate_Combined") | J76: =J71*SUMIFS(tblThresholds[Value], tblThresholds[Year], 2026, tblThresholds[FilingStatus], Filing_Status, tblThresholds[Item], "Medicare_Rate_Combined")
H77: Addl Medicare (0.9% > threshold) | I77: =MAX(0,(I72+I71-SUMIFS(tblThresholds[Value], tblThresholds[Year], 2026, tblThresholds[FilingStatus], Filing_Status, tblThresholds[Item], "Addl_Medicare_Threshold"))*SUMIFS(tblThresholds[Value], tblThresholds[Year], 2026, tblThresholds[FilingStatus], Filing_Status, tblThresholds[Item], "Addl_Medicare_Rate")) | J77: =MAX(0,(J72+J71-SUMIFS(tblThresholds[Value], tblThresholds[Year], 2026, tblThresholds[FilingStatus], Filing_Status, tblThresholds[Item], "Addl_Medicare_Threshold"))*SUMIFS(tblThresholds[Value], tblThresholds[Year], 2026, tblThresholds[FilingStatus], Filing_Status, tblThresholds[Item], "Addl_Medicare_Rate"))
I78: =-(I75+I76)/2 | J78: =-(J75+J76)/2
H80: TOTAL SE TAX | I80: =I75+I76+I77 | J80: =J75+J76+J77 | K80: =I80-J80
H82: 2. PAYROLL TAX
H83: W-2 Wages | I83: =I25 | J83: =J25
H84: Social Security (6.2%) | I84: =MIN(I83,SUMIFS(tblThresholds[Value], tblThresholds[Year], 2026, tblThresholds[FilingStatus], Filing_Status, tblThresholds[Item], "SS_Wage_Base"))*0.062 | J84: =MIN(J83,SUMIFS(tblThresholds[Value], tblThresholds[Year], 2026, tblThresholds[FilingStatus], Filing_Status, tblThresholds[Item], "SS_Wage_Base"))*0.062
H85: Medicare (1.45%) | I85: =I83*0.0145 | J85: =J83*0.0145
H86: Addl Medicare (0.9% > threshold) | I86: =MAX(0,(I83-SUMIFS(tblThresholds[Value], tblThresholds[Year], 2026, tblThresholds[FilingStatus], Filing_Status, tblThresholds[Item], "Addl_Medicare_Threshold"))*SUMIFS(tblThresholds[Value], tblThresholds[Year], 2026, tblThresholds[FilingStatus], Filing_Status, tblThresholds[Item], "Addl_Medicare_Rate")) | J86: =MAX(0,(J83-SUMIFS(tblThresholds[Value], tblThresholds[Year], 2026, tblThresholds[FilingStatus], Filing_Status, tblThresholds[Item], "Addl_Medicare_Threshold"))*SUMIFS(tblThresholds[Value], tblThresholds[Year], 2026, tblThresholds[FilingStatus], Filing_Status, tblThresholds[Item], "Addl_Medicare_Rate"))
H87: TOTAL PAYROLL TAX | I87: =I84+I85+I86 | J87: =J84+J85+J86 | K87: =I87-J87
H88: Employer Social Security (6.2%) | I88: =I84 | J88: =J84 | K88: =I88-J88
H89: Employer Medicare (1.45%) | I89: =I85 | J89: =J85 | K89: =I89-J89
H91: TOTAL PAYROLL TAX (Employee + Employer) | I91: =I87+I88+I89 | J91: =J87+J88+J89 | K91: =I91-J91
H93: 3. ORDINARY INCOME TAX
H94: Taxable Income | I94: =I37 | J94: =J37
H95: Ordinary Taxable (TI - LTCG - QD) | I95: =MAX(0,I94) | J95: =MAX(0,J94)
H96: Tax (SUMPRODUCT bracket lookup) | I96: {=SUMPRODUCT((tblBrackets_FIT[Year]=2026)*(tblBrackets_FIT[FilingStatus]=Filing_Status)*((I95>tblBrackets_FIT[Upper])*(tblBrackets_FIT[Upper]-tblBrackets_FIT[Lower])+(I95>tblBrackets_FIT[Lower])*(I95<=tblBrackets_FIT[Upper])*(I95-tblBrackets_FIT[Lower]))*tblBrackets_FIT[Rate])} | J96: {=SUMPRODUCT((tblBrackets_FIT[Year]=2026)*(tblBrackets_FIT[FilingStatus]=Filing_Status)*((J95>tblBrackets_FIT[Upper])*(tblBrackets_FIT[Upper]-tblBrackets_FIT[Lower])+(J95>tblBrackets_FIT[Lower])*(J95<=tblBrackets_FIT[Upper])*(J95-tblBrackets_FIT[Lower]))*tblBrackets_FIT[Rate])}
H97: TOTAL ORDINARY TAX | I97: =I96 | J97: =J96 | K97: =I97-J97
H99: 4. CAPITAL GAINS / QUALIFIED DIVIDENDS TAX
H100: LTCG + Qualified Dividends | I100: =I31+I30 | J100: =J31+J30
H101: Sec 1250 Recapture Gain | I101: =I33 | J101: =J33
H102: Stacking Base (Ordinary TI for bracket floor) | I102: =I95 | J102: =J95
H103: Full CG Rate Tax (SUMPRODUCT stack) | I103: {=SUMPRODUCT((Tax_Ref!$B$210:$B$281=2026)*(Tax_Ref!$C$210:$C$281=Filing_Status)*((I102+I100>Tax_Ref!$E$210:$E$281)*(Tax_Ref!$E$210:$E$281-Tax_Ref!$D$210:$D$281)+(I102+I100>Tax_Ref!$D$210:$D$281)*(I102+I100<=Tax_Ref!$E$210:$E$281)*(I102+I100-Tax_Ref!$D$210:$D$281))*Tax_Ref!$F$210:$F$281)} | J103: {=SUMPRODUCT((Tax_Ref!$B$210:$B$281=2026)*(Tax_Ref!$C$210:$C$281=Filing_Status)*((J102+J100>Tax_Ref!$E$210:$E$281)*(Tax_Ref!$E$210:$E$281-Tax_Ref!$D$210:$D$281)+(J102+J100>Tax_Ref!$D$210:$D$281)*(J102+J100<=Tax_Ref!$E$210:$E$281)*(J102+J100-Tax_Ref!$D$210:$D$281))*Tax_Ref!$F$210:$F$281)}
H104: CG Rate Tax on Ordinary only | I104: {=SUMPRODUCT((Tax_Ref!$B$210:$B$281=2026)*(Tax_Ref!$C$210:$C$281=Filing_Status)*((I102>Tax_Ref!$E$210:$E$281)*(Tax_Ref!$E$210:$E$281-Tax_Ref!$D$210:$D$281)+(I102>Tax_Ref!$D$210:$D$281)*(I102<=Tax_Ref!$E$210:$E$281)*(I102-Tax_Ref!$D$210:$D$281))*Tax_Ref!$F$210:$F$281)} | J104: {=SUMPRODUCT((Tax_Ref!$B$210:$B$281=2026)*(Tax_Ref!$C$210:$C$281=Filing_Status)*((J102>Tax_Ref!$E$210:$E$281)*(Tax_Ref!$E$210:$E$281-Tax_Ref!$D$210:$D$281)+(J102>Tax_Ref!$D$210:$D$281)*(J102<=Tax_Ref!$E$210:$E$281)*(J102-Tax_Ref!$D$210:$D$281))*Tax_Ref!$F$210:$F$281)}
H105: Net LTCG/QD Tax | I105: =I103-I104 | J105: =J103-J104
I106: =I33*0.25 | J106: =J33*0.25
H107: TOTAL CAP GAINS TAX | I107: =I105+I106 | J107: =J105+J106 | K107: =I107-J107
H109: 5. NET INVESTMENT INCOME TAX (NIIT)
H110: MAGI | I110: =I38 | J110: =J38
H111: NIIT Threshold | I111: =SUMIFS(tblThresholds[Value], tblThresholds[Year], 2026, tblThresholds[FilingStatus], Filing_Status, tblThresholds[Item], "NIIT_Threshold") | J111: =SUMIFS(tblThresholds[Value], tblThresholds[Year], 2026, tblThresholds[FilingStatus], Filing_Status, tblThresholds[Item], "NIIT_Threshold")
H112: Net Investment Income (NII) | I112: =MAX(0,I39) | J112: =MAX(0,J39)
H113: NIIT Base (lesser of NII or MAGI excess) | I113: =MAX(0,I110-I111) | J113: =MAX(0,J110-J111)
H114: NIIT (3.8%) | I114: =MIN(I112,I113)*SUMIFS(tblThresholds[Value], tblThresholds[Year], 2026, tblThresholds[FilingStatus], Filing_Status, tblThresholds[Item], "NIIT_Rate") | J114: =MIN(J112,J113)*SUMIFS(tblThresholds[Value], tblThresholds[Year], 2026, tblThresholds[FilingStatus], Filing_Status, tblThresholds[Item], "NIIT_Rate") | K114: =I114-J114
H116: 6. QBI DEDUCTION (§199A)
H117: QBI-Eligible Income | I117: =I40 | J117: =J40
H118: 20% of QBI | I118: =MAX(0,I117)*0.2 | J118: =MAX(0,J117)*0.2
H119: 50% of W-2 Wages | I119: =MAX(0,I41)*0.2 | J119: =MAX(0,J41)*0.2
H120: 25% W-2 + 2.5% UBIA | I120: =MAX(I23*0.5, I23*0.25+I44*0.025) | J120: =MAX(J23*0.5, J23*0.25+J44*0.025)
H121: Phase-in applies? | I121: =IF(I41>SUMIFS(tblThresholds[Value], tblThresholds[Year], 2026, tblThresholds[FilingStatus], Filing_Status, tblThresholds[Item], "QBI_Threshold_Start"),"YES","NO") | J121: =IF(J41>SUMIFS(tblThresholds[Value], tblThresholds[Year], 2026, tblThresholds[FilingStatus], Filing_Status, tblThresholds[Item], "QBI_Threshold_Start"),"YES","NO")
H122: QBI DEDUCTION | I122: =IF(AND(I45=TRUE,I41>SUMIFS(tblThresholds[Value], tblThresholds[Year], 2026, tblThresholds[FilingStatus], Filing_Status, tblThresholds[Item], "QBI_Threshold_End")),0,IF(I41<=SUMIFS(tblThresholds[Value], tblThresholds[Year], 2026, tblThresholds[FilingStatus], Filing_Status, tblThresholds[Item], "QBI_Threshold_Start"),MIN(I118,I119),MIN(I118,I119,I120))) | J122: =IF(AND(J45=TRUE,J41>SUMIFS(tblThresholds[Value], tblThresholds[Year], 2026, tblThresholds[FilingStatus], Filing_Status, tblThresholds[Item], "QBI_Threshold_End")),0,IF(J41<=SUMIFS(tblThresholds[Value], tblThresholds[Year], 2026, tblThresholds[FilingStatus], Filing_Status, tblThresholds[Item], "QBI_Threshold_Start"),MIN(J118,J119),MIN(J118,J119,J120))) | K122: =J122-I122
H124: 7. COMBINED TAX SUMMARY
H125: Total Income | I125: =J6+J8+J10+J11+J12 | J125: =O13 | K125: Δ Savings
H126: Ordinary Tax | I126: =I97 | J126: =J97 | K126: =I126-J126
H127: Capital Gains Tax | I127: =I107 | J127: =J107 | K127: =I127-J127
H128: Self-Employment Tax | I128: =I80 | J128: =J80 | K128: =I128-J128
H129: Payroll Tax (Employee + Employer) | I129: =I91 | J129: =J91 | K129: =I129-J129
H130: NIIT | I130: =I114 | J130: =J114 | K130: =I130-J130
...

Sheet Y2027
A1: Y2027 — standalone tax planning sandbox
A2: Strategies: enter Amount + Status below. Committed strategies flow to rollup M column. Push to Master_Inputs when final.
A4: ▸ STRATEGIES
A5: StrategyID | B5: Strategy Name | C5: TargetLine | D5: Amount | E5: Status | F5: Notes | G5: CounterLine | H5: Line | I5: Description | J5: Baseline (Master) | K5: PY? | L5: S1 Override | M5: Strategies | N5: Effective | O5: Eff w/ Strategies | P5: Drill
A6: STR-001 | B6: S-Corp Wage Optimization | C6: 1z | H6: 1z | I6: Wages | J6: =SUMIFS(tblMaster_Inputs[Baseline_Amount],tblMaster_Inputs[Year],2027,tblMaster_Inputs[Primary_Line],$H6, tblMaster_Inputs[Activity_Type], "Baseline") | M6: =SUMIFS(tblY2027_Strategies[Amount],tblY2027_Strategies[TargetLine],$H6)-SUMIFS(tblY2027_Strategies[Amount],tblY2027_Strategies[CounterLine],$H6) | N6: =IF(UPPER(K6)="Y",SUMIFS(tblMaster_Inputs[Baseline_Amount],tblMaster_Inputs[Year],2026,tblMaster_Inputs[Primary_Line],"1z"),IF(ISBLANK(L6),J6,L6)) | O6: =N6+M6 | P6: =HYPERLINK("#Y2027!I49","↗ drill")
A7: STR-002 | B7: HSA Family Max | C7: 10 | H7: 2a | I7: Tax-exempt interest | J7: =SUMIFS(tblMaster_Inputs[Helper_Amount],tblMaster_Inputs[Year],2027,tblMaster_Inputs[Helper_Treatment],"TAX_EXEMPT") | M7: =SUMIFS(tblY2027_Strategies[Amount],tblY2027_Strategies[TargetLine],"2a",tblY2027_Strategies[Status],"Committed") | N7: =IF(UPPER(K7)="Y",SUMIFS(tblMaster_Inputs[Helper_Amount],tblMaster_Inputs[Year],2026,tblMaster_Inputs[Helper_Treatment],"TAX_EXEMPT"),IF(ISBLANK(L7),J7,L7)) | O7: =N7 | P7: =HYPERLINK("#Y2027!I49","↗ drill")
A8: STR-003 | B8: Charitable Bunching (DAF) | C8: 12 | H8: 2b | I8: Taxable interest | J8: =SUMIFS(tblMaster_Inputs[Baseline_Amount],tblMaster_Inputs[Year],2027,tblMaster_Inputs[Primary_Line],$H8, tblMaster_Inputs[Activity_Type], "Baseline") | M8: =SUMIFS(tblY2027_Strategies[Amount],tblY2027_Strategies[TargetLine],$H8)-SUMIFS(tblY2027_Strategies[Amount],tblY2027_Strategies[CounterLine],$H8) | N8: =IF(UPPER(K8)="Y",SUMIFS(tblMaster_Inputs[Baseline_Amount],tblMaster_Inputs[Year],2026,tblMaster_Inputs[Primary_Line],"2b"),IF(ISBLANK(L8),J8,L8)) | O8: =N8+M8 | P8: =HYPERLINK("#Y2027!I49","↗ drill")
A9: STR-004 | B9: SEP-IRA / Solo 401(k) | C9: 10 | H9: 3a | I9: Qualified dividends | J9: =SUMIFS(tblMaster_Inputs[Helper_Amount],tblMaster_Inputs[Year],2027,tblMaster_Inputs[Helper_Treatment],"QUAL_DIV") | M9: =SUMIFS(tblY2027_Strategies[Amount],tblY2027_Strategies[TargetLine],"3a",tblY2027_Strategies[Status],"Committed") | N9: =IF(UPPER(K9)="Y",SUMIFS(tblMaster_Inputs[Helper_Amount],tblMaster_Inputs[Year],2026,tblMaster_Inputs[Helper_Treatment],"QUAL_DIV"),IF(ISBLANK(L9),J9,L9)) | O9: =N9 | P9: =HYPERLINK("#Y2027!I49","↗ drill")
A10: STR-005 | B10: Cost Seg Study | C10: 8 | H10: 3b | I10: Ordinary dividends | J10: =SUMIFS(tblMaster_Inputs[Baseline_Amount],tblMaster_Inputs[Year],2027,tblMaster_Inputs[Primary_Line],$H10, tblMaster_Inputs[Activity_Type], "Baseline") | M10: =SUMIFS(tblY2027_Strategies[Amount],tblY2027_Strategies[TargetLine],$H10)-SUMIFS(tblY2027_Strategies[Amount],tblY2027_Strategies[CounterLine],$H10) | N10: =IF(UPPER(K10)="Y",SUMIFS(tblMaster_Inputs[Baseline_Amount],tblMaster_Inputs[Year],2026,tblMaster_Inputs[Primary_Line],"3b"),IF(ISBLANK(L10),J10,L10)) | O10: =N10+M10 | P10: =HYPERLINK("#Y2027!I49","↗ drill")
A11: STR-006 | B11: Roth Conversion | C11: 1z | H11: 7 | I11: Capital gain/(loss) | J11: =SUMIFS(tblMaster_Inputs[Baseline_Amount],tblMaster_Inputs[Year],2027,tblMaster_Inputs[Primary_Line],$H11, tblMaster_Inputs[Activity_Type], "Baseline") | M11: =SUMIFS(tblY2027_Strategies[Amount],tblY2027_Strategies[TargetLine],$H11)-SUMIFS(tblY2027_Strategies[Amount],tblY2027_Strategies[CounterLine],$H11) | N11: =IF(UPPER(K11)="Y",SUMIFS(tblMaster_Inputs[Baseline_Amount],tblMaster_Inputs[Year],2026,tblMaster_Inputs[Primary_Line],"7"),IF(ISBLANK(L11),J11,L11)) | O11: =N11+M11 | P11: =HYPERLINK("#Y2027!I49","↗ drill")
A12: STR-007 | B12: Augusta Rule (§280A) | C12: 8 | H12: 8 | I12: Other income (business) | J12: =SUMIFS(tblMaster_Inputs[Baseline_Amount],tblMaster_Inputs[Year],2027,tblMaster_Inputs[Primary_Line],$H12, tblMaster_Inputs[Activity_Type], "Baseline") | M12: =SUMIFS(tblY2027_Strategies[Amount],tblY2027_Strategies[TargetLine],$H12)-SUMIFS(tblY2027_Strategies[Amount],tblY2027_Strategies[CounterLine],$H12) | N12: =IF(UPPER(K12)="Y",SUMIFS(tblMaster_Inputs[Baseline_Amount],tblMaster_Inputs[Year],2026,tblMaster_Inputs[Primary_Line],"8"),IF(ISBLANK(L12),J12,L12)) | O12: =N12+M12 | P12: =HYPERLINK("#Y2027!I49","↗ drill")
A13: STR-008 | B13: Accountable Plan | C13: 8 | H13: 9 | I13: TOTAL INCOME | J13: =J6+J8+J10+J11+J12 | M13: =M6+M8+M10+M11+M12 | N13: =N6+N8+N10+N11+N12 | O13: =O6+O8+O10+O11+O12 | P13: =HYPERLINK("#Y2027!I49","↗ drill")
A14: STR-009 | B14: Hire Children | C14: 8 | H14: 10 | I14: Adjustments | J14: =SUMIFS(tblMaster_Inputs[Baseline_Amount],tblMaster_Inputs[Year],2027,tblMaster_Inputs[Primary_Line],$H14, tblMaster_Inputs[Activity_Type], "Baseline") | M14: =SUMIFS(tblY2027_Strategies[Amount],tblY2027_Strategies[TargetLine],$H14)-SUMIFS(tblY2027_Strategies[Amount],tblY2027_Strategies[CounterLine],$H14) | N14: =IF(UPPER(K14)="Y",SUMIFS(tblMaster_Inputs[Baseline_Amount],tblMaster_Inputs[Year],2026,tblMaster_Inputs[Primary_Line],"10"),IF(ISBLANK(L14),J14,L14)) | O14: =N14+M14 | P14: =HYPERLINK("#Y2027!I49","↗ drill")
A15: STR-010 | B15: Entity Restructuring | C15: 8 | H15: 11 | I15: AGI | J15: =J13+J14 | M15: =M13+M14 | N15: =N13+N14 | O15: =O13+O14 | P15: =HYPERLINK("#Y2027!I49","↗ drill")
A16: STR-011 | B16: Installment Sale / 1031 | C16: 7 | H16: 12 | I16: Std/Itemized ded | J16: =SUMIFS(tblMaster_Inputs[Baseline_Amount],tblMaster_Inputs[Year],2027,tblMaster_Inputs[Primary_Line],$H16, tblMaster_Inputs[Activity_Type], "Baseline") | M16: =SUMIFS(tblY2027_Strategies[Amount],tblY2027_Strategies[TargetLine],$H16)-SUMIFS(tblY2027_Strategies[Amount],tblY2027_Strategies[CounterLine],$H16) | N16: =IF(UPPER(K16)="Y",SUMIFS(tblMaster_Inputs[Baseline_Amount],tblMaster_Inputs[Year],2026,tblMaster_Inputs[Primary_Line],"12"),IF(ISBLANK(L16),J16,L16)) | O16: =N16+M16 | P16: =HYPERLINK("#Y2027!I49","↗ drill")
A17: STR-012 | B17: Bonus Depreciation §168(k) | C17: 8 | H17: 13 | I17: QBI deduction | J17: =SUMIFS(tblMaster_Inputs[Baseline_Amount],tblMaster_Inputs[Year],2027,tblMaster_Inputs[Primary_Line],$H17, tblMaster_Inputs[Activity_Type], "Baseline") | M17: =SUMIFS(tblY2027_Strategies[Amount],tblY2027_Strategies[TargetLine],$H17)-SUMIFS(tblY2027_Strategies[Amount],tblY2027_Strategies[CounterLine],$H17) | N17: =IF(UPPER(K17)="Y",SUMIFS(tblMaster_Inputs[Baseline_Amount],tblMaster_Inputs[Year],2026,tblMaster_Inputs[Primary_Line],"13"),IF(ISBLANK(L17),J17,L17)) | O17: =N17+M17 | P17: =HYPERLINK("#Y2027!I49","↗ drill")
A18: STR-013 | B18: R&D Credit §41 | C18: 13 | H18: 15 | I18: TAXABLE INCOME | J18: =J15+J16+J17 | M18: =M15+M16+M17 | N18: =N15+N16+N17 | O18: =O15+O16+O17 | P18: =HYPERLINK("#Y2027!I49","↗ drill")
A19: STR-014 | B19: SALT PTE Election | C19: 12
A20: STR-015 | B20: Timing / Deferral | C20: 8
A22: ▸ TAX IMPACT SUMMARY | H22: Description | I22: Amount | J22: Effective | K22: Used by
A23: Metric | B23: Baseline | C23: Effective | D23: Eff w/ Strat | E23: Savings | H23: Owner W-2 | I23: =SUMIFS(tblMaster_Inputs[Baseline_Amount],tblMaster_Inputs[Year],2027,tblMaster_Inputs[Treatment_Profile],"W2_SCorpOwner", tblMaster_Inputs[Activity_Type], "Baseline") | J23: =I23+SUMIFS(tblY2027_Strategies[Amount],tblY2027_Strategies[TargetLine],"1z")-SUMIFS(tblY2027_Strategies[Amount],tblY2027_Strategies[CounterLine],"1z")
A24: Total Income | B24: =J13 | C24: =N13 | D24: =O13 | E24: =B24-D24 | H24: Third-party W-2 | I24: =SUMIFS(tblMaster_Inputs[Baseline_Amount],tblMaster_Inputs[Year],2027,tblMaster_Inputs[Treatment_Profile],"W2_Employee", tblMaster_Inputs[Activity_Type], "Baseline") | J24: =I24
A25: Taxable Income | B25: =J18 | C25: =N18 | D25: =O18 | E25: =B25-D25 | H25: Total W-2 | I25: =I23+I24 | J25: =J23+J24
A26: Total Tax | B26: =I133 | C26: =I133 | D26: =J133 | E26: =B26-D26 | H26: SE business | I26: =SUMIFS(tblMaster_Inputs[Baseline_Amount],tblMaster_Inputs[Year],2027,tblMaster_Inputs[Bucket],"Business Income",tblMaster_Inputs[SE_Subject],"Yes", tblMaster_Inputs[Activity_Type], "Baseline") | J26: =I26
A27: Effective Rate | B27: =I134 | C27: =I134 | D27: =J134 | E27: =B27-D27 | H27: Active non-SE | I27: =SUMIFS(tblMaster_Inputs[Baseline_Amount],tblMaster_Inputs[Year],2027,tblMaster_Inputs[Bucket],"Business Income",tblMaster_Inputs[SE_Subject],"No",tblMaster_Inputs[NIIT_Class],"Active", tblMaster_Inputs[Activity_Type], "Baseline") | J27: =I27+SUMIFS(tblY2027_Strategies[Amount],tblY2027_Strategies[TargetLine],"8")-SUMIFS(tblY2027_Strategies[Amount],tblY2027_Strategies[CounterLine],"8")
A28: Committed Strategies | B28: =COUNTIF(tblY2027_Strategies[Status],"Committed") | C28: Net Strategy Impact | D28: =SUMIF(tblY2027_Strategies[Status],"Committed",tblY2027_Strategies[Amount]) | H28: Passive business | I28: =SUMIFS(tblMaster_Inputs[Baseline_Amount],tblMaster_Inputs[Year],2027,tblMaster_Inputs[Bucket],"Business Income",tblMaster_Inputs[NIIT_Class],"Passive", tblMaster_Inputs[Activity_Type], "Baseline") | J28: =I28
H29: Tax-exempt int | I29: =SUMIFS(tblMaster_Inputs[Helper_Amount],tblMaster_Inputs[Year],2027,tblMaster_Inputs[Helper_Treatment],"TAX_EXEMPT") | J29: =I29+SUMIFS(tblY2027_Strategies[Amount],tblY2027_Strategies[TargetLine],"2a")-SUMIFS(tblY2027_Strategies[Amount],tblY2027_Strategies[CounterLine],"2a")
H30: Qualified div | I30: =SUMIFS(tblMaster_Inputs[Helper_Amount],tblMaster_Inputs[Year],2027,tblMaster_Inputs[Helper_Treatment],"QUAL_DIV", tblMaster_Inputs[Activity_Type], "Baseline") | J30: =I30
H31: LT cap gains | I31: =SUMIFS(tblMaster_Inputs[Baseline_Amount],tblMaster_Inputs[Year],2027,tblMaster_Inputs[Treatment_Profile],"LTCG_Stock")+SUMIFS(tblMaster_Inputs[Baseline_Amount],tblMaster_Inputs[Year],2027,tblMaster_Inputs[Treatment_Profile],"LTCG_RE")+SUMIFS(tblMaster_Inputs[Baseline_Amount],tblMaster_Inputs[Year],2027,tblMaster_Inputs[Treatment_Profile],"LTCG_K1_Passthrough")+SUMIFS(tblMaster_Inputs[Baseline_Amount],tblMaster_Inputs[Year],2027,tblMaster_Inputs[Treatment_Profile],"Sec1250_Recap", tblMaster_Inputs[Activity_Type], "Baseline") | J31: =I31+SUMIFS(tblY2027_Strategies[Amount],tblY2027_Strategies[TargetLine],"7")-SUMIFS(tblY2027_Strategies[Amount],tblY2027_Strategies[CounterLine],"7")
H32: ST cap gains | I32: =SUMIFS(tblMaster_Inputs[Baseline_Amount],tblMaster_Inputs[Year],2027,tblMaster_Inputs[Treatment_Profile],"STCG_Stock", tblMaster_Inputs[Activity_Type], "Baseline") | J32: =I32
H33: §1250 gain | I33: =SUMIFS(tblMaster_Inputs[Helper_Amount],tblMaster_Inputs[Year],2027,tblMaster_Inputs[Helper_Treatment],"SEC1250", tblMaster_Inputs[Activity_Type], "Baseline") | J33: =I33
H36: Description | I36: Value | J36: Effective | K36: Used by
H37: TI-LTCG-QD-1250 | I37: =J18-I31-I30-I33 | J37: =O18-J31-J30-J33
H38: AGI+tax-exempt | I38: =J15+I29 | J38: =O15+J29
H39: Net inv income | I39: =J8+J10+J11+I28 | J39: =O8+O10+O11+J28
H40: QBI-eligible | I40: =I26+I27 | J40: =J26+J27
H41: TI before QBI | I41: =J15+J16 | J41: =O15+O16
H42: Net biz loss | I42: =MIN(0,I26+I27+I28) | J42: =MIN(0,J26+J27+J28)
H43: Net SE | I43: =I26 | J43: =J26
J44: =I44
I45: =IF(Control_Panel!C21="Yes",TRUE,FALSE) | J45: =I45
I46: =Carryovers!F52 | J46: =I46
H49: 1z | K49: =HYPERLINK("#Master_Inputs!A1","✏ open Master_Inputs")
H65: ▸ 7-COMPONENT TAX CALCULATOR | I65: Baseline | J65: Effective | K65: Δ Savings
H66: Dual columns: Baseline (H) vs With Planning (I)
H68: 1. SELF-EMPLOYMENT TAX
H69: SE Tax Label
H70: Net SE Earnings | I70: =I43 | J70: =J43
H71: SE Base (× 0.9235) | I71: =I70*SUMIFS(tblThresholds[Value], tblThresholds[Year], 2027, tblThresholds[FilingStatus], Filing_Status, tblThresholds[Item], "SE_Earnings_Factor") | J71: =J70*SUMIFS(tblThresholds[Value], tblThresholds[Year], 2027, tblThresholds[FilingStatus], Filing_Status, tblThresholds[Item], "SE_Earnings_Factor")
H72: W-2 Wages | I72: =I25 | J72: =J25
H73: Remaining SS Wage Base | I73: =MAX(0,SUMIFS(tblThresholds[Value], tblThresholds[Year], 2027, tblThresholds[FilingStatus], Filing_Status, tblThresholds[Item], "SS_Wage_Base")-I72) | J73: =MAX(0,SUMIFS(tblThresholds[Value], tblThresholds[Year], 2027, tblThresholds[FilingStatus], Filing_Status, tblThresholds[Item], "SS_Wage_Base")-J72)
I74: =MIN(I71,I73) | J74: =MIN(J71,J73)
H75: Social Security Tax (12.4%) | I75: =I74*SUMIFS(tblThresholds[Value], tblThresholds[Year], 2027, tblThresholds[FilingStatus], Filing_Status, tblThresholds[Item], "SS_Rate_Combined") | J75: =J74*SUMIFS(tblThresholds[Value], tblThresholds[Year], 2027, tblThresholds[FilingStatus], Filing_Status, tblThresholds[Item], "SS_Rate_Combined")
H76: Medicare Tax (2.9%) | I76: =I71*SUMIFS(tblThresholds[Value], tblThresholds[Year], 2027, tblThresholds[FilingStatus], Filing_Status, tblThresholds[Item], "Medicare_Rate_Combined") | J76: =J71*SUMIFS(tblThresholds[Value], tblThresholds[Year], 2027, tblThresholds[FilingStatus], Filing_Status, tblThresholds[Item], "Medicare_Rate_Combined")
H77: Addl Medicare (0.9% > threshold) | I77: =MAX(0,(I72+I71-SUMIFS(tblThresholds[Value], tblThresholds[Year], 2027, tblThresholds[FilingStatus], Filing_Status, tblThresholds[Item], "Addl_Medicare_Threshold"))*SUMIFS(tblThresholds[Value], tblThresholds[Year], 2027, tblThresholds[FilingStatus], Filing_Status, tblThresholds[Item], "Addl_Medicare_Rate")) | J77: =MAX(0,(J72+J71-SUMIFS(tblThresholds[Value], tblThresholds[Year], 2027, tblThresholds[FilingStatus], Filing_Status, tblThresholds[Item], "Addl_Medicare_Threshold"))*SUMIFS(tblThresholds[Value], tblThresholds[Year], 2027, tblThresholds[FilingStatus], Filing_Status, tblThresholds[Item], "Addl_Medicare_Rate"))
I78: =-(I75+I76)/2 | J78: =-(J75+J76)/2
H80: TOTAL SE TAX | I80: =I75+I76+I77 | J80: =J75+J76+J77 | K80: =I80-J80
H82: 2. PAYROLL TAX
H83: W-2 Wages | I83: =I25 | J83: =J25
H84: Social Security (6.2%) | I84: =MIN(I83,SUMIFS(tblThresholds[Value], tblThresholds[Year], 2027, tblThresholds[FilingStatus], Filing_Status, tblThresholds[Item], "SS_Wage_Base"))*0.062 | J84: =MIN(J83,SUMIFS(tblThresholds[Value], tblThresholds[Year], 2027, tblThresholds[FilingStatus], Filing_Status, tblThresholds[Item], "SS_Wage_Base"))*0.062
H85: Medicare (1.45%) | I85: =I83*0.0145 | J85: =J83*0.0145
H86: Addl Medicare (0.9% > threshold) | I86: =MAX(0,(I83-SUMIFS(tblThresholds[Value], tblThresholds[Year], 2027, tblThresholds[FilingStatus], Filing_Status, tblThresholds[Item], "Addl_Medicare_Threshold"))*SUMIFS(tblThresholds[Value], tblThresholds[Year], 2027, tblThresholds[FilingStatus], Filing_Status, tblThresholds[Item], "Addl_Medicare_Rate")) | J86: =MAX(0,(J83-SUMIFS(tblThresholds[Value], tblThresholds[Year], 2027, tblThresholds[FilingStatus], Filing_Status, tblThresholds[Item], "Addl_Medicare_Threshold"))*SUMIFS(tblThresholds[Value], tblThresholds[Year], 2027, tblThresholds[FilingStatus], Filing_Status, tblThresholds[Item], "Addl_Medicare_Rate"))
H87: TOTAL PAYROLL TAX | I87: =I84+I85+I86 | J87: =J84+J85+J86 | K87: =I87-J87
H88: Employer Social Security (6.2%) | I88: =I84 | J88: =J84 | K88: =I88-J88
H89: Employer Medicare (1.45%) | I89: =I85 | J89: =J85 | K89: =I89-J89
H91: TOTAL PAYROLL TAX (Employee + Employer) | I91: =I87+I88+I89 | J91: =J87+J88+J89 | K91: =I91-J91
H93: 3. ORDINARY INCOME TAX
H94: Taxable Income | I94: =I37 | J94: =J37
H95: Ordinary Taxable (TI - LTCG - QD) | I95: =MAX(0,I94) | J95: =MAX(0,J94)
H96: Tax (SUMPRODUCT bracket lookup) | I96: {=SUMPRODUCT((tblBrackets_FIT[Year]=2027)*(tblBrackets_FIT[FilingStatus]=Filing_Status)*((I95>tblBrackets_FIT[Upper])*(tblBrackets_FIT[Upper]-tblBrackets_FIT[Lower])+(I95>tblBrackets_FIT[Lower])*(I95<=tblBrackets_FIT[Upper])*(I95-tblBrackets_FIT[Lower]))*tblBrackets_FIT[Rate])} | J96: {=SUMPRODUCT((tblBrackets_FIT[Year]=2027)*(tblBrackets_FIT[FilingStatus]=Filing_Status)*((J95>tblBrackets_FIT[Upper])*(tblBrackets_FIT[Upper]-tblBrackets_FIT[Lower])+(J95>tblBrackets_FIT[Lower])*(J95<=tblBrackets_FIT[Upper])*(J95-tblBrackets_FIT[Lower]))*tblBrackets_FIT[Rate])}
H97: TOTAL ORDINARY TAX | I97: =I96 | J97: =J96 | K97: =I97-J97
H99: 4. CAPITAL GAINS / QUALIFIED DIVIDENDS TAX
H100: LTCG + Qualified Dividends | I100: =I31+I30 | J100: =J31+J30
H101: Sec 1250 Recapture Gain | I101: =I33 | J101: =J33
H102: Stacking Base (Ordinary TI for bracket floor) | I102: =I95 | J102: =J95
H103: Full CG Rate Tax (SUMPRODUCT stack) | I103: {=SUMPRODUCT((Tax_Ref!$B$210:$B$281=2027)*(Tax_Ref!$C$210:$C$281=Filing_Status)*((I102+I100>Tax_Ref!$E$210:$E$281)*(Tax_Ref!$E$210:$E$281-Tax_Ref!$D$210:$D$281)+(I102+I100>Tax_Ref!$D$210:$D$281)*(I102+I100<=Tax_Ref!$E$210:$E$281)*(I102+I100-Tax_Ref!$D$210:$D$281))*Tax_Ref!$F$210:$F$281)} | J103: {=SUMPRODUCT((Tax_Ref!$B$210:$B$281=2027)*(Tax_Ref!$C$210:$C$281=Filing_Status)*((J102+J100>Tax_Ref!$E$210:$E$281)*(Tax_Ref!$E$210:$E$281-Tax_Ref!$D$210:$D$281)+(J102+J100>Tax_Ref!$D$210:$D$281)*(J102+J100<=Tax_Ref!$E$210:$E$281)*(J102+J100-Tax_Ref!$D$210:$D$281))*Tax_Ref!$F$210:$F$281)}
H104: CG Rate Tax on Ordinary only | I104: {=SUMPRODUCT((Tax_Ref!$B$210:$B$281=2027)*(Tax_Ref!$C$210:$C$281=Filing_Status)*((I102>Tax_Ref!$E$210:$E$281)*(Tax_Ref!$E$210:$E$281-Tax_Ref!$D$210:$D$281)+(I102>Tax_Ref!$D$210:$D$281)*(I102<=Tax_Ref!$E$210:$E$281)*(I102-Tax_Ref!$D$210:$D$281))*Tax_Ref!$F$210:$F$281)} | J104: {=SUMPRODUCT((Tax_Ref!$B$210:$B$281=2027)*(Tax_Ref!$C$210:$C$281=Filing_Status)*((J102>Tax_Ref!$E$210:$E$281)*(Tax_Ref!$E$210:$E$281-Tax_Ref!$D$210:$D$281)+(J102>Tax_Ref!$D$210:$D$281)*(J102<=Tax_Ref!$E$210:$E$281)*(J102-Tax_Ref!$D$210:$D$281))*Tax_Ref!$F$210:$F$281)}
H105: Net LTCG/QD Tax | I105: =I103-I104 | J105: =J103-J104
I106: =I33*0.25 | J106: =J33*0.25
H107: TOTAL CAP GAINS TAX | I107: =I105+I106 | J107: =J105+J106 | K107: =I107-J107
H109: 5. NET INVESTMENT INCOME TAX (NIIT)
H110: MAGI | I110: =I38 | J110: =J38
H111: NIIT Threshold | I111: =SUMIFS(tblThresholds[Value], tblThresholds[Year], 2027, tblThresholds[FilingStatus], Filing_Status, tblThresholds[Item], "NIIT_Threshold") | J111: =SUMIFS(tblThresholds[Value], tblThresholds[Year], 2027, tblThresholds[FilingStatus], Filing_Status, tblThresholds[Item], "NIIT_Threshold")
H112: Net Investment Income (NII) | I112: =MAX(0,I39) | J112: =MAX(0,J39)
H113: NIIT Base (lesser of NII or MAGI excess) | I113: =MAX(0,I110-I111) | J113: =MAX(0,J110-J111)
H114: NIIT (3.8%) | I114: =MIN(I112,I113)*SUMIFS(tblThresholds[Value], tblThresholds[Year], 2027, tblThresholds[FilingStatus], Filing_Status, tblThresholds[Item], "NIIT_Rate") | J114: =MIN(J112,J113)*SUMIFS(tblThresholds[Value], tblThresholds[Year], 2027, tblThresholds[FilingStatus], Filing_Status, tblThresholds[Item], "NIIT_Rate") | K114: =I114-J114
H116: 6. QBI DEDUCTION (§199A)
H117: QBI-Eligible Income | I117: =I40 | J117: =J40
H118: 20% of QBI | I118: =MAX(0,I117)*0.2 | J118: =MAX(0,J117)*0.2
H119: 50% of W-2 Wages | I119: =MAX(0,I41)*0.2 | J119: =MAX(0,J41)*0.2
H120: 25% W-2 + 2.5% UBIA | I120: =MAX(I23*0.5, I23*0.25+I44*0.025) | J120: =MAX(J23*0.5, J23*0.25+J44*0.025)
H121: Phase-in applies? | I121: =IF(I41>SUMIFS(tblThresholds[Value], tblThresholds[Year], 2027, tblThresholds[FilingStatus], Filing_Status, tblThresholds[Item], "QBI_Threshold_Start"),"YES","NO") | J121: =IF(J41>SUMIFS(tblThresholds[Value], tblThresholds[Year], 2027, tblThresholds[FilingStatus], Filing_Status, tblThresholds[Item], "QBI_Threshold_Start"),"YES","NO")
H122: QBI DEDUCTION | I122: =IF(AND(I45=TRUE,I41>SUMIFS(tblThresholds[Value], tblThresholds[Year], 2027, tblThresholds[FilingStatus], Filing_Status, tblThresholds[Item], "QBI_Threshold_End")),0,IF(I41<=SUMIFS(tblThresholds[Value], tblThresholds[Year], 2027, tblThresholds[FilingStatus], Filing_Status, tblThresholds[Item], "QBI_Threshold_Start"),MIN(I118,I119),MIN(I118,I119,I120))) | J122: =IF(AND(J45=TRUE,J41>SUMIFS(tblThresholds[Value], tblThresholds[Year], 2027, tblThresholds[FilingStatus], Filing_Status, tblThresholds[Item], "QBI_Threshold_End")),0,IF(J41<=SUMIFS(tblThresholds[Value], tblThresholds[Year], 2027, tblThresholds[FilingStatus], Filing_Status, tblThresholds[Item], "QBI_Threshold_Start"),MIN(J118,J119),MIN(J118,J119,J120))) | K122: =J122-I122
H124: 7. COMBINED TAX SUMMARY
H125: Total Income | I125: =J6+J8+J10+J11+J12 | J125: =O13 | K125: Δ Savings
H126: Ordinary Tax | I126: =I97 | J126: =J97 | K126: =I126-J126
H127: Capital Gains Tax | I127: =I107 | J127: =J107 | K127: =I127-J127
H128: Self-Employment Tax | I128: =I80 | J128: =J80 | K128: =I128-J128
H129: Payroll Tax (Employee + Employer) | I129: =I91 | J129: =J91 | K129: =I129-J129
H130: NIIT | I130: =I114 | J130: =J114 | K130: =I130-J130
...

Sheet Y2028
A1: Y2028 — standalone tax planning sandbox
A2: Strategies: enter Amount + Status below. Committed strategies flow to rollup M column. Push to Master_Inputs when final.
A4: ▸ STRATEGIES
A5: StrategyID | B5: Strategy Name | C5: TargetLine | D5: Amount | E5: Status | F5: Notes | G5: CounterLine | H5: Line | I5: Description | J5: Baseline (Master) | K5: PY? | L5: S1 Override | M5: Strategies | N5: Effective | O5: Eff w/ Strategies | P5: Drill
A6: STR-001 | B6: S-Corp Wage Optimization | C6: 1z | H6: 1z | I6: Wages | J6: =SUMIFS(tblMaster_Inputs[Baseline_Amount],tblMaster_Inputs[Year],2028,tblMaster_Inputs[Primary_Line],$H6, tblMaster_Inputs[Activity_Type], "Baseline") | M6: =SUMIFS(tblY2028_Strategies[Amount],tblY2028_Strategies[TargetLine],$H6)-SUMIFS(tblY2028_Strategies[Amount],tblY2028_Strategies[CounterLine],$H6) | N6: =IF(UPPER(K6)="Y",SUMIFS(tblMaster_Inputs[Baseline_Amount],tblMaster_Inputs[Year],2027,tblMaster_Inputs[Primary_Line],"1z"),IF(ISBLANK(L6),J6,L6)) | O6: =N6+M6 | P6: =HYPERLINK("#Y2028!I49","↗ drill")
A7: STR-002 | B7: HSA Family Max | C7: 10 | H7: 2a | I7: Tax-exempt interest | J7: =SUMIFS(tblMaster_Inputs[Helper_Amount],tblMaster_Inputs[Year],2028,tblMaster_Inputs[Helper_Treatment],"TAX_EXEMPT") | M7: =SUMIFS(tblY2028_Strategies[Amount],tblY2028_Strategies[TargetLine],"2a",tblY2028_Strategies[Status],"Committed") | N7: =IF(UPPER(K7)="Y",SUMIFS(tblMaster_Inputs[Helper_Amount],tblMaster_Inputs[Year],2027,tblMaster_Inputs[Helper_Treatment],"TAX_EXEMPT"),IF(ISBLANK(L7),J7,L7)) | O7: =N7 | P7: =HYPERLINK("#Y2028!I49","↗ drill")
A8: STR-003 | B8: Charitable Bunching (DAF) | C8: 12 | H8: 2b | I8: Taxable interest | J8: =SUMIFS(tblMaster_Inputs[Baseline_Amount],tblMaster_Inputs[Year],2028,tblMaster_Inputs[Primary_Line],$H8, tblMaster_Inputs[Activity_Type], "Baseline") | M8: =SUMIFS(tblY2028_Strategies[Amount],tblY2028_Strategies[TargetLine],$H8)-SUMIFS(tblY2028_Strategies[Amount],tblY2028_Strategies[CounterLine],$H8) | N8: =IF(UPPER(K8)="Y",SUMIFS(tblMaster_Inputs[Baseline_Amount],tblMaster_Inputs[Year],2027,tblMaster_Inputs[Primary_Line],"2b"),IF(ISBLANK(L8),J8,L8)) | O8: =N8+M8 | P8: =HYPERLINK("#Y2028!I49","↗ drill")
A9: STR-004 | B9: SEP-IRA / Solo 401(k) | C9: 10 | H9: 3a | I9: Qualified dividends | J9: =SUMIFS(tblMaster_Inputs[Helper_Amount],tblMaster_Inputs[Year],2028,tblMaster_Inputs[Helper_Treatment],"QUAL_DIV") | M9: =SUMIFS(tblY2028_Strategies[Amount],tblY2028_Strategies[TargetLine],"3a",tblY2028_Strategies[Status],"Committed") | N9: =IF(UPPER(K9)="Y",SUMIFS(tblMaster_Inputs[Helper_Amount],tblMaster_Inputs[Year],2027,tblMaster_Inputs[Helper_Treatment],"QUAL_DIV"),IF(ISBLANK(L9),J9,L9)) | O9: =N9 | P9: =HYPERLINK("#Y2028!I49","↗ drill")
A10: STR-005 | B10: Cost Seg Study | C10: 8 | H10: 3b | I10: Ordinary dividends | J10: =SUMIFS(tblMaster_Inputs[Baseline_Amount],tblMaster_Inputs[Year],2028,tblMaster_Inputs[Primary_Line],$H10, tblMaster_Inputs[Activity_Type], "Baseline") | M10: =SUMIFS(tblY2028_Strategies[Amount],tblY2028_Strategies[TargetLine],$H10)-SUMIFS(tblY2028_Strategies[Amount],tblY2028_Strategies[CounterLine],$H10) | N10: =IF(UPPER(K10)="Y",SUMIFS(tblMaster_Inputs[Baseline_Amount],tblMaster_Inputs[Year],2027,tblMaster_Inputs[Primary_Line],"3b"),IF(ISBLANK(L10),J10,L10)) | O10: =N10+M10 | P10: =HYPERLINK("#Y2028!I49","↗ drill")
A11: STR-006 | B11: Roth Conversion | C11: 1z | H11: 7 | I11: Capital gain/(loss) | J11: =SUMIFS(tblMaster_Inputs[Baseline_Amount],tblMaster_Inputs[Year],2028,tblMaster_Inputs[Primary_Line],$H11, tblMaster_Inputs[Activity_Type], "Baseline") | M11: =SUMIFS(tblY2028_Strategies[Amount],tblY2028_Strategies[TargetLine],$H11)-SUMIFS(tblY2028_Strategies[Amount],tblY2028_Strategies[CounterLine],$H11) | N11: =IF(UPPER(K11)="Y",SUMIFS(tblMaster_Inputs[Baseline_Amount],tblMaster_Inputs[Year],2027,tblMaster_Inputs[Primary_Line],"7"),IF(ISBLANK(L11),J11,L11)) | O11: =N11+M11 | P11: =HYPERLINK("#Y2028!I49","↗ drill")
A12: STR-007 | B12: Augusta Rule (§280A) | C12: 8 | H12: 8 | I12: Other income (business) | J12: =SUMIFS(tblMaster_Inputs[Baseline_Amount],tblMaster_Inputs[Year],2028,tblMaster_Inputs[Primary_Line],$H12, tblMaster_Inputs[Activity_Type], "Baseline") | M12: =SUMIFS(tblY2028_Strategies[Amount],tblY2028_Strategies[TargetLine],$H12)-SUMIFS(tblY2028_Strategies[Amount],tblY2028_Strategies[CounterLine],$H12) | N12: =IF(UPPER(K12)="Y",SUMIFS(tblMaster_Inputs[Baseline_Amount],tblMaster_Inputs[Year],2027,tblMaster_Inputs[Primary_Line],"8"),IF(ISBLANK(L12),J12,L12)) | O12: =N12+M12 | P12: =HYPERLINK("#Y2028!I49","↗ drill")
A13: STR-008 | B13: Accountable Plan | C13: 8 | H13: 9 | I13: TOTAL INCOME | J13: =J6+J8+J10+J11+J12 | M13: =M6+M8+M10+M11+M12 | N13: =N6+N8+N10+N11+N12 | O13: =O6+O8+O10+O11+O12 | P13: =HYPERLINK("#Y2028!I49","↗ drill")
A14: STR-009 | B14: Hire Children | C14: 8 | H14: 10 | I14: Adjustments | J14: =SUMIFS(tblMaster_Inputs[Baseline_Amount],tblMaster_Inputs[Year],2028,tblMaster_Inputs[Primary_Line],$H14, tblMaster_Inputs[Activity_Type], "Baseline") | M14: =SUMIFS(tblY2028_Strategies[Amount],tblY2028_Strategies[TargetLine],$H14)-SUMIFS(tblY2028_Strategies[Amount],tblY2028_Strategies[CounterLine],$H14) | N14: =IF(UPPER(K14)="Y",SUMIFS(tblMaster_Inputs[Baseline_Amount],tblMaster_Inputs[Year],2027,tblMaster_Inputs[Primary_Line],"10"),IF(ISBLANK(L14),J14,L14)) | O14: =N14+M14 | P14: =HYPERLINK("#Y2028!I49","↗ drill")
A15: STR-010 | B15: Entity Restructuring | C15: 8 | H15: 11 | I15: AGI | J15: =J13+J14 | M15: =M13+M14 | N15: =N13+N14 | O15: =O13+O14 | P15: =HYPERLINK("#Y2028!I49","↗ drill")
A16: STR-011 | B16: Installment Sale / 1031 | C16: 7 | H16: 12 | I16: Std/Itemized ded | J16: =SUMIFS(tblMaster_Inputs[Baseline_Amount],tblMaster_Inputs[Year],2028,tblMaster_Inputs[Primary_Line],$H16, tblMaster_Inputs[Activity_Type], "Baseline") | M16: =SUMIFS(tblY2028_Strategies[Amount],tblY2028_Strategies[TargetLine],$H16)-SUMIFS(tblY2028_Strategies[Amount],tblY2028_Strategies[CounterLine],$H16) | N16: =IF(UPPER(K16)="Y",SUMIFS(tblMaster_Inputs[Baseline_Amount],tblMaster_Inputs[Year],2027,tblMaster_Inputs[Primary_Line],"12"),IF(ISBLANK(L16),J16,L16)) | O16: =N16+M16 | P16: =HYPERLINK("#Y2028!I49","↗ drill")
A17: STR-012 | B17: Bonus Depreciation §168(k) | C17: 8 | H17: 13 | I17: QBI deduction | J17: =SUMIFS(tblMaster_Inputs[Baseline_Amount],tblMaster_Inputs[Year],2028,tblMaster_Inputs[Primary_Line],$H17, tblMaster_Inputs[Activity_Type], "Baseline") | M17: =SUMIFS(tblY2028_Strategies[Amount],tblY2028_Strategies[TargetLine],$H17)-SUMIFS(tblY2028_Strategies[Amount],tblY2028_Strategies[CounterLine],$H17) | N17: =IF(UPPER(K17)="Y",SUMIFS(tblMaster_Inputs[Baseline_Amount],tblMaster_Inputs[Year],2027,tblMaster_Inputs[Primary_Line],"13"),IF(ISBLANK(L17),J17,L17)) | O17: =N17+M17 | P17: =HYPERLINK("#Y2028!I49","↗ drill")
A18: STR-013 | B18: R&D Credit §41 | C18: 13 | H18: 15 | I18: TAXABLE INCOME | J18: =J15+J16+J17 | M18: =M15+M16+M17 | N18: =N15+N16+N17 | O18: =O15+O16+O17 | P18: =HYPERLINK("#Y2028!I49","↗ drill")
A19: STR-014 | B19: SALT PTE Election | C19: 12
A20: STR-015 | B20: Timing / Deferral | C20: 8
A22: ▸ TAX IMPACT SUMMARY | H22: Description | I22: Amount | J22: Effective | K22: Used by
A23: Metric | B23: Baseline | C23: Effective | D23: Eff w/ Strat | E23: Savings | H23: Owner W-2 | I23: =SUMIFS(tblMaster_Inputs[Baseline_Amount],tblMaster_Inputs[Year],2028,tblMaster_Inputs[Treatment_Profile],"W2_SCorpOwner", tblMaster_Inputs[Activity_Type], "Baseline") | J23: =I23+SUMIFS(tblY2028_Strategies[Amount],tblY2028_Strategies[TargetLine],"1z")-SUMIFS(tblY2028_Strategies[Amount],tblY2028_Strategies[CounterLine],"1z")
A24: Total Income | B24: =J13 | C24: =N13 | D24: =O13 | E24: =B24-D24 | H24: Third-party W-2 | I24: =SUMIFS(tblMaster_Inputs[Baseline_Amount],tblMaster_Inputs[Year],2028,tblMaster_Inputs[Treatment_Profile],"W2_Employee", tblMaster_Inputs[Activity_Type], "Baseline") | J24: =I24
A25: Taxable Income | B25: =J18 | C25: =N18 | D25: =O18 | E25: =B25-D25 | H25: Total W-2 | I25: =I23+I24 | J25: =J23+J24
A26: Total Tax | B26: =I133 | C26: =I133 | D26: =J133 | E26: =B26-D26 | H26: SE business | I26: =SUMIFS(tblMaster_Inputs[Baseline_Amount],tblMaster_Inputs[Year],2028,tblMaster_Inputs[Bucket],"Business Income",tblMaster_Inputs[SE_Subject],"Yes", tblMaster_Inputs[Activity_Type], "Baseline") | J26: =I26
A27: Effective Rate | B27: =I134 | C27: =I134 | D27: =J134 | E27: =B27-D27 | H27: Active non-SE | I27: =SUMIFS(tblMaster_Inputs[Baseline_Amount],tblMaster_Inputs[Year],2028,tblMaster_Inputs[Bucket],"Business Income",tblMaster_Inputs[SE_Subject],"No",tblMaster_Inputs[NIIT_Class],"Active", tblMaster_Inputs[Activity_Type], "Baseline") | J27: =I27+SUMIFS(tblY2028_Strategies[Amount],tblY2028_Strategies[TargetLine],"8")-SUMIFS(tblY2028_Strategies[Amount],tblY2028_Strategies[CounterLine],"8")
A28: Committed Strategies | B28: =COUNTIF(tblY2028_Strategies[Status],"Committed") | C28: Net Strategy Impact | D28: =SUMIF(tblY2028_Strategies[Status],"Committed",tblY2028_Strategies[Amount]) | H28: Passive business | I28: =SUMIFS(tblMaster_Inputs[Baseline_Amount],tblMaster_Inputs[Year],2028,tblMaster_Inputs[Bucket],"Business Income",tblMaster_Inputs[NIIT_Class],"Passive", tblMaster_Inputs[Activity_Type], "Baseline") | J28: =I28
H29: Tax-exempt int | I29: =SUMIFS(tblMaster_Inputs[Helper_Amount],tblMaster_Inputs[Year],2028,tblMaster_Inputs[Helper_Treatment],"TAX_EXEMPT") | J29: =I29+SUMIFS(tblY2028_Strategies[Amount],tblY2028_Strategies[TargetLine],"2a")-SUMIFS(tblY2028_Strategies[Amount],tblY2028_Strategies[CounterLine],"2a")
H30: Qualified div | I30: =SUMIFS(tblMaster_Inputs[Helper_Amount],tblMaster_Inputs[Year],2028,tblMaster_Inputs[Helper_Treatment],"QUAL_DIV", tblMaster_Inputs[Activity_Type], "Baseline") | J30: =I30
H31: LT cap gains | I31: =SUMIFS(tblMaster_Inputs[Baseline_Amount],tblMaster_Inputs[Year],2028,tblMaster_Inputs[Treatment_Profile],"LTCG_Stock")+SUMIFS(tblMaster_Inputs[Baseline_Amount],tblMaster_Inputs[Year],2028,tblMaster_Inputs[Treatment_Profile],"LTCG_RE")+SUMIFS(tblMaster_Inputs[Baseline_Amount],tblMaster_Inputs[Year],2028,tblMaster_Inputs[Treatment_Profile],"LTCG_K1_Passthrough")+SUMIFS(tblMaster_Inputs[Baseline_Amount],tblMaster_Inputs[Year],2028,tblMaster_Inputs[Treatment_Profile],"Sec1250_Recap", tblMaster_Inputs[Activity_Type], "Baseline") | J31: =I31+SUMIFS(tblY2028_Strategies[Amount],tblY2028_Strategies[TargetLine],"7")-SUMIFS(tblY2028_Strategies[Amount],tblY2028_Strategies[CounterLine],"7")
H32: ST cap gains | I32: =SUMIFS(tblMaster_Inputs[Baseline_Amount],tblMaster_Inputs[Year],2028,tblMaster_Inputs[Treatment_Profile],"STCG_Stock", tblMaster_Inputs[Activity_Type], "Baseline") | J32: =I32
H33: §1250 gain | I33: =SUMIFS(tblMaster_Inputs[Helper_Amount],tblMaster_Inputs[Year],2028,tblMaster_Inputs[Helper_Treatment],"SEC1250", tblMaster_Inputs[Activity_Type], "Baseline") | J33: =I33
H36: Description | I36: Value | J36: Effective | K36: Used by
H37: TI-LTCG-QD-1250 | I37: =J18-I31-I30-I33 | J37: =O18-J31-J30-J33
H38: AGI+tax-exempt | I38: =J15+I29 | J38: =O15+J29
H39: Net inv income | I39: =J8+J10+J11+I28 | J39: =O8+O10+O11+J28
H40: QBI-eligible | I40: =I26+I27 | J40: =J26+J27
H41: TI before QBI | I41: =J15+J16 | J41: =O15+O16
H42: Net biz loss | I42: =MIN(0,I26+I27+I28) | J42: =MIN(0,J26+J27+J28)
H43: Net SE | I43: =I26 | J43: =J26
J44: =I44
I45: =IF(Control_Panel!C21="Yes",TRUE,FALSE) | J45: =I45
I46: =Carryovers!F52 | J46: =I46
H49: 1z | K49: =HYPERLINK("#Master_Inputs!A1","✏ open Master_Inputs")
H65: ▸ 7-COMPONENT TAX CALCULATOR | I65: Baseline | J65: Effective | K65: Δ Savings
H66: Dual columns: Baseline (H) vs With Planning (I)
H68: 1. SELF-EMPLOYMENT TAX
H69: SE Tax Label
H70: Net SE Earnings | I70: =I43 | J70: =J43
H71: SE Base (× 0.9235) | I71: =I70*SUMIFS(tblThresholds[Value], tblThresholds[Year], 2028, tblThresholds[FilingStatus], Filing_Status, tblThresholds[Item], "SE_Earnings_Factor") | J71: =J70*SUMIFS(tblThresholds[Value], tblThresholds[Year], 2028, tblThresholds[FilingStatus], Filing_Status, tblThresholds[Item], "SE_Earnings_Factor")
H72: W-2 Wages | I72: =I25 | J72: =J25
H73: Remaining SS Wage Base | I73: =MAX(0,SUMIFS(tblThresholds[Value], tblThresholds[Year], 2028, tblThresholds[FilingStatus], Filing_Status, tblThresholds[Item], "SS_Wage_Base")-I72) | J73: =MAX(0,SUMIFS(tblThresholds[Value], tblThresholds[Year], 2028, tblThresholds[FilingStatus], Filing_Status, tblThresholds[Item], "SS_Wage_Base")-J72)
I74: =MIN(I71,I73) | J74: =MIN(J71,J73)
H75: Social Security Tax (12.4%) | I75: =I74*SUMIFS(tblThresholds[Value], tblThresholds[Year], 2028, tblThresholds[FilingStatus], Filing_Status, tblThresholds[Item], "SS_Rate_Combined") | J75: =J74*SUMIFS(tblThresholds[Value], tblThresholds[Year], 2028, tblThresholds[FilingStatus], Filing_Status, tblThresholds[Item], "SS_Rate_Combined")
H76: Medicare Tax (2.9%) | I76: =I71*SUMIFS(tblThresholds[Value], tblThresholds[Year], 2028, tblThresholds[FilingStatus], Filing_Status, tblThresholds[Item], "Medicare_Rate_Combined") | J76: =J71*SUMIFS(tblThresholds[Value], tblThresholds[Year], 2028, tblThresholds[FilingStatus], Filing_Status, tblThresholds[Item], "Medicare_Rate_Combined")
H77: Addl Medicare (0.9% > threshold) | I77: =MAX(0,(I72+I71-SUMIFS(tblThresholds[Value], tblThresholds[Year], 2028, tblThresholds[FilingStatus], Filing_Status, tblThresholds[Item], "Addl_Medicare_Threshold"))*SUMIFS(tblThresholds[Value], tblThresholds[Year], 2028, tblThresholds[FilingStatus], Filing_Status, tblThresholds[Item], "Addl_Medicare_Rate")) | J77: =MAX(0,(J72+J71-SUMIFS(tblThresholds[Value], tblThresholds[Year], 2028, tblThresholds[FilingStatus], Filing_Status, tblThresholds[Item], "Addl_Medicare_Threshold"))*SUMIFS(tblThresholds[Value], tblThresholds[Year], 2028, tblThresholds[FilingStatus], Filing_Status, tblThresholds[Item], "Addl_Medicare_Rate"))
I78: =-(I75+I76)/2 | J78: =-(J75+J76)/2
H80: TOTAL SE TAX | I80: =I75+I76+I77 | J80: =J75+J76+J77 | K80: =I80-J80
H82: 2. PAYROLL TAX
H83: W-2 Wages | I83: =I25 | J83: =J25
H84: Social Security (6.2%) | I84: =MIN(I83,SUMIFS(tblThresholds[Value], tblThresholds[Year], 2028, tblThresholds[FilingStatus], Filing_Status, tblThresholds[Item], "SS_Wage_Base"))*0.062 | J84: =MIN(J83,SUMIFS(tblThresholds[Value], tblThresholds[Year], 2028, tblThresholds[FilingStatus], Filing_Status, tblThresholds[Item], "SS_Wage_Base"))*0.062
H85: Medicare (1.45%) | I85: =I83*0.0145 | J85: =J83*0.0145
H86: Addl Medicare (0.9% > threshold) | I86: =MAX(0,(I83-SUMIFS(tblThresholds[Value], tblThresholds[Year], 2028, tblThresholds[FilingStatus], Filing_Status, tblThresholds[Item], "Addl_Medicare_Threshold"))*SUMIFS(tblThresholds[Value], tblThresholds[Year], 2028, tblThresholds[FilingStatus], Filing_Status, tblThresholds[Item], "Addl_Medicare_Rate")) | J86: =MAX(0,(J83-SUMIFS(tblThresholds[Value], tblThresholds[Year], 2028, tblThresholds[FilingStatus], Filing_Status, tblThresholds[Item], "Addl_Medicare_Threshold"))*SUMIFS(tblThresholds[Value], tblThresholds[Year], 2028, tblThresholds[FilingStatus], Filing_Status, tblThresholds[Item], "Addl_Medicare_Rate"))
H87: TOTAL PAYROLL TAX | I87: =I84+I85+I86 | J87: =J84+J85+J86 | K87: =I87-J87
H88: Employer Social Security (6.2%) | I88: =I84 | J88: =J84 | K88: =I88-J88
H89: Employer Medicare (1.45%) | I89: =I85 | J89: =J85 | K89: =I89-J89
H91: TOTAL PAYROLL TAX (Employee + Employer) | I91: =I87+I88+I89 | J91: =J87+J88+J89 | K91: =I91-J91
H93: 3. ORDINARY INCOME TAX
H94: Taxable Income | I94: =I37 | J94: =J37
H95: Ordinary Taxable (TI - LTCG - QD) | I95: =MAX(0,I94) | J95: =MAX(0,J94)
H96: Tax (SUMPRODUCT bracket lookup) | I96: {=SUMPRODUCT((tblBrackets_FIT[Year]=2028)*(tblBrackets_FIT[FilingStatus]=Filing_Status)*((I95>tblBrackets_FIT[Upper])*(tblBrackets_FIT[Upper]-tblBrackets_FIT[Lower])+(I95>tblBrackets_FIT[Lower])*(I95<=tblBrackets_FIT[Upper])*(I95-tblBrackets_FIT[Lower]))*tblBrackets_FIT[Rate])} | J96: {=SUMPRODUCT((tblBrackets_FIT[Year]=2028)*(tblBrackets_FIT[FilingStatus]=Filing_Status)*((J95>tblBrackets_FIT[Upper])*(tblBrackets_FIT[Upper]-tblBrackets_FIT[Lower])+(J95>tblBrackets_FIT[Lower])*(J95<=tblBrackets_FIT[Upper])*(J95-tblBrackets_FIT[Lower]))*tblBrackets_FIT[Rate])}
H97: TOTAL ORDINARY TAX | I97: =I96 | J97: =J96 | K97: =I97-J97
H99: 4. CAPITAL GAINS / QUALIFIED DIVIDENDS TAX
H100: LTCG + Qualified Dividends | I100: =I31+I30 | J100: =J31+J30
H101: Sec 1250 Recapture Gain | I101: =I33 | J101: =J33
H102: Stacking Base (Ordinary TI for bracket floor) | I102: =I95 | J102: =J95
H103: Full CG Rate Tax (SUMPRODUCT stack) | I103: {=SUMPRODUCT((Tax_Ref!$B$210:$B$281=2028)*(Tax_Ref!$C$210:$C$281=Filing_Status)*((I102+I100>Tax_Ref!$E$210:$E$281)*(Tax_Ref!$E$210:$E$281-Tax_Ref!$D$210:$D$281)+(I102+I100>Tax_Ref!$D$210:$D$281)*(I102+I100<=Tax_Ref!$E$210:$E$281)*(I102+I100-Tax_Ref!$D$210:$D$281))*Tax_Ref!$F$210:$F$281)} | J103: {=SUMPRODUCT((Tax_Ref!$B$210:$B$281=2028)*(Tax_Ref!$C$210:$C$281=Filing_Status)*((J102+J100>Tax_Ref!$E$210:$E$281)*(Tax_Ref!$E$210:$E$281-Tax_Ref!$D$210:$D$281)+(J102+J100>Tax_Ref!$D$210:$D$281)*(J102+J100<=Tax_Ref!$E$210:$E$281)*(J102+J100-Tax_Ref!$D$210:$D$281))*Tax_Ref!$F$210:$F$281)}
H104: CG Rate Tax on Ordinary only | I104: {=SUMPRODUCT((Tax_Ref!$B$210:$B$281=2028)*(Tax_Ref!$C$210:$C$281=Filing_Status)*((I102>Tax_Ref!$E$210:$E$281)*(Tax_Ref!$E$210:$E$281-Tax_Ref!$D$210:$D$281)+(I102>Tax_Ref!$D$210:$D$281)*(I102<=Tax_Ref!$E$210:$E$281)*(I102-Tax_Ref!$D$210:$D$281))*Tax_Ref!$F$210:$F$281)} | J104: {=SUMPRODUCT((Tax_Ref!$B$210:$B$281=2028)*(Tax_Ref!$C$210:$C$281=Filing_Status)*((J102>Tax_Ref!$E$210:$E$281)*(Tax_Ref!$E$210:$E$281-Tax_Ref!$D$210:$D$281)+(J102>Tax_Ref!$D$210:$D$281)*(J102<=Tax_Ref!$E$210:$E$281)*(J102-Tax_Ref!$D$210:$D$281))*Tax_Ref!$F$210:$F$281)}
H105: Net LTCG/QD Tax | I105: =I103-I104 | J105: =J103-J104
I106: =I33*0.25 | J106: =J33*0.25
H107: TOTAL CAP GAINS TAX | I107: =I105+I106 | J107: =J105+J106 | K107: =I107-J107
H109: 5. NET INVESTMENT INCOME TAX (NIIT)
H110: MAGI | I110: =I38 | J110: =J38
H111: NIIT Threshold | I111: =SUMIFS(tblThresholds[Value], tblThresholds[Year], 2028, tblThresholds[FilingStatus], Filing_Status, tblThresholds[Item], "NIIT_Threshold") | J111: =SUMIFS(tblThresholds[Value], tblThresholds[Year], 2028, tblThresholds[FilingStatus], Filing_Status, tblThresholds[Item], "NIIT_Threshold")
H112: Net Investment Income (NII) | I112: =MAX(0,I39) | J112: =MAX(0,J39)
H113: NIIT Base (lesser of NII or MAGI excess) | I113: =MAX(0,I110-I111) | J113: =MAX(0,J110-J111)
H114: NIIT (3.8%) | I114: =MIN(I112,I113)*SUMIFS(tblThresholds[Value], tblThresholds[Year], 2028, tblThresholds[FilingStatus], Filing_Status, tblThresholds[Item], "NIIT_Rate") | J114: =MIN(J112,J113)*SUMIFS(tblThresholds[Value], tblThresholds[Year], 2028, tblThresholds[FilingStatus], Filing_Status, tblThresholds[Item], "NIIT_Rate") | K114: =I114-J114
H116: 6. QBI DEDUCTION (§199A)
H117: QBI-Eligible Income | I117: =I40 | J117: =J40
H118: 20% of QBI | I118: =MAX(0,I117)*0.2 | J118: =MAX(0,J117)*0.2
H119: 50% of W-2 Wages | I119: =MAX(0,I41)*0.2 | J119: =MAX(0,J41)*0.2
H120: 25% W-2 + 2.5% UBIA | I120: =MAX(I23*0.5, I23*0.25+I44*0.025) | J120: =MAX(J23*0.5, J23*0.25+J44*0.025)
H121: Phase-in applies? | I121: =IF(I41>SUMIFS(tblThresholds[Value], tblThresholds[Year], 2028, tblThresholds[FilingStatus], Filing_Status, tblThresholds[Item], "QBI_Threshold_Start"),"YES","NO") | J121: =IF(J41>SUMIFS(tblThresholds[Value], tblThresholds[Year], 2028, tblThresholds[FilingStatus], Filing_Status, tblThresholds[Item], "QBI_Threshold_Start"),"YES","NO")
H122: QBI DEDUCTION | I122: =IF(AND(I45=TRUE,I41>SUMIFS(tblThresholds[Value], tblThresholds[Year], 2028, tblThresholds[FilingStatus], Filing_Status, tblThresholds[Item], "QBI_Threshold_End")),0,IF(I41<=SUMIFS(tblThresholds[Value], tblThresholds[Year], 2028, tblThresholds[FilingStatus], Filing_Status, tblThresholds[Item], "QBI_Threshold_Start"),MIN(I118,I119),MIN(I118,I119,I120))) | J122: =IF(AND(J45=TRUE,J41>SUMIFS(tblThresholds[Value], tblThresholds[Year], 2028, tblThresholds[FilingStatus], Filing_Status, tblThresholds[Item], "QBI_Threshold_End")),0,IF(J41<=SUMIFS(tblThresholds[Value], tblThresholds[Year], 2028, tblThresholds[FilingStatus], Filing_Status, tblThresholds[Item], "QBI_Threshold_Start"),MIN(J118,J119),MIN(J118,J119,J120))) | K122: =J122-I122
H124: 7. COMBINED TAX SUMMARY
H125: Total Income | I125: =J6+J8+J10+J11+J12 | J125: =O13 | K125: Δ Savings
H126: Ordinary Tax | I126: =I97 | J126: =J97 | K126: =I126-J126
H127: Capital Gains Tax | I127: =I107 | J127: =J107 | K127: =I127-J127
H128: Self-Employment Tax | I128: =I80 | J128: =J80 | K128: =I128-J128
H129: Payroll Tax (Employee + Employer) | I129: =I91 | J129: =J91 | K129: =I129-J129
H130: NIIT | I130: =I114 | J130: =J114 | K130: =I130-J130
...

Sheet Pivot_Summary
A1: PIVOT — SUMMARY (most condensed; multi-year baseline from Master_Inputs)
A2: Pure baseline aggregation. No overrides, no strategies. Year sheets handle those locally.
A4: Line | B4: Description | C4: 2023 | D4: 2024 | E4: 2025 | F4: 2026 | G4: 2027 | H4: 2028
A5: 1z | B5: Wages | C5: =SUMIFS(tblMaster_Inputs[Baseline_Amount], tblMaster_Inputs[Year], 2023, tblMaster_Inputs[Primary_Line], "1z", tblMaster_Inputs[Activity_Type], "Baseline") | D5: =SUMIFS(tblMaster_Inputs[Baseline_Amount], tblMaster_Inputs[Year], 2024, tblMaster_Inputs[Primary_Line], "1z", tblMaster_Inputs[Activity_Type], "Baseline") | E5: =SUMIFS(tblMaster_Inputs[Baseline_Amount], tblMaster_Inputs[Year], 2025, tblMaster_Inputs[Primary_Line], "1z", tblMaster_Inputs[Activity_Type], "Baseline") | F5: =SUMIFS(tblMaster_Inputs[Baseline_Amount], tblMaster_Inputs[Year], 2026, tblMaster_Inputs[Primary_Line], "1z", tblMaster_Inputs[Activity_Type], "Baseline") | G5: =SUMIFS(tblMaster_Inputs[Baseline_Amount], tblMaster_Inputs[Year], 2027, tblMaster_Inputs[Primary_Line], "1z", tblMaster_Inputs[Activity_Type], "Baseline") | H5: =SUMIFS(tblMaster_Inputs[Baseline_Amount], tblMaster_Inputs[Year], 2028, tblMaster_Inputs[Primary_Line], "1z", tblMaster_Inputs[Activity_Type], "Baseline")
A6: 2 | B6: Interest (taxable, tax-exempt info on Detailed) | C6: =SUMIFS(tblMaster_Inputs[Baseline_Amount], tblMaster_Inputs[Year], 2023, tblMaster_Inputs[Primary_Line], "2b", tblMaster_Inputs[Activity_Type], "Baseline") | D6: =SUMIFS(tblMaster_Inputs[Baseline_Amount], tblMaster_Inputs[Year], 2024, tblMaster_Inputs[Primary_Line], "2b", tblMaster_Inputs[Activity_Type], "Baseline") | E6: =SUMIFS(tblMaster_Inputs[Baseline_Amount], tblMaster_Inputs[Year], 2025, tblMaster_Inputs[Primary_Line], "2b", tblMaster_Inputs[Activity_Type], "Baseline") | F6: =SUMIFS(tblMaster_Inputs[Baseline_Amount], tblMaster_Inputs[Year], 2026, tblMaster_Inputs[Primary_Line], "2b", tblMaster_Inputs[Activity_Type], "Baseline") | G6: =SUMIFS(tblMaster_Inputs[Baseline_Amount], tblMaster_Inputs[Year], 2027, tblMaster_Inputs[Primary_Line], "2b", tblMaster_Inputs[Activity_Type], "Baseline") | H6: =SUMIFS(tblMaster_Inputs[Baseline_Amount], tblMaster_Inputs[Year], 2028, tblMaster_Inputs[Primary_Line], "2b", tblMaster_Inputs[Activity_Type], "Baseline")
A7: 3 | B7: Dividends (qualified info on Detailed) | C7: =SUMIFS(tblMaster_Inputs[Baseline_Amount], tblMaster_Inputs[Year], 2023, tblMaster_Inputs[Primary_Line], "3b", tblMaster_Inputs[Activity_Type], "Baseline") | D7: =SUMIFS(tblMaster_Inputs[Baseline_Amount], tblMaster_Inputs[Year], 2024, tblMaster_Inputs[Primary_Line], "3b", tblMaster_Inputs[Activity_Type], "Baseline") | E7: =SUMIFS(tblMaster_Inputs[Baseline_Amount], tblMaster_Inputs[Year], 2025, tblMaster_Inputs[Primary_Line], "3b", tblMaster_Inputs[Activity_Type], "Baseline") | F7: =SUMIFS(tblMaster_Inputs[Baseline_Amount], tblMaster_Inputs[Year], 2026, tblMaster_Inputs[Primary_Line], "3b", tblMaster_Inputs[Activity_Type], "Baseline") | G7: =SUMIFS(tblMaster_Inputs[Baseline_Amount], tblMaster_Inputs[Year], 2027, tblMaster_Inputs[Primary_Line], "3b", tblMaster_Inputs[Activity_Type], "Baseline") | H7: =SUMIFS(tblMaster_Inputs[Baseline_Amount], tblMaster_Inputs[Year], 2028, tblMaster_Inputs[Primary_Line], "3b", tblMaster_Inputs[Activity_Type], "Baseline")
A8: 7 | B8: Capital gain or (loss) | C8: =SUMIFS(tblMaster_Inputs[Baseline_Amount], tblMaster_Inputs[Year], 2023, tblMaster_Inputs[Primary_Line], "7", tblMaster_Inputs[Activity_Type], "Baseline") | D8: =SUMIFS(tblMaster_Inputs[Baseline_Amount], tblMaster_Inputs[Year], 2024, tblMaster_Inputs[Primary_Line], "7", tblMaster_Inputs[Activity_Type], "Baseline") | E8: =SUMIFS(tblMaster_Inputs[Baseline_Amount], tblMaster_Inputs[Year], 2025, tblMaster_Inputs[Primary_Line], "7", tblMaster_Inputs[Activity_Type], "Baseline") | F8: =SUMIFS(tblMaster_Inputs[Baseline_Amount], tblMaster_Inputs[Year], 2026, tblMaster_Inputs[Primary_Line], "7", tblMaster_Inputs[Activity_Type], "Baseline") | G8: =SUMIFS(tblMaster_Inputs[Baseline_Amount], tblMaster_Inputs[Year], 2027, tblMaster_Inputs[Primary_Line], "7", tblMaster_Inputs[Activity_Type], "Baseline") | H8: =SUMIFS(tblMaster_Inputs[Baseline_Amount], tblMaster_Inputs[Year], 2028, tblMaster_Inputs[Primary_Line], "7", tblMaster_Inputs[Activity_Type], "Baseline")
A9: 8 | B9: Other income (biz total) | C9: =SUMIFS(tblMaster_Inputs[Baseline_Amount], tblMaster_Inputs[Year], 2023, tblMaster_Inputs[Primary_Line], "8", tblMaster_Inputs[Activity_Type], "Baseline") | D9: =SUMIFS(tblMaster_Inputs[Baseline_Amount], tblMaster_Inputs[Year], 2024, tblMaster_Inputs[Primary_Line], "8", tblMaster_Inputs[Activity_Type], "Baseline") | E9: =SUMIFS(tblMaster_Inputs[Baseline_Amount], tblMaster_Inputs[Year], 2025, tblMaster_Inputs[Primary_Line], "8", tblMaster_Inputs[Activity_Type], "Baseline") | F9: =SUMIFS(tblMaster_Inputs[Baseline_Amount], tblMaster_Inputs[Year], 2026, tblMaster_Inputs[Primary_Line], "8", tblMaster_Inputs[Activity_Type], "Baseline") | G9: =SUMIFS(tblMaster_Inputs[Baseline_Amount], tblMaster_Inputs[Year], 2027, tblMaster_Inputs[Primary_Line], "8", tblMaster_Inputs[Activity_Type], "Baseline") | H9: =SUMIFS(tblMaster_Inputs[Baseline_Amount], tblMaster_Inputs[Year], 2028, tblMaster_Inputs[Primary_Line], "8", tblMaster_Inputs[Activity_Type], "Baseline")
A10: 9 | B10: TOTAL INCOME | C10: =C5+C6+C7+C8+C9 | D10: =D5+D6+D7+D8+D9 | E10: =E5+E6+E7+E8+E9 | F10: =F5+F6+F7+F8+F9 | G10: =G5+G6+G7+G8+G9 | H10: =H5+H6+H7+H8+H9
A11: 10 | B11: Adjustments to income | C11: =SUMIFS(tblMaster_Inputs[Baseline_Amount], tblMaster_Inputs[Year], 2023, tblMaster_Inputs[Primary_Line], "10", tblMaster_Inputs[Activity_Type], "Baseline") | D11: =SUMIFS(tblMaster_Inputs[Baseline_Amount], tblMaster_Inputs[Year], 2024, tblMaster_Inputs[Primary_Line], "10", tblMaster_Inputs[Activity_Type], "Baseline") | E11: =SUMIFS(tblMaster_Inputs[Baseline_Amount], tblMaster_Inputs[Year], 2025, tblMaster_Inputs[Primary_Line], "10", tblMaster_Inputs[Activity_Type], "Baseline") | F11: =SUMIFS(tblMaster_Inputs[Baseline_Amount], tblMaster_Inputs[Year], 2026, tblMaster_Inputs[Primary_Line], "10", tblMaster_Inputs[Activity_Type], "Baseline") | G11: =SUMIFS(tblMaster_Inputs[Baseline_Amount], tblMaster_Inputs[Year], 2027, tblMaster_Inputs[Primary_Line], "10", tblMaster_Inputs[Activity_Type], "Baseline") | H11: =SUMIFS(tblMaster_Inputs[Baseline_Amount], tblMaster_Inputs[Year], 2028, tblMaster_Inputs[Primary_Line], "10", tblMaster_Inputs[Activity_Type], "Baseline")
A12: 11 | B12: AGI | C12: =C10+C11 | D12: =D10+D11 | E12: =E10+E11 | F12: =F10+F11 | G12: =G10+G11 | H12: =H10+H11
A13: 12 | B13: Std/Itemized deduction | C13: =SUMIFS(tblMaster_Inputs[Baseline_Amount], tblMaster_Inputs[Year], 2023, tblMaster_Inputs[Primary_Line], "12", tblMaster_Inputs[Activity_Type], "Baseline") | D13: =SUMIFS(tblMaster_Inputs[Baseline_Amount], tblMaster_Inputs[Year], 2024, tblMaster_Inputs[Primary_Line], "12", tblMaster_Inputs[Activity_Type], "Baseline") | E13: =SUMIFS(tblMaster_Inputs[Baseline_Amount], tblMaster_Inputs[Year], 2025, tblMaster_Inputs[Primary_Line], "12", tblMaster_Inputs[Activity_Type], "Baseline") | F13: =SUMIFS(tblMaster_Inputs[Baseline_Amount], tblMaster_Inputs[Year], 2026, tblMaster_Inputs[Primary_Line], "12", tblMaster_Inputs[Activity_Type], "Baseline") | G13: =SUMIFS(tblMaster_Inputs[Baseline_Amount], tblMaster_Inputs[Year], 2027, tblMaster_Inputs[Primary_Line], "12", tblMaster_Inputs[Activity_Type], "Baseline") | H13: =SUMIFS(tblMaster_Inputs[Baseline_Amount], tblMaster_Inputs[Year], 2028, tblMaster_Inputs[Primary_Line], "12", tblMaster_Inputs[Activity_Type], "Baseline")
A14: 13 | B14: QBI deduction | C14: =SUMIFS(tblMaster_Inputs[Baseline_Amount], tblMaster_Inputs[Year], 2023, tblMaster_Inputs[Primary_Line], "13", tblMaster_Inputs[Activity_Type], "Baseline") | D14: =SUMIFS(tblMaster_Inputs[Baseline_Amount], tblMaster_Inputs[Year], 2024, tblMaster_Inputs[Primary_Line], "13", tblMaster_Inputs[Activity_Type], "Baseline") | E14: =SUMIFS(tblMaster_Inputs[Baseline_Amount], tblMaster_Inputs[Year], 2025, tblMaster_Inputs[Primary_Line], "13", tblMaster_Inputs[Activity_Type], "Baseline") | F14: =SUMIFS(tblMaster_Inputs[Baseline_Amount], tblMaster_Inputs[Year], 2026, tblMaster_Inputs[Primary_Line], "13", tblMaster_Inputs[Activity_Type], "Baseline") | G14: =SUMIFS(tblMaster_Inputs[Baseline_Amount], tblMaster_Inputs[Year], 2027, tblMaster_Inputs[Primary_Line], "13", tblMaster_Inputs[Activity_Type], "Baseline") | H14: =SUMIFS(tblMaster_Inputs[Baseline_Amount], tblMaster_Inputs[Year], 2028, tblMaster_Inputs[Primary_Line], "13", tblMaster_Inputs[Activity_Type], "Baseline")
A15: 15 | B15: TAXABLE INCOME | C15: =C12+C13+C14 | D15: =D12+D13+D14 | E15: =E12+E13+E14 | F15: =F12+F13+F14 | G15: =G12+G13+G14 | H15: =H12+H13+H14

Sheet Pivot_Medium
A1: PIVOT — MEDIUM (biz income broken out by entity type; multi-year baseline)
A2: Same as summary but Line 8 broken into Schedule C / Schedule E rental / Partnership K-1 / S-Corp K-1 / Sch F / Trust K-1.
A4: Line | B4: Description | C4: 2023 | D4: 2024 | E4: 2025 | F4: 2026 | G4: 2027 | H4: 2028
A5: 1z | B5: Wages | C5: =SUMIFS(tblMaster_Inputs[Baseline_Amount], tblMaster_Inputs[Year], 2023, tblMaster_Inputs[Primary_Line], "1z", tblMaster_Inputs[Activity_Type], "Baseline") | D5: =SUMIFS(tblMaster_Inputs[Baseline_Amount], tblMaster_Inputs[Year], 2024, tblMaster_Inputs[Primary_Line], "1z", tblMaster_Inputs[Activity_Type], "Baseline") | E5: =SUMIFS(tblMaster_Inputs[Baseline_Amount], tblMaster_Inputs[Year], 2025, tblMaster_Inputs[Primary_Line], "1z", tblMaster_Inputs[Activity_Type], "Baseline") | F5: =SUMIFS(tblMaster_Inputs[Baseline_Amount], tblMaster_Inputs[Year], 2026, tblMaster_Inputs[Primary_Line], "1z", tblMaster_Inputs[Activity_Type], "Baseline") | G5: =SUMIFS(tblMaster_Inputs[Baseline_Amount], tblMaster_Inputs[Year], 2027, tblMaster_Inputs[Primary_Line], "1z", tblMaster_Inputs[Activity_Type], "Baseline") | H5: =SUMIFS(tblMaster_Inputs[Baseline_Amount], tblMaster_Inputs[Year], 2028, tblMaster_Inputs[Primary_Line], "1z", tblMaster_Inputs[Activity_Type], "Baseline")
A6: 2 | B6: Interest | C6: =SUMIFS(tblMaster_Inputs[Baseline_Amount], tblMaster_Inputs[Year], 2023, tblMaster_Inputs[Primary_Line], "2b", tblMaster_Inputs[Activity_Type], "Baseline") | D6: =SUMIFS(tblMaster_Inputs[Baseline_Amount], tblMaster_Inputs[Year], 2024, tblMaster_Inputs[Primary_Line], "2b", tblMaster_Inputs[Activity_Type], "Baseline") | E6: =SUMIFS(tblMaster_Inputs[Baseline_Amount], tblMaster_Inputs[Year], 2025, tblMaster_Inputs[Primary_Line], "2b", tblMaster_Inputs[Activity_Type], "Baseline") | F6: =SUMIFS(tblMaster_Inputs[Baseline_Amount], tblMaster_Inputs[Year], 2026, tblMaster_Inputs[Primary_Line], "2b", tblMaster_Inputs[Activity_Type], "Baseline") | G6: =SUMIFS(tblMaster_Inputs[Baseline_Amount], tblMaster_Inputs[Year], 2027, tblMaster_Inputs[Primary_Line], "2b", tblMaster_Inputs[Activity_Type], "Baseline") | H6: =SUMIFS(tblMaster_Inputs[Baseline_Amount], tblMaster_Inputs[Year], 2028, tblMaster_Inputs[Primary_Line], "2b", tblMaster_Inputs[Activity_Type], "Baseline")
A7: 3 | B7: Dividends | C7: =SUMIFS(tblMaster_Inputs[Baseline_Amount], tblMaster_Inputs[Year], 2023, tblMaster_Inputs[Primary_Line], "3b", tblMaster_Inputs[Activity_Type], "Baseline") | D7: =SUMIFS(tblMaster_Inputs[Baseline_Amount], tblMaster_Inputs[Year], 2024, tblMaster_Inputs[Primary_Line], "3b", tblMaster_Inputs[Activity_Type], "Baseline") | E7: =SUMIFS(tblMaster_Inputs[Baseline_Amount], tblMaster_Inputs[Year], 2025, tblMaster_Inputs[Primary_Line], "3b", tblMaster_Inputs[Activity_Type], "Baseline") | F7: =SUMIFS(tblMaster_Inputs[Baseline_Amount], tblMaster_Inputs[Year], 2026, tblMaster_Inputs[Primary_Line], "3b", tblMaster_Inputs[Activity_Type], "Baseline") | G7: =SUMIFS(tblMaster_Inputs[Baseline_Amount], tblMaster_Inputs[Year], 2027, tblMaster_Inputs[Primary_Line], "3b", tblMaster_Inputs[Activity_Type], "Baseline") | H7: =SUMIFS(tblMaster_Inputs[Baseline_Amount], tblMaster_Inputs[Year], 2028, tblMaster_Inputs[Primary_Line], "3b", tblMaster_Inputs[Activity_Type], "Baseline")
A8: 7 | B8: Capital gain or (loss) | C8: =SUMIFS(tblMaster_Inputs[Baseline_Amount], tblMaster_Inputs[Year], 2023, tblMaster_Inputs[Primary_Line], "7", tblMaster_Inputs[Activity_Type], "Baseline") | D8: =SUMIFS(tblMaster_Inputs[Baseline_Amount], tblMaster_Inputs[Year], 2024, tblMaster_Inputs[Primary_Line], "7", tblMaster_Inputs[Activity_Type], "Baseline") | E8: =SUMIFS(tblMaster_Inputs[Baseline_Amount], tblMaster_Inputs[Year], 2025, tblMaster_Inputs[Primary_Line], "7", tblMaster_Inputs[Activity_Type], "Baseline") | F8: =SUMIFS(tblMaster_Inputs[Baseline_Amount], tblMaster_Inputs[Year], 2026, tblMaster_Inputs[Primary_Line], "7", tblMaster_Inputs[Activity_Type], "Baseline") | G8: =SUMIFS(tblMaster_Inputs[Baseline_Amount], tblMaster_Inputs[Year], 2027, tblMaster_Inputs[Primary_Line], "7", tblMaster_Inputs[Activity_Type], "Baseline") | H8: =SUMIFS(tblMaster_Inputs[Baseline_Amount], tblMaster_Inputs[Year], 2028, tblMaster_Inputs[Primary_Line], "7", tblMaster_Inputs[Activity_Type], "Baseline")
A9: 8.SchC | B9: Schedule C | C9: =SUMIFS(tblMaster_Inputs[Baseline_Amount], tblMaster_Inputs[Year], 2023, tblMaster_Inputs[Treatment_Profile], "SchC_Active", tblMaster_Inputs[Activity_Type], "Baseline") | D9: =SUMIFS(tblMaster_Inputs[Baseline_Amount], tblMaster_Inputs[Year], 2024, tblMaster_Inputs[Treatment_Profile], "SchC_Active", tblMaster_Inputs[Activity_Type], "Baseline") | E9: =SUMIFS(tblMaster_Inputs[Baseline_Amount], tblMaster_Inputs[Year], 2025, tblMaster_Inputs[Treatment_Profile], "SchC_Active", tblMaster_Inputs[Activity_Type], "Baseline") | F9: =SUMIFS(tblMaster_Inputs[Baseline_Amount], tblMaster_Inputs[Year], 2026, tblMaster_Inputs[Treatment_Profile], "SchC_Active", tblMaster_Inputs[Activity_Type], "Baseline") | G9: =SUMIFS(tblMaster_Inputs[Baseline_Amount], tblMaster_Inputs[Year], 2027, tblMaster_Inputs[Treatment_Profile], "SchC_Active", tblMaster_Inputs[Activity_Type], "Baseline") | H9: =SUMIFS(tblMaster_Inputs[Baseline_Amount], tblMaster_Inputs[Year], 2028, tblMaster_Inputs[Treatment_Profile], "SchC_Active", tblMaster_Inputs[Activity_Type], "Baseline")
A10: 8.SchE | B10: Schedule E rental | C10: =SUMIFS(tblMaster_Inputs[Baseline_Amount], tblMaster_Inputs[Year], 2023, tblMaster_Inputs[Treatment_Profile], "SchE_Rental", tblMaster_Inputs[Activity_Type], "Baseline") + SUMIFS(tblMaster_Inputs[Baseline_Amount], tblMaster_Inputs[Year], 2023, tblMaster_Inputs[Treatment_Profile], "SchE_REPro", tblMaster_Inputs[Activity_Type], "Baseline") | D10: =SUMIFS(tblMaster_Inputs[Baseline_Amount], tblMaster_Inputs[Year], 2024, tblMaster_Inputs[Treatment_Profile], "SchE_Rental", tblMaster_Inputs[Activity_Type], "Baseline") + SUMIFS(tblMaster_Inputs[Baseline_Amount], tblMaster_Inputs[Year], 2024, tblMaster_Inputs[Treatment_Profile], "SchE_REPro", tblMaster_Inputs[Activity_Type], "Baseline") | E10: =SUMIFS(tblMaster_Inputs[Baseline_Amount], tblMaster_Inputs[Year], 2025, tblMaster_Inputs[Treatment_Profile], "SchE_Rental", tblMaster_Inputs[Activity_Type], "Baseline") + SUMIFS(tblMaster_Inputs[Baseline_Amount], tblMaster_Inputs[Year], 2025, tblMaster_Inputs[Treatment_Profile], "SchE_REPro", tblMaster_Inputs[Activity_Type], "Baseline") | F10: =SUMIFS(tblMaster_Inputs[Baseline_Amount], tblMaster_Inputs[Year], 2026, tblMaster_Inputs[Treatment_Profile], "SchE_Rental", tblMaster_Inputs[Activity_Type], "Baseline") + SUMIFS(tblMaster_Inputs[Baseline_Amount], tblMaster_Inputs[Year], 2026, tblMaster_Inputs[Treatment_Profile], "SchE_REPro", tblMaster_Inputs[Activity_Type], "Baseline") | G10: =SUMIFS(tblMaster_Inputs[Baseline_Amount], tblMaster_Inputs[Year], 2027, tblMaster_Inputs[Treatment_Profile], "SchE_Rental", tblMaster_Inputs[Activity_Type], "Baseline") + SUMIFS(tblMaster_Inputs[Baseline_Amount], tblMaster_Inputs[Year], 2027, tblMaster_Inputs[Treatment_Profile], "SchE_REPro", tblMaster_Inputs[Activity_Type], "Baseline") | H10: =SUMIFS(tblMaster_Inputs[Baseline_Amount], tblMaster_Inputs[Year], 2028, tblMaster_Inputs[Treatment_Profile], "SchE_Rental", tblMaster_Inputs[Activity_Type], "Baseline") + SUMIFS(tblMaster_Inputs[Baseline_Amount], tblMaster_Inputs[Year], 2028, tblMaster_Inputs[Treatment_Profile], "SchE_REPro", tblMaster_Inputs[Activity_Type], "Baseline")
A11: 8.PTP | B11: Partnership K-1 (active+passive) | C11: =SUMIFS(tblMaster_Inputs[Baseline_Amount], tblMaster_Inputs[Year], 2023, tblMaster_Inputs[Treatment_Profile], "K1_PTP_Active", tblMaster_Inputs[Activity_Type], "Baseline") + SUMIFS(tblMaster_Inputs[Baseline_Amount], tblMaster_Inputs[Year], 2023, tblMaster_Inputs[Treatment_Profile], "K1_PTP_Passive", tblMaster_Inputs[Activity_Type], "Baseline") | D11: =SUMIFS(tblMaster_Inputs[Baseline_Amount], tblMaster_Inputs[Year], 2024, tblMaster_Inputs[Treatment_Profile], "K1_PTP_Active", tblMaster_Inputs[Activity_Type], "Baseline") + SUMIFS(tblMaster_Inputs[Baseline_Amount], tblMaster_Inputs[Year], 2024, tblMaster_Inputs[Treatment_Profile], "K1_PTP_Passive", tblMaster_Inputs[Activity_Type], "Baseline") | E11: =SUMIFS(tblMaster_Inputs[Baseline_Amount], tblMaster_Inputs[Year], 2025, tblMaster_Inputs[Treatment_Profile], "K1_PTP_Active", tblMaster_Inputs[Activity_Type], "Baseline") + SUMIFS(tblMaster_Inputs[Baseline_Amount], tblMaster_Inputs[Year], 2025, tblMaster_Inputs[Treatment_Profile], "K1_PTP_Passive", tblMaster_Inputs[Activity_Type], "Baseline") | F11: =SUMIFS(tblMaster_Inputs[Baseline_Amount], tblMaster_Inputs[Year], 2026, tblMaster_Inputs[Treatment_Profile], "K1_PTP_Active", tblMaster_Inputs[Activity_Type], "Baseline") + SUMIFS(tblMaster_Inputs[Baseline_Amount], tblMaster_Inputs[Year], 2026, tblMaster_Inputs[Treatment_Profile], "K1_PTP_Passive", tblMaster_Inputs[Activity_Type], "Baseline") | G11: =SUMIFS(tblMaster_Inputs[Baseline_Amount], tblMaster_Inputs[Year], 2027, tblMaster_Inputs[Treatment_Profile], "K1_PTP_Active", tblMaster_Inputs[Activity_Type], "Baseline") + SUMIFS(tblMaster_Inputs[Baseline_Amount], tblMaster_Inputs[Year], 2027, tblMaster_Inputs[Treatment_Profile], "K1_PTP_Passive", tblMaster_Inputs[Activity_Type], "Baseline") | H11: =SUMIFS(tblMaster_Inputs[Baseline_Amount], tblMaster_Inputs[Year], 2028, tblMaster_Inputs[Treatment_Profile], "K1_PTP_Active", tblMaster_Inputs[Activity_Type], "Baseline") + SUMIFS(tblMaster_Inputs[Baseline_Amount], tblMaster_Inputs[Year], 2028, tblMaster_Inputs[Treatment_Profile], "K1_PTP_Passive", tblMaster_Inputs[Activity_Type], "Baseline")
A12: 8.SCorp | B12: S-Corp K-1 (active+passive) | C12: =SUMIFS(tblMaster_Inputs[Baseline_Amount], tblMaster_Inputs[Year], 2023, tblMaster_Inputs[Treatment_Profile], "K1_SCorp_Active", tblMaster_Inputs[Activity_Type], "Baseline") + SUMIFS(tblMaster_Inputs[Baseline_Amount], tblMaster_Inputs[Year], 2023, tblMaster_Inputs[Treatment_Profile], "K1_SCorp_Passive", tblMaster_Inputs[Activity_Type], "Baseline") | D12: =SUMIFS(tblMaster_Inputs[Baseline_Amount], tblMaster_Inputs[Year], 2024, tblMaster_Inputs[Treatment_Profile], "K1_SCorp_Active", tblMaster_Inputs[Activity_Type], "Baseline") + SUMIFS(tblMaster_Inputs[Baseline_Amount], tblMaster_Inputs[Year], 2024, tblMaster_Inputs[Treatment_Profile], "K1_SCorp_Passive", tblMaster_Inputs[Activity_Type], "Baseline") | E12: =SUMIFS(tblMaster_Inputs[Baseline_Amount], tblMaster_Inputs[Year], 2025, tblMaster_Inputs[Treatment_Profile], "K1_SCorp_Active", tblMaster_Inputs[Activity_Type], "Baseline") + SUMIFS(tblMaster_Inputs[Baseline_Amount], tblMaster_Inputs[Year], 2025, tblMaster_Inputs[Treatment_Profile], "K1_SCorp_Passive", tblMaster_Inputs[Activity_Type], "Baseline") | F12: =SUMIFS(tblMaster_Inputs[Baseline_Amount], tblMaster_Inputs[Year], 2026, tblMaster_Inputs[Treatment_Profile], "K1_SCorp_Active", tblMaster_Inputs[Activity_Type], "Baseline") + SUMIFS(tblMaster_Inputs[Baseline_Amount], tblMaster_Inputs[Year], 2026, tblMaster_Inputs[Treatment_Profile], "K1_SCorp_Passive", tblMaster_Inputs[Activity_Type], "Baseline") | G12: =SUMIFS(tblMaster_Inputs[Baseline_Amount], tblMaster_Inputs[Year], 2027, tblMaster_Inputs[Treatment_Profile], "K1_SCorp_Active", tblMaster_Inputs[Activity_Type], "Baseline") + SUMIFS(tblMaster_Inputs[Baseline_Amount], tblMaster_Inputs[Year], 2027, tblMaster_Inputs[Treatment_Profile], "K1_SCorp_Passive", tblMaster_Inputs[Activity_Type], "Baseline") | H12: =SUMIFS(tblMaster_Inputs[Baseline_Amount], tblMaster_Inputs[Year], 2028, tblMaster_Inputs[Treatment_Profile], "K1_SCorp_Active", tblMaster_Inputs[Activity_Type], "Baseline") + SUMIFS(tblMaster_Inputs[Baseline_Amount], tblMaster_Inputs[Year], 2028, tblMaster_Inputs[Treatment_Profile], "K1_SCorp_Passive", tblMaster_Inputs[Activity_Type], "Baseline")
A13: 8.SchF | B13: Schedule F / farm | C13: =SUMIFS(tblMaster_Inputs[Baseline_Amount], tblMaster_Inputs[Year], 2023, tblMaster_Inputs[Treatment_Profile], "SchF_Active", tblMaster_Inputs[Activity_Type], "Baseline") | D13: =SUMIFS(tblMaster_Inputs[Baseline_Amount], tblMaster_Inputs[Year], 2024, tblMaster_Inputs[Treatment_Profile], "SchF_Active", tblMaster_Inputs[Activity_Type], "Baseline") | E13: =SUMIFS(tblMaster_Inputs[Baseline_Amount], tblMaster_Inputs[Year], 2025, tblMaster_Inputs[Treatment_Profile], "SchF_Active", tblMaster_Inputs[Activity_Type], "Baseline") | F13: =SUMIFS(tblMaster_Inputs[Baseline_Amount], tblMaster_Inputs[Year], 2026, tblMaster_Inputs[Treatment_Profile], "SchF_Active", tblMaster_Inputs[Activity_Type], "Baseline") | G13: =SUMIFS(tblMaster_Inputs[Baseline_Amount], tblMaster_Inputs[Year], 2027, tblMaster_Inputs[Treatment_Profile], "SchF_Active", tblMaster_Inputs[Activity_Type], "Baseline") | H13: =SUMIFS(tblMaster_Inputs[Baseline_Amount], tblMaster_Inputs[Year], 2028, tblMaster_Inputs[Treatment_Profile], "SchF_Active", tblMaster_Inputs[Activity_Type], "Baseline")
A14: 8.Trust | B14: Trust K-1 | C14: =SUMIFS(tblMaster_Inputs[Baseline_Amount], tblMaster_Inputs[Year], 2023, tblMaster_Inputs[Treatment_Profile], "Trust_K1", tblMaster_Inputs[Activity_Type], "Baseline") | D14: =SUMIFS(tblMaster_Inputs[Baseline_Amount], tblMaster_Inputs[Year], 2024, tblMaster_Inputs[Treatment_Profile], "Trust_K1", tblMaster_Inputs[Activity_Type], "Baseline") | E14: =SUMIFS(tblMaster_Inputs[Baseline_Amount], tblMaster_Inputs[Year], 2025, tblMaster_Inputs[Treatment_Profile], "Trust_K1", tblMaster_Inputs[Activity_Type], "Baseline") | F14: =SUMIFS(tblMaster_Inputs[Baseline_Amount], tblMaster_Inputs[Year], 2026, tblMaster_Inputs[Treatment_Profile], "Trust_K1", tblMaster_Inputs[Activity_Type], "Baseline") | G14: =SUMIFS(tblMaster_Inputs[Baseline_Amount], tblMaster_Inputs[Year], 2027, tblMaster_Inputs[Treatment_Profile], "Trust_K1", tblMaster_Inputs[Activity_Type], "Baseline") | H14: =SUMIFS(tblMaster_Inputs[Baseline_Amount], tblMaster_Inputs[Year], 2028, tblMaster_Inputs[Treatment_Profile], "Trust_K1", tblMaster_Inputs[Activity_Type], "Baseline")
A15: 8 | B15: Other income (Line 8 total) | C15: =C9+C10+C11+C12+C13+C14 | D15: =D9+D10+D11+D12+D13+D14 | E15: =E9+E10+E11+E12+E13+E14 | F15: =F9+F10+F11+F12+F13+F14 | G15: =G9+G10+G11+G12+G13+G14 | H15: =H9+H10+H11+H12+H13+H14
A16: 9 | B16: TOTAL INCOME | C16: =C5+C6+C7+C8+C15 | D16: =D5+D6+D7+D8+D15 | E16: =E5+E6+E7+E8+E15 | F16: =F5+F6+F7+F8+F15 | G16: =G5+G6+G7+G8+G15 | H16: =H5+H6+H7+H8+H15
A17: 10 | B17: Adjustments to income | C17: =SUMIFS(tblMaster_Inputs[Baseline_Amount], tblMaster_Inputs[Year], 2023, tblMaster_Inputs[Primary_Line], "10", tblMaster_Inputs[Activity_Type], "Baseline") | D17: =SUMIFS(tblMaster_Inputs[Baseline_Amount], tblMaster_Inputs[Year], 2024, tblMaster_Inputs[Primary_Line], "10", tblMaster_Inputs[Activity_Type], "Baseline") | E17: =SUMIFS(tblMaster_Inputs[Baseline_Amount], tblMaster_Inputs[Year], 2025, tblMaster_Inputs[Primary_Line], "10", tblMaster_Inputs[Activity_Type], "Baseline") | F17: =SUMIFS(tblMaster_Inputs[Baseline_Amount], tblMaster_Inputs[Year], 2026, tblMaster_Inputs[Primary_Line], "10", tblMaster_Inputs[Activity_Type], "Baseline") | G17: =SUMIFS(tblMaster_Inputs[Baseline_Amount], tblMaster_Inputs[Year], 2027, tblMaster_Inputs[Primary_Line], "10", tblMaster_Inputs[Activity_Type], "Baseline") | H17: =SUMIFS(tblMaster_Inputs[Baseline_Amount], tblMaster_Inputs[Year], 2028, tblMaster_Inputs[Primary_Line], "10", tblMaster_Inputs[Activity_Type], "Baseline")
A18: 11 | B18: AGI | C18: =C16+C17 | D18: =D16+D17 | E18: =E16+E17 | F18: =F16+F17 | G18: =G16+G17 | H18: =H16+H17
A19: 12 | B19: Std/Itemized deduction | C19: =SUMIFS(tblMaster_Inputs[Baseline_Amount], tblMaster_Inputs[Year], 2023, tblMaster_Inputs[Primary_Line], "12", tblMaster_Inputs[Activity_Type], "Baseline") | D19: =SUMIFS(tblMaster_Inputs[Baseline_Amount], tblMaster_Inputs[Year], 2024, tblMaster_Inputs[Primary_Line], "12", tblMaster_Inputs[Activity_Type], "Baseline") | E19: =SUMIFS(tblMaster_Inputs[Baseline_Amount], tblMaster_Inputs[Year], 2025, tblMaster_Inputs[Primary_Line], "12", tblMaster_Inputs[Activity_Type], "Baseline") | F19: =SUMIFS(tblMaster_Inputs[Baseline_Amount], tblMaster_Inputs[Year], 2026, tblMaster_Inputs[Primary_Line], "12", tblMaster_Inputs[Activity_Type], "Baseline") | G19: =SUMIFS(tblMaster_Inputs[Baseline_Amount], tblMaster_Inputs[Year], 2027, tblMaster_Inputs[Primary_Line], "12", tblMaster_Inputs[Activity_Type], "Baseline") | H19: =SUMIFS(tblMaster_Inputs[Baseline_Amount], tblMaster_Inputs[Year], 2028, tblMaster_Inputs[Primary_Line], "12", tblMaster_Inputs[Activity_Type], "Baseline")
A20: 13 | B20: QBI deduction | C20: =SUMIFS(tblMaster_Inputs[Baseline_Amount], tblMaster_Inputs[Year], 2023, tblMaster_Inputs[Primary_Line], "13", tblMaster_Inputs[Activity_Type], "Baseline") | D20: =SUMIFS(tblMaster_Inputs[Baseline_Amount], tblMaster_Inputs[Year], 2024, tblMaster_Inputs[Primary_Line], "13", tblMaster_Inputs[Activity_Type], "Baseline") | E20: =SUMIFS(tblMaster_Inputs[Baseline_Amount], tblMaster_Inputs[Year], 2025, tblMaster_Inputs[Primary_Line], "13", tblMaster_Inputs[Activity_Type], "Baseline") | F20: =SUMIFS(tblMaster_Inputs[Baseline_Amount], tblMaster_Inputs[Year], 2026, tblMaster_Inputs[Primary_Line], "13", tblMaster_Inputs[Activity_Type], "Baseline") | G20: =SUMIFS(tblMaster_Inputs[Baseline_Amount], tblMaster_Inputs[Year], 2027, tblMaster_Inputs[Primary_Line], "13", tblMaster_Inputs[Activity_Type], "Baseline") | H20: =SUMIFS(tblMaster_Inputs[Baseline_Amount], tblMaster_Inputs[Year], 2028, tblMaster_Inputs[Primary_Line], "13", tblMaster_Inputs[Activity_Type], "Baseline")
A21: 15 | B21: TAXABLE INCOME | C21: =C18+C19+C20 | D21: =D18+D19+D20 | E21: =E18+E19+E20 | F21: =F18+F19+F20 | G21: =G18+G19+G20 | H21: =H18+H19+H20

Sheet Pivot_Detailed
A1: PIVOT — DETAILED (full 1040 page-1 lines incl. informational 2a/3a; multi-year baseline)
A2: 2a and 3a are informational (carve-outs of helpers); they don't add to Line 9 Total Income.
A4: Line | B4: Description | C4: 2023 | D4: 2024 | E4: 2025 | F4: 2026 | G4: 2027 | H4: 2028
A5: 1z | B5: Wages | C5: =SUMIFS(tblMaster_Inputs[Baseline_Amount], tblMaster_Inputs[Year], 2023, tblMaster_Inputs[Primary_Line], "1z", tblMaster_Inputs[Activity_Type], "Baseline") | D5: =SUMIFS(tblMaster_Inputs[Baseline_Amount], tblMaster_Inputs[Year], 2024, tblMaster_Inputs[Primary_Line], "1z", tblMaster_Inputs[Activity_Type], "Baseline") | E5: =SUMIFS(tblMaster_Inputs[Baseline_Amount], tblMaster_Inputs[Year], 2025, tblMaster_Inputs[Primary_Line], "1z", tblMaster_Inputs[Activity_Type], "Baseline") | F5: =SUMIFS(tblMaster_Inputs[Baseline_Amount], tblMaster_Inputs[Year], 2026, tblMaster_Inputs[Primary_Line], "1z", tblMaster_Inputs[Activity_Type], "Baseline") | G5: =SUMIFS(tblMaster_Inputs[Baseline_Amount], tblMaster_Inputs[Year], 2027, tblMaster_Inputs[Primary_Line], "1z", tblMaster_Inputs[Activity_Type], "Baseline") | H5: =SUMIFS(tblMaster_Inputs[Baseline_Amount], tblMaster_Inputs[Year], 2028, tblMaster_Inputs[Primary_Line], "1z", tblMaster_Inputs[Activity_Type], "Baseline")
A6: 2a | B6: Tax-exempt interest (informational) | C6: =SUMIFS(tblMaster_Inputs[Helper_Amount], tblMaster_Inputs[Year], 2023, tblMaster_Inputs[Helper_Treatment], "TAX_EXEMPT", tblMaster_Inputs[Activity_Type], "Baseline") | D6: =SUMIFS(tblMaster_Inputs[Helper_Amount], tblMaster_Inputs[Year], 2024, tblMaster_Inputs[Helper_Treatment], "TAX_EXEMPT", tblMaster_Inputs[Activity_Type], "Baseline") | E6: =SUMIFS(tblMaster_Inputs[Helper_Amount], tblMaster_Inputs[Year], 2025, tblMaster_Inputs[Helper_Treatment], "TAX_EXEMPT", tblMaster_Inputs[Activity_Type], "Baseline") | F6: =SUMIFS(tblMaster_Inputs[Helper_Amount], tblMaster_Inputs[Year], 2026, tblMaster_Inputs[Helper_Treatment], "TAX_EXEMPT", tblMaster_Inputs[Activity_Type], "Baseline") | G6: =SUMIFS(tblMaster_Inputs[Helper_Amount], tblMaster_Inputs[Year], 2027, tblMaster_Inputs[Helper_Treatment], "TAX_EXEMPT", tblMaster_Inputs[Activity_Type], "Baseline") | H6: =SUMIFS(tblMaster_Inputs[Helper_Amount], tblMaster_Inputs[Year], 2028, tblMaster_Inputs[Helper_Treatment], "TAX_EXEMPT", tblMaster_Inputs[Activity_Type], "Baseline")
A7: 2b | B7: Taxable interest | C7: =SUMIFS(tblMaster_Inputs[Baseline_Amount], tblMaster_Inputs[Year], 2023, tblMaster_Inputs[Primary_Line], "2b", tblMaster_Inputs[Activity_Type], "Baseline") | D7: =SUMIFS(tblMaster_Inputs[Baseline_Amount], tblMaster_Inputs[Year], 2024, tblMaster_Inputs[Primary_Line], "2b", tblMaster_Inputs[Activity_Type], "Baseline") | E7: =SUMIFS(tblMaster_Inputs[Baseline_Amount], tblMaster_Inputs[Year], 2025, tblMaster_Inputs[Primary_Line], "2b", tblMaster_Inputs[Activity_Type], "Baseline") | F7: =SUMIFS(tblMaster_Inputs[Baseline_Amount], tblMaster_Inputs[Year], 2026, tblMaster_Inputs[Primary_Line], "2b", tblMaster_Inputs[Activity_Type], "Baseline") | G7: =SUMIFS(tblMaster_Inputs[Baseline_Amount], tblMaster_Inputs[Year], 2027, tblMaster_Inputs[Primary_Line], "2b", tblMaster_Inputs[Activity_Type], "Baseline") | H7: =SUMIFS(tblMaster_Inputs[Baseline_Amount], tblMaster_Inputs[Year], 2028, tblMaster_Inputs[Primary_Line], "2b", tblMaster_Inputs[Activity_Type], "Baseline")
A8: 3a | B8: Qualified dividends (informational) | C8: =SUMIFS(tblMaster_Inputs[Helper_Amount], tblMaster_Inputs[Year], 2023, tblMaster_Inputs[Helper_Treatment], "QUAL_DIV", tblMaster_Inputs[Activity_Type], "Baseline") | D8: =SUMIFS(tblMaster_Inputs[Helper_Amount], tblMaster_Inputs[Year], 2024, tblMaster_Inputs[Helper_Treatment], "QUAL_DIV", tblMaster_Inputs[Activity_Type], "Baseline") | E8: =SUMIFS(tblMaster_Inputs[Helper_Amount], tblMaster_Inputs[Year], 2025, tblMaster_Inputs[Helper_Treatment], "QUAL_DIV", tblMaster_Inputs[Activity_Type], "Baseline") | F8: =SUMIFS(tblMaster_Inputs[Helper_Amount], tblMaster_Inputs[Year], 2026, tblMaster_Inputs[Helper_Treatment], "QUAL_DIV", tblMaster_Inputs[Activity_Type], "Baseline") | G8: =SUMIFS(tblMaster_Inputs[Helper_Amount], tblMaster_Inputs[Year], 2027, tblMaster_Inputs[Helper_Treatment], "QUAL_DIV", tblMaster_Inputs[Activity_Type], "Baseline") | H8: =SUMIFS(tblMaster_Inputs[Helper_Amount], tblMaster_Inputs[Year], 2028, tblMaster_Inputs[Helper_Treatment], "QUAL_DIV", tblMaster_Inputs[Activity_Type], "Baseline")
A9: 3b | B9: Ordinary dividends (total incl qualified) | C9: =SUMIFS(tblMaster_Inputs[Baseline_Amount], tblMaster_Inputs[Year], 2023, tblMaster_Inputs[Primary_Line], "3b", tblMaster_Inputs[Activity_Type], "Baseline") | D9: =SUMIFS(tblMaster_Inputs[Baseline_Amount], tblMaster_Inputs[Year], 2024, tblMaster_Inputs[Primary_Line], "3b", tblMaster_Inputs[Activity_Type], "Baseline") | E9: =SUMIFS(tblMaster_Inputs[Baseline_Amount], tblMaster_Inputs[Year], 2025, tblMaster_Inputs[Primary_Line], "3b", tblMaster_Inputs[Activity_Type], "Baseline") | F9: =SUMIFS(tblMaster_Inputs[Baseline_Amount], tblMaster_Inputs[Year], 2026, tblMaster_Inputs[Primary_Line], "3b", tblMaster_Inputs[Activity_Type], "Baseline") | G9: =SUMIFS(tblMaster_Inputs[Baseline_Amount], tblMaster_Inputs[Year], 2027, tblMaster_Inputs[Primary_Line], "3b", tblMaster_Inputs[Activity_Type], "Baseline") | H9: =SUMIFS(tblMaster_Inputs[Baseline_Amount], tblMaster_Inputs[Year], 2028, tblMaster_Inputs[Primary_Line], "3b", tblMaster_Inputs[Activity_Type], "Baseline")
A10: 7 | B10: Capital gain or (loss) | C10: =SUMIFS(tblMaster_Inputs[Baseline_Amount], tblMaster_Inputs[Year], 2023, tblMaster_Inputs[Primary_Line], "7", tblMaster_Inputs[Activity_Type], "Baseline") | D10: =SUMIFS(tblMaster_Inputs[Baseline_Amount], tblMaster_Inputs[Year], 2024, tblMaster_Inputs[Primary_Line], "7", tblMaster_Inputs[Activity_Type], "Baseline") | E10: =SUMIFS(tblMaster_Inputs[Baseline_Amount], tblMaster_Inputs[Year], 2025, tblMaster_Inputs[Primary_Line], "7", tblMaster_Inputs[Activity_Type], "Baseline") | F10: =SUMIFS(tblMaster_Inputs[Baseline_Amount], tblMaster_Inputs[Year], 2026, tblMaster_Inputs[Primary_Line], "7", tblMaster_Inputs[Activity_Type], "Baseline") | G10: =SUMIFS(tblMaster_Inputs[Baseline_Amount], tblMaster_Inputs[Year], 2027, tblMaster_Inputs[Primary_Line], "7", tblMaster_Inputs[Activity_Type], "Baseline") | H10: =SUMIFS(tblMaster_Inputs[Baseline_Amount], tblMaster_Inputs[Year], 2028, tblMaster_Inputs[Primary_Line], "7", tblMaster_Inputs[Activity_Type], "Baseline")
A11: 8 | B11: Other income (biz via Sch 1) | C11: =SUMIFS(tblMaster_Inputs[Baseline_Amount], tblMaster_Inputs[Year], 2023, tblMaster_Inputs[Primary_Line], "8", tblMaster_Inputs[Activity_Type], "Baseline") | D11: =SUMIFS(tblMaster_Inputs[Baseline_Amount], tblMaster_Inputs[Year], 2024, tblMaster_Inputs[Primary_Line], "8", tblMaster_Inputs[Activity_Type], "Baseline") | E11: =SUMIFS(tblMaster_Inputs[Baseline_Amount], tblMaster_Inputs[Year], 2025, tblMaster_Inputs[Primary_Line], "8", tblMaster_Inputs[Activity_Type], "Baseline") | F11: =SUMIFS(tblMaster_Inputs[Baseline_Amount], tblMaster_Inputs[Year], 2026, tblMaster_Inputs[Primary_Line], "8", tblMaster_Inputs[Activity_Type], "Baseline") | G11: =SUMIFS(tblMaster_Inputs[Baseline_Amount], tblMaster_Inputs[Year], 2027, tblMaster_Inputs[Primary_Line], "8", tblMaster_Inputs[Activity_Type], "Baseline") | H11: =SUMIFS(tblMaster_Inputs[Baseline_Amount], tblMaster_Inputs[Year], 2028, tblMaster_Inputs[Primary_Line], "8", tblMaster_Inputs[Activity_Type], "Baseline")
A12: 9 | B12: TOTAL INCOME | C12: =C5+C7+C9+C10+C11 | D12: =D5+D7+D9+D10+D11 | E12: =E5+E7+E9+E10+E11 | F12: =F5+F7+F9+F10+F11 | G12: =G5+G7+G9+G10+G11 | H12: =H5+H7+H9+H10+H11
A13: 10 | B13: Adjustments to income | C13: =SUMIFS(tblMaster_Inputs[Baseline_Amount], tblMaster_Inputs[Year], 2023, tblMaster_Inputs[Primary_Line], "10", tblMaster_Inputs[Activity_Type], "Baseline") | D13: =SUMIFS(tblMaster_Inputs[Baseline_Amount], tblMaster_Inputs[Year], 2024, tblMaster_Inputs[Primary_Line], "10", tblMaster_Inputs[Activity_Type], "Baseline") | E13: =SUMIFS(tblMaster_Inputs[Baseline_Amount], tblMaster_Inputs[Year], 2025, tblMaster_Inputs[Primary_Line], "10", tblMaster_Inputs[Activity_Type], "Baseline") | F13: =SUMIFS(tblMaster_Inputs[Baseline_Amount], tblMaster_Inputs[Year], 2026, tblMaster_Inputs[Primary_Line], "10", tblMaster_Inputs[Activity_Type], "Baseline") | G13: =SUMIFS(tblMaster_Inputs[Baseline_Amount], tblMaster_Inputs[Year], 2027, tblMaster_Inputs[Primary_Line], "10", tblMaster_Inputs[Activity_Type], "Baseline") | H13: =SUMIFS(tblMaster_Inputs[Baseline_Amount], tblMaster_Inputs[Year], 2028, tblMaster_Inputs[Primary_Line], "10", tblMaster_Inputs[Activity_Type], "Baseline")
A14: 11 | B14: AGI | C14: =C12+C13 | D14: =D12+D13 | E14: =E12+E13 | F14: =F12+F13 | G14: =G12+G13 | H14: =H12+H13
A15: 12 | B15: Std/Itemized deduction | C15: =SUMIFS(tblMaster_Inputs[Baseline_Amount], tblMaster_Inputs[Year], 2023, tblMaster_Inputs[Primary_Line], "12", tblMaster_Inputs[Activity_Type], "Baseline") | D15: =SUMIFS(tblMaster_Inputs[Baseline_Amount], tblMaster_Inputs[Year], 2024, tblMaster_Inputs[Primary_Line], "12", tblMaster_Inputs[Activity_Type], "Baseline") | E15: =SUMIFS(tblMaster_Inputs[Baseline_Amount], tblMaster_Inputs[Year], 2025, tblMaster_Inputs[Primary_Line], "12", tblMaster_Inputs[Activity_Type], "Baseline") | F15: =SUMIFS(tblMaster_Inputs[Baseline_Amount], tblMaster_Inputs[Year], 2026, tblMaster_Inputs[Primary_Line], "12", tblMaster_Inputs[Activity_Type], "Baseline") | G15: =SUMIFS(tblMaster_Inputs[Baseline_Amount], tblMaster_Inputs[Year], 2027, tblMaster_Inputs[Primary_Line], "12", tblMaster_Inputs[Activity_Type], "Baseline") | H15: =SUMIFS(tblMaster_Inputs[Baseline_Amount], tblMaster_Inputs[Year], 2028, tblMaster_Inputs[Primary_Line], "12", tblMaster_Inputs[Activity_Type], "Baseline")
A16: 13 | B16: QBI deduction | C16: =SUMIFS(tblMaster_Inputs[Baseline_Amount], tblMaster_Inputs[Year], 2023, tblMaster_Inputs[Primary_Line], "13", tblMaster_Inputs[Activity_Type], "Baseline") | D16: =SUMIFS(tblMaster_Inputs[Baseline_Amount], tblMaster_Inputs[Year], 2024, tblMaster_Inputs[Primary_Line], "13", tblMaster_Inputs[Activity_Type], "Baseline") | E16: =SUMIFS(tblMaster_Inputs[Baseline_Amount], tblMaster_Inputs[Year], 2025, tblMaster_Inputs[Primary_Line], "13", tblMaster_Inputs[Activity_Type], "Baseline") | F16: =SUMIFS(tblMaster_Inputs[Baseline_Amount], tblMaster_Inputs[Year], 2026, tblMaster_Inputs[Primary_Line], "13", tblMaster_Inputs[Activity_Type], "Baseline") | G16: =SUMIFS(tblMaster_Inputs[Baseline_Amount], tblMaster_Inputs[Year], 2027, tblMaster_Inputs[Primary_Line], "13", tblMaster_Inputs[Activity_Type], "Baseline") | H16: =SUMIFS(tblMaster_Inputs[Baseline_Amount], tblMaster_Inputs[Year], 2028, tblMaster_Inputs[Primary_Line], "13", tblMaster_Inputs[Activity_Type], "Baseline")
A17: 15 | B17: TAXABLE INCOME | C17: =C14+C15+C16 | D17: =D14+D15+D16 | E17: =E14+E15+E16 | F17: =F14+F15+F16 | G17: =G14+G15+G16 | H17: =H14+H15+H16

Sheet Pivot_Helpers
A1: PIVOT — HELPERS / TAX-CALC INPUTS (multi-year; sub-carves of main pivot lines; do NOT add to 1040 totals)
A2: These exist for LAMBDA inputs only — qualified div for LTCG stacking, owner W-2 for FICA, etc.
A4: Line | B4: Description | C4: 2023 | D4: 2024 | E4: 2025 | F4: 2026 | G4: 2027 | H4: 2028
A5: W2_OWNER | B5: Owner W-2 wages (Treatment_Profile=W2_SCorpOwner) | C5: =SUMIFS(tblMaster_Inputs[Baseline_Amount], tblMaster_Inputs[Year], 2023, tblMaster_Inputs[Treatment_Profile], "W2_SCorpOwner", tblMaster_Inputs[Activity_Type], "Baseline") | D5: =SUMIFS(tblMaster_Inputs[Baseline_Amount], tblMaster_Inputs[Year], 2024, tblMaster_Inputs[Treatment_Profile], "W2_SCorpOwner", tblMaster_Inputs[Activity_Type], "Baseline") | E5: =SUMIFS(tblMaster_Inputs[Baseline_Amount], tblMaster_Inputs[Year], 2025, tblMaster_Inputs[Treatment_Profile], "W2_SCorpOwner", tblMaster_Inputs[Activity_Type], "Baseline") | F5: =SUMIFS(tblMaster_Inputs[Baseline_Amount], tblMaster_Inputs[Year], 2026, tblMaster_Inputs[Treatment_Profile], "W2_SCorpOwner", tblMaster_Inputs[Activity_Type], "Baseline") | G5: =SUMIFS(tblMaster_Inputs[Baseline_Amount], tblMaster_Inputs[Year], 2027, tblMaster_Inputs[Treatment_Profile], "W2_SCorpOwner", tblMaster_Inputs[Activity_Type], "Baseline") | H5: =SUMIFS(tblMaster_Inputs[Baseline_Amount], tblMaster_Inputs[Year], 2028, tblMaster_Inputs[Treatment_Profile], "W2_SCorpOwner", tblMaster_Inputs[Activity_Type], "Baseline")
A6: W2_THIRD_PARTY | B6: Third-party W-2 wages (Treatment_Profile=W2_Employee) | C6: =SUMIFS(tblMaster_Inputs[Baseline_Amount], tblMaster_Inputs[Year], 2023, tblMaster_Inputs[Treatment_Profile], "W2_Employee", tblMaster_Inputs[Activity_Type], "Baseline") | D6: =SUMIFS(tblMaster_Inputs[Baseline_Amount], tblMaster_Inputs[Year], 2024, tblMaster_Inputs[Treatment_Profile], "W2_Employee", tblMaster_Inputs[Activity_Type], "Baseline") | E6: =SUMIFS(tblMaster_Inputs[Baseline_Amount], tblMaster_Inputs[Year], 2025, tblMaster_Inputs[Treatment_Profile], "W2_Employee", tblMaster_Inputs[Activity_Type], "Baseline") | F6: =SUMIFS(tblMaster_Inputs[Baseline_Amount], tblMaster_Inputs[Year], 2026, tblMaster_Inputs[Treatment_Profile], "W2_Employee", tblMaster_Inputs[Activity_Type], "Baseline") | G6: =SUMIFS(tblMaster_Inputs[Baseline_Amount], tblMaster_Inputs[Year], 2027, tblMaster_Inputs[Treatment_Profile], "W2_Employee", tblMaster_Inputs[Activity_Type], "Baseline") | H6: =SUMIFS(tblMaster_Inputs[Baseline_Amount], tblMaster_Inputs[Year], 2028, tblMaster_Inputs[Treatment_Profile], "W2_Employee", tblMaster_Inputs[Activity_Type], "Baseline")
A7: W2_TOTAL | B7: Total W-2 (owner + third-party) | C7: =C5+C6 | D7: =D5+D6 | E7: =E5+E6 | F7: =F5+F6 | G7: =G5+G6 | H7: =H5+H6
