Workbook
Name Active_Client: Control_Panel!$C$11
Name Active_Year: Control_Panel!$C$8
Name Activity_Type: Dropdown_Lists!$G$4:$G$5
Name AdjToIncome: INDIRECT("Y"&Active_Year&"!$N$14")
Name Adjustment_Docs: Dropdown_Lists!$E$35:$E$39
Name Adjustment_Profiles: Dropdown_Lists!$E$19:$E$23
Name AGI: INDIRECT("Y"&Active_Year&"!$N$15")
Name BI_ACTIVE_NONSE: INDIRECT("Y"&Active_Year&"!$J$27")
Name BI_PASSIVE: INDIRECT("Y"&Active_Year&"!$J$28")
Name BI_SE_SUBJECT: INDIRECT("Y"&Active_Year&"!$J$26")
Name Bucket: Dropdown_Lists!$A$4:$A$11
Name BusinessIncome_Docs: Dropdown_Lists!$A$35:$A$41
Name BusinessIncome_Profiles: Dropdown_Lists!$A$19:$A$27
Name BusinessLoss: INDIRECT("Y"&Active_Year&"!$J$42")
Name CapitalGains_Docs: Dropdown_Lists!$D$35:$D$38
Name CapitalGains_Profiles: Dropdown_Lists!$D$19:$D$23
Name CG_LT: INDIRECT("Y"&Active_Year&"!$J$31")
Name CG_ST: INDIRECT("Y"&Active_Year&"!$J$32")
Name Credit_Docs: Dropdown_Lists!$G$35:$G$37
Name Credit_Profiles: Dropdown_Lists!$G$19:$G$21
Name Drill_Line: INDIRECT("Y"&Active_Year&"!$I$49")
Name Filing_Status: Control_Panel!$C$15
Name InvestmentIncome_Docs: Dropdown_Lists!$C$35:$C$37
Name InvestmentIncome_Profiles: Dropdown_Lists!$C$19:$C$22
Name IsSSTB: INDIRECT("Y"&Active_Year&"!$J$45")
Name Itemized_Docs: Dropdown_Lists!$F$35:$F$38
Name Itemized_Profiles: Dropdown_Lists!$F$19:$F$22
Name Line_1z_Wages: INDIRECT("Y"&Active_Year&"!$N$6")
Name Line_2a_TaxExempt: INDIRECT("Y"&Active_Year&"!$N$7")
Name Line_2b_TaxInt: INDIRECT("Y"&Active_Year&"!$N$8")
Name Line_3a_QualDiv: INDIRECT("Y"&Active_Year&"!$N$9")
Name Line_3b_OrdDiv: INDIRECT("Y"&Active_Year&"!$N$10")
Name Line_7_CapGain: INDIRECT("Y"&Active_Year&"!$N$11")
Name Line_8_OtherInc: INDIRECT("Y"&Active_Year&"!$N$12")
Name MAGI: INDIRECT("Y"&Active_Year&"!$J$38")
Name NetSEIncome: INDIRECT("Y"&Active_Year&"!$J$43")
Name NII: INDIRECT("Y"&Active_Year&"!$J$39")
Name NIIT_Class: Dropdown_Lists!$C$4:$C$7
Name NOL_Carryforward: INDIRECT("Y"&Active_Year&"!$J$46")
Name OrdIncome: INDIRECT("Y"&Active_Year&"!$J$37")
Name Payment_Docs: Dropdown_Lists!$H$35:$H$36
Name Payment_Profiles: Dropdown_Lists!$H$19:$H$20
Name Provenance: Dropdown_Lists!$D$4:$D$13
Name QBI_Deduction: INDIRECT("Y"&Active_Year&"!$N$17")
Name QBI_Income: INDIRECT("Y"&Active_Year&"!$J$40")
Name QUAL_DIV: INDIRECT("Y"&Active_Year&"!$J$30")
Name SEC1250: INDIRECT("Y"&Active_Year&"!$J$33")
Name Slicer_Activity_Type: #N/A
Name Slicer_Activity_Type1: #N/A
Name Slicer_Activity_Type2: #N/A
Name Slicer_Activity_Type3: #N/A
Name Slicer_Bucket: #N/A
Name Slicer_Bucket1: #N/A
Name Slicer_ClientID: #N/A
Name Slicer_ClientID1: #N/A
Name Slicer_NIIT_Class: #N/A
Name Slicer_QBI_Eligible: #N/A
Name Slicer_SE_Subject: #N/A
Name Slicer_Year: #N/A
Name Slicer_Year1: #N/A

Sheet Control_Panel
B2: TAX WORKBOOK — CONTROL PANEL
B3: Settings, navigation, and input reference — start here.
B5: ▸ SETTINGS
B7: PLAN STATUS
B8: Plan Year | C8: 2025
B9: Plan Maturity | C9: Standard Assumptions
B10: Engagement Leader | C10: TBD
B11: Active Client | C11: SAMPLE
B12: Last Refresh | C12: 46161
B14: TAX PROFILE
B15: Filing Status | C15: MFJ
B16: State of Residence | C16: UT
B17: Taxpayer Age | C17: 42
B18: Spouse Age | C18: 40
B19: Dependent Children | C19: 2
B20: REPS Qualified | C20: No
B21: Business is SSTB? | C21: No
B23: ▸ ACTIVE YEAR SNAPSHOT
B24: AGI | C24: {=TEXT(AGI,"$#,##0")}
B25: Taxable Income | C25: {=TEXT(TaxableIncome,"$#,##0")}
B26: Effective Rate | C26: {=TEXT(IFERROR(INDIRECT("Y"&Active_Year&"!I130"),0),"0.0%")}
B27: Total Tax | C27: {=TEXT(IFERROR(INDIRECT("Y"&Active_Year&"!I129"),0),"$#,##0")}
B28: QBI Deduction | C28: {=TEXT(QBI_Deduction,"($#,##0)")}
B30: ▸ NAVIGATION
B32: INPUT / CONFIG
B33: =HYPERLINK("#Master_Inputs!A1", "Master_Inputs") | C33: Baseline income/deductions + committed strategies
B34: =HYPERLINK("#AsFiled!A1", "AsFiled") | C34: Filed return data by year for PY reconciliation
B35: =HYPERLINK("#Carryovers!A1", "Carryovers") | C35: PAL, CL, NOL manual inputs + calculator
B37: YEAR SANDBOXES
B38: =HYPERLINK("#Y2023!A1", "Y2023") | C38: Strategies (A5:F10), rollup, 7-calculator
B39: =HYPERLINK("#Y2024!A1", "Y2024") | C39: Strategies (A5:F10), rollup, 7-calculator
B40: =HYPERLINK("#Y2025!A1", "Y2025") | C40: Strategies (A5:F10), rollup, 7-calculator
B41: =HYPERLINK("#Y2026!A1", "Y2026") | C41: Strategies (A5:F10), rollup, 7-calculator
B42: =HYPERLINK("#Y2027!A1", "Y2027") | C42: Strategies (A5:F10), rollup, 7-calculator
B43: =HYPERLINK("#Y2028!A1", "Y2028") | C43: Strategies (A5:F10), rollup, 7-calculator
B45: DASHBOARDS / RECON
B46: =HYPERLINK("#Tax_Plan_Dashboard!A1", "Tax_Plan_Dashboard") | C46: KPIs + charts with year dropdown
B47: =HYPERLINK("#PY_Recon!A1", "PY_Recon") | C47: Prior year baseline vs AsFiled reconciliation
B48: =HYPERLINK("#Pivot_GPD!A1", "Pivot_GPD") | C48: Multi-year GETPIVOTDATA bridge + VP_ named ranges
B50: PIVOT ENGINE (do not modify)
B51: =HYPERLINK("#Pivot_Summary!A1", "Pivot_Summary") | C51: SUMIFS grid: 1040 lines × years
B52: =HYPERLINK("#Pivot_Medium!A1", "Pivot_Medium") | C52: SUMIFS grid: Line 8 breakout by treatment
B53: =HYPERLINK("#Pivot_Detailed!A1", "Pivot_Detailed") | C53: SUMIFS grid: informational lines (2a, 3a)
B54: =HYPERLINK("#Pivot_Helpers!A1", "Pivot_Helpers") | C54: SUMIFS grid: helper amounts × years
B56: VISUAL PIVOTS
B57: =HYPERLINK("#Visual_Pivot_Income!A1", "Visual_Pivot_Income") | C57: PivotTable: income by 1040 line
B58: =HYPERLINK("#Visual_Pivot_BusinessIncome!A1", "Visual_Pivot_BusinessIncome") | C58: PivotTable: business by treatment
B59: =HYPERLINK("#Visual_Pivot_ByPayor!A1", "Visual_Pivot_ByPayor") | C59: PivotTable: income by payor
B60: =HYPERLINK("#Visual_Pivot_HelperCarveOuts!A1", "Visual_Pivot_HelperCarveOuts") | C60: PivotTable: helper carve-outs
B62: REFERENCE
B63: =HYPERLINK("#Tax_Ref!A1", "Tax_Ref") | C63: Rate tables + Treatment_Profile_Map (5 tables)
B64: =HYPERLINK("#Dropdown_Lists!A1", "Dropdown_Lists") | C64: Validation source lists
B65: =HYPERLINK("#Framework_Ref!A1", "Framework_Ref") | C65: Canon v1.4 + Pecking Order + Strategies catalog
B66: =HYPERLINK("#Glossary!A1", "Glossary") | C66: 100+ terms, PTET table + Tax Limitations
B67: =HYPERLINK("#Questionnaire!A1", "Questionnaire") | C67: 26-question strategy intake (auto-detects from data)
B68: =HYPERLINK("#Connections!A1", "Connections") | C68: External file paths + extraction mapping
B69: =HYPERLINK("#Projection_History!A1", "Projection_History") | C69: Projected vs filed accuracy tracking
B70: =HYPERLINK("#Change_Log!A1", "Change_Log") | C70: Audit trail
B71: =HYPERLINK("#Setup_Guide!A1", "Setup_Guide") | C71: Onboarding + LAMBDA/VBA/Schema docs

Sheet Master_Inputs
A1: MASTER INPUTS — committed baseline source-input items (one row per source document per year)
A2: Adjustments and strategies live on the year sheet. Master is just where baseline data lives.
A4: InputID | B4: Year | C4: ClientID | D4: ClientName | E4: Bucket | F4: Treatment_Profile | G4: Source_Document | H4: Activity_Type | I4: Provenance | J4: Payor | K4: Baseline_Amount | L4: Helper_Amount | M4: Helper_Treatment | N4: SE_Subject | O4: NIIT_Class | P4: QBI_Eligible | Q4: Primary_Line | R4: Consider | S4: Notes
A5: CED|2024|Wages|01 | B5: 2024 | C5: CEDILLO | D5: Ron Cedillo | E5: Wages | F5: W2_SCorpOwner | G5: W-2 | H5: Baseline | I5: PBC - Reviewed | J5: Acme S-Corp | K5: 153648 | L5: 0 | M5: OWNER_PAY | N5: No | O5: Active | P5: No | Q5: 1z | R5: Owner reasonable comp
A6: CED|2024|BI|01 | B6: 2024 | C6: CEDILLO | D6: Ron Cedillo | E6: Business Income | F6: K1_PTP_Passive | G6: K-1 | H6: Baseline | I6: PBC - Reviewed | J6: Cedillo Partnership | K6: -100766 | L6: 0 | M6: K1_SPLIT | N6: No | O6: Passive | P6: Yes | Q6: 8 | R6: Passive loss
A7: CED|2024|II|01 | B7: 2024 | C7: CEDILLO | D7: Ron Cedillo | E7: Investment Income | F7: Div_Ordinary | G7: 1099-DIV | H7: Baseline | I7: PBC - Reviewed | J7: Brokerage | K7: 25922 | L7: 0 | M7: QUAL_DIV | N7: No | O7: Portfolio | P7: No | Q7: 3b | R7: All non-qualified
A8: CED|2024|CG|01 | B8: 2024 | C8: CEDILLO | D8: Ron Cedillo | E8: Capital Gains | F8: LTCG_Stock | G8: 1099-B | H8: Baseline | I8: PBC - Reviewed | J8: Brokerage | K8: 14487 | L8: 0 | M8: LTCG_SPLIT | N8: No | O8: Portfolio | P8: No | Q8: 7 | R8: All long-term
A9: SAM|2025|Wages|01 | B9: 2025 | C9: SAMPLE | D9: Sample Client | E9: Wages | F9: W2_SCorpOwner | G9: W-2 | H9: Baseline | I9: Estimate - Preparer | J9: SampleCo S-Corp | K9: 100000 | L9: 100000 | M9: OWNER_PAY | N9: No | O9: Active | P9: No | Q9: 1z | R9: Owner reasonable comp
A10: SAM|2025|BI|01 | B10: 2025 | C10: SAMPLE | D10: Sample Client | E10: Business Income | F10: K1_SCorp_Active | G10: K-1 | H10: Baseline | I10: PY Rolled Forward | J10: SampleCo S-Corp K-1 | K10: 200000 | L10: 0 | M10: K1_SPLIT | N10: No | O10: Active | P10: Yes | Q10: 8 | R10: Active S-corp K-1
A11: SAM|2025|II_Div|01 | B11: 2025 | C11: SAMPLE | D11: Sample Client | E11: Investment Income | F11: Div_Qualified | G11: 1099-DIV | H11: Baseline | I11: PBC - Received | J11: Brokerage | K11: 10000 | L11: 7000 | M11: QUAL_DIV | N11: No | O11: Portfolio | P11: No | Q11: 3b | R11: $7K qualified
A12: SAM|2025|II_Int|01 | B12: 2025 | C12: SAMPLE | D12: Sample Client | E12: Investment Income | F12: Int_Taxable | G12: 1099-INT | H12: Baseline | I12: PBC - Received | J12: Brokerage | K12: 500 | L12: 0 | M12: NONE | N12: No | O12: Portfolio | P12: No | Q12: 2b | R12: All taxable
A13: SAM|2025|CG|01 | B13: 2025 | C13: SAMPLE | D13: Sample Client | E13: Capital Gains | F13: LTCG_Stock | G13: 1099-B | H13: Baseline | I13: PBC - Requested | J13: Brokerage | K13: 25000 | L13: 0 | M13: LTCG_SPLIT | N13: No | O13: Portfolio | P13: No | Q13: 7 | R13: All long-term
A14: SAM|2025|Itm|01 | B14: 2025 | C14: SAMPLE | D14: Sample Client | E14: Itemized | F14: Itm_SALT | G14: Property Tax Receipt | H14: Baseline | I14: PBC - Received | K14: -10000 | L14: 0 | M14: SALT | N14: No | O14: N/A | P14: No | Q14: 12 | R14: SALT cap
A15: SAM|2025|Strategy|WageOpt|01 | B15: 2025 | C15: SAMPLE | D15: Sample Client | E15: Wages | F15: W2_SCorpOwner | H15: Strategy | I15: Planning | J15: SampleCo S-Corp | K15: -25000 | L15: 0 | M15: OWNER_PAY | N15: No | O15: Active | P15: No | Q15: 1z | R15: Reduce owner W-2 by $25K | S15: STR-001 Committed
A16: SAM|2025|Strategy|WageOpt|02 | B16: 2025 | C16: SAMPLE | D16: Sample Client | E16: Business Income | F16: K1_SCorp_Active | H16: Strategy | I16: Planning | J16: SampleCo S-Corp K-1 | K16: 25000 | L16: 0 | M16: K1_SPLIT | N16: No | O16: Active | P16: Yes | Q16: 8 | R16: Corresponding K-1 increase from wage reduction | S16: STR-001 Committed
A17: SAM|2025|Strategy|HSA|01 | B17: 2025 | C17: SAMPLE | D17: Sample Client | E17: Adjustment | F17: Adj_HSA | H17: Strategy | I17: Planning | K17: -8550 | L17: 0 | M17: NONE | N17: No | O17: N/A | P17: No | Q17: 10 | R17: Family HSA max contribution | S17: STR-002 Committed
A18: SAM|2025|Strategy|CostSeg|01 | B18: 2025 | C18: SAMPLE | D18: Sample Client | E18: Business Income | F18: SchE_Rental | H18: Strategy | I18: Planning | J18: 123 Main St, Salt Lake City | K18: -80000 | L18: 0 | M18: PASSIVE | N18: No | O18: Passive | P18: No | Q18: 8 | R18: Cost seg accelerated depreciation | S18: STR-005 Committed

Sheet AsFiled
B2: ASFILED — Filed Tax Return Data
B3: Filed return amounts by 1040 line. Use Year column filter to view one year at a time. Add rows per year as needed. PY_Recon uses SUMIFS against this table.
B5: InputID | C5: Year | D5: ClientID | E5: ClientName | F5: Bucket | G5: Treatment_Profile | H5: Source_Document | I5: Provenance | J5: Payor | K5: Filed_Amount | L5: Helper_Amount | M5: Helper_Treatment | N5: Primary_Line | O5: Notes
B6: CED|2024|AF|Wages|01 | C6: 2024 | D6: CEDILLO | E6: Ron Cedillo | F6: Wages | G6: W2_SCorpOwner | H6: Filed 1040 | I6: Filed Return | J6: Acme S-Corp | K6: 153648 | L6: 0 | M6: OWNER_PAY | N6: 1z | O6: Per filed Form 1040 Line 1z
B7: CED|2024|AF|BI|01 | C7: 2024 | D7: CEDILLO | E7: Ron Cedillo | F7: Business Income | G7: K1_PTP_Passive | H7: Filed 1040 | I7: Filed Return | J7: Cedillo Partnership | K7: -100766 | L7: 0 | M7: K1_SPLIT | N7: 8 | O7: Per filed Sch 1 / K-1
B8: CED|2024|AF|II|01 | C8: 2024 | D8: CEDILLO | E8: Ron Cedillo | F8: Investment Income | G8: Div_Ordinary | H8: Filed 1040 | I8: Filed Return | J8: Brokerage | K8: 25922 | L8: 0 | M8: QUAL_DIV | N8: 3b | O8: Per filed 1040 Line 3b
B9: CED|2024|AF|CG|01 | C9: 2024 | D9: CEDILLO | E9: Ron Cedillo | F9: Capital Gains | G9: LTCG_Stock | H9: Filed 1040 | I9: Filed Return | J9: Brokerage | K9: 14487 | L9: 0 | M9: LTCG_SPLIT | N9: 7 | O9: Per filed 1040 Line 7
B10: PLACEHOLDER|2023 | C10: 2023 | I10: Estimate | K10: 0 | L10: 0 | O10: Enter 2023 filed data here — add rows as needed
B11: PLACEHOLDER|2025 | C11: 2025 | I11: Estimate | K11: 0 | L11: 0 | O11: Enter 2025 filed data here — add rows as needed
B12: PLACEHOLDER|2026 | C12: 2026 | I12: Estimate | K12: 0 | L12: 0 | O12: Enter 2026 filed data here — add rows as needed
B13: PLACEHOLDER|2027 | C13: 2027 | I13: Estimate | K13: 0 | L13: 0 | O13: Enter 2027 filed data here — add rows as needed
B14: PLACEHOLDER|2028 | C14: 2028 | I14: Estimate | K14: 0 | L14: 0 | O14: Enter 2028 filed data here — add rows as needed

Sheet Tax_Plan_Dashboard
B2: TAX PLAN DASHBOARD
B3: Select year below. KPIs pull baseline from visual pivots via GETPIVOTDATA.
B4: Dashboard Year: | C4: 2025
B5: HEADLINE METRICS | C5: Baseline | D5: Eff w/ Strat | E5: Δ Savings | H5: CHART DATA — Income by 1040 Line
B6: Total Income | C6: {=IFERROR(INDIRECT("Y"&$C$4&"!K13"),0)} | D6: {=IFERROR(INDIRECT("Y"&$C$4&"!P13"),0)} | E6: =C6-D6 | H6: 1040 Line | I6: Baseline | J6: Effective | K6: Strategy Δ
B7: Wages (Line 1z) | C7: {=IFERROR(INDIRECT("Y"&$C$4&"!K6"),0)} | D7: {=IFERROR(INDIRECT("Y"&$C$4&"!P6"),0)} | E7: =C7-D7 | H7: 1040 Line | I7: Baseline | J7: Effective | K7: Strategy Δ
B8: Business Income (Line 8) | C8: {=IFERROR(INDIRECT("Y"&$C$4&"!K12"),0)} | D8: {=IFERROR(INDIRECT("Y"&$C$4&"!P12"),0)} | E8: =C8-D8 | H8: 1z Wages | I8: =IFERROR(INDEX(Pivot_Summary!$C5:$H5,MATCH(TEXT($C$4,"0"),Pivot_Summary!$C$4:$H$4,0)),0) | J8: =IFERROR(INDEX(Pivot_Summary!$O5:$T5,MATCH($C$4,Pivot_Summary!$O$4:$T$4,0)),0) | K8: =IFERROR(INDEX(Pivot_Summary!$I5:$N5,MATCH($C$4,Pivot_Summary!$I$4:$N$4,0)),0)
B9: Capital Gains (Line 7) | C9: {=IFERROR(INDIRECT("Y"&$C$4&"!K11"),0)} | D9: {=IFERROR(INDIRECT("Y"&$C$4&"!P11"),0)} | E9: =C9-D9 | H9: 2b Tax Interest | I9: =IFERROR(INDEX(Pivot_Summary!$C6:$H6,MATCH(TEXT($C$4,"0"),Pivot_Summary!$C$4:$H$4,0)),0) | J9: =IFERROR(INDEX(Pivot_Summary!$O6:$T6,MATCH($C$4,Pivot_Summary!$O$4:$T$4,0)),0) | K9: =IFERROR(INDEX(Pivot_Summary!$I6:$N6,MATCH($C$4,Pivot_Summary!$I$4:$N$4,0)),0)
B10: Investment Income (3b) | C10: {=IFERROR(INDIRECT("Y"&$C$4&"!K10"),0)} | D10: {=IFERROR(INDIRECT("Y"&$C$4&"!P10"),0)} | E10: =C10-D10 | H10: 3b Dividends | I10: =IFERROR(INDEX(Pivot_Summary!$C7:$H7,MATCH(TEXT($C$4,"0"),Pivot_Summary!$C$4:$H$4,0)),0) | J10: =IFERROR(INDEX(Pivot_Summary!$O7:$T7,MATCH($C$4,Pivot_Summary!$O$4:$T$4,0)),0) | K10: =IFERROR(INDEX(Pivot_Summary!$I7:$N7,MATCH($C$4,Pivot_Summary!$I$4:$N$4,0)),0)
B11: Std/Itemized Ded (Line 12) | C11: {=IFERROR(INDIRECT("Y"&$C$4&"!K16"),0)} | D11: {=IFERROR(INDIRECT("Y"&$C$4&"!P16"),0)} | E11: =C11-D11 | H11: 7 Cap Gains | I11: =IFERROR(INDEX(Pivot_Summary!$C8:$H8,MATCH(TEXT($C$4,"0"),Pivot_Summary!$C$4:$H$4,0)),0) | J11: =IFERROR(INDEX(Pivot_Summary!$O8:$T8,MATCH($C$4,Pivot_Summary!$O$4:$T$4,0)),0) | K11: =IFERROR(INDEX(Pivot_Summary!$I8:$N8,MATCH($C$4,Pivot_Summary!$I$4:$N$4,0)),0)
B12: Qualified Dividends | C12: {=IFERROR(INDIRECT("Y"&$C$4&"!J30"),0)} | D12: {=IFERROR(INDIRECT("Y"&$C$4&"!K30"),0)} | E12: =C12-D12 | H12: 8 Business | I12: =IFERROR(INDEX(Pivot_Summary!$C9:$H9,MATCH(TEXT($C$4,"0"),Pivot_Summary!$C$4:$H$4,0)),0) | J12: =IFERROR(INDEX(Pivot_Summary!$O9:$T9,MATCH($C$4,Pivot_Summary!$O$4:$T$4,0)),0) | K12: =IFERROR(INDEX(Pivot_Summary!$I9:$N9,MATCH($C$4,Pivot_Summary!$I$4:$N$4,0)),0)
B13: Owner W-2 Wages | C13: {=IFERROR(INDIRECT("Y"&$C$4&"!J23"),0)} | D13: {=IFERROR(INDIRECT("Y"&$C$4&"!K23"),0)} | E13: =C13-D13
H14: CHART DATA — Business by Treatment
B15: BUSINESS INCOME BREAKDOWN | D15: Strategy Δ | E15: Effective | H15: Treatment | I15: Baseline | J15: Effective | K15: Strategy Δ
B16: S-Corp K-1 Active | C16: =IFERROR(GETPIVOTDATA("Baseline_Amount",Visual_Pivot_BusinessIncome!$B$5,"Treatment_Profile","K1_SCorp_Active","Year",$C$4),0) | D16: =IFERROR(SUMIFS(tblMaster_Inputs[Baseline_Amount],tblMaster_Inputs[Treatment_Profile],"K1_SCorp_Active",tblMaster_Inputs[Year],$C$4,tblMaster_Inputs[Activity_Type],"Strategy")+SUMIFS(tblMaster_Inputs[Baseline_Amount],tblMaster_Inputs[Treatment_Profile],"K1_SCorp_Passive",tblMaster_Inputs[Year],$C$4,tblMaster_Inputs[Activity_Type],"Strategy"),0) | E16: =C16+D16 | H16: Treatment | I16: Baseline | J16: Effective | K16: Strategy Δ
B17: PTP K-1 Passive | C17: =IFERROR(GETPIVOTDATA("Baseline_Amount",Visual_Pivot_BusinessIncome!$B$5,"Treatment_Profile","K1_PTP_Passive","Year",$C$4),0) | D17: =IFERROR(SUMIFS(tblMaster_Inputs[Baseline_Amount],tblMaster_Inputs[Treatment_Profile],"K1_PTP_Passive",tblMaster_Inputs[Year],$C$4,tblMaster_Inputs[Activity_Type],"Strategy")+SUMIFS(tblMaster_Inputs[Baseline_Amount],tblMaster_Inputs[Treatment_Profile],"K1_PTP_Active",tblMaster_Inputs[Year],$C$4,tblMaster_Inputs[Activity_Type],"Strategy"),0) | E17: =C17+D17 | H17: K1_SCorp_Active | I17: =IFERROR(INDEX(Pivot_Medium!$C12:$H12,MATCH(TEXT($C$4,"0"),Pivot_Medium!$C$4:$H$4,0)),0) | J17: =IFERROR(INDEX(Pivot_Medium!$O12:$T12,MATCH($C$4,Pivot_Medium!$O$4:$T$4,0)),0) | K17: =IFERROR(INDEX(Pivot_Medium!$I12:$N12,MATCH($C$4,Pivot_Medium!$I$4:$N$4,0)),0)
B18: Schedule E Rental | C18: =IFERROR(GETPIVOTDATA("Baseline_Amount",Visual_Pivot_BusinessIncome!$B$5,"Treatment_Profile","SchE_Rental","Year",$C$4),0) | D18: =IFERROR(SUMIFS(tblMaster_Inputs[Baseline_Amount],tblMaster_Inputs[Treatment_Profile],"SchE_Rental",tblMaster_Inputs[Year],$C$4,tblMaster_Inputs[Activity_Type],"Strategy")+SUMIFS(tblMaster_Inputs[Baseline_Amount],tblMaster_Inputs[Treatment_Profile],"SchE_REPro",tblMaster_Inputs[Year],$C$4,tblMaster_Inputs[Activity_Type],"Strategy"),0) | E18: =C18+D18 | H18: K1_PTP_Passive | I18: =IFERROR(INDEX(Pivot_Medium!$C11:$H11,MATCH(TEXT($C$4,"0"),Pivot_Medium!$C$4:$H$4,0)),0) | J18: =IFERROR(INDEX(Pivot_Medium!$O11:$T11,MATCH($C$4,Pivot_Medium!$O$4:$T$4,0)),0) | K18: =IFERROR(INDEX(Pivot_Medium!$I11:$N11,MATCH($C$4,Pivot_Medium!$I$4:$N$4,0)),0)
B19: Total Business Income | C19: =IFERROR(GETPIVOTDATA("Baseline_Amount",Visual_Pivot_BusinessIncome!$B$5,"Year",$C$4),0) | D19: =IFERROR(SUMIFS(tblMaster_Inputs[Baseline_Amount],tblMaster_Inputs[Year],$C$4,tblMaster_Inputs[Activity_Type],"Strategy",tblMaster_Inputs[Bucket],"Business Income"),0) | E19: =C19+D19 | H19: SchE_Rental | I19: =IFERROR(INDEX(Pivot_Medium!$C10:$H10,MATCH(TEXT($C$4,"0"),Pivot_Medium!$C$4:$H$4,0)),0) | J19: =IFERROR(INDEX(Pivot_Medium!$O10:$T10,MATCH($C$4,Pivot_Medium!$O$4:$T$4,0)),0) | K19: =IFERROR(INDEX(Pivot_Medium!$I10:$N10,MATCH($C$4,Pivot_Medium!$I$4:$N$4,0)),0)
B37: STRATEGY IMPACT SUMMARY
B38: Strategy | C38: Jeff Ref | D38: Target Line | E38: Amount | F38: Status
B39: {=IFERROR(INDIRECT("Y"&$C$4&"!B6"),"")} | C39: {=IFERROR(INDIRECT("Y"&$C$4&"!H6"),"")} | D39: {=IFERROR(INDIRECT("Y"&$C$4&"!C6"),"")} | E39: {=IFERROR(INDIRECT("Y"&$C$4&"!D6"),"")} | F39: {=IFERROR(INDIRECT("Y"&$C$4&"!E6"),"")}
B40: {=IFERROR(INDIRECT("Y"&$C$4&"!B7"),"")} | C40: {=IFERROR(INDIRECT("Y"&$C$4&"!H7"),"")} | D40: {=IFERROR(INDIRECT("Y"&$C$4&"!C7"),"")} | E40: {=IFERROR(INDIRECT("Y"&$C$4&"!D7"),"")} | F40: {=IFERROR(INDIRECT("Y"&$C$4&"!E7"),"")}
B41: {=IFERROR(INDIRECT("Y"&$C$4&"!B8"),"")} | C41: {=IFERROR(INDIRECT("Y"&$C$4&"!H8"),"")} | D41: {=IFERROR(INDIRECT("Y"&$C$4&"!C8"),"")} | E41: {=IFERROR(INDIRECT("Y"&$C$4&"!D8"),"")} | F41: {=IFERROR(INDIRECT("Y"&$C$4&"!E8"),"")}
B42: {=IFERROR(INDIRECT("Y"&$C$4&"!B9"),"")} | C42: {=IFERROR(INDIRECT("Y"&$C$4&"!H9"),"")} | D42: {=IFERROR(INDIRECT("Y"&$C$4&"!C9"),"")} | E42: {=IFERROR(INDIRECT("Y"&$C$4&"!D9"),"")} | F42: {=IFERROR(INDIRECT("Y"&$C$4&"!E9"),"")}
B43: {=IFERROR(INDIRECT("Y"&$C$4&"!B10"),"")} | C43: {=IFERROR(INDIRECT("Y"&$C$4&"!H10"),"")} | D43: {=IFERROR(INDIRECT("Y"&$C$4&"!C10"),"")} | E43: {=IFERROR(INDIRECT("Y"&$C$4&"!D10"),"")} | F43: {=IFERROR(INDIRECT("Y"&$C$4&"!E10"),"")}
B45: TAX IMPACT | E45: Committed | F45: Net Impact
B46: Baseline Tax | C46: {=IFERROR(INDIRECT("Y"&$C$4&"!J133"),0)} | E46: {=IFERROR(INDIRECT("Y"&$C$4&"!B28"),0)} | F46: {=IFERROR(INDIRECT("Y"&$C$4&"!D28"),0)}
B47: Tax w/ Strategies | C47: {=IFERROR(INDIRECT("Y"&$C$4&"!K133"),0)}
B48: Tax Savings ($) | C48: =C46-C47
B49: Eff. Rate Reduction | C49: {=IFERROR(INDIRECT("Y"&$C$4&"!J134"),0)-IFERROR(INDIRECT("Y"&$C$4&"!K134"),0)}

Sheet PY_Recon
B2: PY RECON — Baseline vs Filed Return
B3: Compares computed Baseline (tblMaster_Inputs) vs AsFiled (tblAsFiled) for Active_Year + Active_Client. Verify the engine before trusting roll-forward.
B5: Recon Year: | C5: 2025 | D5: Client: | E5: SAMPLE
B7: 1040 Line | C7: Description | D7: Computed (Baseline) | E7: Filed (AsFiled) | F7: Variance | G7: Status
B8: 1z | C8: Wages, salaries, tips | D8: =SUMIFS(tblMaster_Inputs[Baseline_Amount],tblMaster_Inputs[Year],$C$5,tblMaster_Inputs[ClientID],$E$5,tblMaster_Inputs[Primary_Line],"1z") | E8: =SUMIFS(tblAsFiled[Filed_Amount],tblAsFiled[Year],$C$5,tblAsFiled[ClientID],$E$5,tblAsFiled[Primary_Line],"1z") | F8: =D8-E8 | G8: =IF(ABS(F8)<1,"✓ OK","⚠ CHECK")
B9: 2b | C9: Taxable interest | D9: =SUMIFS(tblMaster_Inputs[Baseline_Amount],tblMaster_Inputs[Year],$C$5,tblMaster_Inputs[ClientID],$E$5,tblMaster_Inputs[Primary_Line],"2b") | E9: =SUMIFS(tblAsFiled[Filed_Amount],tblAsFiled[Year],$C$5,tblAsFiled[ClientID],$E$5,tblAsFiled[Primary_Line],"2b") | F9: =D9-E9 | G9: =IF(ABS(F9)<1,"✓ OK","⚠ CHECK")
B10: 3b | C10: Ordinary dividends | D10: =SUMIFS(tblMaster_Inputs[Baseline_Amount],tblMaster_Inputs[Year],$C$5,tblMaster_Inputs[ClientID],$E$5,tblMaster_Inputs[Primary_Line],"3b") | E10: =SUMIFS(tblAsFiled[Filed_Amount],tblAsFiled[Year],$C$5,tblAsFiled[ClientID],$E$5,tblAsFiled[Primary_Line],"3b") | F10: =D10-E10 | G10: =IF(ABS(F10)<1,"✓ OK","⚠ CHECK")
B11: 7 | C11: Capital gain or (loss) | D11: =SUMIFS(tblMaster_Inputs[Baseline_Amount],tblMaster_Inputs[Year],$C$5,tblMaster_Inputs[ClientID],$E$5,tblMaster_Inputs[Primary_Line],"7") | E11: =SUMIFS(tblAsFiled[Filed_Amount],tblAsFiled[Year],$C$5,tblAsFiled[ClientID],$E$5,tblAsFiled[Primary_Line],"7") | F11: =D11-E11 | G11: =IF(ABS(F11)<1,"✓ OK","⚠ CHECK")
B12: 8 | C12: Other income (Sch 1 — business) | D12: =SUMIFS(tblMaster_Inputs[Baseline_Amount],tblMaster_Inputs[Year],$C$5,tblMaster_Inputs[ClientID],$E$5,tblMaster_Inputs[Primary_Line],"8") | E12: =SUMIFS(tblAsFiled[Filed_Amount],tblAsFiled[Year],$C$5,tblAsFiled[ClientID],$E$5,tblAsFiled[Primary_Line],"8") | F12: =D12-E12 | G12: =IF(ABS(F12)<1,"✓ OK","⚠ CHECK")
B13: 9 | C13: TOTAL INCOME | D13: =SUM(D8:D12) | E13: =SUM(E8:E12) | F13: =D13-E13 | G13: =IF(ABS(F13)<1,"✓ OK","⚠ CHECK")
B14: 10 | C14: Adjustments to income | D14: =SUMIFS(tblMaster_Inputs[Baseline_Amount],tblMaster_Inputs[Year],$C$5,tblMaster_Inputs[ClientID],$E$5,tblMaster_Inputs[Primary_Line],"10") | E14: =SUMIFS(tblAsFiled[Filed_Amount],tblAsFiled[Year],$C$5,tblAsFiled[ClientID],$E$5,tblAsFiled[Primary_Line],"10") | F14: =D14-E14 | G14: =IF(ABS(F14)<1,"✓ OK","⚠ CHECK")
B15: 11 | C15: AGI | D15: =D13+D14 | E15: =E13+E14 | F15: =D15-E15 | G15: =IF(ABS(F15)<1,"✓ OK","⚠ CHECK")
B16: 12 | C16: Standard / Itemized deduction | D16: =SUMIFS(tblMaster_Inputs[Baseline_Amount],tblMaster_Inputs[Year],$C$5,tblMaster_Inputs[ClientID],$E$5,tblMaster_Inputs[Primary_Line],"12") | E16: =SUMIFS(tblAsFiled[Filed_Amount],tblAsFiled[Year],$C$5,tblAsFiled[ClientID],$E$5,tblAsFiled[Primary_Line],"12") | F16: =D16-E16 | G16: =IF(ABS(F16)<1,"✓ OK","⚠ CHECK")
B17: 13 | C17: QBI deduction | D17: =SUMIFS(tblMaster_Inputs[Baseline_Amount],tblMaster_Inputs[Year],$C$5,tblMaster_Inputs[ClientID],$E$5,tblMaster_Inputs[Primary_Line],"13") | E17: =SUMIFS(tblAsFiled[Filed_Amount],tblAsFiled[Year],$C$5,tblAsFiled[ClientID],$E$5,tblAsFiled[Primary_Line],"13") | F17: =D17-E17 | G17: =IF(ABS(F17)<1,"✓ OK","⚠ CHECK")
B18: 15 | C18: TAXABLE INCOME | D18: =D15+D16+D17 | E18: =E15+E16+E17 | F18: =D18-E18 | G18: =IF(ABS(F18)<1,"✓ OK","⚠ CHECK")
B20: RECON SUMMARY
B21: Lines matched: | C21: =COUNTIF(G8:G18,"✓ OK") | D21: of | E21: =COUNTA(G8:G18)
B22: Overall status: | C22: =IF(C21=E21,"✓ ALL LINES MATCH","⚠ VARIANCES FOUND — REVIEW BEFORE PLANNING")

Sheet Pivot_GPD
B2: PIVOT GETPIVOTDATA — Multi-Year Named Range Bridge
B3: Full year grid + Active_Year column (→ VP_ named ranges). GETPIVOTDATA pulls directly from visual pivots.
B5: INCOME BY 1040 LINE
B6: Named Range | C6: Description | D6: 2023 | E6: 2024 | F6: 2025 | G6: 2026 | H6: 2027 | I6: 2028 | J6: Active Year
B7: VP_Line_1z_Wages | C7: Wages (1z) | D7: =IFERROR(GETPIVOTDATA("Baseline_Amount",Visual_Pivot_Income!$B$5,"Primary_Line","1z","Year",2023),0) | E7: =IFERROR(GETPIVOTDATA("Baseline_Amount",Visual_Pivot_Income!$B$5,"Primary_Line","1z","Year",2024),0) | F7: =IFERROR(GETPIVOTDATA("Baseline_Amount",Visual_Pivot_Income!$B$5,"Primary_Line","1z","Year",2025),0) | G7: =IFERROR(GETPIVOTDATA("Baseline_Amount",Visual_Pivot_Income!$B$5,"Primary_Line","1z","Year",2026),0) | H7: =IFERROR(GETPIVOTDATA("Baseline_Amount",Visual_Pivot_Income!$B$5,"Primary_Line","1z","Year",2027),0) | I7: =IFERROR(GETPIVOTDATA("Baseline_Amount",Visual_Pivot_Income!$B$5,"Primary_Line","1z","Year",2028),0) | J7: =IFERROR(GETPIVOTDATA("Baseline_Amount",Visual_Pivot_Income!$B$5,"Primary_Line","1z","Year",Active_Year),0)
B8: VP_Line_2b_TaxInt | C8: Tax Interest (2b) | D8: =IFERROR(GETPIVOTDATA("Baseline_Amount",Visual_Pivot_Income!$B$5,"Primary_Line","2b","Year",2023),0) | E8: =IFERROR(GETPIVOTDATA("Baseline_Amount",Visual_Pivot_Income!$B$5,"Primary_Line","2b","Year",2024),0) | F8: =IFERROR(GETPIVOTDATA("Baseline_Amount",Visual_Pivot_Income!$B$5,"Primary_Line","2b","Year",2025),0) | G8: =IFERROR(GETPIVOTDATA("Baseline_Amount",Visual_Pivot_Income!$B$5,"Primary_Line","2b","Year",2026),0) | H8: =IFERROR(GETPIVOTDATA("Baseline_Amount",Visual_Pivot_Income!$B$5,"Primary_Line","2b","Year",2027),0) | I8: =IFERROR(GETPIVOTDATA("Baseline_Amount",Visual_Pivot_Income!$B$5,"Primary_Line","2b","Year",2028),0) | J8: =IFERROR(GETPIVOTDATA("Baseline_Amount",Visual_Pivot_Income!$B$5,"Primary_Line","2b","Year",Active_Year),0)
B9: VP_Line_3b_OrdDiv | C9: Ord Dividends (3b) | D9: =IFERROR(GETPIVOTDATA("Baseline_Amount",Visual_Pivot_Income!$B$5,"Primary_Line","3b","Year",2023),0) | E9: =IFERROR(GETPIVOTDATA("Baseline_Amount",Visual_Pivot_Income!$B$5,"Primary_Line","3b","Year",2024),0) | F9: =IFERROR(GETPIVOTDATA("Baseline_Amount",Visual_Pivot_Income!$B$5,"Primary_Line","3b","Year",2025),0) | G9: =IFERROR(GETPIVOTDATA("Baseline_Amount",Visual_Pivot_Income!$B$5,"Primary_Line","3b","Year",2026),0) | H9: =IFERROR(GETPIVOTDATA("Baseline_Amount",Visual_Pivot_Income!$B$5,"Primary_Line","3b","Year",2027),0) | I9: =IFERROR(GETPIVOTDATA("Baseline_Amount",Visual_Pivot_Income!$B$5,"Primary_Line","3b","Year",2028),0) | J9: =IFERROR(GETPIVOTDATA("Baseline_Amount",Visual_Pivot_Income!$B$5,"Primary_Line","3b","Year",Active_Year),0)
B10: VP_Line_7_CapGain | C10: Cap Gains (7) | D10: =IFERROR(GETPIVOTDATA("Baseline_Amount",Visual_Pivot_Income!$B$5,"Primary_Line","7","Year",2023),0) | E10: =IFERROR(GETPIVOTDATA("Baseline_Amount",Visual_Pivot_Income!$B$5,"Primary_Line","7","Year",2024),0) | F10: =IFERROR(GETPIVOTDATA("Baseline_Amount",Visual_Pivot_Income!$B$5,"Primary_Line","7","Year",2025),0) | G10: =IFERROR(GETPIVOTDATA("Baseline_Amount",Visual_Pivot_Income!$B$5,"Primary_Line","7","Year",2026),0) | H10: =IFERROR(GETPIVOTDATA("Baseline_Amount",Visual_Pivot_Income!$B$5,"Primary_Line","7","Year",2027),0) | I10: =IFERROR(GETPIVOTDATA("Baseline_Amount",Visual_Pivot_Income!$B$5,"Primary_Line","7","Year",2028),0) | J10: =IFERROR(GETPIVOTDATA("Baseline_Amount",Visual_Pivot_Income!$B$5,"Primary_Line","7","Year",Active_Year),0)
B11: VP_Line_8_OtherInc | C11: Business/Other (8) | D11: =IFERROR(GETPIVOTDATA("Baseline_Amount",Visual_Pivot_Income!$B$5,"Primary_Line","8","Year",2023),0) | E11: =IFERROR(GETPIVOTDATA("Baseline_Amount",Visual_Pivot_Income!$B$5,"Primary_Line","8","Year",2024),0) | F11: =IFERROR(GETPIVOTDATA("Baseline_Amount",Visual_Pivot_Income!$B$5,"Primary_Line","8","Year",2025),0) | G11: =IFERROR(GETPIVOTDATA("Baseline_Amount",Visual_Pivot_Income!$B$5,"Primary_Line","8","Year",2026),0) | H11: =IFERROR(GETPIVOTDATA("Baseline_Amount",Visual_Pivot_Income!$B$5,"Primary_Line","8","Year",2027),0) | I11: =IFERROR(GETPIVOTDATA("Baseline_Amount",Visual_Pivot_Income!$B$5,"Primary_Line","8","Year",2028),0) | J11: =IFERROR(GETPIVOTDATA("Baseline_Amount",Visual_Pivot_Income!$B$5,"Primary_Line","8","Year",Active_Year),0)
B12: VP_Line_12_Deduction | C12: Std/Item Ded (12) | D12: =IFERROR(GETPIVOTDATA("Baseline_Amount",Visual_Pivot_Income!$B$5,"Primary_Line","12","Year",2023),0) | E12: =IFERROR(GETPIVOTDATA("Baseline_Amount",Visual_Pivot_Income!$B$5,"Primary_Line","12","Year",2024),0) | F12: =IFERROR(GETPIVOTDATA("Baseline_Amount",Visual_Pivot_Income!$B$5,"Primary_Line","12","Year",2025),0) | G12: =IFERROR(GETPIVOTDATA("Baseline_Amount",Visual_Pivot_Income!$B$5,"Primary_Line","12","Year",2026),0) | H12: =IFERROR(GETPIVOTDATA("Baseline_Amount",Visual_Pivot_Income!$B$5,"Primary_Line","12","Year",2027),0) | I12: =IFERROR(GETPIVOTDATA("Baseline_Amount",Visual_Pivot_Income!$B$5,"Primary_Line","12","Year",2028),0) | J12: =IFERROR(GETPIVOTDATA("Baseline_Amount",Visual_Pivot_Income!$B$5,"Primary_Line","12","Year",Active_Year),0)
B13: VP_TotalIncome | C13: Grand Total | D13: =IFERROR(GETPIVOTDATA("Baseline_Amount",Visual_Pivot_Income!$B$5,"Year",2023),0) | E13: =IFERROR(GETPIVOTDATA("Baseline_Amount",Visual_Pivot_Income!$B$5,"Year",2024),0) | F13: =IFERROR(GETPIVOTDATA("Baseline_Amount",Visual_Pivot_Income!$B$5,"Year",2025),0) | G13: =IFERROR(GETPIVOTDATA("Baseline_Amount",Visual_Pivot_Income!$B$5,"Year",2026),0) | H13: =IFERROR(GETPIVOTDATA("Baseline_Amount",Visual_Pivot_Income!$B$5,"Year",2027),0) | I13: =IFERROR(GETPIVOTDATA("Baseline_Amount",Visual_Pivot_Income!$B$5,"Year",2028),0) | J13: =IFERROR(GETPIVOTDATA("Baseline_Amount",Visual_Pivot_Income!$B$5,"Year",Active_Year),0)
B15: HELPER CARVE-OUTS
B16: Named Range | C16: Description | D16: 2023 | E16: 2024 | F16: 2025 | G16: 2026 | H16: 2027 | I16: 2028 | J16: Active Year
B17: VP_OWNER_PAY | C17: Owner Wages | D17: =IFERROR(GETPIVOTDATA("Helper_Amount",Visual_Pivot_HelperCarveOuts!$B$5,"Helper_Treatment","OWNER_PAY","Year",2023),0) | E17: =IFERROR(GETPIVOTDATA("Helper_Amount",Visual_Pivot_HelperCarveOuts!$B$5,"Helper_Treatment","OWNER_PAY","Year",2024),0) | F17: =IFERROR(GETPIVOTDATA("Helper_Amount",Visual_Pivot_HelperCarveOuts!$B$5,"Helper_Treatment","OWNER_PAY","Year",2025),0) | G17: =IFERROR(GETPIVOTDATA("Helper_Amount",Visual_Pivot_HelperCarveOuts!$B$5,"Helper_Treatment","OWNER_PAY","Year",2026),0) | H17: =IFERROR(GETPIVOTDATA("Helper_Amount",Visual_Pivot_HelperCarveOuts!$B$5,"Helper_Treatment","OWNER_PAY","Year",2027),0) | I17: =IFERROR(GETPIVOTDATA("Helper_Amount",Visual_Pivot_HelperCarveOuts!$B$5,"Helper_Treatment","OWNER_PAY","Year",2028),0) | J17: =IFERROR(GETPIVOTDATA("Helper_Amount",Visual_Pivot_HelperCarveOuts!$B$5,"Helper_Treatment","OWNER_PAY","Year",Active_Year),0)
B18: VP_QUAL_DIV | C18: Qualified Dividends | D18: =IFERROR(GETPIVOTDATA("Helper_Amount",Visual_Pivot_HelperCarveOuts!$B$5,"Helper_Treatment","QUAL_DIV","Year",2023),0) | E18: =IFERROR(GETPIVOTDATA("Helper_Amount",Visual_Pivot_HelperCarveOuts!$B$5,"Helper_Treatment","QUAL_DIV","Year",2024),0) | F18: =IFERROR(GETPIVOTDATA("Helper_Amount",Visual_Pivot_HelperCarveOuts!$B$5,"Helper_Treatment","QUAL_DIV","Year",2025),0) | G18: =IFERROR(GETPIVOTDATA("Helper_Amount",Visual_Pivot_HelperCarveOuts!$B$5,"Helper_Treatment","QUAL_DIV","Year",2026),0) | H18: =IFERROR(GETPIVOTDATA("Helper_Amount",Visual_Pivot_HelperCarveOuts!$B$5,"Helper_Treatment","QUAL_DIV","Year",2027),0) | I18: =IFERROR(GETPIVOTDATA("Helper_Amount",Visual_Pivot_HelperCarveOuts!$B$5,"Helper_Treatment","QUAL_DIV","Year",2028),0) | J18: =IFERROR(GETPIVOTDATA("Helper_Amount",Visual_Pivot_HelperCarveOuts!$B$5,"Helper_Treatment","QUAL_DIV","Year",Active_Year),0)
B20: BUSINESS INCOME BY TREATMENT
B21: Named Range | C21: Description | D21: 2023 | E21: 2024 | F21: 2025 | G21: 2026 | H21: 2027 | I21: 2028 | J21: Active Year
B22: VP_BI_K1_SCorp_Active | C22: S-Corp K-1 Active | D22: =IFERROR(GETPIVOTDATA("Baseline_Amount",Visual_Pivot_BusinessIncome!$B$5,"Treatment_Profile","K1_SCorp_Active","Year",2023),0) | E22: =IFERROR(GETPIVOTDATA("Baseline_Amount",Visual_Pivot_BusinessIncome!$B$5,"Treatment_Profile","K1_SCorp_Active","Year",2024),0) | F22: =IFERROR(GETPIVOTDATA("Baseline_Amount",Visual_Pivot_BusinessIncome!$B$5,"Treatment_Profile","K1_SCorp_Active","Year",2025),0) | G22: =IFERROR(GETPIVOTDATA("Baseline_Amount",Visual_Pivot_BusinessIncome!$B$5,"Treatment_Profile","K1_SCorp_Active","Year",2026),0) | H22: =IFERROR(GETPIVOTDATA("Baseline_Amount",Visual_Pivot_BusinessIncome!$B$5,"Treatment_Profile","K1_SCorp_Active","Year",2027),0) | I22: =IFERROR(GETPIVOTDATA("Baseline_Amount",Visual_Pivot_BusinessIncome!$B$5,"Treatment_Profile","K1_SCorp_Active","Year",2028),0) | J22: =IFERROR(GETPIVOTDATA("Baseline_Amount",Visual_Pivot_BusinessIncome!$B$5,"Treatment_Profile","K1_SCorp_Active","Year",Active_Year),0)
B23: VP_BI_K1_PTP_Passive | C23: PTP K-1 Passive | D23: =IFERROR(GETPIVOTDATA("Baseline_Amount",Visual_Pivot_BusinessIncome!$B$5,"Treatment_Profile","K1_PTP_Passive","Year",2023),0) | E23: =IFERROR(GETPIVOTDATA("Baseline_Amount",Visual_Pivot_BusinessIncome!$B$5,"Treatment_Profile","K1_PTP_Passive","Year",2024),0) | F23: =IFERROR(GETPIVOTDATA("Baseline_Amount",Visual_Pivot_BusinessIncome!$B$5,"Treatment_Profile","K1_PTP_Passive","Year",2025),0) | G23: =IFERROR(GETPIVOTDATA("Baseline_Amount",Visual_Pivot_BusinessIncome!$B$5,"Treatment_Profile","K1_PTP_Passive","Year",2026),0) | H23: =IFERROR(GETPIVOTDATA("Baseline_Amount",Visual_Pivot_BusinessIncome!$B$5,"Treatment_Profile","K1_PTP_Passive","Year",2027),0) | I23: =IFERROR(GETPIVOTDATA("Baseline_Amount",Visual_Pivot_BusinessIncome!$B$5,"Treatment_Profile","K1_PTP_Passive","Year",2028),0) | J23: =IFERROR(GETPIVOTDATA("Baseline_Amount",Visual_Pivot_BusinessIncome!$B$5,"Treatment_Profile","K1_PTP_Passive","Year",Active_Year),0)
B24: VP_BI_SchE_Rental | C24: Sch E Rental | D24: =IFERROR(GETPIVOTDATA("Baseline_Amount",Visual_Pivot_BusinessIncome!$B$5,"Treatment_Profile","SchE_Rental","Year",2023),0) | E24: =IFERROR(GETPIVOTDATA("Baseline_Amount",Visual_Pivot_BusinessIncome!$B$5,"Treatment_Profile","SchE_Rental","Year",2024),0) | F24: =IFERROR(GETPIVOTDATA("Baseline_Amount",Visual_Pivot_BusinessIncome!$B$5,"Treatment_Profile","SchE_Rental","Year",2025),0) | G24: =IFERROR(GETPIVOTDATA("Baseline_Amount",Visual_Pivot_BusinessIncome!$B$5,"Treatment_Profile","SchE_Rental","Year",2026),0) | H24: =IFERROR(GETPIVOTDATA("Baseline_Amount",Visual_Pivot_BusinessIncome!$B$5,"Treatment_Profile","SchE_Rental","Year",2027),0) | I24: =IFERROR(GETPIVOTDATA("Baseline_Amount",Visual_Pivot_BusinessIncome!$B$5,"Treatment_Profile","SchE_Rental","Year",2028),0) | J24: =IFERROR(GETPIVOTDATA("Baseline_Amount",Visual_Pivot_BusinessIncome!$B$5,"Treatment_Profile","SchE_Rental","Year",Active_Year),0)
B25: VP_BI_Total | C25: Business Total | D25: =IFERROR(GETPIVOTDATA("Baseline_Amount",Visual_Pivot_BusinessIncome!$B$5,"Year",2023),0) | E25: =IFERROR(GETPIVOTDATA("Baseline_Amount",Visual_Pivot_BusinessIncome!$B$5,"Year",2024),0) | F25: =IFERROR(GETPIVOTDATA("Baseline_Amount",Visual_Pivot_BusinessIncome!$B$5,"Year",2025),0) | G25: =IFERROR(GETPIVOTDATA("Baseline_Amount",Visual_Pivot_BusinessIncome!$B$5,"Year",2026),0) | H25: =IFERROR(GETPIVOTDATA("Baseline_Amount",Visual_Pivot_BusinessIncome!$B$5,"Year",2027),0) | I25: =IFERROR(GETPIVOTDATA("Baseline_Amount",Visual_Pivot_BusinessIncome!$B$5,"Year",2028),0) | J25: =IFERROR(GETPIVOTDATA("Baseline_Amount",Visual_Pivot_BusinessIncome!$B$5,"Year",Active_Year),0)

Sheet Y2023
A1: Y2023 — standalone tax planning sandbox
A2: Strategies: enter Amount + Status below. Committed strategies flow to rollup M column. Push to Master_Inputs when final.
A4: ▸ STRATEGIES
A5: StrategyID | B5: Strategy Name | C5: TargetLine | D5: Amount | E5: Status | F5: Notes | G5: CounterLine | H5: Jeff_Ref_ID | I5: Line | J5: Description | K5: Baseline (Master) | L5: PY? | M5: S1 Override | N5: Strategies | O5: Effective | P5: Eff w/ Strategies | Q5: Drill
A6: STR-001 | B6: S-Corp Wage Optimization | C6: 1z | G6: 8 | H6: STD-008 | I6: 1z | J6: Wages | K6: =SUMIFS(tblMaster_Inputs[Baseline_Amount], tblMaster_Inputs[Year], 2023, tblMaster_Inputs[Primary_Line], $I6, tblMaster_Inputs[Activity_Type], "Baseline") | N6: =SUMIFS(tblY2023_Strategies[Amount],tblY2023_Strategies[TargetLine],$I6)-SUMIFS(tblY2023_Strategies[Amount],tblY2023_Strategies[CounterLine],$I6) | O6: =IF(UPPER(L6)="Y",SUMIFS(tblMaster_Inputs[Baseline_Amount],tblMaster_Inputs[Year],2022,tblMaster_Inputs[Primary_Line],"1z"),IF(ISBLANK(M6),K6,M6)) | P6: =O6+N6 | Q6: =HYPERLINK("#Y2023!I49", "↗ drill")
A7: STR-002 | B7: HSA Family Max | C7: 10 | H7: STD-001 | I7: 2a | J7: Tax-exempt interest (informational — Helper) | K7: =SUMIFS(tblMaster_Inputs[Helper_Amount], tblMaster_Inputs[Year], 2023, tblMaster_Inputs[Helper_Treatment], "TAX_EXEMPT") | N7: =SUMIFS(tblY2023_Strategies[Amount],tblY2023_Strategies[TargetLine],"2a",tblY2023_Strategies[Status],"Committed") | O7: =IF(UPPER(L7)="Y",SUMIFS(tblMaster_Inputs[Helper_Amount],tblMaster_Inputs[Year],2022,tblMaster_Inputs[Helper_Treatment],"TAX_EXEMPT"),IF(ISBLANK(M7),K7,M7)) | P7: =O7 | Q7: =HYPERLINK("#Y2023!I49", "↗ drill")
A8: STR-003 | B8: Charitable Bunching (DAF) | C8: 12 | H8: ADV-002 | I8: 2b | J8: Taxable interest | K8: =SUMIFS(tblMaster_Inputs[Baseline_Amount], tblMaster_Inputs[Year], 2023, tblMaster_Inputs[Primary_Line], $I8, tblMaster_Inputs[Activity_Type], "Baseline") | N8: =SUMIFS(tblY2023_Strategies[Amount],tblY2023_Strategies[TargetLine],$I8)-SUMIFS(tblY2023_Strategies[Amount],tblY2023_Strategies[CounterLine],$I8) | O8: =IF(UPPER(L8)="Y",SUMIFS(tblMaster_Inputs[Baseline_Amount],tblMaster_Inputs[Year],2022,tblMaster_Inputs[Primary_Line],"2b"),IF(ISBLANK(M8),K8,M8)) | P8: =O8+N8 | Q8: =HYPERLINK("#Y2023!I49", "↗ drill")
A9: STR-004 | B9: SEP-IRA / Solo 401(k) | C9: 8 | H9: STD-001 | I9: 3a | J9: Qualified dividends (informational — Helper) | K9: =SUMIFS(tblMaster_Inputs[Helper_Amount], tblMaster_Inputs[Year], 2023, tblMaster_Inputs[Helper_Treatment], "QUAL_DIV") | N9: =SUMIFS(tblY2023_Strategies[Amount],tblY2023_Strategies[TargetLine],"3a",tblY2023_Strategies[Status],"Committed") | O9: =IF(UPPER(L9)="Y",SUMIFS(tblMaster_Inputs[Helper_Amount],tblMaster_Inputs[Year],2022,tblMaster_Inputs[Helper_Treatment],"QUAL_DIV"),IF(ISBLANK(M9),K9,M9)) | P9: =O9 | Q9: =HYPERLINK("#Y2023!I49", "↗ drill")
A10: STR-005 | B10: Cost Seg Study | C10: 8 | H10: STD-012 | I10: 3b | J10: Ordinary dividends (total — incl qualified) | K10: =SUMIFS(tblMaster_Inputs[Baseline_Amount], tblMaster_Inputs[Year], 2023, tblMaster_Inputs[Primary_Line], $I10, tblMaster_Inputs[Activity_Type], "Baseline") | N10: =SUMIFS(tblY2023_Strategies[Amount],tblY2023_Strategies[TargetLine],$I10)-SUMIFS(tblY2023_Strategies[Amount],tblY2023_Strategies[CounterLine],$I10) | O10: =IF(UPPER(L10)="Y",SUMIFS(tblMaster_Inputs[Baseline_Amount],tblMaster_Inputs[Year],2022,tblMaster_Inputs[Primary_Line],"3b"),IF(ISBLANK(M10),K10,M10)) | P10: =O10+N10 | Q10: =HYPERLINK("#Y2023!I49", "↗ drill")
A11: STR-006 | B11: Roth Conversion | C11: 1z | H11: ADV-004 | I11: 7 | J11: Capital gain or (loss) | K11: =SUMIFS(tblMaster_Inputs[Baseline_Amount], tblMaster_Inputs[Year], 2023, tblMaster_Inputs[Primary_Line], $I11, tblMaster_Inputs[Activity_Type], "Baseline") | N11: =SUMIFS(tblY2023_Strategies[Amount],tblY2023_Strategies[TargetLine],$I11)-SUMIFS(tblY2023_Strategies[Amount],tblY2023_Strategies[CounterLine],$I11) | O11: =IF(UPPER(L11)="Y",SUMIFS(tblMaster_Inputs[Baseline_Amount],tblMaster_Inputs[Year],2022,tblMaster_Inputs[Primary_Line],"7"),IF(ISBLANK(M11),K11,M11)) | P11: =O11+N11 | Q11: =HYPERLINK("#Y2023!I49", "↗ drill")
A12: STR-007 | B12: Augusta Rule (§280A) | C12: 8 | H12: STD-002 | I12: 8 | J12: Other income (incl business income via Sch 1) | K12: =SUMIFS(tblMaster_Inputs[Baseline_Amount], tblMaster_Inputs[Year], 2023, tblMaster_Inputs[Primary_Line], $I12, tblMaster_Inputs[Activity_Type], "Baseline") | N12: =SUMIFS(tblY2023_Strategies[Amount],tblY2023_Strategies[TargetLine],$I12)-SUMIFS(tblY2023_Strategies[Amount],tblY2023_Strategies[CounterLine],$I12) | O12: =IF(UPPER(L12)="Y",SUMIFS(tblMaster_Inputs[Baseline_Amount],tblMaster_Inputs[Year],2022,tblMaster_Inputs[Primary_Line],"8"),IF(ISBLANK(M12),K12,M12)) | P12: =O12+N12 | Q12: =HYPERLINK("#Y2023!I49", "↗ drill")
A13: STR-008 | B13: Accountable Plan | C13: 8 | H13: STD-003 | I13: 9 | J13: TOTAL INCOME | K13: =K6+K8+K10+K11+K12 | N13: =N6+N8+N10+N11+N12 | O13: =O6+O8+O10+O11+O12 | P13: =P6+P8+P10+P11+P12 | Q13: =HYPERLINK("#Y2023!I49", "↗ drill")
A14: STR-009 | B14: Hire Children | C14: 8 | F14: Child wages reported on child's own return — counter-impact is cross-return, not within this 1040 | G14: 1z | H14: STD-005 | I14: 10 | J14: Adjustments to income | K14: =SUMIFS(tblMaster_Inputs[Baseline_Amount], tblMaster_Inputs[Year], 2023, tblMaster_Inputs[Primary_Line], $I14, tblMaster_Inputs[Activity_Type], "Baseline") | N14: =SUMIFS(tblY2023_Strategies[Amount],tblY2023_Strategies[TargetLine],$I14)-SUMIFS(tblY2023_Strategies[Amount],tblY2023_Strategies[CounterLine],$I14) | O14: =IF(UPPER(L14)="Y",SUMIFS(tblMaster_Inputs[Baseline_Amount],tblMaster_Inputs[Year],2022,tblMaster_Inputs[Primary_Line],"10"),IF(ISBLANK(M14),K14,M14)) | P14: =O14+N14 | Q14: =HYPERLINK("#Y2023!I49", "↗ drill")
A15: STR-010 | B15: Entity Restructuring | C15: 8 | G15: 1z | H15: STD-007 | I15: 11 | J15: AGI | K15: =K13+K14 | N15: =N13+N14 | O15: =O13+O14 | P15: =P13+P14 | Q15: =HYPERLINK("#Y2023!I49", "↗ drill")
A16: STR-011 | B16: Installment Sale / 1031 | C16: 7 | H16: STD-009 + ADV-006 | I16: 12 | J16: Std/Itemized deduction | K16: =SUMIFS(tblMaster_Inputs[Baseline_Amount], tblMaster_Inputs[Year], 2023, tblMaster_Inputs[Primary_Line], $I16, tblMaster_Inputs[Activity_Type], "Baseline") | N16: =SUMIFS(tblY2023_Strategies[Amount],tblY2023_Strategies[TargetLine],$I16)-SUMIFS(tblY2023_Strategies[Amount],tblY2023_Strategies[CounterLine],$I16) | O16: =IF(UPPER(L16)="Y",SUMIFS(tblMaster_Inputs[Baseline_Amount],tblMaster_Inputs[Year],2022,tblMaster_Inputs[Primary_Line],"12"),IF(ISBLANK(M16),K16,M16)) | P16: =O16+N16 | Q16: =HYPERLINK("#Y2023!I49", "↗ drill")
A17: STR-012 | B17: Bonus Depreciation §168(k) | C17: 8 | H17: STD-012 | I17: 13 | J17: QBI deduction | K17: =SUMIFS(tblMaster_Inputs[Baseline_Amount], tblMaster_Inputs[Year], 2023, tblMaster_Inputs[Primary_Line], $I17, tblMaster_Inputs[Activity_Type], "Baseline") | N17: =SUMIFS(tblY2023_Strategies[Amount],tblY2023_Strategies[TargetLine],$I17)-SUMIFS(tblY2023_Strategies[Amount],tblY2023_Strategies[CounterLine],$I17) | O17: =IF(UPPER(L17)="Y",SUMIFS(tblMaster_Inputs[Baseline_Amount],tblMaster_Inputs[Year],2022,tblMaster_Inputs[Primary_Line],"13"),IF(ISBLANK(M17),K17,M17)) | P17: =O17+N17 | Q17: =HYPERLINK("#Y2023!I49", "↗ drill")
A18: STR-013 | B18: R&D Credit §41 | C18: 13 | I18: 15 | J18: TAXABLE INCOME | K18: =K15+K16+K17 | N18: =N15+N16+N17 | O18: =O15+O16+O17 | P18: =P15+P16+P17 | Q18: =HYPERLINK("#Y2023!I49", "↗ drill")
A19: STR-014 | B19: SALT PTE Election | C19: 12
A20: STR-015 | B20: Timing / Deferral | C20: 8 | H20: STD-006
A22: ▸ TAX IMPACT SUMMARY | I22: Description | J22: Amount | K22: Effective | L22: Used by
A23: Metric | B23: Baseline | C23: Effective | D23: Eff w/ Strat | E23: Savings | I23: Owner W-2 wages | J23: =SUMIFS(tblMaster_Inputs[Baseline_Amount], tblMaster_Inputs[Year], 2023, tblMaster_Inputs[Treatment_Profile], "W2_SCorpOwner", tblMaster_Inputs[Activity_Type], "Baseline") | K23: =J23+SUMIFS(tblY2023_Strategies[Amount],tblY2023_Strategies[TargetLine],"1z")-SUMIFS(tblY2023_Strategies[Amount],tblY2023_Strategies[CounterLine],"1z") | L23: FICA/Employee
A24: Total Income | B24: =K13 | C24: =O13 | D24: =P13 | E24: =B24-D24 | I24: Third-party W-2 wages | J24: =SUMIFS(tblMaster_Inputs[Baseline_Amount], tblMaster_Inputs[Year], 2023, tblMaster_Inputs[Treatment_Profile], "W2_Employee", tblMaster_Inputs[Activity_Type], "Baseline") | K24: =J24 | L24: SE Tax sharing
A25: Taxable Income | B25: =K18 | C25: =O18 | D25: =P18 | E25: =B25-D25 | I25: Total W-2 wages | J25: =J23+J24 | K25: =K23+K24 | L25: SE Tax sharing
A26: Total Tax | B26: =J133 | C26: =J133 | D26: =K133 | E26: =B26-D26 | I26: Business income subject to SE | J26: =SUMIFS(tblMaster_Inputs[Baseline_Amount], tblMaster_Inputs[Year], 2023, tblMaster_Inputs[Bucket], "Business Income", tblMaster_Inputs[SE_Subject], "Yes", tblMaster_Inputs[Activity_Type], "Baseline") | K26: =J26 | L26: SE Tax base
A27: Effective Rate | B27: =J134 | C27: =J134 | D27: =K134 | E27: =B27-D27 | I27: Active business income NOT SE | J27: =SUMIFS(tblMaster_Inputs[Baseline_Amount], tblMaster_Inputs[Year], 2023, tblMaster_Inputs[Bucket], "Business Income", tblMaster_Inputs[SE_Subject], "No", tblMaster_Inputs[NIIT_Class], "Active", tblMaster_Inputs[Activity_Type], "Baseline") | K27: =J27+SUMIFS(tblY2023_Strategies[Amount],tblY2023_Strategies[TargetLine],"8")-SUMIFS(tblY2023_Strategies[Amount],tblY2023_Strategies[CounterLine],"8") | L27: NIIT/QBI
A28: Committed Strategies | B28: =COUNTIF(tblY2023_Strategies[Status],"Committed") | C28: Net Strategy Impact | D28: =SUMIF(tblY2023_Strategies[Status],"Committed",tblY2023_Strategies[Amount]) | I28: Passive business income/loss | J28: =SUMIFS(tblMaster_Inputs[Baseline_Amount], tblMaster_Inputs[Year], 2023, tblMaster_Inputs[Bucket], "Business Income", tblMaster_Inputs[NIIT_Class], "Passive", tblMaster_Inputs[Activity_Type], "Baseline") | K28: =J28 | L28: Passive Loss/NIIT
I29: Tax-exempt interest | J29: =SUMIFS(tblMaster_Inputs[Helper_Amount], tblMaster_Inputs[Year], 2023, tblMaster_Inputs[Helper_Treatment], "TAX_EXEMPT") | K29: =J29+SUMIFS(tblY2023_Strategies[Amount],tblY2023_Strategies[TargetLine],"2a")-SUMIFS(tblY2023_Strategies[Amount],tblY2023_Strategies[CounterLine],"2a") | L29: MAGI
I30: Qualified dividends carve-out | J30: =SUMIFS(tblMaster_Inputs[Helper_Amount], tblMaster_Inputs[Year], 2023, tblMaster_Inputs[Helper_Treatment], "QUAL_DIV", tblMaster_Inputs[Activity_Type], "Baseline") | K30: =J30 | L30: LTCG stacking
I31: Long-term capital gains | J31: =SUMIFS(tblMaster_Inputs[Baseline_Amount], tblMaster_Inputs[Year], 2023, tblMaster_Inputs[Treatment_Profile], "LTCG_Stock") + SUMIFS(tblMaster_Inputs[Baseline_Amount], tblMaster_Inputs[Year], 2023, tblMaster_Inputs[Treatment_Profile], "LTCG_RE") + SUMIFS(tblMaster_Inputs[Baseline_Amount], tblMaster_Inputs[Year], 2023, tblMaster_Inputs[Treatment_Profile], "LTCG_K1_Passthrough") + SUMIFS(tblMaster_Inputs[Baseline_Amount], tblMaster_Inputs[Year], 2023, tblMaster_Inputs[Treatment_Profile], "Sec1250_Recap", tblMaster_Inputs[Activity_Type], "Baseline") | K31: =J31+SUMIFS(tblY2023_Strategies[Amount],tblY2023_Strategies[TargetLine],"7")-SUMIFS(tblY2023_Strategies[Amount],tblY2023_Strategies[CounterLine],"7") | L31: Cap Gains Tax
I32: Short-term capital gains | J32: =SUMIFS(tblMaster_Inputs[Baseline_Amount], tblMaster_Inputs[Year], 2023, tblMaster_Inputs[Treatment_Profile], "STCG_Stock", tblMaster_Inputs[Activity_Type], "Baseline") | K32: =J32 | L32: Ordinary Tax
I33: §1250 unrecaptured gain | J33: =SUMIFS(tblMaster_Inputs[Helper_Amount], tblMaster_Inputs[Year], 2023, tblMaster_Inputs[Helper_Treatment], "SEC1250", tblMaster_Inputs[Activity_Type], "Baseline") | K33: =J33 | L33: 1250 Tax
I36: Description | J36: Value | K36: Effective | L36: Used by
I37: TI - LTCG - QUAL_DIV - SEC1250 | J37: =K18-J31-J30-J33 | K37: =P18-K31-K30-K33 | L37: Ordinary Tax
I38: AGI + tax-exempt interest | J38: =K15+J29 | K38: =P15+K29 | L38: NIIT
I39: Net investment income | J39: =K8+K10+K11+J28 | K39: =P8+P10+P11+K28 | L39: NIIT
I40: QBI-eligible business income | J40: =J26+J27 | K40: =K26+K27 | L40: QBI
I41: TI before QBI deduction | J41: =K15+K16 | K41: =P15+P16 | L41: QBI cap
I42: Net business loss | J42: =MIN(0,J26+J27+J28) | K42: =MIN(0,K26+K27+K28) | L42: EBL
I43: Net SE income | J43: =J26 | K43: =K26 | L43: SE Tax
K44: =J44
J45: =IF(Control_Panel!C21="Yes",TRUE,FALSE) | K45: =J45
J46: =Carryovers!F52 | K46: =J46
I49: 1z | L49: =HYPERLINK("#Master_Inputs!A1", "✏ open Master_Inputs to edit")
I51: Bucket | J51: Treatment_Profile | L51: Payor | M51: Baseline_Amount | N51: Helper_Amount | O51: Notes
I65: ▸ 7-COMPONENT TAX CALCULATOR | J65: Baseline | K65: Effective | L65: Δ Savings
I66: Dual columns: Baseline (H) vs With Planning (I)
I68: 1. SELF-EMPLOYMENT TAX
I69: SE Tax Label
I70: Net SE Earnings | J70: =J43 | K70: =K43
I71: SE Base (× 0.9235) | J71: =J70*SUMIFS(tblThresholds[Value], tblThresholds[Year], 2023, tblThresholds[FilingStatus], Filing_Status, tblThresholds[Item], "SE_Earnings_Factor") | K71: =K70*SUMIFS(tblThresholds[Value], tblThresholds[Year], 2023, tblThresholds[FilingStatus], Filing_Status, tblThresholds[Item], "SE_Earnings_Factor")
I72: W-2 Wages | J72: =J25 | K72: =K25
I73: Remaining SS Wage Base | J73: =MAX(0,SUMIFS(tblThresholds[Value], tblThresholds[Year], 2023, tblThresholds[FilingStatus], Filing_Status, tblThresholds[Item], "SS_Wage_Base")-J72) | K73: =MAX(0,SUMIFS(tblThresholds[Value], tblThresholds[Year], 2023, tblThresholds[FilingStatus], Filing_Status, tblThresholds[Item], "SS_Wage_Base")-K72)
J74: =MIN(J71,J73) | K74: =MIN(K71,K73)
I75: Social Security Tax (12.4%) | J75: =J74*SUMIFS(tblThresholds[Value], tblThresholds[Year], 2023, tblThresholds[FilingStatus], Filing_Status, tblThresholds[Item], "SS_Rate_Combined") | K75: =K74*SUMIFS(tblThresholds[Value], tblThresholds[Year], 2023, tblThresholds[FilingStatus], Filing_Status, tblThresholds[Item], "SS_Rate_Combined")
I76: Medicare Tax (2.9%) | J76: =J71*SUMIFS(tblThresholds[Value], tblThresholds[Year], 2023, tblThresholds[FilingStatus], Filing_Status, tblThresholds[Item], "Medicare_Rate_Combined") | K76: =K71*SUMIFS(tblThresholds[Value], tblThresholds[Year], 2023, tblThresholds[FilingStatus], Filing_Status, tblThresholds[Item], "Medicare_Rate_Combined")
I77: Addl Medicare (0.9% > threshold) | J77: =MAX(0,(J72+J71-SUMIFS(tblThresholds[Value], tblThresholds[Year], 2023, tblThresholds[FilingStatus], Filing_Status, tblThresholds[Item], "Addl_Medicare_Threshold"))*SUMIFS(tblThresholds[Value], tblThresholds[Year], 2023, tblThresholds[FilingStatus], Filing_Status, tblThresholds[Item], "Addl_Medicare_Rate")) | K77: =MAX(0,(K72+K71-SUMIFS(tblThresholds[Value], tblThresholds[Year], 2023, tblThresholds[FilingStatus], Filing_Status, tblThresholds[Item], "Addl_Medicare_Threshold"))*SUMIFS(tblThresholds[Value], tblThresholds[Year], 2023, tblThresholds[FilingStatus], Filing_Status, tblThresholds[Item], "Addl_Medicare_Rate"))
J78: =-(J75+J76)/2 | K78: =-(K75+K76)/2
I80: TOTAL SE TAX | J80: =J75+J76+J77 | K80: =K75+K76+K77 | L80: =J80-K80
I82: 2. PAYROLL TAX
I83: W-2 Wages | J83: =J25 | K83: =K25
I84: Social Security (6.2%) | J84: =MIN(J83,SUMIFS(tblThresholds[Value], tblThresholds[Year], 2023, tblThresholds[FilingStatus], Filing_Status, tblThresholds[Item], "SS_Wage_Base"))*0.062 | K84: =MIN(K83,SUMIFS(tblThresholds[Value], tblThresholds[Year], 2023, tblThresholds[FilingStatus], Filing_Status, tblThresholds[Item], "SS_Wage_Base"))*0.062
I85: Medicare (1.45%) | J85: =J83*0.0145 | K85: =K83*0.0145
I86: Addl Medicare (0.9% > threshold) | J86: =MAX(0,(J83-SUMIFS(tblThresholds[Value], tblThresholds[Year], 2023, tblThresholds[FilingStatus], Filing_Status, tblThresholds[Item], "Addl_Medicare_Threshold"))*SUMIFS(tblThresholds[Value], tblThresholds[Year], 2023, tblThresholds[FilingStatus], Filing_Status, tblThresholds[Item], "Addl_Medicare_Rate")) | K86: =MAX(0,(K83-SUMIFS(tblThresholds[Value], tblThresholds[Year], 2023, tblThresholds[FilingStatus], Filing_Status, tblThresholds[Item], "Addl_Medicare_Threshold"))*SUMIFS(tblThresholds[Value], tblThresholds[Year], 2023, tblThresholds[FilingStatus], Filing_Status, tblThresholds[Item], "Addl_Medicare_Rate"))
I87: TOTAL PAYROLL TAX | J87: =J84+J85+J86 | K87: =K84+K85+K86 | L87: =J87-K87
I88: Employer Social Security (6.2%) | J88: =J84 | K88: =K84 | L88: =J88-K88
I89: Employer Medicare (1.45%) | J89: =J85 | K89: =K85 | L89: =J89-K89
I91: TOTAL PAYROLL TAX (Employee + Employer) | J91: =J87+J88+J89 | K91: =K87+K88+K89 | L91: =J91-K91
I93: 3. ORDINARY INCOME TAX
I94: Taxable Income | J94: =J37 | K94: =K37
I95: Ordinary Taxable (TI - LTCG - QD) | J95: =MAX(0,J94) | K95: =MAX(0,K94)
I96: Tax (SUMPRODUCT bracket lookup) | J96: {=SUMPRODUCT((tblBrackets_FIT[Year]=2023)*(tblBrackets_FIT[FilingStatus]=Filing_Status)*((J95>tblBrackets_FIT[Upper])*(tblBrackets_FIT[Upper]-tblBrackets_FIT[Lower])+(J95>tblBrackets_FIT[Lower])*(J95<=tblBrackets_FIT[Upper])*(J95-tblBrackets_FIT[Lower]))*tblBrackets_FIT[Rate])} | K96: {=SUMPRODUCT((tblBrackets_FIT[Year]=2023)*(tblBrackets_FIT[FilingStatus]=Filing_Status)*((K95>tblBrackets_FIT[Upper])*(tblBrackets_FIT[Upper]-tblBrackets_FIT[Lower])+(K95>tblBrackets_FIT[Lower])*(K95<=tblBrackets_FIT[Upper])*(K95-tblBrackets_FIT[Lower]))*tblBrackets_FIT[Rate])}
I97: TOTAL ORDINARY TAX | J97: =J96 | K97: =K96 | L97: =J97-K97
I99: 4. CAPITAL GAINS / QUALIFIED DIVIDENDS TAX
I100: LTCG + Qualified Dividends | J100: =J31+J30 | K100: =K31+K30
I101: Sec 1250 Recapture Gain | J101: =J33 | K101: =K33
I102: Stacking Base (Ordinary TI for bracket floor) | J102: =J95 | K102: =K95
I103: Full CG Rate Tax (SUMPRODUCT stack) | J103: {=SUMPRODUCT((Tax_Ref!$B$210:$B$281=2023)*(Tax_Ref!$C$210:$C$281=Filing_Status)*((J102+J100>Tax_Ref!$E$210:$E$281)*(Tax_Ref!$E$210:$E$281-Tax_Ref!$D$210:$D$281)+(J102+J100>Tax_Ref!$D$210:$D$281)*(J102+J100<=Tax_Ref!$E$210:$E$281)*(J102+J100-Tax_Ref!$D$210:$D$281))*Tax_Ref!$F$210:$F$281)} | K103: {=SUMPRODUCT((Tax_Ref!$B$210:$B$281=2023)*(Tax_Ref!$C$210:$C$281=Filing_Status)*((K102+K100>Tax_Ref!$E$210:$E$281)*(Tax_Ref!$E$210:$E$281-Tax_Ref!$D$210:$D$281)+(K102+K100>Tax_Ref!$D$210:$D$281)*(K102+K100<=Tax_Ref!$E$210:$E$281)*(K102+K100-Tax_Ref!$D$210:$D$281))*Tax_Ref!$F$210:$F$281)}
I104: CG Rate Tax on Ordinary only | J104: {=SUMPRODUCT((Tax_Ref!$B$210:$B$281=2023)*(Tax_Ref!$C$210:$C$281=Filing_Status)*((J102>Tax_Ref!$E$210:$E$281)*(Tax_Ref!$E$210:$E$281-Tax_Ref!$D$210:$D$281)+(J102>Tax_Ref!$D$210:$D$281)*(J102<=Tax_Ref!$E$210:$E$281)*(J102-Tax_Ref!$D$210:$D$281))*Tax_Ref!$F$210:$F$281)} | K104: {=SUMPRODUCT((Tax_Ref!$B$210:$B$281=2023)*(Tax_Ref!$C$210:$C$281=Filing_Status)*((K102>Tax_Ref!$E$210:$E$281)*(Tax_Ref!$E$210:$E$281-Tax_Ref!$D$210:$D$281)+(K102>Tax_Ref!$D$210:$D$281)*(K102<=Tax_Ref!$E$210:$E$281)*(K102-Tax_Ref!$D$210:$D$281))*Tax_Ref!$F$210:$F$281)}
I105: Net LTCG/QD Tax | J105: =J103-J104 | K105: =K103-K104
J106: =J33*0.25 | K106: =K33*0.25
I107: TOTAL CAP GAINS TAX | J107: =J105+J106 | K107: =K105+K106 | L107: =J107-K107
I109: 5. NET INVESTMENT INCOME TAX (NIIT)
I110: MAGI | J110: =J38 | K110: =K38
I111: NIIT Threshold | J111: =SUMIFS(tblThresholds[Value], tblThresholds[Year], 2023, tblThresholds[FilingStatus], Filing_Status, tblThresholds[Item], "NIIT_Threshold") | K111: =SUMIFS(tblThresholds[Value], tblThresholds[Year], 2023, tblThresholds[FilingStatus], Filing_Status, tblThresholds[Item], "NIIT_Threshold")
I112: Net Investment Income (NII) | J112: =MAX(0,J39) | K112: =MAX(0,K39)
I113: NIIT Base (lesser of NII or MAGI excess) | J113: =MAX(0,J110-J111) | K113: =MAX(0,K110-K111)
I114: NIIT (3.8%) | J114: =MIN(J112,J113)*SUMIFS(tblThresholds[Value], tblThresholds[Year], 2023, tblThresholds[FilingStatus], Filing_Status, tblThresholds[Item], "NIIT_Rate") | K114: =MIN(K112,K113)*SUMIFS(tblThresholds[Value], tblThresholds[Year], 2023, tblThresholds[FilingStatus], Filing_Status, tblThresholds[Item], "NIIT_Rate") | L114: =J114-K114
I116: 6. QBI DEDUCTION (§199A)
I117: QBI-Eligible Income | J117: =J40 | K117: =K40
I118: 20% of QBI | J118: =MAX(0,J117)*0.2 | K118: =MAX(0,K117)*0.2
I119: 50% of W-2 Wages | J119: =MAX(0,J41)*0.2 | K119: =MAX(0,K41)*0.2
I120: 25% W-2 + 2.5% UBIA | J120: =MAX(J23*0.5, J23*0.25+J44*0.025) | K120: =MAX(K23*0.5, K23*0.25+K44*0.025)
I121: Phase-in applies? | J121: =IF(J41>SUMIFS(tblThresholds[Value], tblThresholds[Year], 2023, tblThresholds[FilingStatus], Filing_Status, tblThresholds[Item], "QBI_Threshold_Start"),"YES","NO") | K121: =IF(K41>SUMIFS(tblThresholds[Value], tblThresholds[Year], 2023, tblThresholds[FilingStatus], Filing_Status, tblThresholds[Item], "QBI_Threshold_Start"),"YES","NO")
I122: QBI DEDUCTION | J122: =IF(AND(J45=TRUE,J41>SUMIFS(tblThresholds[Value], tblThresholds[Year], 2023, tblThresholds[FilingStatus], Filing_Status, tblThresholds[Item], "QBI_Threshold_End")),0,IF(J41<=SUMIFS(tblThresholds[Value], tblThresholds[Year], 2023, tblThresholds[FilingStatus], Filing_Status, tblThresholds[Item], "QBI_Threshold_Start"),MIN(J118,J119),MIN(J118,J119,J120))) | K122: =IF(AND(K45=TRUE,K41>SUMIFS(tblThresholds[Value], tblThresholds[Year], 2023, tblThresholds[FilingStatus], Filing_Status, tblThresholds[Item], "QBI_Threshold_End")),0,IF(K41<=SUMIFS(tblThresholds[Value], tblThresholds[Year], 2023, tblThresholds[FilingStatus], Filing_Status, tblThresholds[Item], "QBI_Threshold_Start"),MIN(K118,K119),MIN(K118,K119,K120))) | L122: =K122-J122
I124: 7. COMBINED TAX SUMMARY
I125: Total Income | J125: =K6+K8+K10+K11+K12 | K125: =P13 | L125: Δ Savings
I126: Ordinary Tax | J126: =J97 | K126: =K97 | L126: =J126-K126
I127: Capital Gains Tax | J127: =J107 | K127: =K107 | L127: =J127-K127
I128: Self-Employment Tax | J128: =J80 | K128: =K80 | L128: =J128-K128
I129: Payroll Tax (Employee + Employer) | J129: =J91 | K129: =K91 | L129: =J129-K129
...

Sheet Y2024
A1: Y2024 — standalone tax planning sandbox
A2: Strategies: enter Amount + Status below. Committed strategies flow to rollup M column. Push to Master_Inputs when final.
A4: ▸ STRATEGIES
A5: StrategyID | B5: Strategy Name | C5: TargetLine | D5: Amount | E5: Status | F5: Notes | G5: CounterLine | H5: Jeff_Ref_ID | I5: Line | J5: Description | K5: Baseline (Master) | L5: PY? | M5: S1 Override | N5: Strategies | O5: Effective | P5: Eff w/ Strategies | Q5: Drill
A6: STR-001 | B6: S-Corp Wage Optimization | C6: 1z | G6: 8 | H6: STD-008 | I6: 1z | J6: Wages | K6: =SUMIFS(tblMaster_Inputs[Baseline_Amount],tblMaster_Inputs[Year],2024,tblMaster_Inputs[Primary_Line],$I6, tblMaster_Inputs[Activity_Type], "Baseline") | N6: =SUMIFS(tblY2024_Strategies[Amount],tblY2024_Strategies[TargetLine],$I6)-SUMIFS(tblY2024_Strategies[Amount],tblY2024_Strategies[CounterLine],$I6) | O6: =IF(UPPER(L6)="Y",SUMIFS(tblMaster_Inputs[Baseline_Amount],tblMaster_Inputs[Year],2023,tblMaster_Inputs[Primary_Line],"1z"),IF(ISBLANK(M6),K6,M6)) | P6: =O6+N6 | Q6: =HYPERLINK("#Y2024!I49", "↗ drill")
A7: STR-002 | B7: HSA Family Max | C7: 10 | H7: STD-001 | I7: 2a | J7: Tax-exempt interest (Helper) | K7: =SUMIFS(tblMaster_Inputs[Helper_Amount],tblMaster_Inputs[Year],2024,tblMaster_Inputs[Helper_Treatment],"TAX_EXEMPT") | N7: =SUMIFS(tblY2024_Strategies[Amount],tblY2024_Strategies[TargetLine],"2a",tblY2024_Strategies[Status],"Committed") | O7: =IF(UPPER(L7)="Y",SUMIFS(tblMaster_Inputs[Helper_Amount],tblMaster_Inputs[Year],2023,tblMaster_Inputs[Helper_Treatment],"TAX_EXEMPT"),IF(ISBLANK(M7),K7,M7)) | P7: =O7 | Q7: =HYPERLINK("#Y2024!I49", "↗ drill")
A8: STR-003 | B8: Charitable Bunching (DAF) | C8: 12 | H8: ADV-002 | I8: 2b | J8: Taxable interest | K8: =SUMIFS(tblMaster_Inputs[Baseline_Amount],tblMaster_Inputs[Year],2024,tblMaster_Inputs[Primary_Line],$I8, tblMaster_Inputs[Activity_Type], "Baseline") | N8: =SUMIFS(tblY2024_Strategies[Amount],tblY2024_Strategies[TargetLine],$I8)-SUMIFS(tblY2024_Strategies[Amount],tblY2024_Strategies[CounterLine],$I8) | O8: =IF(UPPER(L8)="Y",SUMIFS(tblMaster_Inputs[Baseline_Amount],tblMaster_Inputs[Year],2023,tblMaster_Inputs[Primary_Line],"2b"),IF(ISBLANK(M8),K8,M8)) | P8: =O8+N8 | Q8: =HYPERLINK("#Y2024!I49", "↗ drill")
A9: STR-004 | B9: SEP-IRA / Solo 401(k) | C9: 8 | H9: STD-001 | I9: 3a | J9: Qualified dividends (Helper) | K9: =SUMIFS(tblMaster_Inputs[Helper_Amount],tblMaster_Inputs[Year],2024,tblMaster_Inputs[Helper_Treatment],"QUAL_DIV") | N9: =SUMIFS(tblY2024_Strategies[Amount],tblY2024_Strategies[TargetLine],"3a",tblY2024_Strategies[Status],"Committed") | O9: =IF(UPPER(L9)="Y",SUMIFS(tblMaster_Inputs[Helper_Amount],tblMaster_Inputs[Year],2023,tblMaster_Inputs[Helper_Treatment],"QUAL_DIV"),IF(ISBLANK(M9),K9,M9)) | P9: =O9 | Q9: =HYPERLINK("#Y2024!I49", "↗ drill")
A10: STR-005 | B10: Cost Seg Study | C10: 8 | H10: STD-012 | I10: 3b | J10: Ordinary dividends | K10: =SUMIFS(tblMaster_Inputs[Baseline_Amount],tblMaster_Inputs[Year],2024,tblMaster_Inputs[Primary_Line],$I10, tblMaster_Inputs[Activity_Type], "Baseline") | N10: =SUMIFS(tblY2024_Strategies[Amount],tblY2024_Strategies[TargetLine],$I10)-SUMIFS(tblY2024_Strategies[Amount],tblY2024_Strategies[CounterLine],$I10) | O10: =IF(UPPER(L10)="Y",SUMIFS(tblMaster_Inputs[Baseline_Amount],tblMaster_Inputs[Year],2023,tblMaster_Inputs[Primary_Line],"3b"),IF(ISBLANK(M10),K10,M10)) | P10: =O10+N10 | Q10: =HYPERLINK("#Y2024!I49", "↗ drill")
A11: STR-006 | B11: Roth Conversion | C11: 1z | H11: ADV-004 | I11: 7 | J11: Capital gain or (loss) | K11: =SUMIFS(tblMaster_Inputs[Baseline_Amount],tblMaster_Inputs[Year],2024,tblMaster_Inputs[Primary_Line],$I11, tblMaster_Inputs[Activity_Type], "Baseline") | N11: =SUMIFS(tblY2024_Strategies[Amount],tblY2024_Strategies[TargetLine],$I11)-SUMIFS(tblY2024_Strategies[Amount],tblY2024_Strategies[CounterLine],$I11) | O11: =IF(UPPER(L11)="Y",SUMIFS(tblMaster_Inputs[Baseline_Amount],tblMaster_Inputs[Year],2023,tblMaster_Inputs[Primary_Line],"7"),IF(ISBLANK(M11),K11,M11)) | P11: =O11+N11 | Q11: =HYPERLINK("#Y2024!I49", "↗ drill")
A12: STR-007 | B12: Augusta Rule (§280A) | C12: 8 | H12: STD-002 | I12: 8 | J12: Other income (business via Sch 1) | K12: =SUMIFS(tblMaster_Inputs[Baseline_Amount],tblMaster_Inputs[Year],2024,tblMaster_Inputs[Primary_Line],$I12, tblMaster_Inputs[Activity_Type], "Baseline") | N12: =SUMIFS(tblY2024_Strategies[Amount],tblY2024_Strategies[TargetLine],$I12)-SUMIFS(tblY2024_Strategies[Amount],tblY2024_Strategies[CounterLine],$I12) | O12: =IF(UPPER(L12)="Y",SUMIFS(tblMaster_Inputs[Baseline_Amount],tblMaster_Inputs[Year],2023,tblMaster_Inputs[Primary_Line],"8"),IF(ISBLANK(M12),K12,M12)) | P12: =O12+N12 | Q12: =HYPERLINK("#Y2024!I49", "↗ drill")
A13: STR-008 | B13: Accountable Plan | C13: 8 | H13: STD-003 | I13: 9 | J13: TOTAL INCOME | K13: =K6+K8+K10+K11+K12 | N13: =N6+N8+N10+N11+N12 | O13: =O6+O8+O10+O11+O12 | P13: =P6+P8+P10+P11+P12 | Q13: =HYPERLINK("#Y2024!I49", "↗ drill")
A14: STR-009 | B14: Hire Children | C14: 8 | F14: Child wages reported on child's own return — counter-impact is cross-return, not within this 1040 | G14: 1z | H14: STD-005 | I14: 10 | J14: Adjustments to income | K14: =SUMIFS(tblMaster_Inputs[Baseline_Amount],tblMaster_Inputs[Year],2024,tblMaster_Inputs[Primary_Line],$I14, tblMaster_Inputs[Activity_Type], "Baseline") | N14: =SUMIFS(tblY2024_Strategies[Amount],tblY2024_Strategies[TargetLine],$I14)-SUMIFS(tblY2024_Strategies[Amount],tblY2024_Strategies[CounterLine],$I14) | O14: =IF(UPPER(L14)="Y",SUMIFS(tblMaster_Inputs[Baseline_Amount],tblMaster_Inputs[Year],2023,tblMaster_Inputs[Primary_Line],"10"),IF(ISBLANK(M14),K14,M14)) | P14: =O14+N14 | Q14: =HYPERLINK("#Y2024!I49", "↗ drill")
A15: STR-010 | B15: Entity Restructuring | C15: 8 | G15: 1z | H15: STD-007 | I15: 11 | J15: AGI | K15: =K13+K14 | N15: =N13+N14 | O15: =O13+O14 | P15: =P13+P14 | Q15: =HYPERLINK("#Y2024!I49", "↗ drill")
A16: STR-011 | B16: Installment Sale / 1031 | C16: 7 | H16: STD-009 + ADV-006 | I16: 12 | J16: Std/Itemized deduction | K16: =SUMIFS(tblMaster_Inputs[Baseline_Amount],tblMaster_Inputs[Year],2024,tblMaster_Inputs[Primary_Line],$I16, tblMaster_Inputs[Activity_Type], "Baseline") | N16: =SUMIFS(tblY2024_Strategies[Amount],tblY2024_Strategies[TargetLine],$I16)-SUMIFS(tblY2024_Strategies[Amount],tblY2024_Strategies[CounterLine],$I16) | O16: =IF(UPPER(L16)="Y",SUMIFS(tblMaster_Inputs[Baseline_Amount],tblMaster_Inputs[Year],2023,tblMaster_Inputs[Primary_Line],"12"),IF(ISBLANK(M16),K16,M16)) | P16: =O16+N16 | Q16: =HYPERLINK("#Y2024!I49", "↗ drill")
A17: STR-012 | B17: Bonus Depreciation §168(k) | C17: 8 | H17: STD-012 | I17: 13 | J17: QBI deduction | K17: =SUMIFS(tblMaster_Inputs[Baseline_Amount],tblMaster_Inputs[Year],2024,tblMaster_Inputs[Primary_Line],$I17, tblMaster_Inputs[Activity_Type], "Baseline") | N17: =SUMIFS(tblY2024_Strategies[Amount],tblY2024_Strategies[TargetLine],$I17)-SUMIFS(tblY2024_Strategies[Amount],tblY2024_Strategies[CounterLine],$I17) | O17: =IF(UPPER(L17)="Y",SUMIFS(tblMaster_Inputs[Baseline_Amount],tblMaster_Inputs[Year],2023,tblMaster_Inputs[Primary_Line],"13"),IF(ISBLANK(M17),K17,M17)) | P17: =O17+N17 | Q17: =HYPERLINK("#Y2024!I49", "↗ drill")
A18: STR-013 | B18: R&D Credit §41 | C18: 13 | I18: 15 | J18: TAXABLE INCOME | K18: =K15+K16+K17 | N18: =N15+N16+N17 | O18: =O15+O16+O17 | P18: =P15+P16+P17 | Q18: =HYPERLINK("#Y2024!I49", "↗ drill")
A19: STR-014 | B19: SALT PTE Election | C19: 12
A20: STR-015 | B20: Timing / Deferral | C20: 8 | H20: STD-006
A22: ▸ TAX IMPACT SUMMARY | I22: Description | J22: Amount | K22: Effective | L22: Used by
A23: Metric | B23: Baseline | C23: Effective | D23: Eff w/ Strat | E23: Savings | I23: Owner W-2 | J23: =SUMIFS(tblMaster_Inputs[Baseline_Amount],tblMaster_Inputs[Year],2024,tblMaster_Inputs[Treatment_Profile],"W2_SCorpOwner", tblMaster_Inputs[Activity_Type], "Baseline") | K23: =J23+SUMIFS(tblY2024_Strategies[Amount],tblY2024_Strategies[TargetLine],"1z")-SUMIFS(tblY2024_Strategies[Amount],tblY2024_Strategies[CounterLine],"1z")
A24: Total Income | B24: =K13 | C24: =O13 | D24: =P13 | E24: =B24-D24 | I24: Third-party W-2 | J24: =SUMIFS(tblMaster_Inputs[Baseline_Amount],tblMaster_Inputs[Year],2024,tblMaster_Inputs[Treatment_Profile],"W2_Employee", tblMaster_Inputs[Activity_Type], "Baseline") | K24: =J24
A25: Taxable Income | B25: =K18 | C25: =O18 | D25: =P18 | E25: =B25-D25 | I25: Total W-2 | J25: =J23+J24 | K25: =K23+K24
A26: Total Tax | B26: =J133 | C26: =J133 | D26: =K133 | E26: =B26-D26 | I26: SE business income | J26: =SUMIFS(tblMaster_Inputs[Baseline_Amount],tblMaster_Inputs[Year],2024,tblMaster_Inputs[Bucket],"Business Income",tblMaster_Inputs[SE_Subject],"Yes", tblMaster_Inputs[Activity_Type], "Baseline") | K26: =J26
A27: Effective Rate | B27: =J134 | C27: =J134 | D27: =K134 | E27: =B27-D27 | I27: Active non-SE business | J27: =SUMIFS(tblMaster_Inputs[Baseline_Amount],tblMaster_Inputs[Year],2024,tblMaster_Inputs[Bucket],"Business Income",tblMaster_Inputs[SE_Subject],"No",tblMaster_Inputs[NIIT_Class],"Active", tblMaster_Inputs[Activity_Type], "Baseline") | K27: =J27+SUMIFS(tblY2024_Strategies[Amount],tblY2024_Strategies[TargetLine],"8")-SUMIFS(tblY2024_Strategies[Amount],tblY2024_Strategies[CounterLine],"8")
A28: Committed Strategies | B28: =COUNTIF(tblY2024_Strategies[Status],"Committed") | C28: Net Strategy Impact | D28: =SUMIF(tblY2024_Strategies[Status],"Committed",tblY2024_Strategies[Amount]) | I28: Passive business | J28: =SUMIFS(tblMaster_Inputs[Baseline_Amount],tblMaster_Inputs[Year],2024,tblMaster_Inputs[Bucket],"Business Income",tblMaster_Inputs[NIIT_Class],"Passive", tblMaster_Inputs[Activity_Type], "Baseline") | K28: =J28
I29: Tax-exempt interest | J29: =SUMIFS(tblMaster_Inputs[Helper_Amount],tblMaster_Inputs[Year],2024,tblMaster_Inputs[Helper_Treatment],"TAX_EXEMPT") | K29: =J29+SUMIFS(tblY2024_Strategies[Amount],tblY2024_Strategies[TargetLine],"2a")-SUMIFS(tblY2024_Strategies[Amount],tblY2024_Strategies[CounterLine],"2a")
I30: Qualified dividends | J30: =SUMIFS(tblMaster_Inputs[Helper_Amount],tblMaster_Inputs[Year],2024,tblMaster_Inputs[Helper_Treatment],"QUAL_DIV", tblMaster_Inputs[Activity_Type], "Baseline") | K30: =J30
I31: Long-term cap gains | J31: =SUMIFS(tblMaster_Inputs[Baseline_Amount],tblMaster_Inputs[Year],2024,tblMaster_Inputs[Treatment_Profile],"LTCG_Stock")+SUMIFS(tblMaster_Inputs[Baseline_Amount],tblMaster_Inputs[Year],2024,tblMaster_Inputs[Treatment_Profile],"LTCG_RE")+SUMIFS(tblMaster_Inputs[Baseline_Amount],tblMaster_Inputs[Year],2024,tblMaster_Inputs[Treatment_Profile],"LTCG_K1_Passthrough")+SUMIFS(tblMaster_Inputs[Baseline_Amount],tblMaster_Inputs[Year],2024,tblMaster_Inputs[Treatment_Profile],"Sec1250_Recap", tblMaster_Inputs[Activity_Type], "Baseline") | K31: =J31+SUMIFS(tblY2024_Strategies[Amount],tblY2024_Strategies[TargetLine],"7")-SUMIFS(tblY2024_Strategies[Amount],tblY2024_Strategies[CounterLine],"7")
I32: Short-term cap gains | J32: =SUMIFS(tblMaster_Inputs[Baseline_Amount],tblMaster_Inputs[Year],2024,tblMaster_Inputs[Treatment_Profile],"STCG_Stock", tblMaster_Inputs[Activity_Type], "Baseline") | K32: =J32
I33: §1250 gain | J33: =SUMIFS(tblMaster_Inputs[Helper_Amount],tblMaster_Inputs[Year],2024,tblMaster_Inputs[Helper_Treatment],"SEC1250", tblMaster_Inputs[Activity_Type], "Baseline") | K33: =J33
I36: Description | J36: Value | K36: Effective | L36: Used by
I37: TI-LTCG-QUAL_DIV-SEC1250 | J37: =K18-J31-J30-J33 | K37: =P18-K31-K30-K33
I38: AGI+tax-exempt | J38: =K15+J29 | K38: =P15+K29
I39: Net inv income | J39: =K8+K10+K11+J28 | K39: =P8+P10+P11+K28
I40: QBI-eligible | J40: =J26+J27 | K40: =K26+K27
I41: TI before QBI | J41: =K15+K16 | K41: =P15+P16
I42: Net biz loss | J42: =MIN(0,J26+J27+J28) | K42: =MIN(0,K26+K27+K28)
I43: Net SE income | J43: =J26 | K43: =K26
K44: =J44
J45: =IF(Control_Panel!C21="Yes",TRUE,FALSE) | K45: =J45
J46: =Carryovers!F52 | K46: =J46
I49: 1z | L49: =HYPERLINK("#Master_Inputs!A1","✏ open Master_Inputs")
I65: ▸ 7-COMPONENT TAX CALCULATOR | J65: Baseline | K65: Effective | L65: Δ Savings
I66: Dual columns: Baseline (H) vs With Planning (I)
I68: 1. SELF-EMPLOYMENT TAX
I69: SE Tax Label
I70: Net SE Earnings | J70: =J43 | K70: =K43
I71: SE Base (× 0.9235) | J71: =J70*SUMIFS(tblThresholds[Value], tblThresholds[Year], 2024, tblThresholds[FilingStatus], Filing_Status, tblThresholds[Item], "SE_Earnings_Factor") | K71: =K70*SUMIFS(tblThresholds[Value], tblThresholds[Year], 2024, tblThresholds[FilingStatus], Filing_Status, tblThresholds[Item], "SE_Earnings_Factor")
I72: W-2 Wages | J72: =J25 | K72: =K25
I73: Remaining SS Wage Base | J73: =MAX(0,SUMIFS(tblThresholds[Value], tblThresholds[Year], 2024, tblThresholds[FilingStatus], Filing_Status, tblThresholds[Item], "SS_Wage_Base")-J72) | K73: =MAX(0,SUMIFS(tblThresholds[Value], tblThresholds[Year], 2024, tblThresholds[FilingStatus], Filing_Status, tblThresholds[Item], "SS_Wage_Base")-K72)
J74: =MIN(J71,J73) | K74: =MIN(K71,K73)
I75: Social Security Tax (12.4%) | J75: =J74*SUMIFS(tblThresholds[Value], tblThresholds[Year], 2024, tblThresholds[FilingStatus], Filing_Status, tblThresholds[Item], "SS_Rate_Combined") | K75: =K74*SUMIFS(tblThresholds[Value], tblThresholds[Year], 2024, tblThresholds[FilingStatus], Filing_Status, tblThresholds[Item], "SS_Rate_Combined")
I76: Medicare Tax (2.9%) | J76: =J71*SUMIFS(tblThresholds[Value], tblThresholds[Year], 2024, tblThresholds[FilingStatus], Filing_Status, tblThresholds[Item], "Medicare_Rate_Combined") | K76: =K71*SUMIFS(tblThresholds[Value], tblThresholds[Year], 2024, tblThresholds[FilingStatus], Filing_Status, tblThresholds[Item], "Medicare_Rate_Combined")
I77: Addl Medicare (0.9% > threshold) | J77: =MAX(0,(J72+J71-SUMIFS(tblThresholds[Value], tblThresholds[Year], 2024, tblThresholds[FilingStatus], Filing_Status, tblThresholds[Item], "Addl_Medicare_Threshold"))*SUMIFS(tblThresholds[Value], tblThresholds[Year], 2024, tblThresholds[FilingStatus], Filing_Status, tblThresholds[Item], "Addl_Medicare_Rate")) | K77: =MAX(0,(K72+K71-SUMIFS(tblThresholds[Value], tblThresholds[Year], 2024, tblThresholds[FilingStatus], Filing_Status, tblThresholds[Item], "Addl_Medicare_Threshold"))*SUMIFS(tblThresholds[Value], tblThresholds[Year], 2024, tblThresholds[FilingStatus], Filing_Status, tblThresholds[Item], "Addl_Medicare_Rate"))
J78: =-(J75+J76)/2 | K78: =-(K75+K76)/2
I80: TOTAL SE TAX | J80: =J75+J76+J77 | K80: =K75+K76+K77 | L80: =J80-K80
I82: 2. PAYROLL TAX
I83: W-2 Wages | J83: =J25 | K83: =K25
I84: Social Security (6.2%) | J84: =MIN(J83,SUMIFS(tblThresholds[Value], tblThresholds[Year], 2024, tblThresholds[FilingStatus], Filing_Status, tblThresholds[Item], "SS_Wage_Base"))*0.062 | K84: =MIN(K83,SUMIFS(tblThresholds[Value], tblThresholds[Year], 2024, tblThresholds[FilingStatus], Filing_Status, tblThresholds[Item], "SS_Wage_Base"))*0.062
I85: Medicare (1.45%) | J85: =J83*0.0145 | K85: =K83*0.0145
I86: Addl Medicare (0.9% > threshold) | J86: =MAX(0,(J83-SUMIFS(tblThresholds[Value], tblThresholds[Year], 2024, tblThresholds[FilingStatus], Filing_Status, tblThresholds[Item], "Addl_Medicare_Threshold"))*SUMIFS(tblThresholds[Value], tblThresholds[Year], 2024, tblThresholds[FilingStatus], Filing_Status, tblThresholds[Item], "Addl_Medicare_Rate")) | K86: =MAX(0,(K83-SUMIFS(tblThresholds[Value], tblThresholds[Year], 2024, tblThresholds[FilingStatus], Filing_Status, tblThresholds[Item], "Addl_Medicare_Threshold"))*SUMIFS(tblThresholds[Value], tblThresholds[Year], 2024, tblThresholds[FilingStatus], Filing_Status, tblThresholds[Item], "Addl_Medicare_Rate"))
I87: TOTAL PAYROLL TAX | J87: =J84+J85+J86 | K87: =K84+K85+K86 | L87: =J87-K87
I88: Employer Social Security (6.2%) | J88: =J84 | K88: =K84 | L88: =J88-K88
I89: Employer Medicare (1.45%) | J89: =J85 | K89: =K85 | L89: =J89-K89
I91: TOTAL PAYROLL TAX (Employee + Employer) | J91: =J87+J88+J89 | K91: =K87+K88+K89 | L91: =J91-K91
I93: 3. ORDINARY INCOME TAX
I94: Taxable Income | J94: =J37 | K94: =K37
I95: Ordinary Taxable (TI - LTCG - QD) | J95: =MAX(0,J94) | K95: =MAX(0,K94)
I96: Tax (SUMPRODUCT bracket lookup) | J96: {=SUMPRODUCT((tblBrackets_FIT[Year]=2024)*(tblBrackets_FIT[FilingStatus]=Filing_Status)*((J95>tblBrackets_FIT[Upper])*(tblBrackets_FIT[Upper]-tblBrackets_FIT[Lower])+(J95>tblBrackets_FIT[Lower])*(J95<=tblBrackets_FIT[Upper])*(J95-tblBrackets_FIT[Lower]))*tblBrackets_FIT[Rate])} | K96: {=SUMPRODUCT((tblBrackets_FIT[Year]=2024)*(tblBrackets_FIT[FilingStatus]=Filing_Status)*((K95>tblBrackets_FIT[Upper])*(tblBrackets_FIT[Upper]-tblBrackets_FIT[Lower])+(K95>tblBrackets_FIT[Lower])*(K95<=tblBrackets_FIT[Upper])*(K95-tblBrackets_FIT[Lower]))*tblBrackets_FIT[Rate])}
I97: TOTAL ORDINARY TAX | J97: =J96 | K97: =K96 | L97: =J97-K97
I99: 4. CAPITAL GAINS / QUALIFIED DIVIDENDS TAX
I100: LTCG + Qualified Dividends | J100: =J31+J30 | K100: =K31+K30
I101: Sec 1250 Recapture Gain | J101: =J33 | K101: =K33
I102: Stacking Base (Ordinary TI for bracket floor) | J102: =J95 | K102: =K95
I103: Full CG Rate Tax (SUMPRODUCT stack) | J103: {=SUMPRODUCT((Tax_Ref!$B$210:$B$281=2024)*(Tax_Ref!$C$210:$C$281=Filing_Status)*((J102+J100>Tax_Ref!$E$210:$E$281)*(Tax_Ref!$E$210:$E$281-Tax_Ref!$D$210:$D$281)+(J102+J100>Tax_Ref!$D$210:$D$281)*(J102+J100<=Tax_Ref!$E$210:$E$281)*(J102+J100-Tax_Ref!$D$210:$D$281))*Tax_Ref!$F$210:$F$281)} | K103: {=SUMPRODUCT((Tax_Ref!$B$210:$B$281=2024)*(Tax_Ref!$C$210:$C$281=Filing_Status)*((K102+K100>Tax_Ref!$E$210:$E$281)*(Tax_Ref!$E$210:$E$281-Tax_Ref!$D$210:$D$281)+(K102+K100>Tax_Ref!$D$210:$D$281)*(K102+K100<=Tax_Ref!$E$210:$E$281)*(K102+K100-Tax_Ref!$D$210:$D$281))*Tax_Ref!$F$210:$F$281)}
I104: CG Rate Tax on Ordinary only | J104: {=SUMPRODUCT((Tax_Ref!$B$210:$B$281=2024)*(Tax_Ref!$C$210:$C$281=Filing_Status)*((J102>Tax_Ref!$E$210:$E$281)*(Tax_Ref!$E$210:$E$281-Tax_Ref!$D$210:$D$281)+(J102>Tax_Ref!$D$210:$D$281)*(J102<=Tax_Ref!$E$210:$E$281)*(J102-Tax_Ref!$D$210:$D$281))*Tax_Ref!$F$210:$F$281)} | K104: {=SUMPRODUCT((Tax_Ref!$B$210:$B$281=2024)*(Tax_Ref!$C$210:$C$281=Filing_Status)*((K102>Tax_Ref!$E$210:$E$281)*(Tax_Ref!$E$210:$E$281-Tax_Ref!$D$210:$D$281)+(K102>Tax_Ref!$D$210:$D$281)*(K102<=Tax_Ref!$E$210:$E$281)*(K102-Tax_Ref!$D$210:$D$281))*Tax_Ref!$F$210:$F$281)}
I105: Net LTCG/QD Tax | J105: =J103-J104 | K105: =K103-K104
J106: =J33*0.25 | K106: =K33*0.25
I107: TOTAL CAP GAINS TAX | J107: =J105+J106 | K107: =K105+K106 | L107: =J107-K107
I109: 5. NET INVESTMENT INCOME TAX (NIIT)
I110: MAGI | J110: =J38 | K110: =K38
I111: NIIT Threshold | J111: =SUMIFS(tblThresholds[Value], tblThresholds[Year], 2024, tblThresholds[FilingStatus], Filing_Status, tblThresholds[Item], "NIIT_Threshold") | K111: =SUMIFS(tblThresholds[Value], tblThresholds[Year], 2024, tblThresholds[FilingStatus], Filing_Status, tblThresholds[Item], "NIIT_Threshold")
I112: Net Investment Income (NII) | J112: =MAX(0,J39) | K112: =MAX(0,K39)
I113: NIIT Base (lesser of NII or MAGI excess) | J113: =MAX(0,J110-J111) | K113: =MAX(0,K110-K111)
I114: NIIT (3.8%) | J114: =MIN(J112,J113)*SUMIFS(tblThresholds[Value], tblThresholds[Year], 2024, tblThresholds[FilingStatus], Filing_Status, tblThresholds[Item], "NIIT_Rate") | K114: =MIN(K112,K113)*SUMIFS(tblThresholds[Value], tblThresholds[Year], 2024, tblThresholds[FilingStatus], Filing_Status, tblThresholds[Item], "NIIT_Rate") | L114: =J114-K114
I116: 6. QBI DEDUCTION (§199A)
I117: QBI-Eligible Income | J117: =J40 | K117: =K40
I118: 20% of QBI | J118: =MAX(0,J117)*0.2 | K118: =MAX(0,K117)*0.2
I119: 50% of W-2 Wages | J119: =MAX(0,J41)*0.2 | K119: =MAX(0,K41)*0.2
I120: 25% W-2 + 2.5% UBIA | J120: =MAX(J23*0.5, J23*0.25+J44*0.025) | K120: =MAX(K23*0.5, K23*0.25+K44*0.025)
I121: Phase-in applies? | J121: =IF(J41>SUMIFS(tblThresholds[Value], tblThresholds[Year], 2024, tblThresholds[FilingStatus], Filing_Status, tblThresholds[Item], "QBI_Threshold_Start"),"YES","NO") | K121: =IF(K41>SUMIFS(tblThresholds[Value], tblThresholds[Year], 2024, tblThresholds[FilingStatus], Filing_Status, tblThresholds[Item], "QBI_Threshold_Start"),"YES","NO")
I122: QBI DEDUCTION | J122: =IF(AND(J45=TRUE,J41>SUMIFS(tblThresholds[Value], tblThresholds[Year], 2024, tblThresholds[FilingStatus], Filing_Status, tblThresholds[Item], "QBI_Threshold_End")),0,IF(J41<=SUMIFS(tblThresholds[Value], tblThresholds[Year], 2024, tblThresholds[FilingStatus], Filing_Status, tblThresholds[Item], "QBI_Threshold_Start"),MIN(J118,J119),MIN(J118,J119,J120))) | K122: =IF(AND(K45=TRUE,K41>SUMIFS(tblThresholds[Value], tblThresholds[Year], 2024, tblThresholds[FilingStatus], Filing_Status, tblThresholds[Item], "QBI_Threshold_End")),0,IF(K41<=SUMIFS(tblThresholds[Value], tblThresholds[Year], 2024, tblThresholds[FilingStatus], Filing_Status, tblThresholds[Item], "QBI_Threshold_Start"),MIN(K118,K119),MIN(K118,K119,K120))) | L122: =K122-J122
I124: 7. COMBINED TAX SUMMARY
I125: Total Income | J125: =K6+K8+K10+K11+K12 | K125: =P13 | L125: Δ Savings
I126: Ordinary Tax | J126: =J97 | K126: =K97 | L126: =J126-K126
I127: Capital Gains Tax | J127: =J107 | K127: =K107 | L127: =J127-K127
I128: Self-Employment Tax | J128: =J80 | K128: =K80 | L128: =J128-K128
I129: Payroll Tax (Employee + Employer) | J129: =J91 | K129: =K91 | L129: =J129-K129
I130: NIIT | J130: =J114 | K130: =K114 | L130: =J130-K130
...

Sheet Y2025
A1: Y2025 — standalone tax planning sandbox
A2: Strategies: enter Amount + Status below. Committed strategies flow to rollup M column. Push to Master_Inputs when final.
A4: ▸ STRATEGIES
A5: StrategyID | B5: Strategy Name | C5: TargetLine | D5: Amount | E5: Status | F5: Notes | G5: CounterLine | H5: Jeff_Ref_ID | I5: Line | J5: Description | K5: Baseline (Master) | L5: PY? | M5: S1 Override | N5: Strategies | O5: Effective | P5: Eff w/ Strategies | Q5: Drill
A6: STR-001 | B6: S-Corp Wage Optimization | C6: 1z | D6: -25000 | E6: Committed | F6: Reduce W-2 $25K, offset by K-1 increase | G6: 8 | H6: STD-008 | I6: 1z | J6: Wages | K6: =SUMIFS(tblMaster_Inputs[Baseline_Amount], tblMaster_Inputs[Year], 2025, tblMaster_Inputs[Primary_Line], $I6, tblMaster_Inputs[Activity_Type], "Baseline") | N6: =SUMIFS(tblY2025_Strategies[Amount],tblY2025_Strategies[TargetLine],$I6)-SUMIFS(tblY2025_Strategies[Amount],tblY2025_Strategies[CounterLine],$I6) | O6: =IF(UPPER(L6)="Y",SUMIFS(tblMaster_Inputs[Baseline_Amount],tblMaster_Inputs[Year],2024,tblMaster_Inputs[Primary_Line],"1z"),IF(ISBLANK(M6),K6,M6)) | P6: =O6+N6 | Q6: =HYPERLINK("#Y2025!I49", "↗ drill")
A7: STR-002 | B7: HSA Family Max | C7: 10 | D7: -8550 | E7: Committed | F7: Family HSA contribution | H7: STD-001 | I7: 2a | J7: Tax-exempt interest (informational — Helper) | K7: =TAX_EXEMPT | N7: =SUMIFS(tblY2025_Strategies[Amount],tblY2025_Strategies[TargetLine],"2a",tblY2025_Strategies[Status],"Committed") | O7: =IF(UPPER(L7)="Y",SUMIFS(tblMaster_Inputs[Helper_Amount],tblMaster_Inputs[Year],2024,tblMaster_Inputs[Helper_Treatment],"TAX_EXEMPT"),IF(ISBLANK(M7),K7,M7)) | P7: =O7 | Q7: =HYPERLINK("#Y2025!I49", "↗ drill")
A8: STR-003 | B8: Charitable Bunching (DAF) | C8: 12 | D8: 15000 | E8: Proposed | F8: Donor-advised fund stacking | H8: ADV-002 | I8: 2b | J8: Taxable interest | K8: =SUMIFS(tblMaster_Inputs[Baseline_Amount], tblMaster_Inputs[Year], 2025, tblMaster_Inputs[Primary_Line], $I8, tblMaster_Inputs[Activity_Type], "Baseline") | N8: =SUMIFS(tblY2025_Strategies[Amount],tblY2025_Strategies[TargetLine],$I8)-SUMIFS(tblY2025_Strategies[Amount],tblY2025_Strategies[CounterLine],$I8) | O8: =IF(UPPER(L8)="Y",SUMIFS(tblMaster_Inputs[Baseline_Amount],tblMaster_Inputs[Year],2024,tblMaster_Inputs[Primary_Line],"2b"),IF(ISBLANK(M8),K8,M8)) | P8: =O8+N8 | Q8: =HYPERLINK("#Y2025!I49", "↗ drill")
A9: STR-004 | B9: SEP-IRA / Solo 401(k) | C9: 8 | D9: -7000 | E9: Approved | F9: Retirement contribution | H9: STD-001 | I9: 3a | J9: Qualified dividends (informational — Helper) | K9: =QUAL_DIV | N9: =SUMIFS(tblY2025_Strategies[Amount],tblY2025_Strategies[TargetLine],"3a",tblY2025_Strategies[Status],"Committed") | O9: =IF(UPPER(L9)="Y",SUMIFS(tblMaster_Inputs[Helper_Amount],tblMaster_Inputs[Year],2024,tblMaster_Inputs[Helper_Treatment],"QUAL_DIV"),IF(ISBLANK(M9),K9,M9)) | P9: =O9 | Q9: =HYPERLINK("#Y2025!I49", "↗ drill")
A10: STR-005 | B10: Cost Seg Study | C10: 8 | D10: -80000 | E10: Committed | F10: 123 Main St — accelerated depreciation | H10: STD-012 | I10: 3b | J10: Ordinary dividends (total — incl qualified) | K10: =SUMIFS(tblMaster_Inputs[Baseline_Amount], tblMaster_Inputs[Year], 2025, tblMaster_Inputs[Primary_Line], $I10, tblMaster_Inputs[Activity_Type], "Baseline") | N10: =SUMIFS(tblY2025_Strategies[Amount],tblY2025_Strategies[TargetLine],$I10)-SUMIFS(tblY2025_Strategies[Amount],tblY2025_Strategies[CounterLine],$I10) | O10: =IF(UPPER(L10)="Y",SUMIFS(tblMaster_Inputs[Baseline_Amount],tblMaster_Inputs[Year],2024,tblMaster_Inputs[Primary_Line],"3b"),IF(ISBLANK(M10),K10,M10)) | P10: =O10+N10 | Q10: =HYPERLINK("#Y2025!I49", "↗ drill")
A11: STR-006 | B11: Roth Conversion | C11: 1z | F11: Conversion amount (increases taxable income) | H11: ADV-004 | I11: 7 | J11: Capital gain or (loss) | K11: =SUMIFS(tblMaster_Inputs[Baseline_Amount], tblMaster_Inputs[Year], 2025, tblMaster_Inputs[Primary_Line], $I11, tblMaster_Inputs[Activity_Type], "Baseline") | N11: =SUMIFS(tblY2025_Strategies[Amount],tblY2025_Strategies[TargetLine],$I11)-SUMIFS(tblY2025_Strategies[Amount],tblY2025_Strategies[CounterLine],$I11) | O11: =IF(UPPER(L11)="Y",SUMIFS(tblMaster_Inputs[Baseline_Amount],tblMaster_Inputs[Year],2024,tblMaster_Inputs[Primary_Line],"7"),IF(ISBLANK(M11),K11,M11)) | P11: =O11+N11 | Q11: =HYPERLINK("#Y2025!I49", "↗ drill")
A12: STR-007 | B12: Augusta Rule (§280A) | C12: 8 | F12: Home rental to S-Corp (≤14 days, tax-free) | H12: STD-002 | I12: 8 | J12: Other income (incl business income via Sch 1) | K12: =SUMIFS(tblMaster_Inputs[Baseline_Amount], tblMaster_Inputs[Year], 2025, tblMaster_Inputs[Primary_Line], $I12, tblMaster_Inputs[Activity_Type], "Baseline") | N12: =SUMIFS(tblY2025_Strategies[Amount],tblY2025_Strategies[TargetLine],$I12)-SUMIFS(tblY2025_Strategies[Amount],tblY2025_Strategies[CounterLine],$I12) | O12: =IF(UPPER(L12)="Y",SUMIFS(tblMaster_Inputs[Baseline_Amount],tblMaster_Inputs[Year],2024,tblMaster_Inputs[Primary_Line],"8"),IF(ISBLANK(M12),K12,M12)) | P12: =O12+N12 | Q12: =HYPERLINK("#Y2025!I49", "↗ drill")
A13: STR-008 | B13: Accountable Plan | C13: 8 | F13: Business expense reimbursement | H13: STD-003 | I13: 9 | J13: TOTAL INCOME | K13: =K6+K8+K10+K11+K12 | N13: =N6+N8+N10+N11+N12 | O13: =O6+O8+O10+O11+O12 | P13: =P6+P8+P10+P11+P12 | Q13: =HYPERLINK("#Y2025!I49", "↗ drill")
A14: STR-009 | B14: Hire Children | C14: 8 | F14: Wages to children under §3121(b)(3) | G14: 1z | H14: STD-005 | I14: 10 | J14: Adjustments to income | K14: =SUMIFS(tblMaster_Inputs[Baseline_Amount], tblMaster_Inputs[Year], 2025, tblMaster_Inputs[Primary_Line], $I14, tblMaster_Inputs[Activity_Type], "Baseline") | N14: =SUMIFS(tblY2025_Strategies[Amount],tblY2025_Strategies[TargetLine],$I14)-SUMIFS(tblY2025_Strategies[Amount],tblY2025_Strategies[CounterLine],$I14) | O14: =IF(UPPER(L14)="Y",SUMIFS(tblMaster_Inputs[Baseline_Amount],tblMaster_Inputs[Year],2024,tblMaster_Inputs[Primary_Line],"10"),IF(ISBLANK(M14),K14,M14)) | P14: =O14+N14 | Q14: =HYPERLINK("#Y2025!I49", "↗ drill")
A15: STR-010 | B15: Entity Restructuring | C15: 8 | F15: Partnership → S-Corp, etc. | G15: 1z | H15: STD-007 | I15: 11 | J15: AGI | K15: =K13+K14 | N15: =N13+N14 | O15: =O13+O14 | P15: =P13+P14 | Q15: =HYPERLINK("#Y2025!I49", "↗ drill")
A16: STR-011 | B16: Installment Sale / 1031 | C16: 7 | F16: Gain deferral strategies | H16: STD-009 + ADV-006 | I16: 12 | J16: Std/Itemized deduction | K16: =SUMIFS(tblMaster_Inputs[Baseline_Amount], tblMaster_Inputs[Year], 2025, tblMaster_Inputs[Primary_Line], $I16, tblMaster_Inputs[Activity_Type], "Baseline") | N16: =SUMIFS(tblY2025_Strategies[Amount],tblY2025_Strategies[TargetLine],$I16)-SUMIFS(tblY2025_Strategies[Amount],tblY2025_Strategies[CounterLine],$I16) | O16: =IF(UPPER(L16)="Y",SUMIFS(tblMaster_Inputs[Baseline_Amount],tblMaster_Inputs[Year],2024,tblMaster_Inputs[Primary_Line],"12"),IF(ISBLANK(M16),K16,M16)) | P16: =O16+N16 | Q16: =HYPERLINK("#Y2025!I49", "↗ drill")
A17: STR-012 | B17: Bonus Depreciation §168(k) | C17: 8 | F17: First-year depreciation | H17: STD-012 | I17: 13 | J17: QBI deduction | K17: =SUMIFS(tblMaster_Inputs[Baseline_Amount], tblMaster_Inputs[Year], 2025, tblMaster_Inputs[Primary_Line], $I17, tblMaster_Inputs[Activity_Type], "Baseline") | N17: =SUMIFS(tblY2025_Strategies[Amount],tblY2025_Strategies[TargetLine],$I17)-SUMIFS(tblY2025_Strategies[Amount],tblY2025_Strategies[CounterLine],$I17) | O17: =IF(UPPER(L17)="Y",SUMIFS(tblMaster_Inputs[Baseline_Amount],tblMaster_Inputs[Year],2024,tblMaster_Inputs[Primary_Line],"13"),IF(ISBLANK(M17),K17,M17)) | P17: =O17+N17 | Q17: =HYPERLINK("#Y2025!I49", "↗ drill")
A18: STR-013 | B18: R&D Credit §41 | C18: 20 | F18: Research credit | I18: 15 | J18: TAXABLE INCOME | K18: =K15+K16+K17 | N18: =N15+N16+N17 | O18: =O15+O16+O17 | P18: =P15+P16+P17 | Q18: =HYPERLINK("#Y2025!I49", "↗ drill")
A19: STR-014 | B19: SALT PTE Election | C19: 12 | F19: State pass-through entity tax
A20: STR-015 | B20: Timing / Deferral | C20: 8 | F20: Income acceleration or deferral | H20: STD-006
A22: ▸ TAX IMPACT SUMMARY | I22: Description | J22: =O5 | K22: =P5 | L22: Used by
A23: Metric | B23: Baseline | C23: Effective | D23: Eff w/ Strat | E23: Savings | I23: long-term capital gains (LT preferential rate; stacks with qualified div) | J23: =SUMIFS(tblMaster_Inputs[Baseline_Amount], tblMaster_Inputs[Year], 2025, tblMaster_Inputs[Treatment_Profile], "W2_SCorpOwner", tblMaster_Inputs[Activity_Type], "Baseline") | K23: =J23+SUMIFS(tblY2025_Strategies[Amount],tblY2025_Strategies[TargetLine],"1z")-SUMIFS(tblY2025_Strategies[Amount],tblY2025_Strategies[CounterLine],"1z") | L23: FICA_Employer/Employee — True Tax Burden box
A24: Total Income | B24: =K13 | C24: =O13 | D24: =P13 | E24: =B24-D24 | I24: where I can simply go through and | J24: =SUMIFS(tblMaster_Inputs[Baseline_Amount], tblMaster_Inputs[Year], 2025, tblMaster_Inputs[Treatment_Profile], "W2_Employee", tblMaster_Inputs[Activity_Type], "Baseline") | K24: =J24 | L24: Calc_SE_Tax (SS-base sharing) · AddlMedicareTax_FN
A25: Taxable Income | B25: =K18 | C25: =O18 | D25: =P18 | E25: =B25-D25 | I25: Total W-2 wages (owner + third-party) | J25: =J23+J24 | K25: =K23+K24 | L25: Calc_SE_Tax (SS-base sharing) · AddlMedicareTax_FN
A26: Total Tax | B26: =J133 | C26: =J133 | D26: =K133 | E26: =B26-D26 | I26: Business income subject to SE tax (Sch C, Sch F, active K-1 PTP) | J26: =SUMIFS(tblMaster_Inputs[Baseline_Amount], tblMaster_Inputs[Year], 2025, tblMaster_Inputs[Bucket], "Business Income", tblMaster_Inputs[SE_Subject], "Yes", tblMaster_Inputs[Activity_Type], "Baseline") | K26: =J26 | L26: Calc_SE_Tax base · AddlMedicareTax_FN
A27: Effective Rate | B27: =J134 | C27: =J134 | D27: =K134 | E27: =B27-D27 | I27: Active business income NOT subject to SE (active S-Corp K-1, etc.) | J27: =SUMIFS(tblMaster_Inputs[Baseline_Amount], tblMaster_Inputs[Year], 2025, tblMaster_Inputs[Bucket], "Business Income", tblMaster_Inputs[SE_Subject], "No", tblMaster_Inputs[NIIT_Class], "Active", tblMaster_Inputs[Activity_Type], "Baseline") | K27: =J27+SUMIFS(tblY2025_Strategies[Amount],tblY2025_Strategies[TargetLine],"8")-SUMIFS(tblY2025_Strategies[Amount],tblY2025_Strategies[CounterLine],"8") | L27: NIIT exclusion (active) · QBI eligible
A28: Committed Strategies | B28: =COUNTIF(tblY2025_Strategies[Status],"Committed") | C28: Net Strategy Impact | D28: =SUMIF(tblY2025_Strategies[Status],"Committed",tblY2025_Strategies[Amount]) | I28: Passive business income / loss (passive K-1s, Sch E rental) | J28: =SUMIFS(tblMaster_Inputs[Baseline_Amount], tblMaster_Inputs[Year], 2025, tblMaster_Inputs[Bucket], "Business Income", tblMaster_Inputs[NIIT_Class], "Passive", tblMaster_Inputs[Activity_Type], "Baseline") | K28: =J28 | L28: PassiveLossAllowed_FN · NIIT inclusion
I29: Tax-exempt interest (Line 2a; reported but not taxed) | J29: =SUMIFS(tblMaster_Inputs[Helper_Amount], tblMaster_Inputs[Year], 2025, tblMaster_Inputs[Helper_Treatment], "TAX_EXEMPT") | K29: =J29+SUMIFS(tblY2025_Strategies[Amount],tblY2025_Strategies[TargetLine],"2a")-SUMIFS(tblY2025_Strategies[Amount],tblY2025_Strategies[CounterLine],"2a") | L29: NIIT_FN (MAGI base)
I30: Qualified dividends (carve-out of Line 3b; LTCG stack) | J30: =SUMIFS(tblMaster_Inputs[Helper_Amount], tblMaster_Inputs[Year], 2025, tblMaster_Inputs[Helper_Treatment], "QUAL_DIV", tblMaster_Inputs[Activity_Type], "Baseline") | K30: =J30 | L30: Calc_CapGainsTax stacking
I31: Long-term capital gains (LT preferential rate; stacks with qualified div) | J31: =SUMIFS(tblMaster_Inputs[Baseline_Amount], tblMaster_Inputs[Year], 2025, tblMaster_Inputs[Treatment_Profile], "LTCG_Stock") + SUMIFS(tblMaster_Inputs[Baseline_Amount], tblMaster_Inputs[Year], 2025, tblMaster_Inputs[Treatment_Profile], "LTCG_RE") + SUMIFS(tblMaster_Inputs[Baseline_Amount], tblMaster_Inputs[Year], 2025, tblMaster_Inputs[Treatment_Profile], "LTCG_K1_Passthrough") + SUMIFS(tblMaster_Inputs[Baseline_Amount], tblMaster_Inputs[Year], 2025, tblMaster_Inputs[Treatment_Profile], "Sec1250_Recap", tblMaster_Inputs[Activity_Type], "Baseline") | K31: =J31+SUMIFS(tblY2025_Strategies[Amount],tblY2025_Strategies[TargetLine],"7")-SUMIFS(tblY2025_Strategies[Amount],tblY2025_Strategies[CounterLine],"7") | L31: Calc_CapGainsTax
I32: Short-term capital gains (taxed as ordinary income) | J32: =SUMIFS(tblMaster_Inputs[Baseline_Amount], tblMaster_Inputs[Year], 2025, tblMaster_Inputs[Treatment_Profile], "STCG_Stock", tblMaster_Inputs[Activity_Type], "Baseline") | K32: =J32 | L32: Calc_OrdinaryTax (ST folded into ordinary income)
I33: §1250 unrecaptured gain (sub-carve of CG_LT; capped at 25% rate) | J33: =SUMIFS(tblMaster_Inputs[Helper_Amount], tblMaster_Inputs[Year], 2025, tblMaster_Inputs[Helper_Treatment], "SEC1250", tblMaster_Inputs[Activity_Type], "Baseline") | K33: =J33 | L33: Calc_1250Tax
I36: Description | J36: Formula / Value | K36: Effective | L36: Used by LAMBDA
I37: Ordinary income (TaxableIncome - CG_LT - QUAL_DIV - SEC1250) | J37: =K18-J31-J30-J33 | K37: =P18-K31-K30-K33 | L37: Calc_CapGainsTax stacking base · Calc_OrdinaryTax (after carve-outs)
I38: Modified AGI = AGI + tax-exempt interest | J38: =K15+J29 | K38: =P15+K29 | L38: Calc_NIIT · PassiveLossAllowed_FN
I39: Net Investment Income = taxable int + div + cap gain + passive | J39: =K8+K10+K11+J28 | K39: =P8+P10+P11+K28 | L39: Calc_NIIT
I40: QBI-eligible business income (active business) | J40: =J26+J27 | K40: =K26+K27 | L40: Calc_QBI_Simple · QBI_FN
I41: Taxable Income BEFORE QBI deduction (= AGI - StdItemDed) | J41: =K15+K16 | K41: =P15+P16 | L41: Calc_QBI_Simple (cap reference)
I42: Net business loss (only when negative; for EBL limit) | J42: =MIN(0,J26+J27+J28) | K42: =MIN(0,K26+K27+K28) | L42: ExcessBusinessLossLimit_FN
I43: Net SE income (alias of BI_SE_SUBJECT for LAMBDA clarity) | J43: =J26 | K43: =K26 | L43: Calc_SE_Tax · AddlMedicareTax_FN · SETax_FN
I44: Unadjusted Basis Immediately After Acquisition (QBI W-2/UBIA test) | J44: 0 | K44: =J44 | L44: QBI_FN
I45: Is Specified Service Trade or Business? (TRUE/FALSE) | J45: =IF(Control_Panel!C21="Yes",TRUE,FALSE) | K45: =J45 | L45: QBI_FN
I46: NOL carryforward available (from prior-year Carryovers; populate manually for now) | J46: =Carryovers!F52 | K46: =J46 | L46: NOLDeductionAllowed_FN
I49: 1z | L49: =HYPERLINK("#Master_Inputs!A1", "✏ open Master_Inputs to edit")
I51: Bucket | J51: Treatment_Profile | L51: Payor | M51: Baseline_Amount | N51: Helper_Amount | O51: Notes
I65: ▸ 7-COMPONENT TAX CALCULATOR | J65: Baseline | K65: Effective | L65: Δ Savings
I66: Dual columns: Baseline (H) vs With Planning (I)
I68: 1. SELF-EMPLOYMENT TAX
I69: SE Tax Label
I70: Net SE Earnings | J70: =J43 | K70: =K43
I71: SE Base (× 0.9235) | J71: =J70*SUMIFS(tblThresholds[Value], tblThresholds[Year], 2025, tblThresholds[FilingStatus], Filing_Status, tblThresholds[Item], "SE_Earnings_Factor") | K71: =K70*SUMIFS(tblThresholds[Value], tblThresholds[Year], 2025, tblThresholds[FilingStatus], Filing_Status, tblThresholds[Item], "SE_Earnings_Factor")
I72: W-2 Wages | J72: =J25 | K72: =K25
I73: Remaining SS Wage Base | J73: =MAX(0,SUMIFS(tblThresholds[Value], tblThresholds[Year], 2025, tblThresholds[FilingStatus], Filing_Status, tblThresholds[Item], "SS_Wage_Base")-J72) | K73: =MAX(0,SUMIFS(tblThresholds[Value], tblThresholds[Year], 2025, tblThresholds[FilingStatus], Filing_Status, tblThresholds[Item], "SS_Wage_Base")-K72)
J74: =MIN(J71,J73) | K74: =MIN(K71,K73)
I75: Social Security Tax (12.4%) | J75: =J74*SUMIFS(tblThresholds[Value], tblThresholds[Year], 2025, tblThresholds[FilingStatus], Filing_Status, tblThresholds[Item], "SS_Rate_Combined") | K75: =K74*SUMIFS(tblThresholds[Value], tblThresholds[Year], 2025, tblThresholds[FilingStatus], Filing_Status, tblThresholds[Item], "SS_Rate_Combined")
I76: Medicare Tax (2.9%) | J76: =J71*SUMIFS(tblThresholds[Value], tblThresholds[Year], 2025, tblThresholds[FilingStatus], Filing_Status, tblThresholds[Item], "Medicare_Rate_Combined") | K76: =K71*SUMIFS(tblThresholds[Value], tblThresholds[Year], 2025, tblThresholds[FilingStatus], Filing_Status, tblThresholds[Item], "Medicare_Rate_Combined")
I77: Addl Medicare (0.9% > threshold) | J77: =MAX(0,(J72+J71-SUMIFS(tblThresholds[Value], tblThresholds[Year], 2025, tblThresholds[FilingStatus], Filing_Status, tblThresholds[Item], "Addl_Medicare_Threshold"))*SUMIFS(tblThresholds[Value], tblThresholds[Year], 2025, tblThresholds[FilingStatus], Filing_Status, tblThresholds[Item], "Addl_Medicare_Rate")) | K77: =MAX(0,(K72+K71-SUMIFS(tblThresholds[Value], tblThresholds[Year], 2025, tblThresholds[FilingStatus], Filing_Status, tblThresholds[Item], "Addl_Medicare_Threshold"))*SUMIFS(tblThresholds[Value], tblThresholds[Year], 2025, tblThresholds[FilingStatus], Filing_Status, tblThresholds[Item], "Addl_Medicare_Rate"))
J78: =-(J75+J76)/2 | K78: =-(K75+K76)/2
I80: TOTAL SE TAX | J80: =J75+J76+J77 | K80: =K75+K76+K77 | L80: =J80-K80
I82: 2. PAYROLL TAX
I83: W-2 Wages | J83: =J25 | K83: =K25
I84: Social Security (6.2%) | J84: =MIN(J83,SUMIFS(tblThresholds[Value], tblThresholds[Year], 2025, tblThresholds[FilingStatus], Filing_Status, tblThresholds[Item], "SS_Wage_Base"))*0.062 | K84: =MIN(K83,SUMIFS(tblThresholds[Value], tblThresholds[Year], 2025, tblThresholds[FilingStatus], Filing_Status, tblThresholds[Item], "SS_Wage_Base"))*0.062
I85: Medicare (1.45%) | J85: =J83*0.0145 | K85: =K83*0.0145
I86: Addl Medicare (0.9% > threshold) | J86: =MAX(0,(J83-SUMIFS(tblThresholds[Value], tblThresholds[Year], 2025, tblThresholds[FilingStatus], Filing_Status, tblThresholds[Item], "Addl_Medicare_Threshold"))*SUMIFS(tblThresholds[Value], tblThresholds[Year], 2025, tblThresholds[FilingStatus], Filing_Status, tblThresholds[Item], "Addl_Medicare_Rate")) | K86: =MAX(0,(K83-SUMIFS(tblThresholds[Value], tblThresholds[Year], 2025, tblThresholds[FilingStatus], Filing_Status, tblThresholds[Item], "Addl_Medicare_Threshold"))*SUMIFS(tblThresholds[Value], tblThresholds[Year], 2025, tblThresholds[FilingStatus], Filing_Status, tblThresholds[Item], "Addl_Medicare_Rate"))
I87: TOTAL PAYROLL TAX | J87: =J84+J85+J86 | K87: =K84+K85+K86 | L87: =J87-K87
I88: Employer Social Security (6.2%) | J88: =J84 | K88: =K84 | L88: =J88-K88
I89: Employer Medicare (1.45%) | J89: =J85 | K89: =K85 | L89: =J89-K89
I91: TOTAL PAYROLL TAX (Employee + Employer) | J91: =J87+J88+J89 | K91: =K87+K88+K89 | L91: =J91-K91
I93: 3. ORDINARY INCOME TAX
I94: Taxable Income | J94: =J37 | K94: =K37
I95: Ordinary Taxable (TI - LTCG - QD) | J95: =MAX(0,J94) | K95: =MAX(0,K94)
I96: Tax (SUMPRODUCT bracket lookup) | J96: {=SUMPRODUCT((tblBrackets_FIT[Year]=2025)*(tblBrackets_FIT[FilingStatus]=Filing_Status)*((J95>tblBrackets_FIT[Upper])*(tblBrackets_FIT[Upper]-tblBrackets_FIT[Lower])+(J95>tblBrackets_FIT[Lower])*(J95<=tblBrackets_FIT[Upper])*(J95-tblBrackets_FIT[Lower]))*tblBrackets_FIT[Rate])} | K96: {=SUMPRODUCT((tblBrackets_FIT[Year]=2025)*(tblBrackets_FIT[FilingStatus]=Filing_Status)*((K95>tblBrackets_FIT[Upper])*(tblBrackets_FIT[Upper]-tblBrackets_FIT[Lower])+(K95>tblBrackets_FIT[Lower])*(K95<=tblBrackets_FIT[Upper])*(K95-tblBrackets_FIT[Lower]))*tblBrackets_FIT[Rate])}
I97: TOTAL ORDINARY TAX | J97: =J96 | K97: =K96 | L97: =J97-K97
I99: 4. CAPITAL GAINS / QUALIFIED DIVIDENDS TAX
I100: LTCG + Qualified Dividends | J100: =J31+J30 | K100: =K31+K30
I101: Sec 1250 Recapture Gain | J101: =J33 | K101: =K33
I102: Stacking Base (Ordinary TI for bracket floor) | J102: =J95 | K102: =K95
I103: Full CG Rate Tax (SUMPRODUCT stack) | J103: {=SUMPRODUCT((Tax_Ref!$B$210:$B$281=2025)*(Tax_Ref!$C$210:$C$281=Filing_Status)*((J102+J100>Tax_Ref!$E$210:$E$281)*(Tax_Ref!$E$210:$E$281-Tax_Ref!$D$210:$D$281)+(J102+J100>Tax_Ref!$D$210:$D$281)*(J102+J100<=Tax_Ref!$E$210:$E$281)*(J102+J100-Tax_Ref!$D$210:$D$281))*Tax_Ref!$F$210:$F$281)} | K103: {=SUMPRODUCT((Tax_Ref!$B$210:$B$281=2025)*(Tax_Ref!$C$210:$C$281=Filing_Status)*((K102+K100>Tax_Ref!$E$210:$E$281)*(Tax_Ref!$E$210:$E$281-Tax_Ref!$D$210:$D$281)+(K102+K100>Tax_Ref!$D$210:$D$281)*(K102+K100<=Tax_Ref!$E$210:$E$281)*(K102+K100-Tax_Ref!$D$210:$D$281))*Tax_Ref!$F$210:$F$281)}
I104: CG Rate Tax on Ordinary only | J104: {=SUMPRODUCT((Tax_Ref!$B$210:$B$281=2025)*(Tax_Ref!$C$210:$C$281=Filing_Status)*((J102>Tax_Ref!$E$210:$E$281)*(Tax_Ref!$E$210:$E$281-Tax_Ref!$D$210:$D$281)+(J102>Tax_Ref!$D$210:$D$281)*(J102<=Tax_Ref!$E$210:$E$281)*(J102-Tax_Ref!$D$210:$D$281))*Tax_Ref!$F$210:$F$281)} | K104: {=SUMPRODUCT((Tax_Ref!$B$210:$B$281=2025)*(Tax_Ref!$C$210:$C$281=Filing_Status)*((K102>Tax_Ref!$E$210:$E$281)*(Tax_Ref!$E$210:$E$281-Tax_Ref!$D$210:$D$281)+(K102>Tax_Ref!$D$210:$D$281)*(K102<=Tax_Ref!$E$210:$E$281)*(K102-Tax_Ref!$D$210:$D$281))*Tax_Ref!$F$210:$F$281)}
I105: Net LTCG/QD Tax | J105: =J103-J104 | K105: =K103-K104
J106: =J33*0.25 | K106: =K33*0.25
I107: TOTAL CAP GAINS TAX | J107: =J105+J106 | K107: =K105+K106 | L107: =J107-K107
I109: 5. NET INVESTMENT INCOME TAX (NIIT)
I110: MAGI | J110: =J38 | K110: =K38
I111: NIIT Threshold | J111: =SUMIFS(tblThresholds[Value], tblThresholds[Year], 2025, tblThresholds[FilingStatus], Filing_Status, tblThresholds[Item], "NIIT_Threshold") | K111: =SUMIFS(tblThresholds[Value], tblThresholds[Year], 2025, tblThresholds[FilingStatus], Filing_Status, tblThresholds[Item], "NIIT_Threshold")
I112: Net Investment Income (NII) | J112: =MAX(0,J39) | K112: =MAX(0,K39)
I113: NIIT Base (lesser of NII or MAGI excess) | J113: =MAX(0,J110-J111) | K113: =MAX(0,K110-K111)
I114: NIIT (3.8%) | J114: =MIN(J112,J113)*SUMIFS(tblThresholds[Value], tblThresholds[Year], 2025, tblThresholds[FilingStatus], Filing_Status, tblThresholds[Item], "NIIT_Rate") | K114: =MIN(K112,K113)*SUMIFS(tblThresholds[Value], tblThresholds[Year], 2025, tblThresholds[FilingStatus], Filing_Status, tblThresholds[Item], "NIIT_Rate") | L114: =J114-K114
I116: 6. QBI DEDUCTION (§199A)
I117: QBI-Eligible Income | J117: =J40 | K117: =K40
I118: 20% of QBI | J118: =MAX(0,J117)*0.2 | K118: =MAX(0,K117)*0.2
I119: 50% of W-2 Wages | J119: =MAX(0,J41)*0.2 | K119: =MAX(0,K41)*0.2
I120: 25% W-2 + 2.5% UBIA | J120: =MAX(J23*0.5, J23*0.25+J44*0.025) | K120: =MAX(K23*0.5, K23*0.25+K44*0.025)
I121: Phase-in applies? | J121: =IF(J41>SUMIFS(tblThresholds[Value], tblThresholds[Year], 2025, tblThresholds[FilingStatus], Filing_Status, tblThresholds[Item], "QBI_Threshold_Start"),"YES","NO") | K121: =IF(K41>SUMIFS(tblThresholds[Value], tblThresholds[Year], 2025, tblThresholds[FilingStatus], Filing_Status, tblThresholds[Item], "QBI_Threshold_Start"),"YES","NO")
I122: QBI DEDUCTION | J122: =IF(AND(J45=TRUE,J41>SUMIFS(tblThresholds[Value], tblThresholds[Year], 2025, tblThresholds[FilingStatus], Filing_Status, tblThresholds[Item], "QBI_Threshold_End")),0,IF(J41<=SUMIFS(tblThresholds[Value], tblThresholds[Year], 2025, tblThresholds[FilingStatus], Filing_Status, tblThresholds[Item], "QBI_Threshold_Start"),MIN(J118,J119),MIN(J118,J119,J120))) | K122: =IF(AND(K45=TRUE,K41>SUMIFS(tblThresholds[Value], tblThresholds[Year], 2025, tblThresholds[FilingStatus], Filing_Status, tblThresholds[Item], "QBI_Threshold_End")),0,IF(K41<=SUMIFS(tblThresholds[Value], tblThresholds[Year], 2025, tblThresholds[FilingStatus], Filing_Status, tblThresholds[Item], "QBI_Threshold_Start"),MIN(K118,K119),MIN(K118,K119,K120))) | L122: =K122-J122
I124: 7. COMBINED TAX SUMMARY
I125: Total Income | J125: =K6+K8+K10+K11+K12 | K125: =P13 | L125: Δ Savings
I126: Ordinary Tax | J126: =J97 | K126: =K97 | L126: =J126-K126
I127: Capital Gains Tax | J127: =J107 | K127: =K107 | L127: =J127-K127
I128: Self-Employment Tax | J128: =J80 | K128: =K80 | L128: =J128-K128
I129: Payroll Tax (Employee + Employer) | J129: =J91 | K129: =K91 | L129: =J129-K129
...

Sheet Y2026
A1: Y2026 — standalone tax planning sandbox
A2: Strategies: enter Amount + Status below. Committed strategies flow to rollup M column. Push to Master_Inputs when final.
A4: ▸ STRATEGIES
A5: StrategyID | B5: Strategy Name | C5: TargetLine | D5: Amount | E5: Status | F5: Notes | G5: CounterLine | H5: Jeff_Ref_ID | I5: Line | J5: Description | K5: Baseline (Master) | L5: PY? | M5: S1 Override | N5: Strategies | O5: Effective | P5: Eff w/ Strategies | Q5: Drill
A6: STR-001 | B6: S-Corp Wage Optimization | C6: 1z | G6: 8 | H6: STD-008 | I6: 1z | J6: Wages | K6: =SUMIFS(tblMaster_Inputs[Baseline_Amount],tblMaster_Inputs[Year],2026,tblMaster_Inputs[Primary_Line],$I6, tblMaster_Inputs[Activity_Type], "Baseline") | N6: =SUMIFS(tblY2026_Strategies[Amount],tblY2026_Strategies[TargetLine],$I6)-SUMIFS(tblY2026_Strategies[Amount],tblY2026_Strategies[CounterLine],$I6) | O6: =IF(UPPER(L6)="Y",SUMIFS(tblMaster_Inputs[Baseline_Amount],tblMaster_Inputs[Year],2025,tblMaster_Inputs[Primary_Line],"1z"),IF(ISBLANK(M6),K6,M6)) | P6: =O6+N6 | Q6: =HYPERLINK("#Y2026!I49","↗ drill")
A7: STR-002 | B7: HSA Family Max | C7: 10 | H7: STD-001 | I7: 2a | J7: Tax-exempt interest | K7: =SUMIFS(tblMaster_Inputs[Helper_Amount],tblMaster_Inputs[Year],2026,tblMaster_Inputs[Helper_Treatment],"TAX_EXEMPT") | N7: =SUMIFS(tblY2026_Strategies[Amount],tblY2026_Strategies[TargetLine],"2a",tblY2026_Strategies[Status],"Committed") | O7: =IF(UPPER(L7)="Y",SUMIFS(tblMaster_Inputs[Helper_Amount],tblMaster_Inputs[Year],2025,tblMaster_Inputs[Helper_Treatment],"TAX_EXEMPT"),IF(ISBLANK(M7),K7,M7)) | P7: =O7 | Q7: =HYPERLINK("#Y2026!I49","↗ drill")
A8: STR-003 | B8: Charitable Bunching (DAF) | C8: 12 | H8: ADV-002 | I8: 2b | J8: Taxable interest | K8: =SUMIFS(tblMaster_Inputs[Baseline_Amount],tblMaster_Inputs[Year],2026,tblMaster_Inputs[Primary_Line],$I8, tblMaster_Inputs[Activity_Type], "Baseline") | N8: =SUMIFS(tblY2026_Strategies[Amount],tblY2026_Strategies[TargetLine],$I8)-SUMIFS(tblY2026_Strategies[Amount],tblY2026_Strategies[CounterLine],$I8) | O8: =IF(UPPER(L8)="Y",SUMIFS(tblMaster_Inputs[Baseline_Amount],tblMaster_Inputs[Year],2025,tblMaster_Inputs[Primary_Line],"2b"),IF(ISBLANK(M8),K8,M8)) | P8: =O8+N8 | Q8: =HYPERLINK("#Y2026!I49","↗ drill")
A9: STR-004 | B9: SEP-IRA / Solo 401(k) | C9: 8 | H9: STD-001 | I9: 3a | J9: Qualified dividends | K9: =SUMIFS(tblMaster_Inputs[Helper_Amount],tblMaster_Inputs[Year],2026,tblMaster_Inputs[Helper_Treatment],"QUAL_DIV") | N9: =SUMIFS(tblY2026_Strategies[Amount],tblY2026_Strategies[TargetLine],"3a",tblY2026_Strategies[Status],"Committed") | O9: =IF(UPPER(L9)="Y",SUMIFS(tblMaster_Inputs[Helper_Amount],tblMaster_Inputs[Year],2025,tblMaster_Inputs[Helper_Treatment],"QUAL_DIV"),IF(ISBLANK(M9),K9,M9)) | P9: =O9 | Q9: =HYPERLINK("#Y2026!I49","↗ drill")
A10: STR-005 | B10: Cost Seg Study | C10: 8 | H10: STD-012 | I10: 3b | J10: Ordinary dividends | K10: =SUMIFS(tblMaster_Inputs[Baseline_Amount],tblMaster_Inputs[Year],2026,tblMaster_Inputs[Primary_Line],$I10, tblMaster_Inputs[Activity_Type], "Baseline") | N10: =SUMIFS(tblY2026_Strategies[Amount],tblY2026_Strategies[TargetLine],$I10)-SUMIFS(tblY2026_Strategies[Amount],tblY2026_Strategies[CounterLine],$I10) | O10: =IF(UPPER(L10)="Y",SUMIFS(tblMaster_Inputs[Baseline_Amount],tblMaster_Inputs[Year],2025,tblMaster_Inputs[Primary_Line],"3b"),IF(ISBLANK(M10),K10,M10)) | P10: =O10+N10 | Q10: =HYPERLINK("#Y2026!I49","↗ drill")
A11: STR-006 | B11: Roth Conversion | C11: 1z | H11: ADV-004 | I11: 7 | J11: Capital gain/(loss) | K11: =SUMIFS(tblMaster_Inputs[Baseline_Amount],tblMaster_Inputs[Year],2026,tblMaster_Inputs[Primary_Line],$I11, tblMaster_Inputs[Activity_Type], "Baseline") | N11: =SUMIFS(tblY2026_Strategies[Amount],tblY2026_Strategies[TargetLine],$I11)-SUMIFS(tblY2026_Strategies[Amount],tblY2026_Strategies[CounterLine],$I11) | O11: =IF(UPPER(L11)="Y",SUMIFS(tblMaster_Inputs[Baseline_Amount],tblMaster_Inputs[Year],2025,tblMaster_Inputs[Primary_Line],"7"),IF(ISBLANK(M11),K11,M11)) | P11: =O11+N11 | Q11: =HYPERLINK("#Y2026!I49","↗ drill")
A12: STR-007 | B12: Augusta Rule (§280A) | C12: 8 | H12: STD-002 | I12: 8 | J12: Other income (business) | K12: =SUMIFS(tblMaster_Inputs[Baseline_Amount],tblMaster_Inputs[Year],2026,tblMaster_Inputs[Primary_Line],$I12, tblMaster_Inputs[Activity_Type], "Baseline") | N12: =SUMIFS(tblY2026_Strategies[Amount],tblY2026_Strategies[TargetLine],$I12)-SUMIFS(tblY2026_Strategies[Amount],tblY2026_Strategies[CounterLine],$I12) | O12: =IF(UPPER(L12)="Y",SUMIFS(tblMaster_Inputs[Baseline_Amount],tblMaster_Inputs[Year],2025,tblMaster_Inputs[Primary_Line],"8"),IF(ISBLANK(M12),K12,M12)) | P12: =O12+N12 | Q12: =HYPERLINK("#Y2026!I49","↗ drill")
A13: STR-008 | B13: Accountable Plan | C13: 8 | H13: STD-003 | I13: 9 | J13: TOTAL INCOME | K13: =K6+K8+K10+K11+K12 | N13: =N6+N8+N10+N11+N12 | O13: =O6+O8+O10+O11+O12 | P13: =P6+P8+P10+P11+P12 | Q13: =HYPERLINK("#Y2026!I49","↗ drill")
A14: STR-009 | B14: Hire Children | C14: 8 | F14: Child wages reported on child's own return — counter-impact is cross-return, not within this 1040 | G14: 1z | H14: STD-005 | I14: 10 | J14: Adjustments | K14: =SUMIFS(tblMaster_Inputs[Baseline_Amount],tblMaster_Inputs[Year],2026,tblMaster_Inputs[Primary_Line],$I14, tblMaster_Inputs[Activity_Type], "Baseline") | N14: =SUMIFS(tblY2026_Strategies[Amount],tblY2026_Strategies[TargetLine],$I14)-SUMIFS(tblY2026_Strategies[Amount],tblY2026_Strategies[CounterLine],$I14) | O14: =IF(UPPER(L14)="Y",SUMIFS(tblMaster_Inputs[Baseline_Amount],tblMaster_Inputs[Year],2025,tblMaster_Inputs[Primary_Line],"10"),IF(ISBLANK(M14),K14,M14)) | P14: =O14+N14 | Q14: =HYPERLINK("#Y2026!I49","↗ drill")
A15: STR-010 | B15: Entity Restructuring | C15: 8 | G15: 1z | H15: STD-007 | I15: 11 | J15: AGI | K15: =K13+K14 | N15: =N13+N14 | O15: =O13+O14 | P15: =P13+P14 | Q15: =HYPERLINK("#Y2026!I49","↗ drill")
A16: STR-011 | B16: Installment Sale / 1031 | C16: 7 | H16: STD-009 + ADV-006 | I16: 12 | J16: Std/Itemized ded | K16: =SUMIFS(tblMaster_Inputs[Baseline_Amount],tblMaster_Inputs[Year],2026,tblMaster_Inputs[Primary_Line],$I16, tblMaster_Inputs[Activity_Type], "Baseline") | N16: =SUMIFS(tblY2026_Strategies[Amount],tblY2026_Strategies[TargetLine],$I16)-SUMIFS(tblY2026_Strategies[Amount],tblY2026_Strategies[CounterLine],$I16) | O16: =IF(UPPER(L16)="Y",SUMIFS(tblMaster_Inputs[Baseline_Amount],tblMaster_Inputs[Year],2025,tblMaster_Inputs[Primary_Line],"12"),IF(ISBLANK(M16),K16,M16)) | P16: =O16+N16 | Q16: =HYPERLINK("#Y2026!I49","↗ drill")
A17: STR-012 | B17: Bonus Depreciation §168(k) | C17: 8 | H17: STD-012 | I17: 13 | J17: QBI deduction | K17: =SUMIFS(tblMaster_Inputs[Baseline_Amount],tblMaster_Inputs[Year],2026,tblMaster_Inputs[Primary_Line],$I17, tblMaster_Inputs[Activity_Type], "Baseline") | N17: =SUMIFS(tblY2026_Strategies[Amount],tblY2026_Strategies[TargetLine],$I17)-SUMIFS(tblY2026_Strategies[Amount],tblY2026_Strategies[CounterLine],$I17) | O17: =IF(UPPER(L17)="Y",SUMIFS(tblMaster_Inputs[Baseline_Amount],tblMaster_Inputs[Year],2025,tblMaster_Inputs[Primary_Line],"13"),IF(ISBLANK(M17),K17,M17)) | P17: =O17+N17 | Q17: =HYPERLINK("#Y2026!I49","↗ drill")
A18: STR-013 | B18: R&D Credit §41 | C18: 13 | I18: 15 | J18: TAXABLE INCOME | K18: =K15+K16+K17 | N18: =N15+N16+N17 | O18: =O15+O16+O17 | P18: =P15+P16+P17 | Q18: =HYPERLINK("#Y2026!I49","↗ drill")
A19: STR-014 | B19: SALT PTE Election | C19: 12
A20: STR-015 | B20: Timing / Deferral | C20: 8 | H20: STD-006
A22: ▸ TAX IMPACT SUMMARY | I22: Description | J22: Amount | K22: Effective | L22: Used by
A23: Metric | B23: Baseline | C23: Effective | D23: Eff w/ Strat | E23: Savings | I23: Owner W-2 | J23: =SUMIFS(tblMaster_Inputs[Baseline_Amount],tblMaster_Inputs[Year],2026,tblMaster_Inputs[Treatment_Profile],"W2_SCorpOwner", tblMaster_Inputs[Activity_Type], "Baseline") | K23: =J23+SUMIFS(tblY2026_Strategies[Amount],tblY2026_Strategies[TargetLine],"1z")-SUMIFS(tblY2026_Strategies[Amount],tblY2026_Strategies[CounterLine],"1z")
A24: Total Income | B24: =K13 | C24: =O13 | D24: =P13 | E24: =B24-D24 | I24: Third-party W-2 | J24: =SUMIFS(tblMaster_Inputs[Baseline_Amount],tblMaster_Inputs[Year],2026,tblMaster_Inputs[Treatment_Profile],"W2_Employee", tblMaster_Inputs[Activity_Type], "Baseline") | K24: =J24
A25: Taxable Income | B25: =K18 | C25: =O18 | D25: =P18 | E25: =B25-D25 | I25: Total W-2 | J25: =J23+J24 | K25: =K23+K24
A26: Total Tax | B26: =J133 | C26: =J133 | D26: =K133 | E26: =B26-D26 | I26: SE business | J26: =SUMIFS(tblMaster_Inputs[Baseline_Amount],tblMaster_Inputs[Year],2026,tblMaster_Inputs[Bucket],"Business Income",tblMaster_Inputs[SE_Subject],"Yes", tblMaster_Inputs[Activity_Type], "Baseline") | K26: =J26
A27: Effective Rate | B27: =J134 | C27: =J134 | D27: =K134 | E27: =B27-D27 | I27: Active non-SE | J27: =SUMIFS(tblMaster_Inputs[Baseline_Amount],tblMaster_Inputs[Year],2026,tblMaster_Inputs[Bucket],"Business Income",tblMaster_Inputs[SE_Subject],"No",tblMaster_Inputs[NIIT_Class],"Active", tblMaster_Inputs[Activity_Type], "Baseline") | K27: =J27+SUMIFS(tblY2026_Strategies[Amount],tblY2026_Strategies[TargetLine],"8")-SUMIFS(tblY2026_Strategies[Amount],tblY2026_Strategies[CounterLine],"8")
A28: Committed Strategies | B28: =COUNTIF(tblY2026_Strategies[Status],"Committed") | C28: Net Strategy Impact | D28: =SUMIF(tblY2026_Strategies[Status],"Committed",tblY2026_Strategies[Amount]) | I28: Passive business | J28: =SUMIFS(tblMaster_Inputs[Baseline_Amount],tblMaster_Inputs[Year],2026,tblMaster_Inputs[Bucket],"Business Income",tblMaster_Inputs[NIIT_Class],"Passive", tblMaster_Inputs[Activity_Type], "Baseline") | K28: =J28
I29: Tax-exempt int | J29: =SUMIFS(tblMaster_Inputs[Helper_Amount],tblMaster_Inputs[Year],2026,tblMaster_Inputs[Helper_Treatment],"TAX_EXEMPT") | K29: =J29+SUMIFS(tblY2026_Strategies[Amount],tblY2026_Strategies[TargetLine],"2a")-SUMIFS(tblY2026_Strategies[Amount],tblY2026_Strategies[CounterLine],"2a")
I30: Qualified div | J30: =SUMIFS(tblMaster_Inputs[Helper_Amount],tblMaster_Inputs[Year],2026,tblMaster_Inputs[Helper_Treatment],"QUAL_DIV", tblMaster_Inputs[Activity_Type], "Baseline") | K30: =J30
I31: LT cap gains | J31: =SUMIFS(tblMaster_Inputs[Baseline_Amount],tblMaster_Inputs[Year],2026,tblMaster_Inputs[Treatment_Profile],"LTCG_Stock")+SUMIFS(tblMaster_Inputs[Baseline_Amount],tblMaster_Inputs[Year],2026,tblMaster_Inputs[Treatment_Profile],"LTCG_RE")+SUMIFS(tblMaster_Inputs[Baseline_Amount],tblMaster_Inputs[Year],2026,tblMaster_Inputs[Treatment_Profile],"LTCG_K1_Passthrough")+SUMIFS(tblMaster_Inputs[Baseline_Amount],tblMaster_Inputs[Year],2026,tblMaster_Inputs[Treatment_Profile],"Sec1250_Recap", tblMaster_Inputs[Activity_Type], "Baseline") | K31: =J31+SUMIFS(tblY2026_Strategies[Amount],tblY2026_Strategies[TargetLine],"7")-SUMIFS(tblY2026_Strategies[Amount],tblY2026_Strategies[CounterLine],"7")
I32: ST cap gains | J32: =SUMIFS(tblMaster_Inputs[Baseline_Amount],tblMaster_Inputs[Year],2026,tblMaster_Inputs[Treatment_Profile],"STCG_Stock", tblMaster_Inputs[Activity_Type], "Baseline") | K32: =J32
I33: §1250 gain | J33: =SUMIFS(tblMaster_Inputs[Helper_Amount],tblMaster_Inputs[Year],2026,tblMaster_Inputs[Helper_Treatment],"SEC1250", tblMaster_Inputs[Activity_Type], "Baseline") | K33: =J33
I36: Description | J36: Value | K36: Effective | L36: Used by
I37: TI-LTCG-QD-1250 | J37: =K18-J31-J30-J33 | K37: =P18-K31-K30-K33
I38: AGI+tax-exempt | J38: =K15+J29 | K38: =P15+K29
I39: Net inv income | J39: =K8+K10+K11+J28 | K39: =P8+P10+P11+K28
I40: QBI-eligible | J40: =J26+J27 | K40: =K26+K27
I41: TI before QBI | J41: =K15+K16 | K41: =P15+P16
I42: Net biz loss | J42: =MIN(0,J26+J27+J28) | K42: =MIN(0,K26+K27+K28)
I43: Net SE | J43: =J26 | K43: =K26
K44: =J44
J45: =IF(Control_Panel!C21="Yes",TRUE,FALSE) | K45: =J45
J46: =Carryovers!F52 | K46: =J46
I49: 1z | L49: =HYPERLINK("#Master_Inputs!A1","✏ open Master_Inputs")
I65: ▸ 7-COMPONENT TAX CALCULATOR | J65: Baseline | K65: Effective | L65: Δ Savings
I66: Dual columns: Baseline (H) vs With Planning (I)
I68: 1. SELF-EMPLOYMENT TAX
I69: SE Tax Label
I70: Net SE Earnings | J70: =J43 | K70: =K43
I71: SE Base (× 0.9235) | J71: =J70*SUMIFS(tblThresholds[Value], tblThresholds[Year], 2026, tblThresholds[FilingStatus], Filing_Status, tblThresholds[Item], "SE_Earnings_Factor") | K71: =K70*SUMIFS(tblThresholds[Value], tblThresholds[Year], 2026, tblThresholds[FilingStatus], Filing_Status, tblThresholds[Item], "SE_Earnings_Factor")
I72: W-2 Wages | J72: =J25 | K72: =K25
I73: Remaining SS Wage Base | J73: =MAX(0,SUMIFS(tblThresholds[Value], tblThresholds[Year], 2026, tblThresholds[FilingStatus], Filing_Status, tblThresholds[Item], "SS_Wage_Base")-J72) | K73: =MAX(0,SUMIFS(tblThresholds[Value], tblThresholds[Year], 2026, tblThresholds[FilingStatus], Filing_Status, tblThresholds[Item], "SS_Wage_Base")-K72)
J74: =MIN(J71,J73) | K74: =MIN(K71,K73)
I75: Social Security Tax (12.4%) | J75: =J74*SUMIFS(tblThresholds[Value], tblThresholds[Year], 2026, tblThresholds[FilingStatus], Filing_Status, tblThresholds[Item], "SS_Rate_Combined") | K75: =K74*SUMIFS(tblThresholds[Value], tblThresholds[Year], 2026, tblThresholds[FilingStatus], Filing_Status, tblThresholds[Item], "SS_Rate_Combined")
I76: Medicare Tax (2.9%) | J76: =J71*SUMIFS(tblThresholds[Value], tblThresholds[Year], 2026, tblThresholds[FilingStatus], Filing_Status, tblThresholds[Item], "Medicare_Rate_Combined") | K76: =K71*SUMIFS(tblThresholds[Value], tblThresholds[Year], 2026, tblThresholds[FilingStatus], Filing_Status, tblThresholds[Item], "Medicare_Rate_Combined")
I77: Addl Medicare (0.9% > threshold) | J77: =MAX(0,(J72+J71-SUMIFS(tblThresholds[Value], tblThresholds[Year], 2026, tblThresholds[FilingStatus], Filing_Status, tblThresholds[Item], "Addl_Medicare_Threshold"))*SUMIFS(tblThresholds[Value], tblThresholds[Year], 2026, tblThresholds[FilingStatus], Filing_Status, tblThresholds[Item], "Addl_Medicare_Rate")) | K77: =MAX(0,(K72+K71-SUMIFS(tblThresholds[Value], tblThresholds[Year], 2026, tblThresholds[FilingStatus], Filing_Status, tblThresholds[Item], "Addl_Medicare_Threshold"))*SUMIFS(tblThresholds[Value], tblThresholds[Year], 2026, tblThresholds[FilingStatus], Filing_Status, tblThresholds[Item], "Addl_Medicare_Rate"))
J78: =-(J75+J76)/2 | K78: =-(K75+K76)/2
I80: TOTAL SE TAX | J80: =J75+J76+J77 | K80: =K75+K76+K77 | L80: =J80-K80
I82: 2. PAYROLL TAX
I83: W-2 Wages | J83: =J25 | K83: =K25
I84: Social Security (6.2%) | J84: =MIN(J83,SUMIFS(tblThresholds[Value], tblThresholds[Year], 2026, tblThresholds[FilingStatus], Filing_Status, tblThresholds[Item], "SS_Wage_Base"))*0.062 | K84: =MIN(K83,SUMIFS(tblThresholds[Value], tblThresholds[Year], 2026, tblThresholds[FilingStatus], Filing_Status, tblThresholds[Item], "SS_Wage_Base"))*0.062
I85: Medicare (1.45%) | J85: =J83*0.0145 | K85: =K83*0.0145
I86: Addl Medicare (0.9% > threshold) | J86: =MAX(0,(J83-SUMIFS(tblThresholds[Value], tblThresholds[Year], 2026, tblThresholds[FilingStatus], Filing_Status, tblThresholds[Item], "Addl_Medicare_Threshold"))*SUMIFS(tblThresholds[Value], tblThresholds[Year], 2026, tblThresholds[FilingStatus], Filing_Status, tblThresholds[Item], "Addl_Medicare_Rate")) | K86: =MAX(0,(K83-SUMIFS(tblThresholds[Value], tblThresholds[Year], 2026, tblThresholds[FilingStatus], Filing_Status, tblThresholds[Item], "Addl_Medicare_Threshold"))*SUMIFS(tblThresholds[Value], tblThresholds[Year], 2026, tblThresholds[FilingStatus], Filing_Status, tblThresholds[Item], "Addl_Medicare_Rate"))
I87: TOTAL PAYROLL TAX | J87: =J84+J85+J86 | K87: =K84+K85+K86 | L87: =J87-K87
I88: Employer Social Security (6.2%) | J88: =J84 | K88: =K84 | L88: =J88-K88
I89: Employer Medicare (1.45%) | J89: =J85 | K89: =K85 | L89: =J89-K89
I91: TOTAL PAYROLL TAX (Employee + Employer) | J91: =J87+J88+J89 | K91: =K87+K88+K89 | L91: =J91-K91
I93: 3. ORDINARY INCOME TAX
I94: Taxable Income | J94: =J37 | K94: =K37
I95: Ordinary Taxable (TI - LTCG - QD) | J95: =MAX(0,J94) | K95: =MAX(0,K94)
I96: Tax (SUMPRODUCT bracket lookup) | J96: {=SUMPRODUCT((tblBrackets_FIT[Year]=2026)*(tblBrackets_FIT[FilingStatus]=Filing_Status)*((J95>tblBrackets_FIT[Upper])*(tblBrackets_FIT[Upper]-tblBrackets_FIT[Lower])+(J95>tblBrackets_FIT[Lower])*(J95<=tblBrackets_FIT[Upper])*(J95-tblBrackets_FIT[Lower]))*tblBrackets_FIT[Rate])} | K96: {=SUMPRODUCT((tblBrackets_FIT[Year]=2026)*(tblBrackets_FIT[FilingStatus]=Filing_Status)*((K95>tblBrackets_FIT[Upper])*(tblBrackets_FIT[Upper]-tblBrackets_FIT[Lower])+(K95>tblBrackets_FIT[Lower])*(K95<=tblBrackets_FIT[Upper])*(K95-tblBrackets_FIT[Lower]))*tblBrackets_FIT[Rate])}
I97: TOTAL ORDINARY TAX | J97: =J96 | K97: =K96 | L97: =J97-K97
I99: 4. CAPITAL GAINS / QUALIFIED DIVIDENDS TAX
I100: LTCG + Qualified Dividends | J100: =J31+J30 | K100: =K31+K30
I101: Sec 1250 Recapture Gain | J101: =J33 | K101: =K33
I102: Stacking Base (Ordinary TI for bracket floor) | J102: =J95 | K102: =K95
I103: Full CG Rate Tax (SUMPRODUCT stack) | J103: {=SUMPRODUCT((Tax_Ref!$B$210:$B$281=2026)*(Tax_Ref!$C$210:$C$281=Filing_Status)*((J102+J100>Tax_Ref!$E$210:$E$281)*(Tax_Ref!$E$210:$E$281-Tax_Ref!$D$210:$D$281)+(J102+J100>Tax_Ref!$D$210:$D$281)*(J102+J100<=Tax_Ref!$E$210:$E$281)*(J102+J100-Tax_Ref!$D$210:$D$281))*Tax_Ref!$F$210:$F$281)} | K103: {=SUMPRODUCT((Tax_Ref!$B$210:$B$281=2026)*(Tax_Ref!$C$210:$C$281=Filing_Status)*((K102+K100>Tax_Ref!$E$210:$E$281)*(Tax_Ref!$E$210:$E$281-Tax_Ref!$D$210:$D$281)+(K102+K100>Tax_Ref!$D$210:$D$281)*(K102+K100<=Tax_Ref!$E$210:$E$281)*(K102+K100-Tax_Ref!$D$210:$D$281))*Tax_Ref!$F$210:$F$281)}
I104: CG Rate Tax on Ordinary only | J104: {=SUMPRODUCT((Tax_Ref!$B$210:$B$281=2026)*(Tax_Ref!$C$210:$C$281=Filing_Status)*((J102>Tax_Ref!$E$210:$E$281)*(Tax_Ref!$E$210:$E$281-Tax_Ref!$D$210:$D$281)+(J102>Tax_Ref!$D$210:$D$281)*(J102<=Tax_Ref!$E$210:$E$281)*(J102-Tax_Ref!$D$210:$D$281))*Tax_Ref!$F$210:$F$281)} | K104: {=SUMPRODUCT((Tax_Ref!$B$210:$B$281=2026)*(Tax_Ref!$C$210:$C$281=Filing_Status)*((K102>Tax_Ref!$E$210:$E$281)*(Tax_Ref!$E$210:$E$281-Tax_Ref!$D$210:$D$281)+(K102>Tax_Ref!$D$210:$D$281)*(K102<=Tax_Ref!$E$210:$E$281)*(K102-Tax_Ref!$D$210:$D$281))*Tax_Ref!$F$210:$F$281)}
I105: Net LTCG/QD Tax | J105: =J103-J104 | K105: =K103-K104
J106: =J33*0.25 | K106: =K33*0.25
I107: TOTAL CAP GAINS TAX | J107: =J105+J106 | K107: =K105+K106 | L107: =J107-K107
I109: 5. NET INVESTMENT INCOME TAX (NIIT)
I110: MAGI | J110: =J38 | K110: =K38
I111: NIIT Threshold | J111: =SUMIFS(tblThresholds[Value], tblThresholds[Year], 2026, tblThresholds[FilingStatus], Filing_Status, tblThresholds[Item], "NIIT_Threshold") | K111: =SUMIFS(tblThresholds[Value], tblThresholds[Year], 2026, tblThresholds[FilingStatus], Filing_Status, tblThresholds[Item], "NIIT_Threshold")
I112: Net Investment Income (NII) | J112: =MAX(0,J39) | K112: =MAX(0,K39)
I113: NIIT Base (lesser of NII or MAGI excess) | J113: =MAX(0,J110-J111) | K113: =MAX(0,K110-K111)
I114: NIIT (3.8%) | J114: =MIN(J112,J113)*SUMIFS(tblThresholds[Value], tblThresholds[Year], 2026, tblThresholds[FilingStatus], Filing_Status, tblThresholds[Item], "NIIT_Rate") | K114: =MIN(K112,K113)*SUMIFS(tblThresholds[Value], tblThresholds[Year], 2026, tblThresholds[FilingStatus], Filing_Status, tblThresholds[Item], "NIIT_Rate") | L114: =J114-K114
I116: 6. QBI DEDUCTION (§199A)
I117: QBI-Eligible Income | J117: =J40 | K117: =K40
I118: 20% of QBI | J118: =MAX(0,J117)*0.2 | K118: =MAX(0,K117)*0.2
I119: 50% of W-2 Wages | J119: =MAX(0,J41)*0.2 | K119: =MAX(0,K41)*0.2
I120: 25% W-2 + 2.5% UBIA | J120: =MAX(J23*0.5, J23*0.25+J44*0.025) | K120: =MAX(K23*0.5, K23*0.25+K44*0.025)
I121: Phase-in applies? | J121: =IF(J41>SUMIFS(tblThresholds[Value], tblThresholds[Year], 2026, tblThresholds[FilingStatus], Filing_Status, tblThresholds[Item], "QBI_Threshold_Start"),"YES","NO") | K121: =IF(K41>SUMIFS(tblThresholds[Value], tblThresholds[Year], 2026, tblThresholds[FilingStatus], Filing_Status, tblThresholds[Item], "QBI_Threshold_Start"),"YES","NO")
I122: QBI DEDUCTION | J122: =IF(AND(J45=TRUE,J41>SUMIFS(tblThresholds[Value], tblThresholds[Year], 2026, tblThresholds[FilingStatus], Filing_Status, tblThresholds[Item], "QBI_Threshold_End")),0,IF(J41<=SUMIFS(tblThresholds[Value], tblThresholds[Year], 2026, tblThresholds[FilingStatus], Filing_Status, tblThresholds[Item], "QBI_Threshold_Start"),MIN(J118,J119),MIN(J118,J119,J120))) | K122: =IF(AND(K45=TRUE,K41>SUMIFS(tblThresholds[Value], tblThresholds[Year], 2026, tblThresholds[FilingStatus], Filing_Status, tblThresholds[Item], "QBI_Threshold_End")),0,IF(K41<=SUMIFS(tblThresholds[Value], tblThresholds[Year], 2026, tblThresholds[FilingStatus], Filing_Status, tblThresholds[Item], "QBI_Threshold_Start"),MIN(K118,K119),MIN(K118,K119,K120))) | L122: =K122-J122
I124: 7. COMBINED TAX SUMMARY
I125: Total Income | J125: =K6+K8+K10+K11+K12 | K125: =P13 | L125: Δ Savings
I126: Ordinary Tax | J126: =J97 | K126: =K97 | L126: =J126-K126
I127: Capital Gains Tax | J127: =J107 | K127: =K107 | L127: =J127-K127
I128: Self-Employment Tax | J128: =J80 | K128: =K80 | L128: =J128-K128
I129: Payroll Tax (Employee + Employer) | J129: =J91 | K129: =K91 | L129: =J129-K129
I130: NIIT | J130: =J114 | K130: =K114 | L130: =J130-K130
...

Sheet Y2027
A1: Y2027 — standalone tax planning sandbox
A2: Strategies: enter Amount + Status below. Committed strategies flow to rollup M column. Push to Master_Inputs when final.
A4: ▸ STRATEGIES
A5: StrategyID | B5: Strategy Name | C5: TargetLine | D5: Amount | E5: Status | F5: Notes | G5: CounterLine | H5: Jeff_Ref_ID | I5: Line | J5: Description | K5: Baseline (Master) | L5: PY? | M5: S1 Override | N5: Strategies | O5: Effective | P5: Eff w/ Strategies | Q5: Drill
A6: STR-001 | B6: S-Corp Wage Optimization | C6: 1z | G6: 8 | H6: STD-008 | I6: 1z | J6: Wages | K6: =SUMIFS(tblMaster_Inputs[Baseline_Amount],tblMaster_Inputs[Year],2027,tblMaster_Inputs[Primary_Line],$I6, tblMaster_Inputs[Activity_Type], "Baseline") | N6: =SUMIFS(tblY2027_Strategies[Amount],tblY2027_Strategies[TargetLine],$I6)-SUMIFS(tblY2027_Strategies[Amount],tblY2027_Strategies[CounterLine],$I6) | O6: =IF(UPPER(L6)="Y",SUMIFS(tblMaster_Inputs[Baseline_Amount],tblMaster_Inputs[Year],2026,tblMaster_Inputs[Primary_Line],"1z"),IF(ISBLANK(M6),K6,M6)) | P6: =O6+N6 | Q6: =HYPERLINK("#Y2027!I49","↗ drill")
A7: STR-002 | B7: HSA Family Max | C7: 10 | H7: STD-001 | I7: 2a | J7: Tax-exempt interest | K7: =SUMIFS(tblMaster_Inputs[Helper_Amount],tblMaster_Inputs[Year],2027,tblMaster_Inputs[Helper_Treatment],"TAX_EXEMPT") | N7: =SUMIFS(tblY2027_Strategies[Amount],tblY2027_Strategies[TargetLine],"2a",tblY2027_Strategies[Status],"Committed") | O7: =IF(UPPER(L7)="Y",SUMIFS(tblMaster_Inputs[Helper_Amount],tblMaster_Inputs[Year],2026,tblMaster_Inputs[Helper_Treatment],"TAX_EXEMPT"),IF(ISBLANK(M7),K7,M7)) | P7: =O7 | Q7: =HYPERLINK("#Y2027!I49","↗ drill")
A8: STR-003 | B8: Charitable Bunching (DAF) | C8: 12 | H8: ADV-002 | I8: 2b | J8: Taxable interest | K8: =SUMIFS(tblMaster_Inputs[Baseline_Amount],tblMaster_Inputs[Year],2027,tblMaster_Inputs[Primary_Line],$I8, tblMaster_Inputs[Activity_Type], "Baseline") | N8: =SUMIFS(tblY2027_Strategies[Amount],tblY2027_Strategies[TargetLine],$I8)-SUMIFS(tblY2027_Strategies[Amount],tblY2027_Strategies[CounterLine],$I8) | O8: =IF(UPPER(L8)="Y",SUMIFS(tblMaster_Inputs[Baseline_Amount],tblMaster_Inputs[Year],2026,tblMaster_Inputs[Primary_Line],"2b"),IF(ISBLANK(M8),K8,M8)) | P8: =O8+N8 | Q8: =HYPERLINK("#Y2027!I49","↗ drill")
A9: STR-004 | B9: SEP-IRA / Solo 401(k) | C9: 8 | H9: STD-001 | I9: 3a | J9: Qualified dividends | K9: =SUMIFS(tblMaster_Inputs[Helper_Amount],tblMaster_Inputs[Year],2027,tblMaster_Inputs[Helper_Treatment],"QUAL_DIV") | N9: =SUMIFS(tblY2027_Strategies[Amount],tblY2027_Strategies[TargetLine],"3a",tblY2027_Strategies[Status],"Committed") | O9: =IF(UPPER(L9)="Y",SUMIFS(tblMaster_Inputs[Helper_Amount],tblMaster_Inputs[Year],2026,tblMaster_Inputs[Helper_Treatment],"QUAL_DIV"),IF(ISBLANK(M9),K9,M9)) | P9: =O9 | Q9: =HYPERLINK("#Y2027!I49","↗ drill")
A10: STR-005 | B10: Cost Seg Study | C10: 8 | H10: STD-012 | I10: 3b | J10: Ordinary dividends | K10: =SUMIFS(tblMaster_Inputs[Baseline_Amount],tblMaster_Inputs[Year],2027,tblMaster_Inputs[Primary_Line],$I10, tblMaster_Inputs[Activity_Type], "Baseline") | N10: =SUMIFS(tblY2027_Strategies[Amount],tblY2027_Strategies[TargetLine],$I10)-SUMIFS(tblY2027_Strategies[Amount],tblY2027_Strategies[CounterLine],$I10) | O10: =IF(UPPER(L10)="Y",SUMIFS(tblMaster_Inputs[Baseline_Amount],tblMaster_Inputs[Year],2026,tblMaster_Inputs[Primary_Line],"3b"),IF(ISBLANK(M10),K10,M10)) | P10: =O10+N10 | Q10: =HYPERLINK("#Y2027!I49","↗ drill")
A11: STR-006 | B11: Roth Conversion | C11: 1z | H11: ADV-004 | I11: 7 | J11: Capital gain/(loss) | K11: =SUMIFS(tblMaster_Inputs[Baseline_Amount],tblMaster_Inputs[Year],2027,tblMaster_Inputs[Primary_Line],$I11, tblMaster_Inputs[Activity_Type], "Baseline") | N11: =SUMIFS(tblY2027_Strategies[Amount],tblY2027_Strategies[TargetLine],$I11)-SUMIFS(tblY2027_Strategies[Amount],tblY2027_Strategies[CounterLine],$I11) | O11: =IF(UPPER(L11)="Y",SUMIFS(tblMaster_Inputs[Baseline_Amount],tblMaster_Inputs[Year],2026,tblMaster_Inputs[Primary_Line],"7"),IF(ISBLANK(M11),K11,M11)) | P11: =O11+N11 | Q11: =HYPERLINK("#Y2027!I49","↗ drill")
A12: STR-007 | B12: Augusta Rule (§280A) | C12: 8 | H12: STD-002 | I12: 8 | J12: Other income (business) | K12: =SUMIFS(tblMaster_Inputs[Baseline_Amount],tblMaster_Inputs[Year],2027,tblMaster_Inputs[Primary_Line],$I12, tblMaster_Inputs[Activity_Type], "Baseline") | N12: =SUMIFS(tblY2027_Strategies[Amount],tblY2027_Strategies[TargetLine],$I12)-SUMIFS(tblY2027_Strategies[Amount],tblY2027_Strategies[CounterLine],$I12) | O12: =IF(UPPER(L12)="Y",SUMIFS(tblMaster_Inputs[Baseline_Amount],tblMaster_Inputs[Year],2026,tblMaster_Inputs[Primary_Line],"8"),IF(ISBLANK(M12),K12,M12)) | P12: =O12+N12 | Q12: =HYPERLINK("#Y2027!I49","↗ drill")
A13: STR-008 | B13: Accountable Plan | C13: 8 | H13: STD-003 | I13: 9 | J13: TOTAL INCOME | K13: =K6+K8+K10+K11+K12 | N13: =N6+N8+N10+N11+N12 | O13: =O6+O8+O10+O11+O12 | P13: =P6+P8+P10+P11+P12 | Q13: =HYPERLINK("#Y2027!I49","↗ drill")
A14: STR-009 | B14: Hire Children | C14: 8 | F14: Child wages reported on child's own return — counter-impact is cross-return, not within this 1040 | G14: 1z | H14: STD-005 | I14: 10 | J14: Adjustments | K14: =SUMIFS(tblMaster_Inputs[Baseline_Amount],tblMaster_Inputs[Year],2027,tblMaster_Inputs[Primary_Line],$I14, tblMaster_Inputs[Activity_Type], "Baseline") | N14: =SUMIFS(tblY2027_Strategies[Amount],tblY2027_Strategies[TargetLine],$I14)-SUMIFS(tblY2027_Strategies[Amount],tblY2027_Strategies[CounterLine],$I14) | O14: =IF(UPPER(L14)="Y",SUMIFS(tblMaster_Inputs[Baseline_Amount],tblMaster_Inputs[Year],2026,tblMaster_Inputs[Primary_Line],"10"),IF(ISBLANK(M14),K14,M14)) | P14: =O14+N14 | Q14: =HYPERLINK("#Y2027!I49","↗ drill")
A15: STR-010 | B15: Entity Restructuring | C15: 8 | G15: 1z | H15: STD-007 | I15: 11 | J15: AGI | K15: =K13+K14 | N15: =N13+N14 | O15: =O13+O14 | P15: =P13+P14 | Q15: =HYPERLINK("#Y2027!I49","↗ drill")
A16: STR-011 | B16: Installment Sale / 1031 | C16: 7 | H16: STD-009 + ADV-006 | I16: 12 | J16: Std/Itemized ded | K16: =SUMIFS(tblMaster_Inputs[Baseline_Amount],tblMaster_Inputs[Year],2027,tblMaster_Inputs[Primary_Line],$I16, tblMaster_Inputs[Activity_Type], "Baseline") | N16: =SUMIFS(tblY2027_Strategies[Amount],tblY2027_Strategies[TargetLine],$I16)-SUMIFS(tblY2027_Strategies[Amount],tblY2027_Strategies[CounterLine],$I16) | O16: =IF(UPPER(L16)="Y",SUMIFS(tblMaster_Inputs[Baseline_Amount],tblMaster_Inputs[Year],2026,tblMaster_Inputs[Primary_Line],"12"),IF(ISBLANK(M16),K16,M16)) | P16: =O16+N16 | Q16: =HYPERLINK("#Y2027!I49","↗ drill")
A17: STR-012 | B17: Bonus Depreciation §168(k) | C17: 8 | H17: STD-012 | I17: 13 | J17: QBI deduction | K17: =SUMIFS(tblMaster_Inputs[Baseline_Amount],tblMaster_Inputs[Year],2027,tblMaster_Inputs[Primary_Line],$I17, tblMaster_Inputs[Activity_Type], "Baseline") | N17: =SUMIFS(tblY2027_Strategies[Amount],tblY2027_Strategies[TargetLine],$I17)-SUMIFS(tblY2027_Strategies[Amount],tblY2027_Strategies[CounterLine],$I17) | O17: =IF(UPPER(L17)="Y",SUMIFS(tblMaster_Inputs[Baseline_Amount],tblMaster_Inputs[Year],2026,tblMaster_Inputs[Primary_Line],"13"),IF(ISBLANK(M17),K17,M17)) | P17: =O17+N17 | Q17: =HYPERLINK("#Y2027!I49","↗ drill")
A18: STR-013 | B18: R&D Credit §41 | C18: 13 | I18: 15 | J18: TAXABLE INCOME | K18: =K15+K16+K17 | N18: =N15+N16+N17 | O18: =O15+O16+O17 | P18: =P15+P16+P17 | Q18: =HYPERLINK("#Y2027!I49","↗ drill")
A19: STR-014 | B19: SALT PTE Election | C19: 12
A20: STR-015 | B20: Timing / Deferral | C20: 8 | H20: STD-006
A22: ▸ TAX IMPACT SUMMARY | I22: Description | J22: Amount | K22: Effective | L22: Used by
A23: Metric | B23: Baseline | C23: Effective | D23: Eff w/ Strat | E23: Savings | I23: Owner W-2 | J23: =SUMIFS(tblMaster_Inputs[Baseline_Amount],tblMaster_Inputs[Year],2027,tblMaster_Inputs[Treatment_Profile],"W2_SCorpOwner", tblMaster_Inputs[Activity_Type], "Baseline") | K23: =J23+SUMIFS(tblY2027_Strategies[Amount],tblY2027_Strategies[TargetLine],"1z")-SUMIFS(tblY2027_Strategies[Amount],tblY2027_Strategies[CounterLine],"1z")
A24: Total Income | B24: =K13 | C24: =O13 | D24: =P13 | E24: =B24-D24 | I24: Third-party W-2 | J24: =SUMIFS(tblMaster_Inputs[Baseline_Amount],tblMaster_Inputs[Year],2027,tblMaster_Inputs[Treatment_Profile],"W2_Employee", tblMaster_Inputs[Activity_Type], "Baseline") | K24: =J24
A25: Taxable Income | B25: =K18 | C25: =O18 | D25: =P18 | E25: =B25-D25 | I25: Total W-2 | J25: =J23+J24 | K25: =K23+K24
A26: Total Tax | B26: =J133 | C26: =J133 | D26: =K133 | E26: =B26-D26 | I26: SE business | J26: =SUMIFS(tblMaster_Inputs[Baseline_Amount],tblMaster_Inputs[Year],2027,tblMaster_Inputs[Bucket],"Business Income",tblMaster_Inputs[SE_Subject],"Yes", tblMaster_Inputs[Activity_Type], "Baseline") | K26: =J26
A27: Effective Rate | B27: =J134 | C27: =J134 | D27: =K134 | E27: =B27-D27 | I27: Active non-SE | J27: =SUMIFS(tblMaster_Inputs[Baseline_Amount],tblMaster_Inputs[Year],2027,tblMaster_Inputs[Bucket],"Business Income",tblMaster_Inputs[SE_Subject],"No",tblMaster_Inputs[NIIT_Class],"Active", tblMaster_Inputs[Activity_Type], "Baseline") | K27: =J27+SUMIFS(tblY2027_Strategies[Amount],tblY2027_Strategies[TargetLine],"8")-SUMIFS(tblY2027_Strategies[Amount],tblY2027_Strategies[CounterLine],"8")
A28: Committed Strategies | B28: =COUNTIF(tblY2027_Strategies[Status],"Committed") | C28: Net Strategy Impact | D28: =SUMIF(tblY2027_Strategies[Status],"Committed",tblY2027_Strategies[Amount]) | I28: Passive business | J28: =SUMIFS(tblMaster_Inputs[Baseline_Amount],tblMaster_Inputs[Year],2027,tblMaster_Inputs[Bucket],"Business Income",tblMaster_Inputs[NIIT_Class],"Passive", tblMaster_Inputs[Activity_Type], "Baseline") | K28: =J28
I29: Tax-exempt int | J29: =SUMIFS(tblMaster_Inputs[Helper_Amount],tblMaster_Inputs[Year],2027,tblMaster_Inputs[Helper_Treatment],"TAX_EXEMPT") | K29: =J29+SUMIFS(tblY2027_Strategies[Amount],tblY2027_Strategies[TargetLine],"2a")-SUMIFS(tblY2027_Strategies[Amount],tblY2027_Strategies[CounterLine],"2a")
I30: Qualified div | J30: =SUMIFS(tblMaster_Inputs[Helper_Amount],tblMaster_Inputs[Year],2027,tblMaster_Inputs[Helper_Treatment],"QUAL_DIV", tblMaster_Inputs[Activity_Type], "Baseline") | K30: =J30
I31: LT cap gains | J31: =SUMIFS(tblMaster_Inputs[Baseline_Amount],tblMaster_Inputs[Year],2027,tblMaster_Inputs[Treatment_Profile],"LTCG_Stock")+SUMIFS(tblMaster_Inputs[Baseline_Amount],tblMaster_Inputs[Year],2027,tblMaster_Inputs[Treatment_Profile],"LTCG_RE")+SUMIFS(tblMaster_Inputs[Baseline_Amount],tblMaster_Inputs[Year],2027,tblMaster_Inputs[Treatment_Profile],"LTCG_K1_Passthrough")+SUMIFS(tblMaster_Inputs[Baseline_Amount],tblMaster_Inputs[Year],2027,tblMaster_Inputs[Treatment_Profile],"Sec1250_Recap", tblMaster_Inputs[Activity_Type], "Baseline") | K31: =J31+SUMIFS(tblY2027_Strategies[Amount],tblY2027_Strategies[TargetLine],"7")-SUMIFS(tblY2027_Strategies[Amount],tblY2027_Strategies[CounterLine],"7")
I32: ST cap gains | J32: =SUMIFS(tblMaster_Inputs[Baseline_Amount],tblMaster_Inputs[Year],2027,tblMaster_Inputs[Treatment_Profile],"STCG_Stock", tblMaster_Inputs[Activity_Type], "Baseline") | K32: =J32
I33: §1250 gain | J33: =SUMIFS(tblMaster_Inputs[Helper_Amount],tblMaster_Inputs[Year],2027,tblMaster_Inputs[Helper_Treatment],"SEC1250", tblMaster_Inputs[Activity_Type], "Baseline") | K33: =J33
I36: Description | J36: Value | K36: Effective | L36: Used by
I37: TI-LTCG-QD-1250 | J37: =K18-J31-J30-J33 | K37: =P18-K31-K30-K33
I38: AGI+tax-exempt | J38: =K15+J29 | K38: =P15+K29
I39: Net inv income | J39: =K8+K10+K11+J28 | K39: =P8+P10+P11+K28
I40: QBI-eligible | J40: =J26+J27 | K40: =K26+K27
I41: TI before QBI | J41: =K15+K16 | K41: =P15+P16
I42: Net biz loss | J42: =MIN(0,J26+J27+J28) | K42: =MIN(0,K26+K27+K28)
I43: Net SE | J43: =J26 | K43: =K26
K44: =J44
J45: =IF(Control_Panel!C21="Yes",TRUE,FALSE) | K45: =J45
J46: =Carryovers!F52 | K46: =J46
I49: 1z | L49: =HYPERLINK("#Master_Inputs!A1","✏ open Master_Inputs")
I65: ▸ 7-COMPONENT TAX CALCULATOR | J65: Baseline | K65: Effective | L65: Δ Savings
I66: Dual columns: Baseline (H) vs With Planning (I)
I68: 1. SELF-EMPLOYMENT TAX
I69: SE Tax Label
I70: Net SE Earnings | J70: =J43 | K70: =K43
I71: SE Base (× 0.9235) | J71: =J70*SUMIFS(tblThresholds[Value], tblThresholds[Year], 2027, tblThresholds[FilingStatus], Filing_Status, tblThresholds[Item], "SE_Earnings_Factor") | K71: =K70*SUMIFS(tblThresholds[Value], tblThresholds[Year], 2027, tblThresholds[FilingStatus], Filing_Status, tblThresholds[Item], "SE_Earnings_Factor")
I72: W-2 Wages | J72: =J25 | K72: =K25
I73: Remaining SS Wage Base | J73: =MAX(0,SUMIFS(tblThresholds[Value], tblThresholds[Year], 2027, tblThresholds[FilingStatus], Filing_Status, tblThresholds[Item], "SS_Wage_Base")-J72) | K73: =MAX(0,SUMIFS(tblThresholds[Value], tblThresholds[Year], 2027, tblThresholds[FilingStatus], Filing_Status, tblThresholds[Item], "SS_Wage_Base")-K72)
J74: =MIN(J71,J73) | K74: =MIN(K71,K73)
I75: Social Security Tax (12.4%) | J75: =J74*SUMIFS(tblThresholds[Value], tblThresholds[Year], 2027, tblThresholds[FilingStatus], Filing_Status, tblThresholds[Item], "SS_Rate_Combined") | K75: =K74*SUMIFS(tblThresholds[Value], tblThresholds[Year], 2027, tblThresholds[FilingStatus], Filing_Status, tblThresholds[Item], "SS_Rate_Combined")
I76: Medicare Tax (2.9%) | J76: =J71*SUMIFS(tblThresholds[Value], tblThresholds[Year], 2027, tblThresholds[FilingStatus], Filing_Status, tblThresholds[Item], "Medicare_Rate_Combined") | K76: =K71*SUMIFS(tblThresholds[Value], tblThresholds[Year], 2027, tblThresholds[FilingStatus], Filing_Status, tblThresholds[Item], "Medicare_Rate_Combined")
I77: Addl Medicare (0.9% > threshold) | J77: =MAX(0,(J72+J71-SUMIFS(tblThresholds[Value], tblThresholds[Year], 2027, tblThresholds[FilingStatus], Filing_Status, tblThresholds[Item], "Addl_Medicare_Threshold"))*SUMIFS(tblThresholds[Value], tblThresholds[Year], 2027, tblThresholds[FilingStatus], Filing_Status, tblThresholds[Item], "Addl_Medicare_Rate")) | K77: =MAX(0,(K72+K71-SUMIFS(tblThresholds[Value], tblThresholds[Year], 2027, tblThresholds[FilingStatus], Filing_Status, tblThresholds[Item], "Addl_Medicare_Threshold"))*SUMIFS(tblThresholds[Value], tblThresholds[Year], 2027, tblThresholds[FilingStatus], Filing_Status, tblThresholds[Item], "Addl_Medicare_Rate"))
J78: =-(J75+J76)/2 | K78: =-(K75+K76)/2
I80: TOTAL SE TAX | J80: =J75+J76+J77 | K80: =K75+K76+K77 | L80: =J80-K80
I82: 2. PAYROLL TAX
I83: W-2 Wages | J83: =J25 | K83: =K25
I84: Social Security (6.2%) | J84: =MIN(J83,SUMIFS(tblThresholds[Value], tblThresholds[Year], 2027, tblThresholds[FilingStatus], Filing_Status, tblThresholds[Item], "SS_Wage_Base"))*0.062 | K84: =MIN(K83,SUMIFS(tblThresholds[Value], tblThresholds[Year], 2027, tblThresholds[FilingStatus], Filing_Status, tblThresholds[Item], "SS_Wage_Base"))*0.062
I85: Medicare (1.45%) | J85: =J83*0.0145 | K85: =K83*0.0145
I86: Addl Medicare (0.9% > threshold) | J86: =MAX(0,(J83-SUMIFS(tblThresholds[Value], tblThresholds[Year], 2027, tblThresholds[FilingStatus], Filing_Status, tblThresholds[Item], "Addl_Medicare_Threshold"))*SUMIFS(tblThresholds[Value], tblThresholds[Year], 2027, tblThresholds[FilingStatus], Filing_Status, tblThresholds[Item], "Addl_Medicare_Rate")) | K86: =MAX(0,(K83-SUMIFS(tblThresholds[Value], tblThresholds[Year], 2027, tblThresholds[FilingStatus], Filing_Status, tblThresholds[Item], "Addl_Medicare_Threshold"))*SUMIFS(tblThresholds[Value], tblThresholds[Year], 2027, tblThresholds[FilingStatus], Filing_Status, tblThresholds[Item], "Addl_Medicare_Rate"))
I87: TOTAL PAYROLL TAX | J87: =J84+J85+J86 | K87: =K84+K85+K86 | L87: =J87-K87
I88: Employer Social Security (6.2%) | J88: =J84 | K88: =K84 | L88: =J88-K88
I89: Employer Medicare (1.45%) | J89: =J85 | K89: =K85 | L89: =J89-K89
I91: TOTAL PAYROLL TAX (Employee + Employer) | J91: =J87+J88+J89 | K91: =K87+K88+K89 | L91: =J91-K91
I93: 3. ORDINARY INCOME TAX
I94: Taxable Income | J94: =J37 | K94: =K37
I95: Ordinary Taxable (TI - LTCG - QD) | J95: =MAX(0,J94) | K95: =MAX(0,K94)
I96: Tax (SUMPRODUCT bracket lookup) | J96: {=SUMPRODUCT((tblBrackets_FIT[Year]=2027)*(tblBrackets_FIT[FilingStatus]=Filing_Status)*((J95>tblBrackets_FIT[Upper])*(tblBrackets_FIT[Upper]-tblBrackets_FIT[Lower])+(J95>tblBrackets_FIT[Lower])*(J95<=tblBrackets_FIT[Upper])*(J95-tblBrackets_FIT[Lower]))*tblBrackets_FIT[Rate])} | K96: {=SUMPRODUCT((tblBrackets_FIT[Year]=2027)*(tblBrackets_FIT[FilingStatus]=Filing_Status)*((K95>tblBrackets_FIT[Upper])*(tblBrackets_FIT[Upper]-tblBrackets_FIT[Lower])+(K95>tblBrackets_FIT[Lower])*(K95<=tblBrackets_FIT[Upper])*(K95-tblBrackets_FIT[Lower]))*tblBrackets_FIT[Rate])}
I97: TOTAL ORDINARY TAX | J97: =J96 | K97: =K96 | L97: =J97-K97
I99: 4. CAPITAL GAINS / QUALIFIED DIVIDENDS TAX
I100: LTCG + Qualified Dividends | J100: =J31+J30 | K100: =K31+K30
I101: Sec 1250 Recapture Gain | J101: =J33 | K101: =K33
I102: Stacking Base (Ordinary TI for bracket floor) | J102: =J95 | K102: =K95
I103: Full CG Rate Tax (SUMPRODUCT stack) | J103: {=SUMPRODUCT((Tax_Ref!$B$210:$B$281=2027)*(Tax_Ref!$C$210:$C$281=Filing_Status)*((J102+J100>Tax_Ref!$E$210:$E$281)*(Tax_Ref!$E$210:$E$281-Tax_Ref!$D$210:$D$281)+(J102+J100>Tax_Ref!$D$210:$D$281)*(J102+J100<=Tax_Ref!$E$210:$E$281)*(J102+J100-Tax_Ref!$D$210:$D$281))*Tax_Ref!$F$210:$F$281)} | K103: {=SUMPRODUCT((Tax_Ref!$B$210:$B$281=2027)*(Tax_Ref!$C$210:$C$281=Filing_Status)*((K102+K100>Tax_Ref!$E$210:$E$281)*(Tax_Ref!$E$210:$E$281-Tax_Ref!$D$210:$D$281)+(K102+K100>Tax_Ref!$D$210:$D$281)*(K102+K100<=Tax_Ref!$E$210:$E$281)*(K102+K100-Tax_Ref!$D$210:$D$281))*Tax_Ref!$F$210:$F$281)}
I104: CG Rate Tax on Ordinary only | J104: {=SUMPRODUCT((Tax_Ref!$B$210:$B$281=2027)*(Tax_Ref!$C$210:$C$281=Filing_Status)*((J102>Tax_Ref!$E$210:$E$281)*(Tax_Ref!$E$210:$E$281-Tax_Ref!$D$210:$D$281)+(J102>Tax_Ref!$D$210:$D$281)*(J102<=Tax_Ref!$E$210:$E$281)*(J102-Tax_Ref!$D$210:$D$281))*Tax_Ref!$F$210:$F$281)} | K104: {=SUMPRODUCT((Tax_Ref!$B$210:$B$281=2027)*(Tax_Ref!$C$210:$C$281=Filing_Status)*((K102>Tax_Ref!$E$210:$E$281)*(Tax_Ref!$E$210:$E$281-Tax_Ref!$D$210:$D$281)+(K102>Tax_Ref!$D$210:$D$281)*(K102<=Tax_Ref!$E$210:$E$281)*(K102-Tax_Ref!$D$210:$D$281))*Tax_Ref!$F$210:$F$281)}
I105: Net LTCG/QD Tax | J105: =J103-J104 | K105: =K103-K104
J106: =J33*0.25 | K106: =K33*0.25
I107: TOTAL CAP GAINS TAX | J107: =J105+J106 | K107: =K105+K106 | L107: =J107-K107
I109: 5. NET INVESTMENT INCOME TAX (NIIT)
I110: MAGI | J110: =J38 | K110: =K38
I111: NIIT Threshold | J111: =SUMIFS(tblThresholds[Value], tblThresholds[Year], 2027, tblThresholds[FilingStatus], Filing_Status, tblThresholds[Item], "NIIT_Threshold") | K111: =SUMIFS(tblThresholds[Value], tblThresholds[Year], 2027, tblThresholds[FilingStatus], Filing_Status, tblThresholds[Item], "NIIT_Threshold")
I112: Net Investment Income (NII) | J112: =MAX(0,J39) | K112: =MAX(0,K39)
I113: NIIT Base (lesser of NII or MAGI excess) | J113: =MAX(0,J110-J111) | K113: =MAX(0,K110-K111)
I114: NIIT (3.8%) | J114: =MIN(J112,J113)*SUMIFS(tblThresholds[Value], tblThresholds[Year], 2027, tblThresholds[FilingStatus], Filing_Status, tblThresholds[Item], "NIIT_Rate") | K114: =MIN(K112,K113)*SUMIFS(tblThresholds[Value], tblThresholds[Year], 2027, tblThresholds[FilingStatus], Filing_Status, tblThresholds[Item], "NIIT_Rate") | L114: =J114-K114
I116: 6. QBI DEDUCTION (§199A)
I117: QBI-Eligible Income | J117: =J40 | K117: =K40
I118: 20% of QBI | J118: =MAX(0,J117)*0.2 | K118: =MAX(0,K117)*0.2
I119: 50% of W-2 Wages | J119: =MAX(0,J41)*0.2 | K119: =MAX(0,K41)*0.2
I120: 25% W-2 + 2.5% UBIA | J120: =MAX(J23*0.5, J23*0.25+J44*0.025) | K120: =MAX(K23*0.5, K23*0.25+K44*0.025)
I121: Phase-in applies? | J121: =IF(J41>SUMIFS(tblThresholds[Value], tblThresholds[Year], 2027, tblThresholds[FilingStatus], Filing_Status, tblThresholds[Item], "QBI_Threshold_Start"),"YES","NO") | K121: =IF(K41>SUMIFS(tblThresholds[Value], tblThresholds[Year], 2027, tblThresholds[FilingStatus], Filing_Status, tblThresholds[Item], "QBI_Threshold_Start"),"YES","NO")
I122: QBI DEDUCTION | J122: =IF(AND(J45=TRUE,J41>SUMIFS(tblThresholds[Value], tblThresholds[Year], 2027, tblThresholds[FilingStatus], Filing_Status, tblThresholds[Item], "QBI_Threshold_End")),0,IF(J41<=SUMIFS(tblThresholds[Value], tblThresholds[Year], 2027, tblThresholds[FilingStatus], Filing_Status, tblThresholds[Item], "QBI_Threshold_Start"),MIN(J118,J119),MIN(J118,J119,J120))) | K122: =IF(AND(K45=TRUE,K41>SUMIFS(tblThresholds[Value], tblThresholds[Year], 2027, tblThresholds[FilingStatus], Filing_Status, tblThresholds[Item], "QBI_Threshold_End")),0,IF(K41<=SUMIFS(tblThresholds[Value], tblThresholds[Year], 2027, tblThresholds[FilingStatus], Filing_Status, tblThresholds[Item], "QBI_Threshold_Start"),MIN(K118,K119),MIN(K118,K119,K120))) | L122: =K122-J122
I124: 7. COMBINED TAX SUMMARY
I125: Total Income | J125: =K6+K8+K10+K11+K12 | K125: =P13 | L125: Δ Savings
I126: Ordinary Tax | J126: =J97 | K126: =K97 | L126: =J126-K126
I127: Capital Gains Tax | J127: =J107 | K127: =K107 | L127: =J127-K127
I128: Self-Employment Tax | J128: =J80 | K128: =K80 | L128: =J128-K128
I129: Payroll Tax (Employee + Employer) | J129: =J91 | K129: =K91 | L129: =J129-K129
I130: NIIT | J130: =J114 | K130: =K114 | L130: =J130-K130
...

Sheet Y2028
A1: Y2028 — standalone tax planning sandbox
A2: Strategies: enter Amount + Status below. Committed strategies flow to rollup M column. Push to Master_Inputs when final.
A4: ▸ STRATEGIES
A5: StrategyID | B5: Strategy Name | C5: TargetLine | D5: Amount | E5: Status | F5: Notes | G5: CounterLine | H5: Jeff_Ref_ID | I5: Line | J5: Description | K5: Baseline (Master) | L5: PY? | M5: S1 Override | N5: Strategies | O5: Effective | P5: Eff w/ Strategies | Q5: Drill
A6: STR-001 | B6: S-Corp Wage Optimization | C6: 1z | G6: 8 | H6: STD-008 | I6: 1z | J6: Wages | K6: =SUMIFS(tblMaster_Inputs[Baseline_Amount],tblMaster_Inputs[Year],2028,tblMaster_Inputs[Primary_Line],$I6, tblMaster_Inputs[Activity_Type], "Baseline") | N6: =SUMIFS(tblY2028_Strategies[Amount],tblY2028_Strategies[TargetLine],$I6)-SUMIFS(tblY2028_Strategies[Amount],tblY2028_Strategies[CounterLine],$I6) | O6: =IF(UPPER(L6)="Y",SUMIFS(tblMaster_Inputs[Baseline_Amount],tblMaster_Inputs[Year],2027,tblMaster_Inputs[Primary_Line],"1z"),IF(ISBLANK(M6),K6,M6)) | P6: =O6+N6 | Q6: =HYPERLINK("#Y2028!I49","↗ drill")
A7: STR-002 | B7: HSA Family Max | C7: 10 | H7: STD-001 | I7: 2a | J7: Tax-exempt interest | K7: =SUMIFS(tblMaster_Inputs[Helper_Amount],tblMaster_Inputs[Year],2028,tblMaster_Inputs[Helper_Treatment],"TAX_EXEMPT") | N7: =SUMIFS(tblY2028_Strategies[Amount],tblY2028_Strategies[TargetLine],"2a",tblY2028_Strategies[Status],"Committed") | O7: =IF(UPPER(L7)="Y",SUMIFS(tblMaster_Inputs[Helper_Amount],tblMaster_Inputs[Year],2027,tblMaster_Inputs[Helper_Treatment],"TAX_EXEMPT"),IF(ISBLANK(M7),K7,M7)) | P7: =O7 | Q7: =HYPERLINK("#Y2028!I49","↗ drill")
A8: STR-003 | B8: Charitable Bunching (DAF) | C8: 12 | H8: ADV-002 | I8: 2b | J8: Taxable interest | K8: =SUMIFS(tblMaster_Inputs[Baseline_Amount],tblMaster_Inputs[Year],2028,tblMaster_Inputs[Primary_Line],$I8, tblMaster_Inputs[Activity_Type], "Baseline") | N8: =SUMIFS(tblY2028_Strategies[Amount],tblY2028_Strategies[TargetLine],$I8)-SUMIFS(tblY2028_Strategies[Amount],tblY2028_Strategies[CounterLine],$I8) | O8: =IF(UPPER(L8)="Y",SUMIFS(tblMaster_Inputs[Baseline_Amount],tblMaster_Inputs[Year],2027,tblMaster_Inputs[Primary_Line],"2b"),IF(ISBLANK(M8),K8,M8)) | P8: =O8+N8 | Q8: =HYPERLINK("#Y2028!I49","↗ drill")
A9: STR-004 | B9: SEP-IRA / Solo 401(k) | C9: 8 | H9: STD-001 | I9: 3a | J9: Qualified dividends | K9: =SUMIFS(tblMaster_Inputs[Helper_Amount],tblMaster_Inputs[Year],2028,tblMaster_Inputs[Helper_Treatment],"QUAL_DIV") | N9: =SUMIFS(tblY2028_Strategies[Amount],tblY2028_Strategies[TargetLine],"3a",tblY2028_Strategies[Status],"Committed") | O9: =IF(UPPER(L9)="Y",SUMIFS(tblMaster_Inputs[Helper_Amount],tblMaster_Inputs[Year],2027,tblMaster_Inputs[Helper_Treatment],"QUAL_DIV"),IF(ISBLANK(M9),K9,M9)) | P9: =O9 | Q9: =HYPERLINK("#Y2028!I49","↗ drill")
A10: STR-005 | B10: Cost Seg Study | C10: 8 | H10: STD-012 | I10: 3b | J10: Ordinary dividends | K10: =SUMIFS(tblMaster_Inputs[Baseline_Amount],tblMaster_Inputs[Year],2028,tblMaster_Inputs[Primary_Line],$I10, tblMaster_Inputs[Activity_Type], "Baseline") | N10: =SUMIFS(tblY2028_Strategies[Amount],tblY2028_Strategies[TargetLine],$I10)-SUMIFS(tblY2028_Strategies[Amount],tblY2028_Strategies[CounterLine],$I10) | O10: =IF(UPPER(L10)="Y",SUMIFS(tblMaster_Inputs[Baseline_Amount],tblMaster_Inputs[Year],2027,tblMaster_Inputs[Primary_Line],"3b"),IF(ISBLANK(M10),K10,M10)) | P10: =O10+N10 | Q10: =HYPERLINK("#Y2028!I49","↗ drill")
A11: STR-006 | B11: Roth Conversion | C11: 1z | H11: ADV-004 | I11: 7 | J11: Capital gain/(loss) | K11: =SUMIFS(tblMaster_Inputs[Baseline_Amount],tblMaster_Inputs[Year],2028,tblMaster_Inputs[Primary_Line],$I11, tblMaster_Inputs[Activity_Type], "Baseline") | N11: =SUMIFS(tblY2028_Strategies[Amount],tblY2028_Strategies[TargetLine],$I11)-SUMIFS(tblY2028_Strategies[Amount],tblY2028_Strategies[CounterLine],$I11) | O11: =IF(UPPER(L11)="Y",SUMIFS(tblMaster_Inputs[Baseline_Amount],tblMaster_Inputs[Year],2027,tblMaster_Inputs[Primary_Line],"7"),IF(ISBLANK(M11),K11,M11)) | P11: =O11+N11 | Q11: =HYPERLINK("#Y2028!I49","↗ drill")
A12: STR-007 | B12: Augusta Rule (§280A) | C12: 8 | H12: STD-002 | I12: 8 | J12: Other income (business) | K12: =SUMIFS(tblMaster_Inputs[Baseline_Amount],tblMaster_Inputs[Year],2028,tblMaster_Inputs[Primary_Line],$I12, tblMaster_Inputs[Activity_Type], "Baseline") | N12: =SUMIFS(tblY2028_Strategies[Amount],tblY2028_Strategies[TargetLine],$I12)-SUMIFS(tblY2028_Strategies[Amount],tblY2028_Strategies[CounterLine],$I12) | O12: =IF(UPPER(L12)="Y",SUMIFS(tblMaster_Inputs[Baseline_Amount],tblMaster_Inputs[Year],2027,tblMaster_Inputs[Primary_Line],"8"),IF(ISBLANK(M12),K12,M12)) | P12: =O12+N12 | Q12: =HYPERLINK("#Y2028!I49","↗ drill")
A13: STR-008 | B13: Accountable Plan | C13: 8 | H13: STD-003 | I13: 9 | J13: TOTAL INCOME | K13: =K6+K8+K10+K11+K12 | N13: =N6+N8+N10+N11+N12 | O13: =O6+O8+O10+O11+O12 | P13: =P6+P8+P10+P11+P12 | Q13: =HYPERLINK("#Y2028!I49","↗ drill")
A14: STR-009 | B14: Hire Children | C14: 8 | F14: Child wages reported on child's own return — counter-impact is cross-return, not within this 1040 | G14: 1z | H14: STD-005 | I14: 10 | J14: Adjustments | K14: =SUMIFS(tblMaster_Inputs[Baseline_Amount],tblMaster_Inputs[Year],2028,tblMaster_Inputs[Primary_Line],$I14, tblMaster_Inputs[Activity_Type], "Baseline") | N14: =SUMIFS(tblY2028_Strategies[Amount],tblY2028_Strategies[TargetLine],$I14)-SUMIFS(tblY2028_Strategies[Amount],tblY2028_Strategies[CounterLine],$I14) | O14: =IF(UPPER(L14)="Y",SUMIFS(tblMaster_Inputs[Baseline_Amount],tblMaster_Inputs[Year],2027,tblMaster_Inputs[Primary_Line],"10"),IF(ISBLANK(M14),K14,M14)) | P14: =O14+N14 | Q14: =HYPERLINK("#Y2028!I49","↗ drill")
A15: STR-010 | B15: Entity Restructuring | C15: 8 | G15: 1z | H15: STD-007 | I15: 11 | J15: AGI | K15: =K13+K14 | N15: =N13+N14 | O15: =O13+O14 | P15: =P13+P14 | Q15: =HYPERLINK("#Y2028!I49","↗ drill")
A16: STR-011 | B16: Installment Sale / 1031 | C16: 7 | H16: STD-009 + ADV-006 | I16: 12 | J16: Std/Itemized ded | K16: =SUMIFS(tblMaster_Inputs[Baseline_Amount],tblMaster_Inputs[Year],2028,tblMaster_Inputs[Primary_Line],$I16, tblMaster_Inputs[Activity_Type], "Baseline") | N16: =SUMIFS(tblY2028_Strategies[Amount],tblY2028_Strategies[TargetLine],$I16)-SUMIFS(tblY2028_Strategies[Amount],tblY2028_Strategies[CounterLine],$I16) | O16: =IF(UPPER(L16)="Y",SUMIFS(tblMaster_Inputs[Baseline_Amount],tblMaster_Inputs[Year],2027,tblMaster_Inputs[Primary_Line],"12"),IF(ISBLANK(M16),K16,M16)) | P16: =O16+N16 | Q16: =HYPERLINK("#Y2028!I49","↗ drill")
A17: STR-012 | B17: Bonus Depreciation §168(k) | C17: 8 | H17: STD-012 | I17: 13 | J17: QBI deduction | K17: =SUMIFS(tblMaster_Inputs[Baseline_Amount],tblMaster_Inputs[Year],2028,tblMaster_Inputs[Primary_Line],$I17, tblMaster_Inputs[Activity_Type], "Baseline") | N17: =SUMIFS(tblY2028_Strategies[Amount],tblY2028_Strategies[TargetLine],$I17)-SUMIFS(tblY2028_Strategies[Amount],tblY2028_Strategies[CounterLine],$I17) | O17: =IF(UPPER(L17)="Y",SUMIFS(tblMaster_Inputs[Baseline_Amount],tblMaster_Inputs[Year],2027,tblMaster_Inputs[Primary_Line],"13"),IF(ISBLANK(M17),K17,M17)) | P17: =O17+N17 | Q17: =HYPERLINK("#Y2028!I49","↗ drill")
A18: STR-013 | B18: R&D Credit §41 | C18: 13 | I18: 15 | J18: TAXABLE INCOME | K18: =K15+K16+K17 | N18: =N15+N16+N17 | O18: =O15+O16+O17 | P18: =P15+P16+P17 | Q18: =HYPERLINK("#Y2028!I49","↗ drill")
A19: STR-014 | B19: SALT PTE Election | C19: 12
A20: STR-015 | B20: Timing / Deferral | C20: 8 | H20: STD-006
A22: ▸ TAX IMPACT SUMMARY | I22: Description | J22: Amount | K22: Effective | L22: Used by
A23: Metric | B23: Baseline | C23: Effective | D23: Eff w/ Strat | E23: Savings | I23: Owner W-2 | J23: =SUMIFS(tblMaster_Inputs[Baseline_Amount],tblMaster_Inputs[Year],2028,tblMaster_Inputs[Treatment_Profile],"W2_SCorpOwner", tblMaster_Inputs[Activity_Type], "Baseline") | K23: =J23+SUMIFS(tblY2028_Strategies[Amount],tblY2028_Strategies[TargetLine],"1z")-SUMIFS(tblY2028_Strategies[Amount],tblY2028_Strategies[CounterLine],"1z")
A24: Total Income | B24: =K13 | C24: =O13 | D24: =P13 | E24: =B24-D24 | I24: Third-party W-2 | J24: =SUMIFS(tblMaster_Inputs[Baseline_Amount],tblMaster_Inputs[Year],2028,tblMaster_Inputs[Treatment_Profile],"W2_Employee", tblMaster_Inputs[Activity_Type], "Baseline") | K24: =J24
A25: Taxable Income | B25: =K18 | C25: =O18 | D25: =P18 | E25: =B25-D25 | I25: Total W-2 | J25: =J23+J24 | K25: =K23+K24
A26: Total Tax | B26: =J133 | C26: =J133 | D26: =K133 | E26: =B26-D26 | I26: SE business | J26: =SUMIFS(tblMaster_Inputs[Baseline_Amount],tblMaster_Inputs[Year],2028,tblMaster_Inputs[Bucket],"Business Income",tblMaster_Inputs[SE_Subject],"Yes", tblMaster_Inputs[Activity_Type], "Baseline") | K26: =J26
A27: Effective Rate | B27: =J134 | C27: =J134 | D27: =K134 | E27: =B27-D27 | I27: Active non-SE | J27: =SUMIFS(tblMaster_Inputs[Baseline_Amount],tblMaster_Inputs[Year],2028,tblMaster_Inputs[Bucket],"Business Income",tblMaster_Inputs[SE_Subject],"No",tblMaster_Inputs[NIIT_Class],"Active", tblMaster_Inputs[Activity_Type], "Baseline") | K27: =J27+SUMIFS(tblY2028_Strategies[Amount],tblY2028_Strategies[TargetLine],"8")-SUMIFS(tblY2028_Strategies[Amount],tblY2028_Strategies[CounterLine],"8")
A28: Committed Strategies | B28: =COUNTIF(tblY2028_Strategies[Status],"Committed") | C28: Net Strategy Impact | D28: =SUMIF(tblY2028_Strategies[Status],"Committed",tblY2028_Strategies[Amount]) | I28: Passive business | J28: =SUMIFS(tblMaster_Inputs[Baseline_Amount],tblMaster_Inputs[Year],2028,tblMaster_Inputs[Bucket],"Business Income",tblMaster_Inputs[NIIT_Class],"Passive", tblMaster_Inputs[Activity_Type], "Baseline") | K28: =J28
I29: Tax-exempt int | J29: =SUMIFS(tblMaster_Inputs[Helper_Amount],tblMaster_Inputs[Year],2028,tblMaster_Inputs[Helper_Treatment],"TAX_EXEMPT") | K29: =J29+SUMIFS(tblY2028_Strategies[Amount],tblY2028_Strategies[TargetLine],"2a")-SUMIFS(tblY2028_Strategies[Amount],tblY2028_Strategies[CounterLine],"2a")
I30: Qualified div | J30: =SUMIFS(tblMaster_Inputs[Helper_Amount],tblMaster_Inputs[Year],2028,tblMaster_Inputs[Helper_Treatment],"QUAL_DIV", tblMaster_Inputs[Activity_Type], "Baseline") | K30: =J30
I31: LT cap gains | J31: =SUMIFS(tblMaster_Inputs[Baseline_Amount],tblMaster_Inputs[Year],2028,tblMaster_Inputs[Treatment_Profile],"LTCG_Stock")+SUMIFS(tblMaster_Inputs[Baseline_Amount],tblMaster_Inputs[Year],2028,tblMaster_Inputs[Treatment_Profile],"LTCG_RE")+SUMIFS(tblMaster_Inputs[Baseline_Amount],tblMaster_Inputs[Year],2028,tblMaster_Inputs[Treatment_Profile],"LTCG_K1_Passthrough")+SUMIFS(tblMaster_Inputs[Baseline_Amount],tblMaster_Inputs[Year],2028,tblMaster_Inputs[Treatment_Profile],"Sec1250_Recap", tblMaster_Inputs[Activity_Type], "Baseline") | K31: =J31+SUMIFS(tblY2028_Strategies[Amount],tblY2028_Strategies[TargetLine],"7")-SUMIFS(tblY2028_Strategies[Amount],tblY2028_Strategies[CounterLine],"7")
I32: ST cap gains | J32: =SUMIFS(tblMaster_Inputs[Baseline_Amount],tblMaster_Inputs[Year],2028,tblMaster_Inputs[Treatment_Profile],"STCG_Stock", tblMaster_Inputs[Activity_Type], "Baseline") | K32: =J32
I33: §1250 gain | J33: =SUMIFS(tblMaster_Inputs[Helper_Amount],tblMaster_Inputs[Year],2028,tblMaster_Inputs[Helper_Treatment],"SEC1250", tblMaster_Inputs[Activity_Type], "Baseline") | K33: =J33
I36: Description | J36: Value | K36: Effective | L36: Used by
I37: TI-LTCG-QD-1250 | J37: =K18-J31-J30-J33 | K37: =P18-K31-K30-K33
I38: AGI+tax-exempt | J38: =K15+J29 | K38: =P15+K29
I39: Net inv income | J39: =K8+K10+K11+J28 | K39: =P8+P10+P11+K28
I40: QBI-eligible | J40: =J26+J27 | K40: =K26+K27
I41: TI before QBI | J41: =K15+K16 | K41: =P15+P16
I42: Net biz loss | J42: =MIN(0,J26+J27+J28) | K42: =MIN(0,K26+K27+K28)
I43: Net SE | J43: =J26 | K43: =K26
K44: =J44
J45: =IF(Control_Panel!C21="Yes",TRUE,FALSE) | K45: =J45
J46: =Carryovers!F52 | K46: =J46
I49: 1z | L49: =HYPERLINK("#Master_Inputs!A1","✏ open Master_Inputs")
I65: ▸ 7-COMPONENT TAX CALCULATOR | J65: Baseline | K65: Effective | L65: Δ Savings
I66: Dual columns: Baseline (H) vs With Planning (I)
I68: 1. SELF-EMPLOYMENT TAX
I69: SE Tax Label
I70: Net SE Earnings | J70: =J43 | K70: =K43
I71: SE Base (× 0.9235) | J71: =J70*SUMIFS(tblThresholds[Value], tblThresholds[Year], 2028, tblThresholds[FilingStatus], Filing_Status, tblThresholds[Item], "SE_Earnings_Factor") | K71: =K70*SUMIFS(tblThresholds[Value], tblThresholds[Year], 2028, tblThresholds[FilingStatus], Filing_Status, tblThresholds[Item], "SE_Earnings_Factor")
I72: W-2 Wages | J72: =J25 | K72: =K25
I73: Remaining SS Wage Base | J73: =MAX(0,SUMIFS(tblThresholds[Value], tblThresholds[Year], 2028, tblThresholds[FilingStatus], Filing_Status, tblThresholds[Item], "SS_Wage_Base")-J72) | K73: =MAX(0,SUMIFS(tblThresholds[Value], tblThresholds[Year], 2028, tblThresholds[FilingStatus], Filing_Status, tblThresholds[Item], "SS_Wage_Base")-K72)
J74: =MIN(J71,J73) | K74: =MIN(K71,K73)
I75: Social Security Tax (12.4%) | J75: =J74*SUMIFS(tblThresholds[Value], tblThresholds[Year], 2028, tblThresholds[FilingStatus], Filing_Status, tblThresholds[Item], "SS_Rate_Combined") | K75: =K74*SUMIFS(tblThresholds[Value], tblThresholds[Year], 2028, tblThresholds[FilingStatus], Filing_Status, tblThresholds[Item], "SS_Rate_Combined")
I76: Medicare Tax (2.9%) | J76: =J71*SUMIFS(tblThresholds[Value], tblThresholds[Year], 2028, tblThresholds[FilingStatus], Filing_Status, tblThresholds[Item], "Medicare_Rate_Combined") | K76: =K71*SUMIFS(tblThresholds[Value], tblThresholds[Year], 2028, tblThresholds[FilingStatus], Filing_Status, tblThresholds[Item], "Medicare_Rate_Combined")
I77: Addl Medicare (0.9% > threshold) | J77: =MAX(0,(J72+J71-SUMIFS(tblThresholds[Value], tblThresholds[Year], 2028, tblThresholds[FilingStatus], Filing_Status, tblThresholds[Item], "Addl_Medicare_Threshold"))*SUMIFS(tblThresholds[Value], tblThresholds[Year], 2028, tblThresholds[FilingStatus], Filing_Status, tblThresholds[Item], "Addl_Medicare_Rate")) | K77: =MAX(0,(K72+K71-SUMIFS(tblThresholds[Value], tblThresholds[Year], 2028, tblThresholds[FilingStatus], Filing_Status, tblThresholds[Item], "Addl_Medicare_Threshold"))*SUMIFS(tblThresholds[Value], tblThresholds[Year], 2028, tblThresholds[FilingStatus], Filing_Status, tblThresholds[Item], "Addl_Medicare_Rate"))
J78: =-(J75+J76)/2 | K78: =-(K75+K76)/2
I80: TOTAL SE TAX | J80: =J75+J76+J77 | K80: =K75+K76+K77 | L80: =J80-K80
I82: 2. PAYROLL TAX
I83: W-2 Wages | J83: =J25 | K83: =K25
I84: Social Security (6.2%) | J84: =MIN(J83,SUMIFS(tblThresholds[Value], tblThresholds[Year], 2028, tblThresholds[FilingStatus], Filing_Status, tblThresholds[Item], "SS_Wage_Base"))*0.062 | K84: =MIN(K83,SUMIFS(tblThresholds[Value], tblThresholds[Year], 2028, tblThresholds[FilingStatus], Filing_Status, tblThresholds[Item], "SS_Wage_Base"))*0.062
I85: Medicare (1.45%) | J85: =J83*0.0145 | K85: =K83*0.0145
I86: Addl Medicare (0.9% > threshold) | J86: =MAX(0,(J83-SUMIFS(tblThresholds[Value], tblThresholds[Year], 2028, tblThresholds[FilingStatus], Filing_Status, tblThresholds[Item], "Addl_Medicare_Threshold"))*SUMIFS(tblThresholds[Value], tblThresholds[Year], 2028, tblThresholds[FilingStatus], Filing_Status, tblThresholds[Item], "Addl_Medicare_Rate")) | K86: =MAX(0,(K83-SUMIFS(tblThresholds[Value], tblThresholds[Year], 2028, tblThresholds[FilingStatus], Filing_Status, tblThresholds[Item], "Addl_Medicare_Threshold"))*SUMIFS(tblThresholds[Value], tblThresholds[Year], 2028, tblThresholds[FilingStatus], Filing_Status, tblThresholds[Item], "Addl_Medicare_Rate"))
I87: TOTAL PAYROLL TAX | J87: =J84+J85+J86 | K87: =K84+K85+K86 | L87: =J87-K87
I88: Employer Social Security (6.2%) | J88: =J84 | K88: =K84 | L88: =J88-K88
I89: Employer Medicare (1.45%) | J89: =J85 | K89: =K85 | L89: =J89-K89
I91: TOTAL PAYROLL TAX (Employee + Employer) | J91: =J87+J88+J89 | K91: =K87+K88+K89 | L91: =J91-K91
I93: 3. ORDINARY INCOME TAX
I94: Taxable Income | J94: =J37 | K94: =K37
I95: Ordinary Taxable (TI - LTCG - QD) | J95: =MAX(0,J94) | K95: =MAX(0,K94)
I96: Tax (SUMPRODUCT bracket lookup) | J96: {=SUMPRODUCT((tblBrackets_FIT[Year]=2028)*(tblBrackets_FIT[FilingStatus]=Filing_Status)*((J95>tblBrackets_FIT[Upper])*(tblBrackets_FIT[Upper]-tblBrackets_FIT[Lower])+(J95>tblBrackets_FIT[Lower])*(J95<=tblBrackets_FIT[Upper])*(J95-tblBrackets_FIT[Lower]))*tblBrackets_FIT[Rate])} | K96: {=SUMPRODUCT((tblBrackets_FIT[Year]=2028)*(tblBrackets_FIT[FilingStatus]=Filing_Status)*((K95>tblBrackets_FIT[Upper])*(tblBrackets_FIT[Upper]-tblBrackets_FIT[Lower])+(K95>tblBrackets_FIT[Lower])*(K95<=tblBrackets_FIT[Upper])*(K95-tblBrackets_FIT[Lower]))*tblBrackets_FIT[Rate])}
I97: TOTAL ORDINARY TAX | J97: =J96 | K97: =K96 | L97: =J97-K97
I99: 4. CAPITAL GAINS / QUALIFIED DIVIDENDS TAX
I100: LTCG + Qualified Dividends | J100: =J31+J30 | K100: =K31+K30
I101: Sec 1250 Recapture Gain | J101: =J33 | K101: =K33
I102: Stacking Base (Ordinary TI for bracket floor) | J102: =J95 | K102: =K95
I103: Full CG Rate Tax (SUMPRODUCT stack) | J103: {=SUMPRODUCT((Tax_Ref!$B$210:$B$281=2028)*(Tax_Ref!$C$210:$C$281=Filing_Status)*((J102+J100>Tax_Ref!$E$210:$E$281)*(Tax_Ref!$E$210:$E$281-Tax_Ref!$D$210:$D$281)+(J102+J100>Tax_Ref!$D$210:$D$281)*(J102+J100<=Tax_Ref!$E$210:$E$281)*(J102+J100-Tax_Ref!$D$210:$D$281))*Tax_Ref!$F$210:$F$281)} | K103: {=SUMPRODUCT((Tax_Ref!$B$210:$B$281=2028)*(Tax_Ref!$C$210:$C$281=Filing_Status)*((K102+K100>Tax_Ref!$E$210:$E$281)*(Tax_Ref!$E$210:$E$281-Tax_Ref!$D$210:$D$281)+(K102+K100>Tax_Ref!$D$210:$D$281)*(K102+K100<=Tax_Ref!$E$210:$E$281)*(K102+K100-Tax_Ref!$D$210:$D$281))*Tax_Ref!$F$210:$F$281)}
I104: CG Rate Tax on Ordinary only | J104: {=SUMPRODUCT((Tax_Ref!$B$210:$B$281=2028)*(Tax_Ref!$C$210:$C$281=Filing_Status)*((J102>Tax_Ref!$E$210:$E$281)*(Tax_Ref!$E$210:$E$281-Tax_Ref!$D$210:$D$281)+(J102>Tax_Ref!$D$210:$D$281)*(J102<=Tax_Ref!$E$210:$E$281)*(J102-Tax_Ref!$D$210:$D$281))*Tax_Ref!$F$210:$F$281)} | K104: {=SUMPRODUCT((Tax_Ref!$B$210:$B$281=2028)*(Tax_Ref!$C$210:$C$281=Filing_Status)*((K102>Tax_Ref!$E$210:$E$281)*(Tax_Ref!$E$210:$E$281-Tax_Ref!$D$210:$D$281)+(K102>Tax_Ref!$D$210:$D$281)*(K102<=Tax_Ref!$E$210:$E$281)*(K102-Tax_Ref!$D$210:$D$281))*Tax_Ref!$F$210:$F$281)}
I105: Net LTCG/QD Tax | J105: =J103-J104 | K105: =K103-K104
J106: =J33*0.25 | K106: =K33*0.25
I107: TOTAL CAP GAINS TAX | J107: =J105+J106 | K107: =K105+K106 | L107: =J107-K107
I109: 5. NET INVESTMENT INCOME TAX (NIIT)
I110: MAGI | J110: =J38 | K110: =K38
I111: NIIT Threshold | J111: =SUMIFS(tblThresholds[Value], tblThresholds[Year], 2028, tblThresholds[FilingStatus], Filing_Status, tblThresholds[Item], "NIIT_Threshold") | K111: =SUMIFS(tblThresholds[Value], tblThresholds[Year], 2028, tblThresholds[FilingStatus], Filing_Status, tblThresholds[Item], "NIIT_Threshold")
I112: Net Investment Income (NII) | J112: =MAX(0,J39) | K112: =MAX(0,K39)
I113: NIIT Base (lesser of NII or MAGI excess) | J113: =MAX(0,J110-J111) | K113: =MAX(0,K110-K111)
I114: NIIT (3.8%) | J114: =MIN(J112,J113)*SUMIFS(tblThresholds[Value], tblThresholds[Year], 2028, tblThresholds[FilingStatus], Filing_Status, tblThresholds[Item], "NIIT_Rate") | K114: =MIN(K112,K113)*SUMIFS(tblThresholds[Value], tblThresholds[Year], 2028, tblThresholds[FilingStatus], Filing_Status, tblThresholds[Item], "NIIT_Rate") | L114: =J114-K114
I116: 6. QBI DEDUCTION (§199A)
I117: QBI-Eligible Income | J117: =J40 | K117: =K40
I118: 20% of QBI | J118: =MAX(0,J117)*0.2 | K118: =MAX(0,K117)*0.2
I119: 50% of W-2 Wages | J119: =MAX(0,J41)*0.2 | K119: =MAX(0,K41)*0.2
I120: 25% W-2 + 2.5% UBIA | J120: =MAX(J23*0.5, J23*0.25+J44*0.025) | K120: =MAX(K23*0.5, K23*0.25+K44*0.025)
I121: Phase-in applies? | J121: =IF(J41>SUMIFS(tblThresholds[Value], tblThresholds[Year], 2028, tblThresholds[FilingStatus], Filing_Status, tblThresholds[Item], "QBI_Threshold_Start"),"YES","NO") | K121: =IF(K41>SUMIFS(tblThresholds[Value], tblThresholds[Year], 2028, tblThresholds[FilingStatus], Filing_Status, tblThresholds[Item], "QBI_Threshold_Start"),"YES","NO")
I122: QBI DEDUCTION | J122: =IF(AND(J45=TRUE,J41>SUMIFS(tblThresholds[Value], tblThresholds[Year], 2028, tblThresholds[FilingStatus], Filing_Status, tblThresholds[Item], "QBI_Threshold_End")),0,IF(J41<=SUMIFS(tblThresholds[Value], tblThresholds[Year], 2028, tblThresholds[FilingStatus], Filing_Status, tblThresholds[Item], "QBI_Threshold_Start"),MIN(J118,J119),MIN(J118,J119,J120))) | K122: =IF(AND(K45=TRUE,K41>SUMIFS(tblThresholds[Value], tblThresholds[Year], 2028, tblThresholds[FilingStatus], Filing_Status, tblThresholds[Item], "QBI_Threshold_End")),0,IF(K41<=SUMIFS(tblThresholds[Value], tblThresholds[Year], 2028, tblThresholds[FilingStatus], Filing_Status, tblThresholds[Item], "QBI_Threshold_Start"),MIN(K118,K119),MIN(K118,K119,K120))) | L122: =K122-J122
I124: 7. COMBINED TAX SUMMARY
I125: Total Income | J125: =K6+K8+K10+K11+K12 | K125: =P13 | L125: Δ Savings
I126: Ordinary Tax | J126: =J97 | K126: =K97 | L126: =J126-K126
I127: Capital Gains Tax | J127: =J107 | K127: =K107 | L127: =J127-K127
I128: Self-Employment Tax | J128: =J80 | K128: =K80 | L128: =J128-K128
I129: Payroll Tax (Employee + Employer) | J129: =J91 | K129: =K91 | L129: =J129-K129
I130: NIIT | J130: =J114 | K130: =K114 | L130: =J130-K130
...

Sheet Pivot_Summary
A1: PIVOT — SUMMARY (most condensed; multi-year baseline from Master_Inputs)
A2: Pure baseline aggregation. No overrides, no strategies. Year sheets handle those locally.
I3: Strategy | O3: Effective
A4: Line | B4: Description | C4: 2023 | D4: 2024 | E4: 2025 | F4: 2026 | G4: 2027 | H4: 2028 | I4: 2023 | J4: 2024 | K4: 2025 | L4: 2026 | M4: 2027 | N4: 2028 | O4: 2023 | P4: 2024 | Q4: 2025 | R4: 2026 | S4: 2027 | T4: 2028
A5: 1z | B5: Wages | C5: =SUMIFS(tblMaster_Inputs[Baseline_Amount], tblMaster_Inputs[Year], 2023, tblMaster_Inputs[Primary_Line], "1z", tblMaster_Inputs[Activity_Type], "Baseline") | D5: =SUMIFS(tblMaster_Inputs[Baseline_Amount], tblMaster_Inputs[Year], 2024, tblMaster_Inputs[Primary_Line], "1z", tblMaster_Inputs[Activity_Type], "Baseline") | E5: =SUMIFS(tblMaster_Inputs[Baseline_Amount], tblMaster_Inputs[Year], 2025, tblMaster_Inputs[Primary_Line], "1z", tblMaster_Inputs[Activity_Type], "Baseline") | F5: =SUMIFS(tblMaster_Inputs[Baseline_Amount], tblMaster_Inputs[Year], 2026, tblMaster_Inputs[Primary_Line], "1z", tblMaster_Inputs[Activity_Type], "Baseline") | G5: =SUMIFS(tblMaster_Inputs[Baseline_Amount], tblMaster_Inputs[Year], 2027, tblMaster_Inputs[Primary_Line], "1z", tblMaster_Inputs[Activity_Type], "Baseline") | H5: =SUMIFS(tblMaster_Inputs[Baseline_Amount], tblMaster_Inputs[Year], 2028, tblMaster_Inputs[Primary_Line], "1z", tblMaster_Inputs[Activity_Type], "Baseline") | I5: =SUMIFS(tblMaster_Inputs[Baseline_Amount], tblMaster_Inputs[Year], 2023, tblMaster_Inputs[Primary_Line], "1z", tblMaster_Inputs[Activity_Type], "Strategy") | J5: =SUMIFS(tblMaster_Inputs[Baseline_Amount], tblMaster_Inputs[Year], 2024, tblMaster_Inputs[Primary_Line], "1z", tblMaster_Inputs[Activity_Type], "Strategy") | K5: =SUMIFS(tblMaster_Inputs[Baseline_Amount], tblMaster_Inputs[Year], 2025, tblMaster_Inputs[Primary_Line], "1z", tblMaster_Inputs[Activity_Type], "Strategy") | L5: =SUMIFS(tblMaster_Inputs[Baseline_Amount], tblMaster_Inputs[Year], 2026, tblMaster_Inputs[Primary_Line], "1z", tblMaster_Inputs[Activity_Type], "Strategy") | M5: =SUMIFS(tblMaster_Inputs[Baseline_Amount], tblMaster_Inputs[Year], 2027, tblMaster_Inputs[Primary_Line], "1z", tblMaster_Inputs[Activity_Type], "Strategy") | N5: =SUMIFS(tblMaster_Inputs[Baseline_Amount], tblMaster_Inputs[Year], 2028, tblMaster_Inputs[Primary_Line], "1z", tblMaster_Inputs[Activity_Type], "Strategy") | O5: =C5+I5 | P5: =D5+J5 | Q5: =E5+K5 | R5: =F5+L5 | S5: =G5+M5 | T5: =H5+N5
A6: 2 | B6: Interest (taxable, tax-exempt info on Detailed) | C6: =SUMIFS(tblMaster_Inputs[Baseline_Amount], tblMaster_Inputs[Year], 2023, tblMaster_Inputs[Primary_Line], "2b", tblMaster_Inputs[Activity_Type], "Baseline") | D6: =SUMIFS(tblMaster_Inputs[Baseline_Amount], tblMaster_Inputs[Year], 2024, tblMaster_Inputs[Primary_Line], "2b", tblMaster_Inputs[Activity_Type], "Baseline") | E6: =SUMIFS(tblMaster_Inputs[Baseline_Amount], tblMaster_Inputs[Year], 2025, tblMaster_Inputs[Primary_Line], "2b", tblMaster_Inputs[Activity_Type], "Baseline") | F6: =SUMIFS(tblMaster_Inputs[Baseline_Amount], tblMaster_Inputs[Year], 2026, tblMaster_Inputs[Primary_Line], "2b", tblMaster_Inputs[Activity_Type], "Baseline") | G6: =SUMIFS(tblMaster_Inputs[Baseline_Amount], tblMaster_Inputs[Year], 2027, tblMaster_Inputs[Primary_Line], "2b", tblMaster_Inputs[Activity_Type], "Baseline") | H6: =SUMIFS(tblMaster_Inputs[Baseline_Amount], tblMaster_Inputs[Year], 2028, tblMaster_Inputs[Primary_Line], "2b", tblMaster_Inputs[Activity_Type], "Baseline") | I6: =SUMIFS(tblMaster_Inputs[Baseline_Amount], tblMaster_Inputs[Year], 2023, tblMaster_Inputs[Primary_Line], "2b", tblMaster_Inputs[Activity_Type], "Strategy") | J6: =SUMIFS(tblMaster_Inputs[Baseline_Amount], tblMaster_Inputs[Year], 2024, tblMaster_Inputs[Primary_Line], "2b", tblMaster_Inputs[Activity_Type], "Strategy") | K6: =SUMIFS(tblMaster_Inputs[Baseline_Amount], tblMaster_Inputs[Year], 2025, tblMaster_Inputs[Primary_Line], "2b", tblMaster_Inputs[Activity_Type], "Strategy") | L6: =SUMIFS(tblMaster_Inputs[Baseline_Amount], tblMaster_Inputs[Year], 2026, tblMaster_Inputs[Primary_Line], "2b", tblMaster_Inputs[Activity_Type], "Strategy") | M6: =SUMIFS(tblMaster_Inputs[Baseline_Amount], tblMaster_Inputs[Year], 2027, tblMaster_Inputs[Primary_Line], "2b", tblMaster_Inputs[Activity_Type], "Strategy") | N6: =SUMIFS(tblMaster_Inputs[Baseline_Amount], tblMaster_Inputs[Year], 2028, tblMaster_Inputs[Primary_Line], "2b", tblMaster_Inputs[Activity_Type], "Strategy") | O6: =C6+I6 | P6: =D6+J6 | Q6: =E6+K6 | R6: =F6+L6 | S6: =G6+M6 | T6: =H6+N6
A7: 3 | B7: Dividends (qualified info on Detailed) | C7: =SUMIFS(tblMaster_Inputs[Baseline_Amount], tblMaster_Inputs[Year], 2023, tblMaster_Inputs[Primary_Line], "3b", tblMaster_Inputs[Activity_Type], "Baseline") | D7: =SUMIFS(tblMaster_Inputs[Baseline_Amount], tblMaster_Inputs[Year], 2024, tblMaster_Inputs[Primary_Line], "3b", tblMaster_Inputs[Activity_Type], "Baseline") | E7: =SUMIFS(tblMaster_Inputs[Baseline_Amount], tblMaster_Inputs[Year], 2025, tblMaster_Inputs[Primary_Line], "3b", tblMaster_Inputs[Activity_Type], "Baseline") | F7: =SUMIFS(tblMaster_Inputs[Baseline_Amount], tblMaster_Inputs[Year], 2026, tblMaster_Inputs[Primary_Line], "3b", tblMaster_Inputs[Activity_Type], "Baseline") | G7: =SUMIFS(tblMaster_Inputs[Baseline_Amount], tblMaster_Inputs[Year], 2027, tblMaster_Inputs[Primary_Line], "3b", tblMaster_Inputs[Activity_Type], "Baseline") | H7: =SUMIFS(tblMaster_Inputs[Baseline_Amount], tblMaster_Inputs[Year], 2028, tblMaster_Inputs[Primary_Line], "3b", tblMaster_Inputs[Activity_Type], "Baseline") | I7: =SUMIFS(tblMaster_Inputs[Baseline_Amount], tblMaster_Inputs[Year], 2023, tblMaster_Inputs[Primary_Line], "3b", tblMaster_Inputs[Activity_Type], "Strategy") | J7: =SUMIFS(tblMaster_Inputs[Baseline_Amount], tblMaster_Inputs[Year], 2024, tblMaster_Inputs[Primary_Line], "3b", tblMaster_Inputs[Activity_Type], "Strategy") | K7: =SUMIFS(tblMaster_Inputs[Baseline_Amount], tblMaster_Inputs[Year], 2025, tblMaster_Inputs[Primary_Line], "3b", tblMaster_Inputs[Activity_Type], "Strategy") | L7: =SUMIFS(tblMaster_Inputs[Baseline_Amount], tblMaster_Inputs[Year], 2026, tblMaster_Inputs[Primary_Line], "3b", tblMaster_Inputs[Activity_Type], "Strategy") | M7: =SUMIFS(tblMaster_Inputs[Baseline_Amount], tblMaster_Inputs[Year], 2027, tblMaster_Inputs[Primary_Line], "3b", tblMaster_Inputs[Activity_Type], "Strategy") | N7: =SUMIFS(tblMaster_Inputs[Baseline_Amount], tblMaster_Inputs[Year], 2028, tblMaster_Inputs[Primary_Line], "3b", tblMaster_Inputs[Activity_Type], "Strategy") | O7: =C7+I7 | P7: =D7+J7 | Q7: =E7+K7 | R7: =F7+L7 | S7: =G7+M7 | T7: =H7+N7
A8: 7 | B8: Capital gain or (loss) | C8: =SUMIFS(tblMaster_Inputs[Baseline_Amount], tblMaster_Inputs[Year], 2023, tblMaster_Inputs[Primary_Line], "7", tblMaster_Inputs[Activity_Type], "Baseline") | D8: =SUMIFS(tblMaster_Inputs[Baseline_Amount], tblMaster_Inputs[Year], 2024, tblMaster_Inputs[Primary_Line], "7", tblMaster_Inputs[Activity_Type], "Baseline") | E8: =SUMIFS(tblMaster_Inputs[Baseline_Amount], tblMaster_Inputs[Year], 2025, tblMaster_Inputs[Primary_Line], "7", tblMaster_Inputs[Activity_Type], "Baseline") | F8: =SUMIFS(tblMaster_Inputs[Baseline_Amount], tblMaster_Inputs[Year], 2026, tblMaster_Inputs[Primary_Line], "7", tblMaster_Inputs[Activity_Type], "Baseline") | G8: =SUMIFS(tblMaster_Inputs[Baseline_Amount], tblMaster_Inputs[Year], 2027, tblMaster_Inputs[Primary_Line], "7", tblMaster_Inputs[Activity_Type], "Baseline") | H8: =SUMIFS(tblMaster_Inputs[Baseline_Amount], tblMaster_Inputs[Year], 2028, tblMaster_Inputs[Primary_Line], "7", tblMaster_Inputs[Activity_Type], "Baseline") | I8: =SUMIFS(tblMaster_Inputs[Baseline_Amount], tblMaster_Inputs[Year], 2023, tblMaster_Inputs[Primary_Line], "7", tblMaster_Inputs[Activity_Type], "Strategy") | J8: =SUMIFS(tblMaster_Inputs[Baseline_Amount], tblMaster_Inputs[Year], 2024, tblMaster_Inputs[Primary_Line], "7", tblMaster_Inputs[Activity_Type], "Strategy") | K8: =SUMIFS(tblMaster_Inputs[Baseline_Amount], tblMaster_Inputs[Year], 2025, tblMaster_Inputs[Primary_Line], "7", tblMaster_Inputs[Activity_Type], "Strategy") | L8: =SUMIFS(tblMaster_Inputs[Baseline_Amount], tblMaster_Inputs[Year], 2026, tblMaster_Inputs[Primary_Line], "7", tblMaster_Inputs[Activity_Type], "Strategy") | M8: =SUMIFS(tblMaster_Inputs[Baseline_Amount], tblMaster_Inputs[Year], 2027, tblMaster_Inputs[Primary_Line], "7", tblMaster_Inputs[Activity_Type], "Strategy") | N8: =SUMIFS(tblMaster_Inputs[Baseline_Amount], tblMaster_Inputs[Year], 2028, tblMaster_Inputs[Primary_Line], "7", tblMaster_Inputs[Activity_Type], "Strategy") | O8: =C8+I8 | P8: =D8+J8 | Q8: =E8+K8 | R8: =F8+L8 | S8: =G8+M8 | T8: =H8+N8
A9: 8 | B9: Other income (biz total) | C9: =SUMIFS(tblMaster_Inputs[Baseline_Amount], tblMaster_Inputs[Year], 2023, tblMaster_Inputs[Primary_Line], "8", tblMaster_Inputs[Activity_Type], "Baseline") | D9: =SUMIFS(tblMaster_Inputs[Baseline_Amount], tblMaster_Inputs[Year], 2024, tblMaster_Inputs[Primary_Line], "8", tblMaster_Inputs[Activity_Type], "Baseline") | E9: =SUMIFS(tblMaster_Inputs[Baseline_Amount], tblMaster_Inputs[Year], 2025, tblMaster_Inputs[Primary_Line], "8", tblMaster_Inputs[Activity_Type], "Baseline") | F9: =SUMIFS(tblMaster_Inputs[Baseline_Amount], tblMaster_Inputs[Year], 2026, tblMaster_Inputs[Primary_Line], "8", tblMaster_Inputs[Activity_Type], "Baseline") | G9: =SUMIFS(tblMaster_Inputs[Baseline_Amount], tblMaster_Inputs[Year], 2027, tblMaster_Inputs[Primary_Line], "8", tblMaster_Inputs[Activity_Type], "Baseline") | H9: =SUMIFS(tblMaster_Inputs[Baseline_Amount], tblMaster_Inputs[Year], 2028, tblMaster_Inputs[Primary_Line], "8", tblMaster_Inputs[Activity_Type], "Baseline") | I9: =SUMIFS(tblMaster_Inputs[Baseline_Amount], tblMaster_Inputs[Year], 2023, tblMaster_Inputs[Primary_Line], "8", tblMaster_Inputs[Activity_Type], "Strategy") | J9: =SUMIFS(tblMaster_Inputs[Baseline_Amount], tblMaster_Inputs[Year], 2024, tblMaster_Inputs[Primary_Line], "8", tblMaster_Inputs[Activity_Type], "Strategy") | K9: =SUMIFS(tblMaster_Inputs[Baseline_Amount], tblMaster_Inputs[Year], 2025, tblMaster_Inputs[Primary_Line], "8", tblMaster_Inputs[Activity_Type], "Strategy") | L9: =SUMIFS(tblMaster_Inputs[Baseline_Amount], tblMaster_Inputs[Year], 2026, tblMaster_Inputs[Primary_Line], "8", tblMaster_Inputs[Activity_Type], "Strategy") | M9: =SUMIFS(tblMaster_Inputs[Baseline_Amount], tblMaster_Inputs[Year], 2027, tblMaster_Inputs[Primary_Line], "8", tblMaster_Inputs[Activity_Type], "Strategy") | N9: =SUMIFS(tblMaster_Inputs[Baseline_Amount], tblMaster_Inputs[Year], 2028, tblMaster_Inputs[Primary_Line], "8", tblMaster_Inputs[Activity_Type], "Strategy") | O9: =C9+I9 | P9: =D9+J9 | Q9: =E9+K9 | R9: =F9+L9 | S9: =G9+M9 | T9: =H9+N9
A10: 9 | B10: TOTAL INCOME | C10: =C5+C6+C7+C8+C9 | D10: =D5+D6+D7+D8+D9 | E10: =E5+E6+E7+E8+E9 | F10: =F5+F6+F7+F8+F9 | G10: =G5+G6+G7+G8+G9 | H10: =H5+H6+H7+H8+H9 | I10: =I5+I6+I7+I8+I9 | J10: =J5+J6+J7+J8+J9 | ... N10: =N5+N6+N7+N8+N9 | O10: =C10+I10 | P10: =D10+J10 | Q10: =E10+K10 | R10: =F10+L10 | S10: =G10+M10 | T10: =H10+N10
A11: 10 | B11: Adjustments to income | C11: =SUMIFS(tblMaster_Inputs[Baseline_Amount], tblMaster_Inputs[Year], 2023, tblMaster_Inputs[Primary_Line], "10", tblMaster_Inputs[Activity_Type], "Baseline") | D11: =SUMIFS(tblMaster_Inputs[Baseline_Amount], tblMaster_Inputs[Year], 2024, tblMaster_Inputs[Primary_Line], "10", tblMaster_Inputs[Activity_Type], "Baseline") | E11: =SUMIFS(tblMaster_Inputs[Baseline_Amount], tblMaster_Inputs[Year], 2025, tblMaster_Inputs[Primary_Line], "10", tblMaster_Inputs[Activity_Type], "Baseline") | F11: =SUMIFS(tblMaster_Inputs[Baseline_Amount], tblMaster_Inputs[Year], 2026, tblMaster_Inputs[Primary_Line], "10", tblMaster_Inputs[Activity_Type], "Baseline") | G11: =SUMIFS(tblMaster_Inputs[Baseline_Amount], tblMaster_Inputs[Year], 2027, tblMaster_Inputs[Primary_Line], "10", tblMaster_Inputs[Activity_Type], "Baseline") | H11: =SUMIFS(tblMaster_Inputs[Baseline_Amount], tblMaster_Inputs[Year], 2028, tblMaster_Inputs[Primary_Line], "10", tblMaster_Inputs[Activity_Type], "Baseline") | I11: =SUMIFS(tblMaster_Inputs[Baseline_Amount], tblMaster_Inputs[Year], 2023, tblMaster_Inputs[Primary_Line], "10", tblMaster_Inputs[Activity_Type], "Strategy") | J11: =SUMIFS(tblMaster_Inputs[Baseline_Amount], tblMaster_Inputs[Year], 2024, tblMaster_Inputs[Primary_Line], "10", tblMaster_Inputs[Activity_Type], "Strategy") | K11: =SUMIFS(tblMaster_Inputs[Baseline_Amount], tblMaster_Inputs[Year], 2025, tblMaster_Inputs[Primary_Line], "10", tblMaster_Inputs[Activity_Type], "Strategy") | L11: =SUMIFS(tblMaster_Inputs[Baseline_Amount], tblMaster_Inputs[Year], 2026, tblMaster_Inputs[Primary_Line], "10", tblMaster_Inputs[Activity_Type], "Strategy") | M11: =SUMIFS(tblMaster_Inputs[Baseline_Amount], tblMaster_Inputs[Year], 2027, tblMaster_Inputs[Primary_Line], "10", tblMaster_Inputs[Activity_Type], "Strategy") | N11: =SUMIFS(tblMaster_Inputs[Baseline_Amount], tblMaster_Inputs[Year], 2028, tblMaster_Inputs[Primary_Line], "10", tblMaster_Inputs[Activity_Type], "Strategy") | O11: =C11+I11 | P11: =D11+J11 | Q11: =E11+K11 | R11: =F11+L11 | S11: =G11+M11 | T11: =H11+N11
A12: 11 | B12: AGI | C12: =C10+C11 | D12: =D10+D11 | E12: =E10+E11 | F12: =F10+F11 | G12: =G10+G11 | H12: =H10+H11 | I12: =I10+I11 | J12: =J10+J11 | ... N12: =N10+N11 | O12: =C12+I12 | P12: =D12+J12 | Q12: =E12+K12 | R12: =F12+L12 | S12: =G12+M12 | T12: =H12+N12
A13: 12 | B13: Std/Itemized deduction | C13: =SUMIFS(tblMaster_Inputs[Baseline_Amount], tblMaster_Inputs[Year], 2023, tblMaster_Inputs[Primary_Line], "12", tblMaster_Inputs[Activity_Type], "Baseline") | D13: =SUMIFS(tblMaster_Inputs[Baseline_Amount], tblMaster_Inputs[Year], 2024, tblMaster_Inputs[Primary_Line], "12", tblMaster_Inputs[Activity_Type], "Baseline") | E13: =SUMIFS(tblMaster_Inputs[Baseline_Amount], tblMaster_Inputs[Year], 2025, tblMaster_Inputs[Primary_Line], "12", tblMaster_Inputs[Activity_Type], "Baseline") | F13: =SUMIFS(tblMaster_Inputs[Baseline_Amount], tblMaster_Inputs[Year], 2026, tblMaster_Inputs[Primary_Line], "12", tblMaster_Inputs[Activity_Type], "Baseline") | G13: =SUMIFS(tblMaster_Inputs[Baseline_Amount], tblMaster_Inputs[Year], 2027, tblMaster_Inputs[Primary_Line], "12", tblMaster_Inputs[Activity_Type], "Baseline") | H13: =SUMIFS(tblMaster_Inputs[Baseline_Amount], tblMaster_Inputs[Year], 2028, tblMaster_Inputs[Primary_Line], "12", tblMaster_Inputs[Activity_Type], "Baseline") | I13: =SUMIFS(tblMaster_Inputs[Baseline_Amount], tblMaster_Inputs[Year], 2023, tblMaster_Inputs[Primary_Line], "12", tblMaster_Inputs[Activity_Type], "Strategy") | J13: =SUMIFS(tblMaster_Inputs[Baseline_Amount], tblMaster_Inputs[Year], 2024, tblMaster_Inputs[Primary_Line], "12", tblMaster_Inputs[Activity_Type], "Strategy") | K13: =SUMIFS(tblMaster_Inputs[Baseline_Amount], tblMaster_Inputs[Year], 2025, tblMaster_Inputs[Primary_Line], "12", tblMaster_Inputs[Activity_Type], "Strategy") | L13: =SUMIFS(tblMaster_Inputs[Baseline_Amount], tblMaster_Inputs[Year], 2026, tblMaster_Inputs[Primary_Line], "12", tblMaster_Inputs[Activity_Type], "Strategy") | M13: =SUMIFS(tblMaster_Inputs[Baseline_Amount], tblMaster_Inputs[Year], 2027, tblMaster_Inputs[Primary_Line], "12", tblMaster_Inputs[Activity_Type], "Strategy") | N13: =SUMIFS(tblMaster_Inputs[Baseline_Amount], tblMaster_Inputs[Year], 2028, tblMaster_Inputs[Primary_Line], "12", tblMaster_Inputs[Activity_Type], "Strategy") | O13: =C13+I13 | P13: =D13+J13 | Q13: =E13+K13 | R13: =F13+L13 | S13: =G13+M13 | T13: =H13+N13
A14: 13 | B14: QBI deduction | C14: =SUMIFS(tblMaster_Inputs[Baseline_Amount], tblMaster_Inputs[Year], 2023, tblMaster_Inputs[Primary_Line], "13", tblMaster_Inputs[Activity_Type], "Baseline") | D14: =SUMIFS(tblMaster_Inputs[Baseline_Amount], tblMaster_Inputs[Year], 2024, tblMaster_Inputs[Primary_Line], "13", tblMaster_Inputs[Activity_Type], "Baseline") | E14: =SUMIFS(tblMaster_Inputs[Baseline_Amount], tblMaster_Inputs[Year], 2025, tblMaster_Inputs[Primary_Line], "13", tblMaster_Inputs[Activity_Type], "Baseline") | F14: =SUMIFS(tblMaster_Inputs[Baseline_Amount], tblMaster_Inputs[Year], 2026, tblMaster_Inputs[Primary_Line], "13", tblMaster_Inputs[Activity_Type], "Baseline") | G14: =SUMIFS(tblMaster_Inputs[Baseline_Amount], tblMaster_Inputs[Year], 2027, tblMaster_Inputs[Primary_Line], "13", tblMaster_Inputs[Activity_Type], "Baseline") | H14: =SUMIFS(tblMaster_Inputs[Baseline_Amount], tblMaster_Inputs[Year], 2028, tblMaster_Inputs[Primary_Line], "13", tblMaster_Inputs[Activity_Type], "Baseline") | I14: =SUMIFS(tblMaster_Inputs[Baseline_Amount], tblMaster_Inputs[Year], 2023, tblMaster_Inputs[Primary_Line], "13", tblMaster_Inputs[Activity_Type], "Strategy") | J14: =SUMIFS(tblMaster_Inputs[Baseline_Amount], tblMaster_Inputs[Year], 2024, tblMaster_Inputs[Primary_Line], "13", tblMaster_Inputs[Activity_Type], "Strategy") | K14: =SUMIFS(tblMaster_Inputs[Baseline_Amount], tblMaster_Inputs[Year], 2025, tblMaster_Inputs[Primary_Line], "13", tblMaster_Inputs[Activity_Type], "Strategy") | L14: =SUMIFS(tblMaster_Inputs[Baseline_Amount], tblMaster_Inputs[Year], 2026, tblMaster_Inputs[Primary_Line], "13", tblMaster_Inputs[Activity_Type], "Strategy") | M14: =SUMIFS(tblMaster_Inputs[Baseline_Amount], tblMaster_Inputs[Year], 2027, tblMaster_Inputs[Primary_Line], "13", tblMaster_Inputs[Activity_Type], "Strategy") | N14: =SUMIFS(tblMaster_Inputs[Baseline_Amount], tblMaster_Inputs[Year], 2028, tblMaster_Inputs[Primary_Line], "13", tblMaster_Inputs[Activity_Type], "Strategy") | O14: =C14+I14 | P14: =D14+J14 | Q14: =E14+K14 | R14: =F14+L14 | S14: =G14+M14 | T14: =H14+N14
A15: 15 | B15: TAXABLE INCOME | C15: =C12+C13+C14 | D15: =D12+D13+D14 | E15: =E12+E13+E14 | F15: =F12+F13+F14 | G15: =G12+G13+G14 | H15: =H12+H13+H14 | I15: =I12+I13+I14 | J15: =J12+J13+J14 | ... N15: =N12+N13+N14 | O15: =C15+I15 | P15: =D15+J15 | Q15: =E15+K15 | R15: =F15+L15 | S15: =G15+M15 | T15: =H15+N15

Sheet Pivot_Medium
A1: PIVOT — MEDIUM (biz income broken out by entity type; multi-year baseline)
A2: Same as summary but Line 8 broken into Schedule C / Schedule E rental / Partnership K-1 / S-Corp K-1 / Sch F / Trust K-1.
I3: Strategy | O3: Effective
A4: Line | B4: Description | C4: 2023 | D4: 2024 | E4: 2025 | F4: 2026 | G4: 2027 | H4: 2028 | I4: 2023 | J4: 2024 | K4: 2025 | L4: 2026 | M4: 2027 | N4: 2028 | O4: 2023 | P4: 2024 | Q4: 2025 | R4: 2026 | S4: 2027 | T4: 2028
A5: 1z | B5: Wages | C5: =SUMIFS(tblMaster_Inputs[Baseline_Amount], tblMaster_Inputs[Year], 2023, tblMaster_Inputs[Primary_Line], "1z", tblMaster_Inputs[Activity_Type], "Baseline") | D5: =SUMIFS(tblMaster_Inputs[Baseline_Amount], tblMaster_Inputs[Year], 2024, tblMaster_Inputs[Primary_Line], "1z", tblMaster_Inputs[Activity_Type], "Baseline") | E5: =SUMIFS(tblMaster_Inputs[Baseline_Amount], tblMaster_Inputs[Year], 2025, tblMaster_Inputs[Primary_Line], "1z", tblMaster_Inputs[Activity_Type], "Baseline") | F5: =SUMIFS(tblMaster_Inputs[Baseline_Amount], tblMaster_Inputs[Year], 2026, tblMaster_Inputs[Primary_Line], "1z", tblMaster_Inputs[Activity_Type], "Baseline") | G5: =SUMIFS(tblMaster_Inputs[Baseline_Amount], tblMaster_Inputs[Year], 2027, tblMaster_Inputs[Primary_Line], "1z", tblMaster_Inputs[Activity_Type], "Baseline") | H5: =SUMIFS(tblMaster_Inputs[Baseline_Amount], tblMaster_Inputs[Year], 2028, tblMaster_Inputs[Primary_Line], "1z", tblMaster_Inputs[Activity_Type], "Baseline") | I5: =SUMIFS(tblMaster_Inputs[Baseline_Amount], tblMaster_Inputs[Year], 2023, tblMaster_Inputs[Primary_Line], "1z", tblMaster_Inputs[Activity_Type], "Strategy") | J5: =SUMIFS(tblMaster_Inputs[Baseline_Amount], tblMaster_Inputs[Year], 2024, tblMaster_Inputs[Primary_Line], "1z", tblMaster_Inputs[Activity_Type], "Strategy") | K5: =SUMIFS(tblMaster_Inputs[Baseline_Amount], tblMaster_Inputs[Year], 2025, tblMaster_Inputs[Primary_Line], "1z", tblMaster_Inputs[Activity_Type], "Strategy") | L5: =SUMIFS(tblMaster_Inputs[Baseline_Amount], tblMaster_Inputs[Year], 2026, tblMaster_Inputs[Primary_Line], "1z", tblMaster_Inputs[Activity_Type], "Strategy") | M5: =SUMIFS(tblMaster_Inputs[Baseline_Amount], tblMaster_Inputs[Year], 2027, tblMaster_Inputs[Primary_Line], "1z", tblMaster_Inputs[Activity_Type], "Strategy") | N5: =SUMIFS(tblMaster_Inputs[Baseline_Amount], tblMaster_Inputs[Year], 2028, tblMaster_Inputs[Primary_Line], "1z", tblMaster_Inputs[Activity_Type], "Strategy") | O5: =C5+I5 | P5: =D5+J5 | Q5: =E5+K5 | R5: =F5+L5 | S5: =G5+M5 | T5: =H5+N5
A6: 2 | B6: Interest | C6: =SUMIFS(tblMaster_Inputs[Baseline_Amount], tblMaster_Inputs[Year], 2023, tblMaster_Inputs[Primary_Line], "2b", tblMaster_Inputs[Activity_Type], "Baseline") | D6: =SUMIFS(tblMaster_Inputs[Baseline_Amount], tblMaster_Inputs[Year], 2024, tblMaster_Inputs[Primary_Line], "2b", tblMaster_Inputs[Activity_Type], "Baseline") | E6: =SUMIFS(tblMaster_Inputs[Baseline_Amount], tblMaster_Inputs[Year], 2025, tblMaster_Inputs[Primary_Line], "2b", tblMaster_Inputs[Activity_Type], "Baseline") | F6: =SUMIFS(tblMaster_Inputs[Baseline_Amount], tblMaster_Inputs[Year], 2026, tblMaster_Inputs[Primary_Line], "2b", tblMaster_Inputs[Activity_Type], "Baseline") | G6: =SUMIFS(tblMaster_Inputs[Baseline_Amount], tblMaster_Inputs[Year], 2027, tblMaster_Inputs[Primary_Line], "2b", tblMaster_Inputs[Activity_Type], "Baseline") | H6: =SUMIFS(tblMaster_Inputs[Baseline_Amount], tblMaster_Inputs[Year], 2028, tblMaster_Inputs[Primary_Line], "2b", tblMaster_Inputs[Activity_Type], "Baseline") | I6: =SUMIFS(tblMaster_Inputs[Baseline_Amount], tblMaster_Inputs[Year], 2023, tblMaster_Inputs[Primary_Line], "2b", tblMaster_Inputs[Activity_Type], "Strategy") | J6: =SUMIFS(tblMaster_Inputs[Baseline_Amount], tblMaster_Inputs[Year], 2024, tblMaster_Inputs[Primary_Line], "2b", tblMaster_Inputs[Activity_Type], "Strategy") | K6: =SUMIFS(tblMaster_Inputs[Baseline_Amount], tblMaster_Inputs[Year], 2025, tblMaster_Inputs[Primary_Line], "2b", tblMaster_Inputs[Activity_Type], "Strategy") | L6: =SUMIFS(tblMaster_Inputs[Baseline_Amount], tblMaster_Inputs[Year], 2026, tblMaster_Inputs[Primary_Line], "2b", tblMaster_Inputs[Activity_Type], "Strategy") | M6: =SUMIFS(tblMaster_Inputs[Baseline_Amount], tblMaster_Inputs[Year], 2027, tblMaster_Inputs[Primary_Line], "2b", tblMaster_Inputs[Activity_Type], "Strategy") | N6: =SUMIFS(tblMaster_Inputs[Baseline_Amount], tblMaster_Inputs[Year], 2028, tblMaster_Inputs[Primary_Line], "2b", tblMaster_Inputs[Activity_Type], "Strategy") | O6: =C6+I6 | P6: =D6+J6 | Q6: =E6+K6 | R6: =F6+L6 | S6: =G6+M6 | T6: =H6+N6
A7: 3 | B7: Dividends | C7: =SUMIFS(tblMaster_Inputs[Baseline_Amount], tblMaster_Inputs[Year], 2023, tblMaster_Inputs[Primary_Line], "3b", tblMaster_Inputs[Activity_Type], "Baseline") | D7: =SUMIFS(tblMaster_Inputs[Baseline_Amount], tblMaster_Inputs[Year], 2024, tblMaster_Inputs[Primary_Line], "3b", tblMaster_Inputs[Activity_Type], "Baseline") | E7: =SUMIFS(tblMaster_Inputs[Baseline_Amount], tblMaster_Inputs[Year], 2025, tblMaster_Inputs[Primary_Line], "3b", tblMaster_Inputs[Activity_Type], "Baseline") | F7: =SUMIFS(tblMaster_Inputs[Baseline_Amount], tblMaster_Inputs[Year], 2026, tblMaster_Inputs[Primary_Line], "3b", tblMaster_Inputs[Activity_Type], "Baseline") | G7: =SUMIFS(tblMaster_Inputs[Baseline_Amount], tblMaster_Inputs[Year], 2027, tblMaster_Inputs[Primary_Line], "3b", tblMaster_Inputs[Activity_Type], "Baseline") | H7: =SUMIFS(tblMaster_Inputs[Baseline_Amount], tblMaster_Inputs[Year], 2028, tblMaster_Inputs[Primary_Line], "3b", tblMaster_Inputs[Activity_Type], "Baseline") | I7: =SUMIFS(tblMaster_Inputs[Baseline_Amount], tblMaster_Inputs[Year], 2023, tblMaster_Inputs[Primary_Line], "3b", tblMaster_Inputs[Activity_Type], "Strategy") | J7: =SUMIFS(tblMaster_Inputs[Baseline_Amount], tblMaster_Inputs[Year], 2024, tblMaster_Inputs[Primary_Line], "3b", tblMaster_Inputs[Activity_Type], "Strategy") | K7: =SUMIFS(tblMaster_Inputs[Baseline_Amount], tblMaster_Inputs[Year], 2025, tblMaster_Inputs[Primary_Line], "3b", tblMaster_Inputs[Activity_Type], "Strategy") | L7: =SUMIFS(tblMaster_Inputs[Baseline_Amount], tblMaster_Inputs[Year], 2026, tblMaster_Inputs[Primary_Line], "3b", tblMaster_Inputs[Activity_Type], "Strategy") | M7: =SUMIFS(tblMaster_Inputs[Baseline_Amount], tblMaster_Inputs[Year], 2027, tblMaster_Inputs[Primary_Line], "3b", tblMaster_Inputs[Activity_Type], "Strategy") | N7: =SUMIFS(tblMaster_Inputs[Baseline_Amount], tblMaster_Inputs[Year], 2028, tblMaster_Inputs[Primary_Line], "3b", tblMaster_Inputs[Activity_Type], "Strategy") | O7: =C7+I7 | P7: =D7+J7 | Q7: =E7+K7 | R7: =F7+L7 | S7: =G7+M7 | T7: =H7+N7
A8: 7 | B8: Capital gain or (loss) | C8: =SUMIFS(tblMaster_Inputs[Baseline_Amount], tblMaster_Inputs[Year], 2023, tblMaster_Inputs[Primary_Line], "7", tblMaster_Inputs[Activity_Type], "Baseline") | D8: =SUMIFS(tblMaster_Inputs[Baseline_Amount], tblMaster_Inputs[Year], 2024, tblMaster_Inputs[Primary_Line], "7", tblMaster_Inputs[Activity_Type], "Baseline") | E8: =SUMIFS(tblMaster_Inputs[Baseline_Amount], tblMaster_Inputs[Year], 2025, tblMaster_Inputs[Primary_Line], "7", tblMaster_Inputs[Activity_Type], "Baseline") | F8: =SUMIFS(tblMaster_Inputs[Baseline_Amount], tblMaster_Inputs[Year], 2026, tblMaster_Inputs[Primary_Line], "7", tblMaster_Inputs[Activity_Type], "Baseline") | G8: =SUMIFS(tblMaster_Inputs[Baseline_Amount], tblMaster_Inputs[Year], 2027, tblMaster_Inputs[Primary_Line], "7", tblMaster_Inputs[Activity_Type], "Baseline") | H8: =SUMIFS(tblMaster_Inputs[Baseline_Amount], tblMaster_Inputs[Year], 2028, tblMaster_Inputs[Primary_Line], "7", tblMaster_Inputs[Activity_Type], "Baseline") | I8: =SUMIFS(tblMaster_Inputs[Baseline_Amount], tblMaster_Inputs[Year], 2023, tblMaster_Inputs[Primary_Line], "7", tblMaster_Inputs[Activity_Type], "Strategy") | J8: =SUMIFS(tblMaster_Inputs[Baseline_Amount], tblMaster_Inputs[Year], 2024, tblMaster_Inputs[Primary_Line], "7", tblMaster_Inputs[Activity_Type], "Strategy") | K8: =SUMIFS(tblMaster_Inputs[Baseline_Amount], tblMaster_Inputs[Year], 2025, tblMaster_Inputs[Primary_Line], "7", tblMaster_Inputs[Activity_Type], "Strategy") | L8: =SUMIFS(tblMaster_Inputs[Baseline_Amount], tblMaster_Inputs[Year], 2026, tblMaster_Inputs[Primary_Line], "7", tblMaster_Inputs[Activity_Type], "Strategy") | M8: =SUMIFS(tblMaster_Inputs[Baseline_Amount], tblMaster_Inputs[Year], 2027, tblMaster_Inputs[Primary_Line], "7", tblMaster_Inputs[Activity_Type], "Strategy") | N8: =SUMIFS(tblMaster_Inputs[Baseline_Amount], tblMaster_Inputs[Year], 2028, tblMaster_Inputs[Primary_Line], "7", tblMaster_Inputs[Activity_Type], "Strategy") | O8: =C8+I8 | P8: =D8+J8 | Q8: =E8+K8 | R8: =F8+L8 | S8: =G8+M8 | T8: =H8+N8
A9: 8.SchC | B9: Schedule C | C9: =SUMIFS(tblMaster_Inputs[Baseline_Amount], tblMaster_Inputs[Year], 2023, tblMaster_Inputs[Treatment_Profile], "SchC_Active", tblMaster_Inputs[Activity_Type], "Baseline") | D9: =SUMIFS(tblMaster_Inputs[Baseline_Amount], tblMaster_Inputs[Year], 2024, tblMaster_Inputs[Treatment_Profile], "SchC_Active", tblMaster_Inputs[Activity_Type], "Baseline") | E9: =SUMIFS(tblMaster_Inputs[Baseline_Amount], tblMaster_Inputs[Year], 2025, tblMaster_Inputs[Treatment_Profile], "SchC_Active", tblMaster_Inputs[Activity_Type], "Baseline") | F9: =SUMIFS(tblMaster_Inputs[Baseline_Amount], tblMaster_Inputs[Year], 2026, tblMaster_Inputs[Treatment_Profile], "SchC_Active", tblMaster_Inputs[Activity_Type], "Baseline") | G9: =SUMIFS(tblMaster_Inputs[Baseline_Amount], tblMaster_Inputs[Year], 2027, tblMaster_Inputs[Treatment_Profile], "SchC_Active", tblMaster_Inputs[Activity_Type], "Baseline") | H9: =SUMIFS(tblMaster_Inputs[Baseline_Amount], tblMaster_Inputs[Year], 2028, tblMaster_Inputs[Treatment_Profile], "SchC_Active", tblMaster_Inputs[Activity_Type], "Baseline") | I9: =SUMIFS(tblMaster_Inputs[Baseline_Amount], tblMaster_Inputs[Year], 2023, tblMaster_Inputs[Treatment_Profile], "SchC_Active", tblMaster_Inputs[Activity_Type], "Strategy") | J9: =SUMIFS(tblMaster_Inputs[Baseline_Amount], tblMaster_Inputs[Year], 2024, tblMaster_Inputs[Treatment_Profile], "SchC_Active", tblMaster_Inputs[Activity_Type], "Strategy") | K9: =SUMIFS(tblMaster_Inputs[Baseline_Amount], tblMaster_Inputs[Year], 2025, tblMaster_Inputs[Treatment_Profile], "SchC_Active", tblMaster_Inputs[Activity_Type], "Strategy") | L9: =SUMIFS(tblMaster_Inputs[Baseline_Amount], tblMaster_Inputs[Year], 2026, tblMaster_Inputs[Treatment_Profile], "SchC_Active", tblMaster_Inputs[Activity_Type], "Strategy") | M9: =SUMIFS(tblMaster_Inputs[Baseline_Amount], tblMaster_Inputs[Year], 2027, tblMaster_Inputs[Treatment_Profile], "SchC_Active", tblMaster_Inputs[Activity_Type], "Strategy") | N9: =SUMIFS(tblMaster_Inputs[Baseline_Amount], tblMaster_Inputs[Year], 2028, tblMaster_Inputs[Treatment_Profile], "SchC_Active", tblMaster_Inputs[Activity_Type], "Strategy") | O9: =C9+I9 | P9: =D9+J9 | Q9: =E9+K9 | R9: =F9+L9 | S9: =G9+M9 | T9: =H9+N9
A10: 8.SchE | B10: Schedule E rental | C10: =SUMIFS(tblMaster_Inputs[Baseline_Amount], tblMaster_Inputs[Year], 2023, tblMaster_Inputs[Treatment_Profile], "SchE_Rental", tblMaster_Inputs[Activity_Type], "Baseline") + SUMIFS(tblMaster_Inputs[Baseline_Amount], tblMaster_Inputs[Year], 2023, tblMaster_Inputs[Treatment_Profile], "SchE_REPro", tblMaster_Inputs[Activity_Type], "Baseline") | D10: =SUMIFS(tblMaster_Inputs[Baseline_Amount], tblMaster_Inputs[Year], 2024, tblMaster_Inputs[Treatment_Profile], "SchE_Rental", tblMaster_Inputs[Activity_Type], "Baseline") + SUMIFS(tblMaster_Inputs[Baseline_Amount], tblMaster_Inputs[Year], 2024, tblMaster_Inputs[Treatment_Profile], "SchE_REPro", tblMaster_Inputs[Activity_Type], "Baseline") | E10: =SUMIFS(tblMaster_Inputs[Baseline_Amount], tblMaster_Inputs[Year], 2025, tblMaster_Inputs[Treatment_Profile], "SchE_Rental", tblMaster_Inputs[Activity_Type], "Baseline") + SUMIFS(tblMaster_Inputs[Baseline_Amount], tblMaster_Inputs[Year], 2025, tblMaster_Inputs[Treatment_Profile], "SchE_REPro", tblMaster_Inputs[Activity_Type], "Baseline") | F10: =SUMIFS(tblMaster_Inputs[Baseline_Amount], tblMaster_Inputs[Year], 2026, tblMaster_Inputs[Treatment_Profile], "SchE_Rental", tblMaster_Inputs[Activity_Type], "Baseline") + SUMIFS(tblMaster_Inputs[Baseline_Amount], tblMaster_Inputs[Year], 2026, tblMaster_Inputs[Treatment_Profile], "SchE_REPro", tblMaster_Inputs[Activity_Type], "Baseline") | G10: =SUMIFS(tblMaster_Inputs[Baseline_Amount], tblMaster_Inputs[Year], 2027, tblMaster_Inputs[Treatment_Profile], "SchE_Rental", tblMaster_Inputs[Activity_Type], "Baseline") + SUMIFS(tblMaster_Inputs[Baseline_Amount], tblMaster_Inputs[Year], 2027, tblMaster_Inputs[Treatment_Profile], "SchE_REPro", tblMaster_Inputs[Activity_Type], "Baseline") | H10: =SUMIFS(tblMaster_Inputs[Baseline_Amount], tblMaster_Inputs[Year], 2028, tblMaster_Inputs[Treatment_Profile], "SchE_Rental", tblMaster_Inputs[Activity_Type], "Baseline") + SUMIFS(tblMaster_Inputs[Baseline_Amount], tblMaster_Inputs[Year], 2028, tblMaster_Inputs[Treatment_Profile], "SchE_REPro", tblMaster_Inputs[Activity_Type], "Baseline") | I10: =SUMIFS(tblMaster_Inputs[Baseline_Amount], tblMaster_Inputs[Year], 2023, tblMaster_Inputs[Treatment_Profile], "SchE_Rental", tblMaster_Inputs[Activity_Type], "Strategy") + SUMIFS(tblMaster_Inputs[Baseline_Amount], tblMaster_Inputs[Year], 2023, tblMaster_Inputs[Treatment_Profile], "SchE_REPro", tblMaster_Inputs[Activity_Type], "Strategy") | J10: =SUMIFS(tblMaster_Inputs[Baseline_Amount], tblMaster_Inputs[Year], 2024, tblMaster_Inputs[Treatment_Profile], "SchE_Rental", tblMaster_Inputs[Activity_Type], "Strategy") + SUMIFS(tblMaster_Inputs[Baseline_Amount], tblMaster_Inputs[Year], 2024, tblMaster_Inputs[Treatment_Profile], "SchE_REPro", tblMaster_Inputs[Activity_Type], "Strategy") | K10: =SUMIFS(tblMaster_Inputs[Baseline_Amount], tblMaster_Inputs[Year], 2025, tblMaster_Inputs[Treatment_Profile], "SchE_Rental", tblMaster_Inputs[Activity_Type], "Strategy") + SUMIFS(tblMaster_Inputs[Baseline_Amount], tblMaster_Inputs[Year], 2025, tblMaster_Inputs[Treatment_Profile], "SchE_REPro", tblMaster_Inputs[Activity_Type], "Strategy") | L10: =SUMIFS(tblMaster_Inputs[Baseline_Amount], tblMaster_Inputs[Year], 2026, tblMaster_Inputs[Treatment_Profile], "SchE_Rental", tblMaster_Inputs[Activity_Type], "Strategy") + SUMIFS(tblMaster_Inputs[Baseline_Amount], tblMaster_Inputs[Year], 2026, tblMaster_Inputs[Treatment_Profile], "SchE_REPro", tblMaster_Inputs[Activity_Type], "Strategy") | M10: =SUMIFS(tblMaster_Inputs[Baseline_Amount], tblMaster_Inputs[Year], 2027, tblMaster_Inputs[Treatment_Profile], "SchE_Rental", tblMaster_Inputs[Activity_Type], "Strategy") + SUMIFS(tblMaster_Inputs[Baseline_Amount], tblMaster_Inputs[Year], 2027, tblMaster_Inputs[Treatment_Profile], "SchE_REPro", tblMaster_Inputs[Activity_Type], "Strategy") | N10: =SUMIFS(tblMaster_Inputs[Baseline_Amount], tblMaster_Inputs[Year], 2028, tblMaster_Inputs[Treatment_Profile], "SchE_Rental", tblMaster_Inputs[Activity_Type], "Strategy") + SUMIFS(tblMaster_Inputs[Baseline_Amount], tblMaster_Inputs[Year], 2028, tblMaster_Inputs[Treatment_Profile], "SchE_REPro", tblMaster_Inputs[Activity_Type], "Strategy") | O10: =C10+I10 | P10: =D10+J10 | Q10: =E10+K10 | R10: =F10+L10 | S10: =G10+M10 | T10: =H10+N10
